Workbook
Name ANALISTA: #REF!
Name BALANCEO: #REF!
Name ESTADO: #REF!
Name PLANTAS: #REF!
Name PRENDA: #REF!
Name PROCESO: #REF!
Name TIPO: #REF!

Sheet Resumen costos Ptar Bogotá
B3: Bogotá
B4: COSTO PLANTA DE TRATAMIENTO DE AGUA RESIDUAL | E4: EJECUTADO PTAR AÑO 2025 BOGOTÁ
B5: Clasificación | C5: Detalle | D5: Unidad | E5: Enero 2025 | F5: Febrero 2025 | G5: Marzo 2025 | H5: Abril 2025 | I5: Mayo 2025 | J5: Junio 2025 | K5: Julio 2025 | L5: Agosto 2025 | M5: Septiembre 2025 | N5: Octubre 2025 | O5: Noviembre 2025 | P5: Total general | Q5: Diferencia | R5: % Variación | S5: $/Kg | T5: Kg/Año | U5: Kg/m3
C6: ACIDO CLORHIDRICO 31,5% | D6: kg | E6: 359600 | F6: 775000 | G6: 372000 | H6: 372000 | I6: 372000 | J6: 372000 | K6: 372000 | L6: 372000 | M6: 372000 | N6: 372000 | O6: 372000 | P6: =+SUM(E6:O6) -> 4482600 | Q6: =+O6-N6 -> 0 | R6: =+IFERROR((O6-N6)/N6,0) -> 0 | S6: 1650 | T6: =P6/S6 -> 2716.7273 | U6: =T6/$V$8 -> 0.013583636
C7: SODIO BISULFITO | D7: kg | E7: 91000 | F7: 91000 | G7: 91000 | H7: 91000 | I7: 91000 | J7: 91000 | K7: 91000 | L7: 91000 | M7: 91000 | N7: 91000 | O7: 91000 | P7: =+SUM(E7:O7) -> 1001000 | Q7: =+O7-N7 -> 0 | R7: =+IFERROR((O7-N7)/N7,0) -> 0 | S7: 4200 | T7: =P7/S7 -> 238.33333 | U7: =T7/$V$8 -> 0.0011916667 | V7: =P108 -> 508614
C8: NITRATO DE PLATA | D8: kg | E8: 150800 | F8: 150800 | G8: 150800 | H8: 150800 | I8: 150800 | J8: 150800 | K8: 150800 | L8: 150800 | M8: 150800 | N8: 150800 | O8: 150800 | P8: =+SUM(E8:O8) -> 1658800 | Q8: =+O8-N8 -> 0 | R8: =+IFERROR((O8-N8)/N8,0) -> 0 | S8: 180000 | T8: =P8/S8 -> 9.2155556 | U8: =T8/$V$7 -> 1.8118958e-05 | V8: 200000
C9: INSUMOS HACH | D9: uni | E9: 0 | F9: 0 | G9: 0 | H9: 12832747 | I9: 15149313 | J9: 0 | K9: 0 | L9: 0 | M9: 0 | N9: 0 | O9: 4421528.8 | P9: =+SUM(E9:O9) -> 32403589 | Q9: =+O9-N9 -> 4421528.8 | R9: =+IFERROR((O9-N9)/N9,0) -> 0 | U9: =T9/$V$7 -> 0 | W9: 7680
C10: ACIDIFICANTE | D10: kg | E10: 48418570 | F10: 36323100 | G10: 30697300 | H10: 43917930 | I10: 46821332 | J10: 26661400 | K10: 31421316 | L10: 33429482 | M10: 31223190 | N10: 21221007 | O10: 33089488 | P10: =+SUM(E10:O10) -> 3.8322411e+08 | Q10: =+O10-N10 -> 11868481 | R10: =+IFERROR((O10-N10)/N10,0) -> 0.55927984 | S10: 2446 | T10: =P10/S10 -> 156673.8 | U10: =T10/$V$7 -> 0.30804068 | W10: =W9/V7 -> 0.01509986
C11: QUIMICO FLOCULANTE PARA TRATAMIENTO DE AGUA (Cationico) | D11: kg | E11: 7566500 | F11: 3067500 | G11: 6646250 | H11: 11554250 | I11: 8282250 | J11: 6544000 | K11: 8486750 | L11: 6646250 | M11: 12576750 | N11: 14867150 | O11: 8732150 | P11: =+SUM(E11:O11) -> 94969800 | Q11: =+O11-N11 -> -6135000 | R11: =+IFERROR((O11-N11)/N11,0) -> -0.41265475 | S11: 20450 | T11: =P11/S11 -> 4644 | U11: =T11/$V$7 -> 0.0091306964
C12: QUIMICO FLOCULANTE PARA TRATAMIENTO DE AGUA (Anionico) | D12: kg | E12: 4823610 | F12: 9236700 | G12: 4002570 | H12: 6157800 | I12: 4536246 | J12: 1334190 | K12: 7081470 | L12: 4823610 | M12: 4762032 | N12: 4018990.8 | O12: 5788332 | P12: =+SUM(E12:O12) -> 56565551 | Q12: =+O12-N12 -> 1769341.2 | R12: =+IFERROR((O12-N12)/N12,0) -> 0.44024515 | S12: 20526 | T12: =P12/S12 -> 2755.8 | U12: =T12/$V$7 -> 0.0054182543
C13: QUIMICO COAGULANTE PARA TRATAMIENTO DE AGUA (Coagulante) | D13: kg | E13: 30945388 | F13: 138960020 | G13: 53367206 | H13: 49252534 | I13: 73118530 | J13: 21907484 | K13: 53437955 | L13: 46067706 | M13: 57560488 | N13: 59429160 | O13: 34878134 | P13: =+SUM(E13:O13) -> 618924605 | Q13: =+O13-N13 -> -24551026 | R13: =+IFERROR((O13-N13)/N13,0) -> -0.41311413 | S13: 2246 | T13: =P13/S13 -> 275567.5 | U13: =T13/$V$7 -> 0.54180085
C14: QUIMICO COAGULANTE PARA TRATAMIENTO DE AGUA (Decolorante) | D14: kg | E14: 159385590 | F14: 153612160 | G14: 135150158 | H14: 164121100 | I14: 151017360 | J14: 101897796 | K14: 170270776 | L14: 109305950 | M14: 151017360 | N14: 131361750 | O14: 140404628 | P14: =+SUM(E14:O14) -> 1567544628 | Q14: =+O14-N14 -> 9042878 | R14: =+IFERROR((O14-N14)/N14,0) -> 0.068839506 | S14: 12974 | T14: =P14/S14 -> 120822 | U14: =T14/$V$7 -> 0.23755146
C15: HIPOCLORITO DE SODIO | D15: kg | E15: 1647000 | F15: 317199.99 | G15: 317199.99 | H15: 317199.99 | I15: 317199.99 | J15: 317199.99 | K15: 317199.99 | L15: 317199.99 | M15: 317199.99 | N15: 317199.99 | O15: 317199.99 | P15: =+SUM(E15:O15) -> 4818999.9 | Q15: =+O15-N15 -> 0 | R15: =+IFERROR((O15-N15)/N15,0) -> 0 | S15: 1298 | T15: =P15/S15 -> 3712.6347 | U15: =T15/$V$7 -> 0.0072995135
C16: SODA CAUSTICA LIQUI48% 90 KL | D16: kg | E16: 449331.6 | F16: 449331.6 | G16: 449331.6 | H16: 449331.6 | I16: 449331.6 | J16: 449331.6 | K16: 449331.6 | L16: 449331.6 | M16: 449331.6 | N16: 449331.6 | O16: 449331.6 | P16: =+SUM(E16:O16) -> 4942647.6 | Q16: =+O16-N16 -> 0 | R16: =+IFERROR((O16-N16)/N16,0) -> 0 | S16: 1862 | T16: =P16/S16 -> 2654.4831 | U16: =T16/$V$8 -> 0.013272416
C17: QUIMICO ANTINCRUSTANTE PARA ÓSMOSIS INVERSA | D17: kg | E17: 9068935.9 | F17: 9068935.9 | G17: 9068935.9 | H17: 9068935.9 | I17: 9068935.9 | J17: 9068935.9 | K17: 9068935.9 | L17: 9068935.9 | M17: 9068935.9 | N17: 9068935.9 | O17: 9068935.9 | P17: =+SUM(E17:O17) -> 99758295 | Q17: =+O17-N17 -> 0 | R17: =+IFERROR((O17-N17)/N17,0) -> 0 | S17: 36239 | T17: =P17/S17 -> 2752.7883 | U17: =T17/$V$8 -> 0.013763942
C18: QUIMICO PARA TRATAMIENTO CIP ALCALINO ÓSMOSIS INVERSA | D18: kg | E18: 543261.04 | F18: 543261.04 | G18: 543261.04 | H18: 543261.04 | I18: 543261.04 | J18: 543261.04 | K18: 543261.04 | L18: 543261.04 | M18: 543261.04 | N18: 543261.04 | O18: 543261.04 | P18: =+SUM(E18:O18) -> 5975871.4 | Q18: =+O18-N18 -> 0 | R18: =+IFERROR((O18-N18)/N18,0) -> 0 | S18: 32490 | T18: =P18/S18 -> 183.92956 | U18: =T18/$V$8 -> 0.00091964781
C19: QUIMICO PARA TRATAMIENTO BIODISPERSANTE ÓMOSIS INVERSA | D19: kg | E19: 6330327.6 | F19: 6330327.6 | G19: 6330327.6 | H19: 6330327.6 | I19: 6330327.6 | J19: 6330327.6 | K19: 6330327.6 | L19: 6330327.6 | M19: 6330327.6 | N19: 6330327.6 | O19: 6330327.6 | P19: =+SUM(E19:O19) -> 69633604 | Q19: =+O19-N19 -> 0 | R19: =+IFERROR((O19-N19)/N19,0) -> 0 | S19: 19160 | T19: =P19/S19 -> 3634.3217 | U19: =T19/$V$8 -> 0.018171608
C20: QUIMICO PARA TRATAMIENTO CIP ACIDO ÓMOSIS INVERSA | D20: Kg | E20: 543261.04 | F20: 543261.04 | G20: 543261.04 | H20: 543261.04 | I20: 543261.04 | J20: 543261.04 | K20: 543261.04 | L20: 543261.04 | M20: 543261.04 | N20: 543261.04 | O20: 543261.04 | P20: =+SUM(E20:O20) -> 5975871.4 | Q20: =+O20-N20 -> 0 | R20: =+IFERROR((O20-N20)/N20,0) -> 0 | S20: 34156 | T20: =P20/S20 -> 174.95818 | U20: =T20/$V$8 -> 0.00087479088
C21: ACIDO CITRICO | D21: ml | E21: 0 | F21: 0 | G21: 527415.29 | H21: 0 | I21: 0 | J21: 527415.29 | K21: 0 | L21: 0 | M21: 527415.29 | O21: 527415.29 | P21: =+SUM(E21:O21) -> 2109661.2 | Q21: =+O21-N21 -> 527415.29 | R21: =+IFERROR((O21-N21)/N21,0) -> 0 | S21: 5200 | T21: =P21/S21 -> 405.70407 | U21: =T21/$V$7 -> 0.00079766595
C22: Subtotal | E22: =SUM(E6:E21) -> 2.7032318e+08 | F22: =SUM(F6:F21) -> 3.594686e+08 | G22: =SUM(G6:G21) -> 2.4825702e+08 | H22: =SUM(H6:H21) -> 3.0570248e+08 | I22: =SUM(I6:I21) -> 3.1679115e+08 | J22: =SUM(J6:J21) -> 1.767384e+08 | K22: =SUM(K6:K21) -> 2.8856438e+08 | L22: =SUM(L6:L21) -> 2.1813912e+08 | ... O22: =SUM(O6:O21) -> 2.4570779e+08 | P22: =+SUM(E22:O22) -> 2.9539896e+09 | Q22: =+O22-N22 -> -3056381.5 | R22: =+IFERROR((O22-N22)/N22,0) -> -0.012286261
B23: Disposición | C23: DISPOSICIÓN DE LODOS | E23: 32990880 | F23: 29812080 | G23: 32990880 | H23: 32990880 | I23: 32990880 | J23: 32990880 | K23: 32990880 | L23: 32990880 | M23: 53422896 | N23: 108517008 | O23: 2530000 | P23: =+SUM(E23:O23) -> 425218144 | Q23: =+O23-N23 -> -105987008 | R23: =+IFERROR((O23-N23)/N23,0) -> -0.97668568 | S23: 96 | U23: 3.4
C24: TRANSPORTE DE LODOS | S24: 600000
C25: LAVADO DE TANQUES - CARCAMOS | E25: 28778200 | F25: 32794000 | G25: 32837500 | H25: 32837500 | I25: 32837500 | J25: 32837500 | K25: 32968000 | L25: 0 | M25: 66081000 | N25: 32939000 | O25: 33142000 | P25: =+SUM(E25:O25) -> 358052200 | Q25: =+O25-N25 -> 203000 | R25: =+IFERROR((O25-N25)/N25,0) -> 0.0061629072 | S25: 290 | T25: 1140000 | U25: 2.5
C26: Subtotal | E26: =SUM(E23:E25) -> 61769080 | F26: =SUM(F23:F25) -> 62606080 | G26: =SUM(G23:G25) -> 65828380 | H26: =SUM(H23:H25) -> 65828380 | I26: =SUM(I23:I25) -> 65828380 | J26: =SUM(J23:J25) -> 65828380 | K26: =SUM(K23:K25) -> 65958880 | L26: =SUM(L23:L25) -> 32990880 | ... O26: =SUM(O23:O25) -> 35672000 | P26: =+SUM(E26:O26) -> 783270344 | Q26: =+O26-N26 -> -105784008 | R26: =+IFERROR((O26-N26)/N26,0) -> -0.74782266
B27: Consumibles | C27: MEMBRANAS DE ÓSMOSIS INVERSA | D27: Und | E27: 0 | F27: 0 | G27: 0 | H27: 0 | I27: 150552000 | J27: 0 | K27: 0 | L27: 0 | M27: 0 | N27: 0 | O27: 0 | P27: =+SUM(E27:O27) -> 150552000 | Q27: =+O27-N27 -> 0 | R27: =+IFERROR((O27-N27)/N27,0) -> 0
C28: MEMBRANAS DE ULTRAFILTRACIÓN | D28: Und | E28: 0 | F28: 0 | G28: 0 | H28: 0 | I28: 0 | J28: 0 | K28: 0 | L28: 0 | M28: 0 | N28: 0 | O28: 0 | P28: =+SUM(E28:O28) -> 0 | Q28: =+O28-N28 -> 0 | R28: =+IFERROR((O28-N28)/N28,0) -> 0
C29: SILICA GEL | D29: Und | E29: 0 | F29: 0 | G29: 0 | H29: 0 | I29: 0 | J29: 0 | K29: 0 | L29: 0 | M29: 0 | N29: 0 | O29: 0 | P29: =+SUM(E29:O29) -> 0 | Q29: =+O29-N29 -> 0 | R29: =+IFERROR((O29-N29)/N29,0) -> 0
C30: CUBETA PARA ESPECTROFOTÓMETRO | D30: Und | E30: 0 | F30: 0 | G30: 0 | H30: 0 | I30: 0 | J30: 0 | K30: 0 | L30: 0 | M30: 0 | N30: 0 | O30: 0 | P30: =+SUM(E30:O30) -> 0 | Q30: =+O30-N30 -> 0 | R30: =+IFERROR((O30-N30)/N30,0) -> 0
C31: EMBUDO | D31: Und | E31: 0 | F31: 0 | G31: 0 | H31: 0 | I31: 0 | J31: 0 | K31: 0 | L31: 0 | M31: 0 | N31: 200000 | O31: 0 | P31: =+SUM(E31:O31) -> 200000 | Q31: =+O31-N31 -> -200000 | R31: =+IFERROR((O31-N31)/N31,0) -> -1
C32: CONO | D32: Und | E32: 0 | F32: 0 | G32: 0 | H32: 0 | I32: 0 | J32: 0 | K32: 0 | L32: 0 | M32: 0 | N32: 648000 | O32: 0 | P32: =+SUM(E32:O32) -> 648000 | Q32: =+O32-N32 -> -648000 | R32: =+IFERROR((O32-N32)/N32,0) -> -1
C33: FRASCO | D33: Und | E33: 0 | F33: 0 | G33: 0 | H33: 0 | I33: 0 | J33: 125858.29 | K33: 0 | L33: 0 | M33: 0 | N33: 0 | O33: 0 | P33: =+SUM(E33:O33) -> 125858.29 | Q33: =+O33-N33 -> 0 | R33: =+IFERROR((O33-N33)/N33,0) -> 0
C34: CARTUCHO | D34: Und | E34: 1925410 | F34: 3209016.7 | G34: 287700 | H34: 1444057.5 | I34: 1399370.1 | J34: 3498425.2 | K34: 1706617.8 | L34: 2901250.3 | M34: 6776050.6 | N34: 7623057 | O34: 5082038 | P34: =+SUM(E34:O34) -> 35852993 | Q34: =+O34-N34 -> -2541019 | R34: =+IFERROR((O34-N34)/N34,0) -> -0.33333333
C35: FILTRO | D35: Und | E35: 0 | F35: 0 | G35: 0 | H35: 143706 | I35: 0 | J35: 9813067.6 | K35: 0 | L35: 0 | M35: 1495881.6 | N35: 558000 | O35: 1834000 | P35: =+SUM(E35:O35) -> 13844655 | Q35: =+O35-N35 -> 1276000 | R35: =+IFERROR((O35-N35)/N35,0) -> 2.2867384
C36: CEPILLO GRATA EN BRONCE | D36: Und | E36: 0 | F36: 0 | G36: 0 | H36: 7800 | I36: 0 | J36: 0 | K36: 0 | L36: 0 | M36: 0 | N36: 0 | O36: 0 | P36: =+SUM(E36:O36) -> 7800 | Q36: =+O36-N36 -> 0 | R36: =+IFERROR((O36-N36)/N36,0) -> 0
C37: PIPETA | D37: Und | E37: 0 | F37: 0 | G37: 0 | H37: 0 | I37: 0 | J37: 0 | K37: 0 | L37: 0 | M37: 0 | N37: 77200 | O37: 0 | P37: =+SUM(E37:O37) -> 77200 | Q37: =+O37-N37 -> -77200 | R37: =+IFERROR((O37-N37)/N37,0) -> -1
C38: JERINGA | D38: Und | E38: 0 | F38: 0 | G38: 0 | H38: 0 | I38: 0 | J38: 0 | K38: 0 | L38: 0 | M38: 0 | N38: 0 | O38: 0 | P38: =+SUM(E38:O38) -> 0 | Q38: =+O38-N38 -> 0 | R38: =+IFERROR((O38-N38)/N38,0) -> 0
C39: CRISOL | D39: Und | E39: 0 | F39: 0 | G39: 0 | H39: 0 | I39: 0 | J39: 0 | K39: 0 | L39: 0 | M39: 0 | N39: 0 | O39: 209346 | P39: =+SUM(E39:O39) -> 209346 | Q39: =+O39-N39 -> 209346 | R39: =+IFERROR((O39-N39)/N39,0) -> 0
C40: MATERIALES VARIOS | D40: Und | E40: 0 | F40: 0 | G40: 0 | H40: 0 | I40: 0 | J40: 0 | K40: 0 | L40: 0 | M40: 0 | N40: 56100 | O40: 0 | P40: =+SUM(E40:O40) -> 56100 | Q40: =+O40-N40 -> -56100 | R40: =+IFERROR((O40-N40)/N40,0) -> -1
C41: Subtotal | E41: =SUM(E27:E40) -> 1925410 | F41: =SUM(F27:F40) -> 3209016.7 | G41: =SUM(G27:G40) -> 287700 | H41: =SUM(H27:H40) -> 1595563.5 | I41: =SUM(I27:I40) -> 1.5195137e+08 | J41: =SUM(J27:J40) -> 13437351 | K41: =SUM(K27:K40) -> 1706617.8 | L41: =SUM(L27:L40) -> 2901250.3 | ... O41: =SUM(O27:O40) -> 7125384 | P41: =+SUM(E41:O41) -> 2.0157395e+08 | Q41: =+O41-N41 -> -2036973 | R41: =+IFERROR((O41-N41)/N41,0) -> -0.22231976
B42: Análisis Laboratorio | C42: DENSIMETRO | D42: Und | E42: 0 | F42: 0 | G42: 0 | H42: 0 | I42: 0 | J42: 0 | K42: 0 | L42: 0 | M42: 0 | N42: 0 | O42: 0 | P42: =+SUM(E42:O42) -> 0 | Q42: =+O42-N42 -> 0 | R42: =+IFERROR((O42-N42)/N42,0) -> 0
C43: HIERRO | D43: Und | E43: 0 | F43: 0 | G43: 0 | H43: 0 | I43: 0 | J43: 0 | K43: 0 | L43: 0 | M43: 0 | N43: 0 | O43: 0 | P43: =+SUM(E43:O43) -> 0 | Q43: =+O43-N43 -> 0 | R43: =+IFERROR((O43-N43)/N43,0) -> 0
C44: DUREZA RB | D44: Und | E44: 0 | F44: 0 | G44: 0 | H44: 0 | I44: 0 | J44: 0 | K44: 0 | L44: 0 | M44: 0 | N44: 0 | O44: 0 | P44: =+SUM(E44:O44) -> 0 | Q44: =+O44-N44 -> 0 | R44: =+IFERROR((O44-N44)/N44,0) -> 0
C45: ERLENMEYER | D45: Und | E45: 0 | F45: 0 | G45: 0 | H45: 0 | I45: 0 | J45: 0 | K45: 0 | L45: 0 | M45: 0 | N45: 0 | O45: 0 | P45: =+SUM(E45:O45) -> 0 | Q45: =+O45-N45 -> 0 | R45: =+IFERROR((O45-N45)/N45,0) -> 0
C46: BEAKER P/LABORATORIO | D46: Und | E46: 0 | F46: 0 | G46: 0 | H46: 0 | I46: 0 | J46: 0 | K46: 0 | L46: 0 | M46: 0 | N46: 0 | O46: 20200 | P46: =+SUM(E46:O46) -> 20200 | Q46: =+O46-N46 -> 20200 | R46: =+IFERROR((O46-N46)/N46,0) -> 0
C47: BURETA LABORATORIO | D47: Und | E47: 0 | F47: 0 | G47: 0 | H47: 0 | I47: 0 | J47: 0 | K47: 0 | L47: 0 | M47: 0 | N47: 182000 | O47: 0 | P47: =+SUM(E47:O47) -> 182000 | Q47: =+O47-N47 -> -182000 | R47: =+IFERROR((O47-N47)/N47,0) -> -1
C48: ACCESORIO | D48: Und | E48: 0 | F48: 0 | G48: 0 | H48: 0 | I48: 0 | J48: 0 | K48: 0 | L48: 0 | M48: 0 | N48: 0 | O48: 0 | P48: =+SUM(E48:O48) -> 0 | Q48: =+O48-N48 -> 0 | R48: =+IFERROR((O48-N48)/N48,0) -> 0
C49: MEDICION DE CALIDAD DE AGUA DE VERTIMIENTO | D49: Und | E49: 0 | F49: 0 | G49: 0 | H49: 0 | I49: 0 | J49: 0 | K49: 0 | L49: 0 | M49: 0 | N49: 0 | O49: 0 | P49: =+SUM(E49:O49) -> 0 | Q49: =+O49-N49 -> 0 | R49: =+IFERROR((O49-N49)/N49,0) -> 0
C50: MEDICIÓN OLORES OFENSIVO | D50: Und | E50: 0 | F50: 0 | G50: 0 | H50: 0 | I50: 0 | J50: 0 | K50: 0 | L50: 0 | M50: 0 | N50: 0 | O50: 0 | P50: =+SUM(E50:O50) -> 0 | Q50: =+O50-N50 -> 0 | R50: =+IFERROR((O50-N50)/N50,0) -> 0
C51: MONITOREO PRESIÓN SONORA | D51: Und | E51: 0 | F51: 0 | G51: 0 | H51: 0 | I51: 0 | J51: 0 | K51: 0 | L51: 0 | M51: 0 | N51: 0 | O51: 740000 | P51: =+SUM(E51:O51) -> 740000 | Q51: =+O51-N51 -> 740000 | R51: =+IFERROR((O51-N51)/N51,0) -> 0
C52: Subtotal | E52: =SUM(E42:E51) -> 0 | F52: =SUM(F42:F51) -> 0 | G52: =SUM(G42:G51) -> 0 | H52: =SUM(H42:H51) -> 0 | L52: =SUM(L42:L51) -> 0 | M52: =SUM(M42:M51) -> 0 | N52: =SUM(N42:N51) -> 182000 | O52: =SUM(O42:O51) -> 760200 | P52: =+SUM(E52:O52) -> 942200 | Q52: =+O52-N52 -> 578200 | R52: =+IFERROR((O52-N52)/N52,0) -> 3.1769231
B53: Sueldos | C53: COORDINADOR Y OPERARIOS | E53: 55946331 | F53: 52346040 | G53: 53032325 | H53: 50338157 | I53: 55358773 | J53: 59021762 | K53: 62486970 | L53: 56207894 | M53: 58136249 | N53: 56192849 | O53: 53997396 | P53: =+SUM(E53:O53) -> 6.1306475e+08 | Q53: =+O53-N53 -> -2195453 | R53: =+IFERROR((O53-N53)/N53,0) -> -0.039069971
C54: OTROS SERVICIOS( Exámenes médicos) | E54: 283417 | F54: 77425.76 | G54: 186922.88 | H54: 150422.88 | I54: 58122.88 | J54: 217122.88 | K54: 100261.18 | L54: 11561.18 | M54: 123961.18 | N54: 11561.18 | O54: 239761.18 | P54: =+SUM(E54:O54) -> 1460540.2 | Q54: =+O54-N54 -> 228200 | R54: =+IFERROR((O54-N54)/N54,0) -> 19.73847
C55: PRUEBAS CARGOS | E55: 0 | F55: 0 | G55: 55000 | H55: 0 | I55: 0 | J55: 0 | K55: 0 | L55: 0 | M55: 0 | N55: 0 | O55: 225000 | P55: =+SUM(E55:O55) -> 280000 | Q55: =+O55-N55 -> 225000 | R55: =+IFERROR((O55-N55)/N55,0) -> 0
C56: DOTACIÓN | E56: 0 | F56: 0 | G56: 18525.04 | H56: 20500 | I56: 175293.22 | J56: 0 | K56: 7773.1 | L56: 1728602.6 | M56: 2990061 | N56: 0 | O56: 0 | P56: =+SUM(E56:O56) -> 4940755 | Q56: =+O56-N56 -> 0 | R56: =+IFERROR((O56-N56)/N56,0) -> 0
C57: Subtotal | E57: =+SUM(E53:E56) -> 56229748 | F57: =+SUM(F53:F56) -> 52423466 | G57: =+SUM(G53:G56) -> 53292773 | H57: =+SUM(H53:H56) -> 50509080 | I57: =+SUM(I53:I56) -> 55592189 | J57: =+SUM(J53:J56) -> 59238885 | K57: =+SUM(K53:K56) -> 62595004 | L57: =+SUM(L53:L56) -> 57948058 | ... O57: =+SUM(O53:O56) -> 54462157 | P57: =+SUM(E57:O57) -> 6.1974604e+08 | Q57: =+O57-N57 -> -1742253 | R57: =+IFERROR((O57-N57)/N57,0) -> -0.030998511
B58: Mantenimiento | C58: CALIBRACIONES | E58: 0 | F58: 15000000 | G58: 0 | H58: 0 | I58: 0 | J58: 0 | K58: 0 | L58: 0 | M58: 0 | N58: 0 | O58: 0 | P58: =+SUM(E58:O58) -> 15000000 | Q58: =+O58-N58 -> 0 | R58: =+IFERROR((O58-N58)/N58,0) -> 0
C59: MANTENIMIENTOS | E59: 17882193 | F59: 0 | G59: 0 | H59: 0 | I59: 6641000 | J59: 0 | K59: 5941884.9 | L59: 7566500 | M59: 10658585 | N59: 19091400 | O59: 0 | P59: =+SUM(E59:O59) -> 67781563 | Q59: =+O59-N59 -> -19091400 | R59: =+IFERROR((O59-N59)/N59,0) -> -1
C60: ALQUILER DE MAQUINARIA | E60: 0 | F60: 0 | G60: 0 | H60: 0 | I60: 0 | J60: 0 | K60: 0 | L60: 0 | M60: 337500 | N60: 0 | O60: 0 | P60: =+SUM(E60:O60) -> 337500 | Q60: =+O60-N60 -> 0 | R60: =+IFERROR((O60-N60)/N60,0) -> 0
C61: MATERIALES MANTENIMIENTO | E61: 13369613 | F61: 10553490 | G61: 13369613 | H61: 13369613 | I61: 13369613 | J61: 13369613 | K61: 11037441 | L61: 2296666.6 | M61: 3485339.9 | N61: 8501356.8 | O61: 19923499 | P61: =+SUM(E61:O61) -> 1.2264586e+08 | Q61: =+O61-N61 -> 11422142 | R61: =+IFERROR((O61-N61)/N61,0) -> 1.3435669
C62: OTROS MATERIALES MANTENIMIENTO | E62: 165019.92 | F62: 41624 | G62: 180192.31 | H62: 199333.33 | I62: 1301352.5 | J62: 2544360.7 | K62: 9807.82 | L62: 48484.95 | M62: 189472.66 | N62: 200900 | O62: 163305.24 | P62: =+SUM(E62:O62) -> 5043853.5 | Q62: =+O62-N62 -> -37594.76 | R62: =+IFERROR((O62-N62)/N62,0) -> -0.18713171
C63: Subtotal | E63: =SUM(E58:E62) -> 31416825 | F63: =SUM(F58:F62) -> 25595114 | G63: =SUM(G58:G62) -> 13549805 | H63: =SUM(H58:H62) -> 13568946 | I63: =SUM(I58:I62) -> 21311965 | J63: =SUM(J58:J62) -> 15913973 | K63: =SUM(K58:K62) -> 16989134 | L63: =SUM(L58:L62) -> 9911651.5 | ... O63: =SUM(O58:O62) -> 20086804 | P63: =+SUM(E63:O63) -> 2.1080877e+08 | Q63: =+O63-N63 -> -7706853 | R63: =+IFERROR((O63-N63)/N63,0) -> -0.2772882
B64: Consumo Eléctrico | C64: CONSUMO ELÉCTRICO PTAR | D64: kW | E64: 2494512.4 | F64: 2318023.4 | G64: 2674664.8 | H64: 2299429.7 | I64: 2531617.2 | J64: 3061053.9 | K64: 22206978 | L64: 14080556 | M64: 22728395 | N64: 37010944 | O64: 21822672 | P64: =+SUM(E64:O64) -> 1.3322885e+08 | Q64: =+O64-N64 -> -15188272 | R64: =+IFERROR((O64-N64)/N64,0) -> -0.41037245 | S64: =P64/11 -> 12111713 | T64: =S64*12 -> 1.4534056e+08
C65: Subtotal | E65: =SUM(E64:E64) -> 2494512.4 | F65: =SUM(F64:F64) -> 2318023.4 | G65: =SUM(G64:G64) -> 2674664.8 | H65: =SUM(H64:H64) -> 2299429.7 | I65: =SUM(I64:I64) -> 2531617.2 | J65: =SUM(J64:J64) -> 3061053.9 | K65: =SUM(K64:K64) -> 22206978 | L65: =SUM(L64:L64) -> 14080556 | ... O65: =SUM(O64:O64) -> 21822672 | P65: =+SUM(E65:O65) -> 1.3322885e+08 | Q65: =+O65-N65 -> -15188272 | R65: =+IFERROR((O65-N65)/N65,0) -> -0.41037245
B66: Consumo Agua Potable | C66: PREPARACIÓN FLOCULANTE | D66: m3 | E66: 73526.21 | F66: 41728.23 | G66: 101169.58 | H66: 62509.65 | I66: 69585.3 | J66: 89292.7 | K66: 62141.67 | L66: 70182.73 | M66: 41924.08 | N66: 39801.3 | O66: 59234.85 | P66: =+SUM(E66:O66) -> 711096.3 | Q66: =+O66-N66 -> 19433.55 | R66: =+IFERROR((O66-N66)/N66,0) -> 0.4882642
C67: ASEO Y VIGILANCIA | E67: 115098.92 | F67: 145078.25 | G67: 165137.68 | H67: 151009.91 | I67: 143940 | J67: 150406.93 | K67: 3418557.4 | L67: 3245243.1 | M67: 3322544.4 | N67: 3222377.8 | O67: 3360618.5 | P67: =+SUM(E67:O67) -> 17440013 | Q67: =+O67-N67 -> 138240.63 | R67: =+IFERROR((O67-N67)/N67,0) -> 0.042900192
C68: Subtotal | E68: =SUM(E66:E67) -> 188625.13 | F68: =SUM(F66:F67) -> 186806.48 | G68: =SUM(G66:G67) -> 266307.26 | H68: =SUM(H66:H67) -> 213519.56 | I68: =SUM(I66:I67) -> 213525.3 | J68: =SUM(J66:J67) -> 239699.63 | K68: =SUM(K66:K67) -> 3480699.1 | L68: =SUM(L66:L67) -> 3315425.8 | ... O68: =SUM(O66:O67) -> 3419853.3 | P68: =+SUM(E68:O68) -> 18151109 | Q68: =+O68-N68 -> 157674.18 | R68: =+IFERROR((O68-N68)/N68,0) -> 0.048334004
B69: Inversión | C69: INVERSIÓN DYE | E69: 0 | F69: 0 | G69: 0 | P69: =+SUM(E69:O69) -> 0 | Q69: =+O69-N69 -> 0 | R69: =+IFERROR((O69-N69)/N69,0) -> 0
C70: LICENCIA DE CONSTRUCCIÓN | E70: 0 | F70: 0 | G70: 0 | P70: =+SUM(E70:O70) -> 0 | Q70: =+O70-N70 -> 0 | R70: =+IFERROR((O70-N70)/N70,0) -> 0
C71: INVERSIÓN JABONOSAS | E71: 0 | F71: 0 | G71: 0 | P71: =+SUM(E71:O71) -> 0 | Q71: =+O71-N71 -> 0 | R71: =+IFERROR((O71-N71)/N71,0) -> 0
C72: INVERSIÓN LAVANDERÍA | E72: 0 | F72: 0 | G72: 0 | P72: =+SUM(E72:O72) -> 0 | Q72: =+O72-N72 -> 0 | R72: =+IFERROR((O72-N72)/N72,0) -> 0
C73: INVERSIÓN PTAR | E73: 0 | F73: 0 | G73: 0 | P73: =+SUM(E73:O73) -> 0 | Q73: =+O73-N73 -> 0 | R73: =+IFERROR((O73-N73)/N73,0) -> 0
C74: PROYECTO TI | E74: 133657.54 | F74: 579291.99 | G74: 5919192.9 | H74: 584650.28 | I74: 1726062.1 | J74: 1035567.9 | K74: 1132028 | L74: 1088278.9 | M74: 1241053.9 | N74: 632607.48 | O74: 587029.24 | P74: =+SUM(E74:O74) -> 14659420 | Q74: =+O74-N74 -> -45578.24 | R74: =+IFERROR((O74-N74)/N74,0) -> -0.072048215
C75: Subtotal | E75: =SUM(E69:E74) -> 133657.54 | F75: =SUM(F69:F74) -> 579291.99 | G75: =SUM(G69:G74) -> 5919192.9 | H75: =SUM(H69:H74) -> 584650.28 | I75: =SUM(I69:I74) -> 1726062.1 | J75: =SUM(J69:J74) -> 1035567.9 | K75: =SUM(K69:K74) -> 1132028 | L75: =SUM(L69:L74) -> 1088278.9 | ... O75: =SUM(O69:O74) -> 587029.24 | P75: =+SUM(E75:O75) -> 14659420 | Q75: =+O75-N75 -> -45578.24 | R75: =+IFERROR((O75-N75)/N75,0) -> -0.072048215
B76: Honorarios | C76: HONORARIOS | E76: 0 | F76: 0 | G76: 0 | H76: 0 | I76: 0 | J76: 0 | K76: 0 | L76: 600000 | M76: 10103000 | N76: 10500000 | O76: 0 | P76: =+SUM(E76:O76) -> 21203000 | Q76: =+O76-N76 -> -10500000 | R76: =+IFERROR((O76-N76)/N76,0) -> -1
B77: Seguros | C77: SEGUROS | E77: 5598290.5 | F77: 5607530.5 | G77: 12274479 | H77: 126023.34 | I77: 6289572.7 | J77: 6490463.2 | K77: 5905734.3 | L77: 6228704.2 | M77: 6228704.1 | N77: 6268704.2 | O77: 5944031.7 | P77: =+SUM(E77:O77) -> 66962238 | Q77: =+O77-N77 -> -324672.42 | R77: =+IFERROR((O77-N77)/N77,0) -> -0.051792589
B78: Transporte y viajes | C78: TRANSPORTE-ASESORIAS | E78: 0 | F78: 4195 | G78: 34693 | H78: 18658 | I78: 0 | J78: 0 | K78: 0 | L78: 0 | M78: 0 | N78: 0 | O78: 0 | P78: =+SUM(E78:O78) -> 57546 | Q78: =+O78-N78 -> 0 | R78: =+IFERROR((O78-N78)/N78,0) -> 0
B79: Diversos | C79: DIVERSOS | F79: 0 | G79: 0 | H79: 0 | I79: 0 | J79: 0 | K79: 0 | L79: 0 | M79: 0 | N79: 0 | O79: 0 | P79: =+SUM(E79:O79) -> 0 | Q79: =+O79-N79 -> 0 | R79: =+IFERROR((O79-N79)/N79,0) -> 0
B80: Gestión Humana | C80: GESTION HUMANA | E80: 18485.51 | F80: 235065.62 | G80: 6704.71 | H80: 31613.51 | I80: 19176.68 | J80: 19295.16 | K80: 29326.07 | L80: 60008.75 | M80: 60262.15 | N80: 573792.17 | O80: 50503.72 | P80: =+SUM(E80:O80) -> 1104234 | Q80: =+O80-N80 -> -523288.45 | R80: =+IFERROR((O80-N80)/N80,0) -> -0.91198256
B81: Arriendos | C81: ARRIENDO Y ADMINISTRACIÓN | E81: 3181158 | F81: 3195479.8 | G81: 3346578.1 | H81: 3346578.1 | I81: 3346578.1 | J81: 3346578.1 | K81: 3346578.1 | L81: 3346578.1 | M81: 3346578.1 | N81: 3346578.1 | O81: 3346578.1 | P81: =+SUM(E81:O81) -> 36495841 | Q81: =+O81-N81 -> 0 | R81: =+IFERROR((O81-N81)/N81,0) -> -1.391455e-16
B82: Ambiental | C82: SEGURIDAD AMBIENTAL | E82: 151795.13 | F82: 0 | G82: 0 | H82: 0 | I82: 268900 | J82: 24356.68 | K82: 54356.68 | L82: 0 | M82: 2805190 | N82: 0 | O82: 0 | P82: =+SUM(E82:O82) -> 3304598.5 | Q82: =+O82-N82 -> 0 | R82: =+IFERROR((O82-N82)/N82,0) -> 0
B83: Obsequios | C83: OBSEQUIOS GH | E83: 0 | F83: 1015.48 | G83: 28080 | H83: 0 | I83: 0 | J83: 413.86 | K83: 44928 | L83: 0 | M83: 0 | N83: 0 | O83: 419.53 | P83: =+SUM(E83:O83) -> 74856.87 | Q83: =+O83-N83 -> 419.53 | R83: =+IFERROR((O83-N83)/N83,0) -> 0
B84: Control | C84: CONTROL DE PLAGAS | E84: 0 | F84: 0 | G84: 0 | H84: 44453.5 | I84: 18382 | J84: 0 | K84: 3685.5 | L84: 26218.92 | M84: 0 | N84: 0 | O84: 33855.64 | P84: =+SUM(E84:O84) -> 126595.56 | Q84: =+O84-N84 -> 33855.64 | R84: =+IFERROR((O84-N84)/N84,0) -> 0
B85: Aseo y cafeteria | C85: ELEMENTOS DE ASEO Y CAFETERIA | E85: 0 | F85: 3545.3 | G85: 3545.3 | H85: 7576.8 | I85: 16130.96 | J85: 10428.33 | K85: 11675.73 | L85: 4859.88 | M85: 0 | N85: 2557.83 | O85: 9719.75 | P85: =+SUM(E85:O85) -> 70039.88 | Q85: =+O85-N85 -> 7161.92 | R85: =+IFERROR((O85-N85)/N85,0) -> 2.7999984
B86: Papeleria | C86: ELEMENTOS DE PAPELERIA | E86: 0 | F86: 0 | G86: 0 | H86: 0 | I86: 0 | J86: 0 | K86: 0 | L86: 0 | M86: 0 | N86: 0 | O86: 0 | P86: =+SUM(E86:O86) -> 0 | Q86: =+O86-N86 -> 0 | R86: =+IFERROR((O86-N86)/N86,0) -> 0
B87: Servicio contraprestacion | C87: SONIDO | E87: 175.5 | F87: 245.7 | G87: 245.7 | H87: 245.7 | I87: 245.7 | J87: 245.7 | K87: 354.9 | L87: 354.9 | M87: 253.5 | N87: 253.5 | O87: 253.5 | P87: =+SUM(E87:O87) -> 2874.3 | Q87: =+O87-N87 -> 0 | R87: =+IFERROR((O87-N87)/N87,0) -> 0
C88: Subtotal | E88: =+SUM(E76:E87) -> 8949904.7 | F88: =SUM(F76:F87) -> 9047077.3 | G88: =SUM(G76:G87) -> 15694326 | H88: =SUM(H76:H87) -> 3575149 | I88: =SUM(I76:I87) -> 9958986.2 | J88: =SUM(J76:J87) -> 9891781 | K88: =SUM(K76:K87) -> 9396639.3 | L88: =SUM(L76:L87) -> 10266725 | M88: =SUM(M76:M87) -> 22543988 | ... O88: =SUM(O76:O87) -> 9385362 | P88: =+SUM(E88:O88) -> 1.2940182e+08 | Q88: =+O88-N88 -> -11306524 | R88: =+IFERROR((O88-N88)/N88,0) -> -0.54642307
B89: Depreciación | C89: CONSTRUCCIONES Y EDIFICACIONES | E89: 8574247.3 | F89: 8574246.7 | G89: 8574247.3 | H89: -406628.23 | I89: 6329028.6 | J89: 9219329.7 | K89: 8682435 | L89: 1946200.4 | M89: 8681857.4 | N89: 4191419.3 | O89: 6436638.6 | P89: =+SUM(E89:O89) -> 70803022 | Q89: =+O89-N89 -> 2245219.3 | R89: =+IFERROR((O89-N89)/N89,0) -> 0.53567042
C90: DERECHOS DE USO EDIFICACIONES | E90: 1925534.6 | F90: 1925534.6 | G90: 1284351.2 | H90: 1284351.2 | I90: 1284351.2 | J90: 1284351.2 | K90: 1284351.2 | L90: 1284351.2 | M90: 1284351.2 | N90: 1284351.2 | O90: 1284351.2 | P90: =+SUM(E90:O90) -> 15410230 | Q90: =+O90-N90 -> 0 | R90: =+IFERROR((O90-N90)/N90,0) -> 0
C91: OBRA CIVIL | E91: 10990060 | F91: 10990060 | G91: 10990060 | H91: 11322215 | I91: 11322215 | J91: 11635143 | K91: 11098248 | L91: 11097670 | M91: 11097670 | N91: 11097670 | O91: 11097670 | P91: =+SUM(E91:O91) -> 1.2273868e+08 | Q91: =+O91-N91 -> 0 | R91: =+IFERROR((O91-N91)/N91,0) -> 0
C92: EQUIPO DE OFICINA | E92: 1349525.2 | F92: 1356172.8 | G92: 1419958.4 | H92: 1412337.2 | I92: 3132365.1 | J92: 3132363.2 | K92: 3132365.1 | L92: 3132363.2 | M92: 3132365.1 | N92: 4852389.8 | O92: 4803989.1 | P92: =+SUM(E92:O92) -> 30856194 | Q92: =+O92-N92 -> -48400.73 | R92: =+IFERROR((O92-N92)/N92,0) -> -0.009974617
C93: MAQUINARIA Y EQUIPO 1 | E93: 0 | F93: 0 | G93: 0 | H93: 0 | I93: 0 | J93: 0 | K93: 0 | L93: 0 | M93: 0 | N93: 0 | O93: 0 | P93: =+SUM(E93:O93) -> 0 | Q93: =+O93-N93 -> 0 | R93: =+IFERROR((O93-N93)/N93,0) -> 0
C94: MAQUINARIA Y EQUIPO | E94: 1.8581078e+08 | F94: 1.9148905e+08 | G94: 1.8864992e+08 | H94: 1.8865368e+08 | I94: 1.8838034e+08 | J94: 1.887579e+08 | K94: 2.6667354e+08 | L94: 2.0413882e+08 | M94: 2.0585885e+08 | N94: 2.0585885e+08 | O94: 2.0585885e+08 | P94: =+SUM(E94:O94) -> 2.2201306e+09 | Q94: =+O94-N94 -> 5.9700003 | R94: =+IFERROR((O94-N94)/N94,0) -> 2.9000455e-08
C95: Subtotal | E95: =SUM(E89:E94) -> 2.0865015e+08 | F95: =SUM(F89:F94) -> 2.1433507e+08 | G95: =SUM(G89:G94) -> 2.1091854e+08 | H95: =SUM(H89:H94) -> 2.0226595e+08 | I95: =SUM(I89:I94) -> 2.104483e+08 | J95: =SUM(J89:J94) -> 2.1402909e+08 | K95: =SUM(K89:K94) -> 2.9087094e+08 | L95: =SUM(L89:L94) -> 2.2159941e+08 | ... O95: =SUM(O89:O94) -> 2.294815e+08 | P95: =+SUM(E95:O95) -> 2.4599387e+09 | Q95: =+O95-N95 -> 2196824.6 | R95: =+IFERROR((O95-N95)/N95,0) -> 0.0096655199
B96: Agua acueducto | C96: m3 ACUEDUCTO | D96: m3 | E96: =+E108-E99-E105-E100 -> 19209 | F96: =+F108-F99-F105-F100 -> 20671.752 | G96: =+G108-G99-G105-G100 -> 17078.157 | H96: =+H108-H99-H106-H100 -> 18924.529 | I96: =+I108-I99-I106-I100 -> 15174.373 | J96: =+J108-J99-J106-J100 -> 26086.722 | K96: =+K108-K99-K106-K101 -> 27760 | L96: =+L108-L99-L106-L101 -> 29121 | M96: =+M108-M99-M106-M101 -> 16446 | N96: =+N108-N99-N106-N101 -> 23569 | O96: =+O108-O99-O106-O101 -> 19359 | P96: =+SUM(E96:O96) -> 233399.53 | Q96: =+O96-N96 -> -4210 | R96: =+IFERROR((O96-N96)/N96,0) -> -0.17862446
C97: COSTO m3 AGUA ACUEDUCTO | D97: m3 | E97: =10021*E96 -> 192493389 | F97: =10183*F96 -> 2.1050045e+08 | G97: =10183*G96 -> 1.7390687e+08 | H97: =10183*H96 -> 1.9270848e+08 | I97: =10183*I96 -> 1.5452064e+08 | J97: =10578*J96 -> 2.7594534e+08 | K97: =10608*K96 -> 294478080 | L97: =10577*L96 -> 308012817 | M97: =10834*M96 -> 178175964 | N97: =10945*N96 -> 257962705 | O97: =10945*O96 -> 211884255 | P97: =+SUM(E97:O97) -> 2.450589e+09 | Q97: =+O97-N97 -> -46078450 | R97: =+IFERROR((O97-N97)/N97,0) -> -0.17862446
B98: Agua carrotanque | C98: COSTO m3 AGUA CARROTANQUE | D98: m3 | E98: 30724200 | F98: 69945500 | G98: 59760000 | H98: 53185200 | I98: 63827600 | J98: 65029600 | K98: 81788000 | L98: 5283200 | M98: 67221100 | N98: 2540000 | O98: 1016000 | P98: =+SUM(E98:O98) -> 500320400 | Q98: =+O98-N98 -> -1524000 | R98: =+IFERROR((O98-N98)/N98,0) -> -0.6
C99: m3 CARROTANQUE | D99: m3 | E99: =E98/11700 -> 2626 | F99: =F98/11700 -> 5978.2479 | G99: =G98/12100 -> 4938.843 | H99: =H98/12100 -> 4395.4711 | I99: =I98/12062 -> 5291.6266 | J99: =J98/12062 -> 5391.2784 | K99: =K98/12700 -> 6440 | L99: =L98/12700 -> 416 | M99: =M98/12700 -> 5293 | N99: =N98/12700 -> 200 | O99: =O98/12700 -> 80 | P99: =+SUM(E99:O99) -> 41050.467 | Q99: =+O99-N99 -> -120 | R99: =+IFERROR((O99-N99)/N99,0) -> -0.6
B100: Agua PTAP | C100: m3 PLANTA PTAP (Tratados) | D100: m3 | E100: 7402 | F100: 6965 | G100: 8080 | H100: 7039 | I100: 9290 | J100: 1726 | K100: 8873 | L100: 9053 | M100: 7395 | N100: 8753 | O100: 8753 | P100: =+SUM(E100:O100) -> 83329 | Q100: =+O100-N100 -> 0 | R100: =+IFERROR((O100-N100)/N100,0) -> 0
C101: m3 PLANTA PTAP (Recuperados) | D101: m3 | E101: 7402 | F101: 6965 | G101: 8080 | H101: 7039 | I101: 9290 | J101: 1726 | K101: 5958 | L101: 7100 | M101: 5045 | N101: 5799 | O101: 5799 | P101: =+SUM(E101:O101) -> 70203 | Q101: =+O101-N101 -> 0 | R101: =+IFERROR((O101-N101)/N101,0) -> 0
C102: COSTO m3 PTAP | D102: m3 | E102: =+E100*382 -> 2827564 | F102: =+F100*932 -> 6491380 | G102: =+G100*2868 -> 23173440 | H102: =+H100*2198 -> 15471722 | I102: =+I100*3180 -> 29542200 | J102: =+J100*14203 -> 24514378 | K102: =+K100*2612 -> 23176276 | L102: =+L100*5966 -> 54010198 | M102: =+M100*1851 -> 13688145 | N102: =+N100*2528 -> 22127584 | O102: =+O100*2168 -> 18976504 | P102: =+SUM(E102:O102) -> 233999391 | Q102: =+O102-N102 -> -3151080 | R102: =+IFERROR((O102-N102)/N102,0) -> -0.14240506
...

Sheet PROYEC COSTO M3 PERMODA BOGOTA
B2: CONSUMO TOTAL (M3) PLAN MAESTRO BOGOTA - CON RECIRCULACIÓN OSMOSIS INVERSA Y PTAP (Pozo Subterraneo) | D2: Volumen requerido por Producción (M3) | E2: Porcentaje
D3: ='PLAN MAESTRO BOGOTA RECIRCU'!AG3 -> 379147.92 | E3: 1 | F3: $/m3 | G3: $ Total
B4: TRATAMIENTO DE AGUA RESIDUAL | C4: PTAR (Costo de Tratamiento hasta Fase 2 - Cumplimiento Ambiental) OPEX Con depreciación | D4: =D3 -> 379147.92 | E4: 1 | F4: ='PLAN MAESTRO BOGOTA RECIRCU'!AP4 -> 11828.253 | G4: =D4*F4 -> 4.4846576e+09
B5: FUENTES DE ABASTECIMIENTO | C5: OSMOSIS INVERSA (Costo procesamiento de agua permeada para planta de producción) | D5: =D4*0.65 -> 246446.14 | E5: =(D5/D3) -> 0.65 | F5: ='PLAN MAESTRO BOGOTA RECIRCU'!AP5 -> 3602.7536 | G5: =D5*F5 -> 8.8788474e+08
C6: PTAP - OPEX Con depreciación | D6: ='PLAN MAESTRO BOGOTA RECIRCU'!AN6 -> 95848.197 | E6: =(D6/D3) -> 0.25279896 | F6: ='PLAN MAESTRO BOGOTA RECIRCU'!AP6 -> 5622.9088 | G6: =D6*F6 -> 5.3894567e+08
C7: ACUEDUCTO | D7: =D4-D5-D6-D8 -> 34615.622 | E7: =(D7/D3) -> 0.091298464 | F7: ='PLAN MAESTRO BOGOTA RECIRCU'!AP7 -> 10763 | G7: =D7*F7 -> 3.7256794e+08
C8: CARRO TANQUES | D8: ='PLAN MAESTRO BOGOTA RECIRCU'!AN8 -> 2237.9511 | E8: =(D8/D3) -> 0.0059025805 | F8: ='PLAN MAESTRO BOGOTA RECIRCU'!AP8 -> 12700 | G8: =D8*F8 -> 28421979
F9: TOTAL | G9: =SUM(G4:G8) -> 6.312478e+09
D10: COSTO DE TRATAMIENTO DE AGUA RESIDUAL | F10: TOTAL ($/Año) | G10: =G4 -> 4.4846576e+09
D11: INDICADOR POR M3 TRATADO AGUA RESIDUAL | F11: $/M3 | G11: =G10/D4 -> 11828.253
D12: COSTO DE SUMINISTRO DE AGUA A PROCESO TEXTIL | F12: TOTAL ($/Año) | G12: =SUM(G5:G8) -> 1.8278203e+09
D13: INDICADOR POR M3 DE AGUA A PROCESO TEXTIL | F13: $/m3 | G13: =G12/D3 -> 4820.8635
D14: COSTO TOTAL M3 PERMODA (Tratado + Fuentes) | F14: TOTAL ($/Año) | G14: =G10+G12 -> 6.312478e+09
D15: INDICADOR PERMODA BOGOTA (Tratamiento + Suministro) | F15: $/M3 | G15: =G14/D3 -> 16649.117
B17: CONSUMO TOTAL (M3) PLAN MAESTRO BOGOTA - CON RECIRCULACIÓN OSMOSIS INVERSA Y SIN PTAP (Pozo Subterraneo) | D17: Volumen requerido por Producción (M3) | E17: Porcentaje
D18: =D3 -> 379147.92 | E18: 1 | F18: $/m3 | G18: $ Total
B19: TRATAMIENTO DE AGUA RESIDUAL | C19: PTAR (Costo de Tratamiento hasta Fase 2 - Cumplimiento Ambiental) OPEX Con depreciación | D19: =D18 -> 379147.92 | E19: 1 | F19: =F4 -> 11828.253 | G19: =D19*F19 -> 4.4846576e+09
B20: FUENTES DE ABASTECIMIENTO | C20: OSMOSIS INVERSA (Costo procesamiento de agua permeada para planta de producción) | D20: =D5 -> 246446.14 | E20: =(D20/D18) -> 0.65 | F20: =F5 -> 3602.7536 | G20: =D20*F20 -> 8.8788474e+08
C21: PTAP - OPEX Con depreciación | D21: ='PLAN MAESTRO BOGOTA RECIRCU'!AN21 -> 0 | E21: =(D21/D18) -> 0 | F21: =F6 -> 5622.9088 | G21: =D21*F21 -> 0
C22: ACUEDUCTO | D22: =D18-D20-D23 -> 130463.82 | E22: =(D22/D18) -> 0.34409742 | F22: =F7 -> 10763 | G22: =D22*F22 -> 1.4041821e+09
C23: CARRO TANQUES | D23: =D8 -> 2237.9511 | E23: =(D23/D18) -> 0.0059025805 | F23: =F8 -> 12700 | G23: =D23*F23 -> 28421979
F24: TOTAL | G24: =SUM(G19:G23) -> 6.8051464e+09
D25: COSTO DE TRATAMIENTO DE AGUA RESIDUAL | F25: TOTAL ($/Año) | G25: =G19 -> 4.4846576e+09
D26: INDICADOR POR M3 TRATADO AGUA RESIDUAL | F26: $/M3 | G26: =G25/D19 -> 11828.253
D27: COSTO DE SUMINISTRO DE AGUA A PROCESO TEXTIL | F27: TOTAL ($/Año) | G27: =SUM(G20:G23) -> 2.3204888e+09
D28: INDICADOR POR M3 DE AGUA A PROCESO TEXTIL | F28: $/m3 | G28: =G27/D18 -> 6120.2732
D29: COSTO TOTAL M3 PERMODA (Tratado + Fuentes) | F29: TOTAL ($/Año) | G29: =G25+G27 -> 6.8051464e+09
D30: INDICADOR PERMODA BOGOTA (Tratamiento + Suministro) | F30: $/M3 | G30: =G29/D18 -> 17948.527
B32: CONSUMO TOTAL (M3) PLAN MAESTRO BOGOTA - CON PTAP (Pozo Subterraneo) Y SIN RECIRCULACIÓN DE OSMOSIS INVERSA | D32: Volumen requerido por Producción (M3) | E32: Porcentaje
D33: =D3 -> 379147.92 | E33: 1 | F33: $/m3 | G33: $ Total
B34: TRATAMIENTO DE AGUA RESIDUAL | C34: PTAR (Costo de Tratamiento hasta Fase 2 - Cumplimiento Ambiental) OPEX Con depreciación | D34: =D33 -> 379147.92 | E34: 1 | F34: =F4 -> 11828.253 | G34: =D34*F34 -> 4.4846576e+09
B35: FUENTES DE ABASTECIMIENTO | C35: OSMOSIS INVERSA (Costo procesamiento de agua permeada para planta de producción) | D35: ='PLAN MAESTRO BOGOTA RECIRCU'!AN17 -> 0 | E35: =(D35/D33) -> 0 | F35: =F5 -> 3602.7536 | G35: =D35*F35 -> 0
C36: PTAP - OPEX Con depreciación | D36: ='PLAN MAESTRO BOGOTA RECIRCU'!AN18 -> 95848.197 | E36: =(D36/D33) -> 0.25279896 | F36: =F6 -> 5622.9088 | G36: =D36*F36 -> 5.3894567e+08
C37: ACUEDUCTO | D37: ='PLAN MAESTRO BOGOTA RECIRCU'!AN19 -> 230400 | E37: =(D37/D33) -> 0.6076784 | F37: =F7 -> 10763 | G37: =D37*F37 -> 2479795200
C38: CARRO TANQUES | D38: ='PLAN MAESTRO BOGOTA RECIRCU'!AN20 -> 52899.718 | E38: =(D38/D33) -> 0.13952264 | F38: =F8 -> 12700 | G38: =D38*F38 -> 6.7182642e+08
F39: TOTAL | G39: =SUM(G34:G38) -> 8.1752249e+09
D40: COSTO DE TRATAMIENTO DE AGUA RESIDUAL | F40: TOTAL ($/Año) | G40: =G34 -> 4.4846576e+09
D41: INDICADOR POR M3 TRATADO AGUA RESIDUAL | F41: $/M3 | G41: =G40/D34 -> 11828.253
D42: COSTO DE SUMINISTRO DE AGUA A PROCESO TEXTIL | F42: TOTAL ($/Año) | G42: =SUM(G35:G38) -> 3.6905673e+09
D43: INDICADOR POR M3 DE AGUA A PROCESO TEXTIL | F43: $/m3 | G43: =G42/D33 -> 9733.8457
D44: COSTO TOTAL M3 PERMODA (Tratado + Fuentes) | F44: TOTAL ($/Año) | G44: =G40+G42 -> 8.1752249e+09
D45: INDICADOR PERMODA BOGOTA (Tratamiento + Suministro) | F45: $/M3 | G45: =G44/D33 -> 21562.099
B47: CONSUMO TOTAL (M3) PLAN MAESTRO BOGOTA - SIN PTAP (Pozo Subterraneo) Y SIN RECIRCULACIÓN DE OSMOSIS INVERSA | D47: Volumen requerido por Producción (M3) | E47: Porcentaje
D48: =D33 -> 379147.92 | E48: 1 | F48: $/m3 | G48: $ Total
B49: TRATAMIENTO DE AGUA RESIDUAL | C49: PTAR (Costo de Tratamiento hasta Fase 2 - Cumplimiento Ambiental) OPEX Con depreciación | D49: =D48 -> 379147.92 | E49: 1 | F49: =F4 -> 11828.253 | G49: =D49*F49 -> 4.4846576e+09
B50: FUENTES DE ABASTECIMIENTO | C50: OSMOSIS INVERSA (Costo procesamiento de agua permeada para planta de producción) | D50: ='PLAN MAESTRO BOGOTA RECIRCU'!AN34 -> 0 | E50: =(D50/D48) -> 0 | F50: =F5 -> 3602.7536 | G50: =D50*F50 -> 0
C51: PTAP - OPEX Con depreciación | D51: ='PLAN MAESTRO BOGOTA RECIRCU'!AN35 -> 0 | E51: =(D51/D48) -> 0 | F51: =F6 -> 5622.9088 | G51: =D51*F51 -> 0
C52: ACUEDUCTO | D52: ='PLAN MAESTRO BOGOTA RECIRCU'!AN36 -> 230400 | E52: =(D52/D48) -> 0.6076784 | F52: =F7 -> 10763 | G52: =D52*F52 -> 2479795200
C53: CARRO TANQUES | D53: ='PLAN MAESTRO BOGOTA RECIRCU'!AN37 -> 148747.92 | E53: =(D53/D48) -> 0.3923216 | F53: =F8 -> 12700 | G53: =D53*F53 -> 1.8890985e+09
F54: TOTAL | G54: =SUM(G49:G53) -> 8.8535513e+09
D55: COSTO DE TRATAMIENTO DE AGUA RESIDUAL | F55: TOTAL ($/Año) | G55: =G49 -> 4.4846576e+09
D56: INDICADOR POR M3 TRATADO AGUA RESIDUAL | F56: $/M3 | G56: =G55/D49 -> 11828.253
D57: COSTO DE SUMINISTRO DE AGUA A PROCESO TEXTIL | F57: TOTAL ($/Año) | G57: =SUM(G50:G53) -> 4.3688937e+09
D58: INDICADOR POR M3 DE AGUA A PROCESO TEXTIL | F58: $/m3 | G58: =G57/D48 -> 11522.927
D59: COSTO TOTAL M3 PERMODA (Tratado + Fuentes) | F59: TOTAL ($/Año) | G59: =G55+G57 -> 8.8535513e+09
D60: INDICADOR PERMODA BOGOTA (Tratamiento + Suministro) | F60: $/M3 | G60: =G59/D48 -> 23351.18
H62: PROYECCIÓN DE AHORROS
H63: Ahorro Global ($/Año) | I63: Ahorro por m3 ($/m3) | J63: OBSERVACIONES
B64: MODELO 1 | C64: CONSUMO TOTAL (M3) PLAN MAESTRO BOGOTA - CON RECIRCULACIÓN OSMOSIS INVERSA Y PTAP (Pozo Subterraneo) | D64: COSTO TOTAL M3 PERMODA (Tratado + Fuentes) | F64: TOTAL ($/Año) | G64: =G14 -> 6.312478e+09 | H64: =G70-G64 -> 2.5410734e+09 | I64: =G71-G65 -> 6702.0635 | J64: El ahorro proyectado al utilizar el sistema de osmosis inversa y la PTAP se da en este marco, garantizando que las fuentes internas de PERMODA sean representativas y correspondan al 83,5% de suplencia, el resto (16,5%) corresponderián a fuentes externas (15,91% Acueducto y 0,59% Carrotanques). | L64: 35 | M64: =(G65/1000)*L64 -> 582.71909 | N64: 60 | O64: =(G65/1000)*N64 -> 998.94701
D65: INDICADOR PERMODA BOGOTA (Tratamiento + Suministro) | F65: $/M3 | G65: =G15 -> 16649.117
B66: MODELO 2 | C66: CONSUMO TOTAL (M3) PLAN MAESTRO BOGOTA - CON RECIRCULACIÓN OSMOSIS INVERSA Y SIN PTAP (Pozo Subterraneo) | D66: COSTO TOTAL M3 PERMODA (Tratado + Fuentes) | F66: TOTAL ($/Año) | G66: =G29 -> 6.8051464e+09 | H66: =G70-G66 -> 2.0484049e+09 | I66: =G71-G67 -> 5402.6538 | J66: El ahorro proyectado al utilizar el sistema de osmosis inversa y no tener la PTAP se da en este marco, garantizando que las fuentes internas de PERMODA sean representativas y correspondan al 54,78% de suplencia, el resto (45,22%) corresponderián a fuentes externas (44,63% Acueducto y 0,59% Carrotanques).
D67: INDICADOR PERMODA BOGOTA (Tratamiento + Suministro) | F67: $/M3 | G67: =G30 -> 17948.527
B68: MODELO 3 | C68: CONSUMO TOTAL (M3) PLAN MAESTRO BOGOTA - CON PTAP (Pozo Subterraneo) Y SIN RECIRCULACIÓN DE OSMOSIS INVERSA | D68: COSTO TOTAL M3 PERMODA (Tratado + Fuentes) | F68: TOTAL ($/Año) | G68: =G44 -> 8.1752249e+09 | H68: =G70-G68 -> 6.7832643e+08 | I68: =G71-G69 -> 1789.0813 | J68: El ahorro proyectado al utilizar unicamente la PTAP se da en este marco (Sin Osmosis Inversa), garantizando que la fuente interna de PERMODA LTDA represente un 28,72% , el resto (71,28%) corresponderián a fuentes externas (60,77% Acueducto y 10,51% Carrotanques). Para este modelo es importante tener en cuenta que la red de acueducto no sería capaz de suplir toda la necesidad, ya que nos suministra en promedio 32 m3/h, por tal motivo la suplencia por parte de carro tanques debe aumentar.
D69: INDICADOR PERMODA BOGOTA (Tratamiento + Suministro) | F69: $/M3 | G69: =G45 -> 21562.099
B70: MODELO 4 | C70: CONSUMO TOTAL (M3) PLAN MAESTRO BOGOTA - SIN PTAP (Pozo Subterraneo) Y SIN RECIRCULACIÓN DE OSMOSIS INVERSA | D70: COSTO TOTAL M3 PERMODA (Tratado + Fuentes) | F70: TOTAL ($/Año) | G70: =G59 -> 8.8535513e+09 | J70: Efectivamente este modelo es el mas costos para PERMODA LTDA, ya que al no contar con fuentes internas (Osmosis Inversa y PTAP), todo lo debería suplir con el máximo de acueducto y aumentar el abastecimiento por medio de carro tanques
D71: INDICADOR PERMODA BOGOTA (Tratamiento + Suministro) | F71: $/M3 | G71: =G60 -> 23351.18
C73: PROYECTO PTAR BOGOTA | D73: COSTO ($) COP | E73: PAYBACK (Indicador financiero que mide el tiempo necesario para recuperar el capital inicial invertido en un proyecto) | G73: Cash Flow Anual (Fujo de caja anual)
C74: PROYECTO PTAR CWT | D74: ='PROYECCIÓN DEPRECIACIÓN PTAR'!R6 -> 7.9709108e+09
C75: OBRAS CIVILES - TANQUES | D75: ='PROYECCIÓN DEPRECIACIÓN PTAR'!E26 -> 6.3134958e+09
C76: NEGOCIACIÓN CON CWT (A FAVOR) | D76: ='PLAN MAESTRO BOGOTA RECIRCU'!AO59 -> 2160000000 | E76: PAYBACK | G76: AHORROS PROYECTADOS CON OSMOSIS INVERSA | J76: OPEX RO
C77: TOTAL INVERSIÓN PTAR (CAPEX) | D77: =SUM(D74:D75)-D76 -> 1.2124407e+10 | E77: =D77/J78 -> 5.9189502 | F77: Años | G77: =H66 -> 2.0484049e+09 | J77: =G5 -> 8.8788474e+08
G78: CF | J78: =G77 -> 2.0484049e+09
C80: PROYECTO PTAP BOGOTA | D80: COSTO ($) COP | E80: PAYBACK | G80: Cash Flow Anual (Fujo de caja anual)
C81: PROYECTO PTAP DPWATERING | D81: 1527416878
C82: TOTAL INVERSIÓN PTAP (CAPEX) | D82: =SUM(D81:D81) -> 1527416878
E83: PAYBACK | G83: AHORROS PROYECTADOS CON PTAP | J83: OPEX PTAP
E84: =D82/J85 -> 2.2517431 | F84: Años | G84: =H68 -> 6.7832643e+08 | J84: =G6 -> 5.3894567e+08
G85: CF | J85: =G84 -> 6.7832643e+08
C87: PROYECTOS PTAR - PTAP | D87: COSTO ($) COP | E87: PAYBACK | G87: Cash Flow Anual (Fujo de caja anual)
C88: TOTAL INVERSIÓN PTAR | D88: =D77 -> 1.2124407e+10
C89: TOTAL INVERSIÓN PTAP (CAPEX) | D89: =D82 -> 1527416878
C90: TOTAL INVERSIÓN PTAP (CAPEX) | D90: =SUM(D88:D89) -> 1.3651823e+10 | E90: PAYBACK | G90: AHORROS PROYECTADOS CON PTAR Y PTAP | J90: OPEX PTAR + OPEX PTAP
E91: =D90/J92 -> 5.3724633 | F91: Años | G91: =H64 -> 2.5410734e+09 | J91: =J84+J77 -> 1.4268304e+09
G92: CF | J92: =G91 -> 2.5410734e+09

Sheet PLAN MAESTRO BOGOTA RECIRCU
B2: PLAN MAESTRO 2026 | D2: Indicador de Consumo (Histórico 2025) | E2: Enero | F2: Consumo de Agua proyectado (m3/MES) | G2: Febrero | H2: Consumo de Agua proyectado (m3/MES) | I2: Marzo | J2: Consumo de Agua proyectado (m3/MES) | K2: Abril | L2: Consumo de Agua proyectado (m3/MES) | M2: Mayo | N2: Consumo de Agua proyectado (m3/MES) | O2: Junio | P2: Consumo de Agua proyectado (m3/MES) | Q2: Julio | R2: Consumo de Agua proyectado (m3/MES) | S2: Agosto | T2: Consumo de Agua proyectado (m3/MES) | U2: Septiembre | V2: Consumo de Agua proyectado (m3/MES) | W2: Octubre | X2: Consumo de Agua proyectado (m3/MES) | Y2: Noviembre | Z2: Consumo de Agua proyectado (m3/MES) | AA2: Diciembre | AB2: Consumo de Agua proyectado (m3/MES) | AE2: CONSUMO TOTAL (M3) PLAN MAESTRO | AG2: Volumen (M3) | AH2: Porcentaje | AL2: CONSUMO TOTAL (M3) PLAN MAESTRO | AN2: Volumen (M3) | AO2: Porcentaje
B3: Kg de Tintorería | C3: 2874043 | D3: 60 | E3: 206773 | F3: 10753 | G3: 181023.6 | H3: =($D$3*G3)/1000 -> 10861.416 | I3: 161903.52 | J3: =($D$3*I3)/1000 -> 9714.2113 | K3: 235633.98 | L3: =($D$3*K3)/1000 -> 14138.039 | M3: 235826.67 | N3: =($D$3*M3)/1000 -> 14149.6 | O3: 269355.01 | P3: =($D$3*O3)/1000 -> 16161.301 | Q3: 335661.52 | R3: =($D$3*Q3)/1000 -> 20139.691 | S3: 368144.87 | T3: =($D$3*S3)/1000 -> 22088.692 | U3: 352203.61 | V3: =($D$3*U3)/1000 -> 21132.217 | W3: 318382.77 | X3: =($D$3*W3)/1000 -> 19102.966 | Y3: 117403.25 | Z3: =($D$3*Y3)/1000 -> 7044.1949 | AA3: 108686.58 | AB3: =($D$3*AA3)/1000 -> 6521.1949 | AG3: =SUM(F5:AB5) -> 379147.92 | AH3: 1 | AI3: $/m3 | AJ3: $ Total | AN3: =AG3 -> 379147.92 | AO3: 1 | AP3: $/m3 | AQ3: $ Total
B4: Und de Lavandería | C4: 6060688 | D4: 34 | E4: 361783 | F4: 16476 | G4: 464000 | H4: =($D$4*G4)/1000 -> 15776 | I4: 460500 | J4: =($D$4*I4)/1000 -> 15657 | K4: 437000 | L4: =($D$4*K4)/1000 -> 14858 | M4: 508000 | N4: =($D$4*M4)/1000 -> 17272 | O4: 532000 | P4: =($D$4*O4)/1000 -> 18088 | Q4: 599100 | R4: =($D$4*Q4)/1000 -> 20369.4 | S4: 535200 | T4: =($D$4*S4)/1000 -> 18196.8 | U4: 657359.42 | V4: =($D$4*U4)/1000 -> 22350.22 | W4: 639859.42 | X4: =($D$4*W4)/1000 -> 21755.22 | Y4: 577690.62 | Z4: =($D$4*Y4)/1000 -> 19641.481 | AA4: 202978.55 | AB4: =($D$4*AA4)/1000 -> 6901.2705 | AE4: TRATAMIENTO DE AGUA RESIDUAL | AF4: PTAR (Costo de Tratamiento hasta Fase 2 - Cumplimiento Ambiental) OPEX SIN DEPRECIACIÓN | AG4: =AG3 -> 379147.92 | AH4: 1 | AI4: ='PROYECCIÓN INSUMOS QUÍMICOS'!V22+'PROYECCIÓN RESIDUOS Y LODOS'!U10+'PROYECCIÓN CONSUMIBLES PTAR'!U12+'PROYECCIÓN CALIBR-MANTE PTAR'!U12+'PROYECCIÓN NOMINA PTAR'!U10+'PROYECCIÓN ELECTRICIDAD PTAR'!U8 -> 10067.306 | AJ4: =AG4*AI4 -> 3.8169981e+09 | AL4: TRATAMIENTO DE AGUA RESIDUAL | AM4: PTAR (Costo de Tratamiento hasta Fase 2 - Cumplimiento Ambiental) OPEX CON DEPRECIACIÓN | AN4: =AN3 -> 379147.92 | AO4: 1 | AP4: =AI4+'PROYECCIÓN DEPRECIACIÓN PTAR'!U10 -> 11828.253 | AQ4: =AN4*AP4 -> 4.4846576e+09
B5: Consumo Total (m3/Mes) | F5: 27229 | H5: =SUM(H3:H4) -> 26637.416 | J5: =SUM(J3:J4) -> 25371.211 | L5: =SUM(L3:L4) -> 28996.039 | N5: =SUM(N3:N4) -> 31421.6 | P5: =SUM(P3:P4) -> 34249.301 | R5: =SUM(R3:R4) -> 40509.091 | T5: =SUM(T3:T4) -> 40285.492 | V5: =SUM(V3:V4) -> 43482.437 | X5: =SUM(X3:X4) -> 40858.186 | Z5: =SUM(Z3:Z4) -> 26685.676 | AB5: =SUM(AB3:AB4) -> 13422.465 | AE5: FUENTES ABASTECIMIENTO | AF5: OSMOSIS INVERSA (Costo procesar por RO - OPEX) SIN DEPRECIACIÓN | AG5: =F8+H8+J8+L8+N8+P8+R8+T8+V8+X8+Z8+AB8 -> 221583.52 | AH5: =(AG5/$AG$3) -> 0.58442501 | AI5: ='PROYECCIÓN INSUMOS QUÍMICOS'!V23+'PROYECCIÓN CONSUMIBLES PTAR'!U13+'PROYECCIÓN CALIBR-MANTE PTAR'!U13+'PROYECCIÓN NOMINA PTAR'!U11+'PROYECCIÓN ELECTRICIDAD PTAR'!U9 -> 3406.3554 | AJ5: =AG5*AI5 -> 7.5479224e+08 | AL5: FUENTES ABASTECIMIENTO | AM5: OSMOSIS INVERSA (Costo procesar por RO - OPEX) SIN DEPRECIACIÓN | AN5: =AG5 -> 221583.52 | AO5: =(AN5/$AG$3) -> 0.58442501 | AP5: =AI5+'PROYECCIÓN DEPRECIACIÓN PTAR'!U11 -> 3602.7536 | AQ5: =AN5*AP5 -> 7.9831084e+08
B6: FUENTES DE ABASTECIMIENTO | E6: % | F6: M3 | G6: % | H6: M3 | I6: % | J6: M3 | K6: % | L6: M3 | M6: % | N6: M3 | O6: % | P6: M3 | Q6: % | R6: M3 | S6: % | T6: M3 | U6: % | V6: M3 | W6: % | X6: M3 | Y6: % | Z6: M3 | AA6: % | AB6: M3 | AF6: PTAP (Costo de Tratamiento de Agua de Pozo Sin depreciación) | AG6: =F9+H9+J9+L9+N9+P9+R9+T9+V9+X9+Z9+AB9 -> 95848.197 | AH6: =(AG6/$AG$3) -> 0.25279896 | AI6: ='PROYECCIÓN INSUMOS QUÍMICOS'!V35+'PROYECCIÓN RESIDUOS Y LODOS'!U18+'PROYECCIÓN CONSUMIBLES PTAR'!U23+'PROYECCIÓN CALIBR-MANTE PTAR'!U22+'PROYECCIÓN NOMINA PTAR'!U20+'PROYECCIÓN ELECTRICIDAD PTAR'!U16+'PROYECCIÓN PAGO USO POZO'!U8 -> 5062.1281 | AJ6: =AG6*AI6 -> 4.8519585e+08 | AM6: PTAP (Costo de Tratamiento de Agua de Pozo Sin depreciación) | AN6: =AG6 -> 95848.197 | AO6: =(AN6/$AG$3) -> 0.25279896 | AP6: =AI6+'PROYECCIÓN DEPRECIACIÓN PTAR'!U19 -> 5622.9088 | AQ6: =AN6*AP6 -> 5.3894567e+08
B7: ACUEDUCTO (M3) | E7: =(F7*100%)/F5 -> 0.36519887 | F7: 9944 | G7: 0.3652 | H7: =$H$5*$G$7 -> 9727.9843 | I7: 0.3652 | J7: =$J$5*$I$7 -> 9265.5664 | K7: =100%-K8-K9-K10 -> 0.3652 | L7: =$L$5*$K$7 -> 10589.353 | M7: =100%-M8-M9-M10 -> 0.0434 | N7: =$N$5*$M$7 -> 1363.6975 | O7: =100%-O8-O9-O10 -> 0.0434 | P7: =$P$5*$O$7 -> 1486.4196 | Q7: =100%-Q8-Q9-Q10 -> 0.1034 | R7: =$R$5*$Q$7 -> 4188.6401 | S7: =100%-S8-S9-S10 -> 0.1034 | T7: =$T$5*$S$7 -> 4165.5199 | U7: =100%-U8-U9-U10 -> 0.1134 | V7: =$V$5*$U$7 -> 4930.9083 | W7: =100%-W8-W9-W10 -> 0.0934 | X7: =$X$5*$W$7 -> 3816.1546 | Y7: 0 | Z7: =$Z$5*$Y$7 -> 0 | AA7: 0 | AB7: =$AB$5*$AA$7 -> 0 | AF7: ACUEDUCTO | AG7: =F7+H7+J7+L7+N7+P7+R7+T7+V7+X7+Z7+AB7 -> 59478.244 | AH7: =(AG7/$AG$3) -> 0.15687346 | AI7: 10763 | AJ7: =AG7*AI7 -> 6.4016434e+08 | AM7: ACUEDUCTO | AN7: =AG7 -> 59478.244 | AO7: =(AN7/$AG$3) -> 0.15687346 | AP7: 10763 | AQ7: =AN7*AP7 -> 6.4016434e+08
B8: OSMOSIS INVERSA - PTAR (M3 | E8: 0.4203 | F8: 11443 | G8: 0.4203 | H8: =$H$5*$G$8 -> 11195.706 | I8: 0.4203 | J8: =$J$5*$I$8 -> 10663.52 | K8: 0.4203 | L8: =$L$5*$K$8 -> 12187.035 | M8: 0.65 | N8: =$N$5*$M$8 -> 20424.04 | O8: 0.65 | P8: =$P$5*$O$8 -> 22262.045 | Q8: 0.65 | R8: =$R$5*$Q$8 -> 26330.909 | S8: 0.65 | T8: =$T$5*$S$8 -> 26185.57 | U8: 0.65 | V8: =$V$5*$U$8 -> 28263.584 | W8: 0.65 | X8: =$X$5*$W$8 -> 26557.821 | Y8: 0.65 | Z8: =Z5*Y8 -> 17345.689 | AA8: 0.65 | AB8: =AB5-AB9 -> 8724.6025 | AF8: CARRO TANQUES | AG8: =F10+H10+J10+L10+N10+P10+R10+T10+V10+X10+Z10+AB10 -> 2237.9511 | AH8: =(AG8/$AG$3) -> 0.0059025805 | AI8: 12700 | AJ8: =AG8*AI8 -> 28421979 | AM8: CARRO TANQUES | AN8: =AG8 -> 2237.9511 | AO8: =(AN8/$AG$3) -> 0.0059025805 | AP8: 12700 | AQ8: =AN8*AP8 -> 28421979
B9: PTAP (M3) | E9: 0.2079 | F9: 5662 | G9: 0.2079 | H9: =$H$5*$G$9 -> 5537.9188 | I9: 0.2079 | J9: =$J$5*$I$9 -> 5274.6748 | K9: 0.2079 | L9: =$L$5*$K$9 -> 6028.2765 | M9: 0.3 | N9: =+N5*M9 -> 9426.4801 | O9: 0.3 | P9: =+P5*O9 -> 10274.79 | Q9: 0.24 | R9: =+R5*Q9 -> 9722.182 | S9: 0.24 | T9: =+T5*S9 -> 9668.5181 | U9: 0.23 | V9: =+V5*U9 -> 10000.96 | W9: 0.25 | X9: =+X5*W9 -> 10214.547 | Y9: 0.35 | Z9: =+Z5*Y9 -> 9339.9865 | AA9: 0.35 | AB9: =+AB5*AA9 -> 4697.8629 | AI9: TOTAL | AJ9: =SUM(AJ4:AJ8) -> 5.7255725e+09 | AP9: TOTAL | AQ9: =SUM(AQ4:AQ8) -> 6.4905005e+09
B10: CARRO TANQUES (M3) | E10: 0.0066 | F10: 180 | G10: 0.0066 | H10: =$H$5*$G$10 -> 175.80695 | I10: 0.0066 | J10: =$J$5*$I$10 -> 167.44999 | K10: 0.0066 | L10: =$L$5*$K$10 -> 191.37386 | M10: =+N10/N5 -> 0.0066 | N10: =$N$5*$E$10 -> 207.38256 | O10: 0.0066 | P10: =$P$5*$O$10 -> 226.04538 | Q10: 0.0066 | R10: =$R$5*$Q$10 -> 267.36 | S10: 0.0066 | T10: =$T$5*$S$10 -> 265.88425 | U10: 0.0066 | V10: =$V$5*$U$10 -> 286.98408 | W10: 0.0066 | X10: =$X$5*$W$10 -> 269.66403 | Y10: 0 | Z10: =$Z$5*$Y$10 -> 0 | AA10: 0 | AB10: =$AB$5*$AA$10 -> 0 | AG10: COSTO DE TRATAMIENTO DE AGUA RESIDUAL | AI10: $/M3 | AJ10: =AJ4/AG4 -> 10067.306 | AN10: COSTO DE TRATAMIENTO DE AGUA RESIDUAL | AP10: $/M3 | AQ10: =AQ4/AN4 -> 11828.253
AG11: COSTO DE SUMINISTRO DE AGUA A PROCESO | AI11: $/M3 | AJ11: =SUM(AJ5:AJ8)/AG3 -> 5033.8518 | AN11: COSTO DE SUMINISTRO DE AGUA A PROCESO | AP11: $/M3 | AQ11: =SUM(AQ5:AQ8)/AN3 -> 5290.3966
G12: Febrero | H12: Consumo de Agua proyectado (m3/MES) | AG12: COSTO TOTAL M3 PERMODA | AI12: $/M3 | AJ12: =SUM(AJ10:AJ11) -> 15101.158 | AN12: COSTO TOTAL M3 PERMODA | AP12: $/M3 | AQ12: =SUM(AQ10:AQ11) -> 17118.65
G13: 130962 | H13: =(41*G13)/1000 -> 5369.442
G14: 450288 | H14: =(45.7*G14)/1000 -> 20578.162 | AE14: CONSUMO TOTAL (M3) PLAN MAESTRO | AG14: Volumen (M3) | AH14: Porcentaje | AL14: CONSUMO TOTAL (M3) PLAN MAESTRO | AN14: Volumen (M3) | AO14: Porcentaje
H15: 26204 | AG15: =AG3 -> 379147.92 | AH15: 1 | AI15: $/m3 | AJ15: $ Total | AN15: =AN3 -> 379147.92 | AO15: 1 | AP15: $/m3 | AQ15: $ Total
B16: FUENTES DE ABASTECIMIENTO | G16: % | H16: M3 | AE16: TRATAMIENTO DE AGUA RESIDUAL | AF16: PTAR (Costo de Tratamiento hasta Fase 2 - Cumplimiento Ambiental) OPEX SIN DEPRECIACIÓN | AG16: =AG15 -> 379147.92 | AH16: 1 | AI16: =AI4 -> 10067.306 | AJ16: =AG16*AI16 -> 3.8169981e+09 | AL16: TRATAMIENTO DE AGUA RESIDUAL | AM16: PTAR (Costo de Tratamiento hasta Fase 2 - Cumplimiento Ambiental) OPEX CON DEPRECIACIÓN | AN16: =AN15 -> 379147.92 | AO16: 1 | AP16: =AP4 -> 11828.253 | AQ16: =AN16*AP16 -> 4.4846576e+09
B17: ACUEDUCTO (M3) | G17: =(H17*100%)/$H$15 -> 0.3876889 | H17: 10159 | AE17: FUENTES ABASTECIMIENTO | AF17: OSMOSIS INVERSA (Costo procesar por RO - OPEX) SIN DEPRECIACIÓN | AG17: 0 | AH17: =(AG17/$AG$3) -> 0 | AI17: 0 | AJ17: =AG17*AI17 -> 0 | AL17: FUENTES ABASTECIMIENTO | AM17: OSMOSIS INVERSA (Costo procesar por RO - OPEX) SIN DEPRECIACIÓN | AN17: 0 | AO17: =(AN17/$AG$3) -> 0 | AP17: 0 | AQ17: 0
B18: OSMOSIS INVERSA - PTAR (M3 | G18: =(H18*100%)/$H$15 -> 0.43050679 | H18: 11281 | AF18: PTAP | AG18: =AG6 -> 95848.197 | AH18: =(AG18/$AG$3) -> 0.25279896 | AI18: =AI6 -> 5062.1281 | AJ18: =AG18*AI18 -> 4.8519585e+08 | AM18: PTAP | AN18: =AN6 -> 95848.197 | AO18: =(AN18/$AG$3) -> 0.25279896 | AP18: =AP6 -> 5622.9088 | AQ18: =AN18*AP18 -> 5.3894567e+08
B19: PTAP (M3) | G19: =(H19*100%)/$H$15 -> 0.17005037 | H19: 4456 | AF19: ACUEDUCTO | AG19: 230400 | AH19: =(AG19/$AG$3) -> 0.6076784 | AI19: 10763 | AJ19: =AG19*AI19 -> 2479795200 | AM19: ACUEDUCTO | AN19: 230400 | AO19: =(AN19/$AG$3) -> 0.6076784 | AP19: 10763 | AQ19: =AN19*AP19 -> 2479795200
B20: CARRO TANQUES (M3) | G20: =(H20*100%)/$H$15 -> 0.011753931 | H20: 308 | AF20: CARRO TANQUES | AG20: =AG15-AG18-AG19 -> 52899.718 | AH20: =(AG20/$AG$3) -> 0.13952264 | AI20: 12700 | AJ20: =AG20*AI20 -> 6.7182642e+08 | AM20: CARRO TANQUES | AN20: =AN15-AN18-AN19 -> 52899.718 | AO20: =(AN20/$AG$3) -> 0.13952264 | AP20: 12700 | AQ20: =AN20*AP20 -> 6.7182642e+08
AI21: TOTAL | AJ21: =SUM(AJ16:AJ20) -> 7.4538156e+09 | AP21: TOTAL | AQ21: =SUM(AQ16:AQ20) -> 8.1752249e+09
AG22: COSTO DE TRATAMIENTO DE AGUA RESIDUAL | AI22: $/M3 | AJ22: =AJ16/AG16 -> 10067.306 | AN22: COSTO DE TRATAMIENTO DE AGUA RESIDUAL | AP22: $/M3 | AQ22: =AQ16/AN16 -> 11828.253
AG23: COSTO DE SUMINISTRO DE AGUA A PROCESO | AI23: $/M3 | AJ23: =SUM(AJ17:AJ20)/AG15 -> 9592.0809 | AN23: COSTO DE SUMINISTRO DE AGUA A PROCESO | AP23: $/M3 | AQ23: =SUM(AQ17:AQ20)/AN15 -> 9733.8457
AG24: COSTO TOTAL M3 PERMODA | AI24: $/M3 | AJ24: =SUM(AJ22:AJ23) -> 19659.387 | AN24: COSTO TOTAL M3 PERMODA | AP24: $/M3 | AQ24: =SUM(AQ22:AQ23) -> 21562.099 | AR24: =AQ24-AQ12 -> 4443.4491
AH26: PROYECCIÓN CON RECIRCULACIÓN | AJ26: =AJ9 -> 5.7255725e+09 | AO26: PROYECCIÓN CON RECIRCULACIÓN | AQ26: =AQ9 -> 6.4905005e+09
AH27: PROYECCIÓN SIN RECIRCULACIÓN | AJ27: =AJ21 -> 7.4538156e+09 | AO27: PROYECCIÓN SIN RECIRCULACIÓN | AQ27: =AQ21 -> 8.1752249e+09
AH29: AHORRO PROYECTADO RECIRCULANDO | AJ29: =AJ27-AJ26 -> 1.7282431e+09 | AO29: AHORRO PROYECTADO RECIRCULANDO | AQ29: =AQ27-AQ26 -> 1.6847245e+09
AE31: CONSUMO TOTAL (M3) PLAN MAESTRO | AG31: Volumen (M3) | AH31: Porcentaje | AL31: CONSUMO TOTAL (M3) PLAN MAESTRO | AN31: Volumen (M3) | AO31: Porcentaje
AG32: =AG15 -> 379147.92 | AH32: 1 | AI32: $/m3 | AJ32: $ Total | AN32: =AN15 -> 379147.92 | AO32: 1 | AP32: $/m3 | AQ32: $ Total
AE33: TRATAMIENTO DE AGUA RESIDUAL | AF33: PTAR (Costo de Tratamiento hasta Fase 2 - Cumplimiento Ambiental) OPEX SIN DEPRECIACIÓN | AG33: =AG32 -> 379147.92 | AH33: 1 | AI33: =AI16 -> 10067.306 | AJ33: =AG33*AI33 -> 3.8169981e+09 | AL33: TRATAMIENTO DE AGUA RESIDUAL | AM33: PTAR (Costo de Tratamiento hasta Fase 2 - Cumplimiento Ambiental) OPEX CON DEPRECIACIÓN | AN33: =AN32 -> 379147.92 | AO33: 1 | AP33: =AP16 -> 11828.253 | AQ33: =AN33*AP33 -> 4.4846576e+09
AE34: FUENTES ABASTECIMIENTO | AF34: OSMOSIS INVERSA (Costo procesar por RO - OPEX) SIN DEPRECIACIÓN | AG34: 0 | AH34: =(AG34/$AG$3) -> 0 | AI34: 0 | AJ34: =AG34*AI34 -> 0 | AL34: FUENTES ABASTECIMIENTO | AM34: OSMOSIS INVERSA (Costo procesar por RO - OPEX) SIN DEPRECIACIÓN | AN34: 0 | AO34: =(AN34/$AG$3) -> 0 | AP34: 0 | AQ34: 0
AF35: PTAP | AG35: 0 | AH35: =(AG35/$AG$3) -> 0 | AI35: 0 | AJ35: =AG35*AI35 -> 0 | AM35: PTAP | AN35: 0 | AO35: =(AN35/$AG$3) -> 0 | AP35: 0 | AQ35: =AN35*AP35 -> 0
AF36: ACUEDUCTO | AG36: 230400 | AH36: =(AG36/$AG$3) -> 0.6076784 | AI36: 10763 | AJ36: =AG36*AI36 -> 2479795200 | AM36: ACUEDUCTO | AN36: 230400 | AO36: =(AN36/$AG$3) -> 0.6076784 | AP36: 10763 | AQ36: =AN36*AP36 -> 2479795200
AF37: CARRO TANQUES | AG37: =AG32-AG35-AG36 -> 148747.92 | AH37: =(AG37/$AG$3) -> 0.3923216 | AI37: 12700 | AJ37: =AG37*AI37 -> 1.8890985e+09 | AM37: CARRO TANQUES | AN37: =AN32-AN35-AN36 -> 148747.92 | AO37: =(AN37/$AG$3) -> 0.3923216 | AP37: 12700 | AQ37: =AN37*AP37 -> 1.8890985e+09
AI38: TOTAL | AJ38: =SUM(AJ33:AJ37) -> 8.1858918e+09 | AP38: TOTAL | AQ38: =SUM(AQ33:AQ37) -> 8.8535513e+09
AG39: COSTO DE TRATAMIENTO DE AGUA RESIDUAL | AI39: $/M3 | AJ39: =AJ33/AG33 -> 10067.306 | AN39: COSTO DE TRATAMIENTO DE AGUA RESIDUAL | AP39: $/M3 | AQ39: =AQ33/AN33 -> 11828.253
AG40: COSTO DE SUMINISTRO DE AGUA A PROCESO | AI40: $/M3 | AJ40: =SUM(AJ34:AJ37)/AG32 -> 11522.927 | AN40: COSTO DE SUMINISTRO DE AGUA A PROCESO | AP40: $/M3 | AQ40: =SUM(AQ34:AQ37)/AN32 -> 11522.927
AG41: COSTO TOTAL M3 PERMODA | AI41: $/M3 | AJ41: =SUM(AJ39:AJ40) -> 21590.233 | AN41: COSTO TOTAL M3 PERMODA | AP41: $/M3 | AQ41: =SUM(AQ39:AQ40) -> 23351.18 | AR41: =AQ41-AQ12 -> 6232.5304
AH43: PROYECCIÓN CON RECIRCULACIÓN Y PTAP | AJ43: =AJ26 -> 5.7255725e+09 | AO43: PROYECCIÓN CON RECIRCULACIÓN Y PTAP | AQ43: =AQ9 -> 6.4905005e+09
AH44: PROYECCIÓN SIN RECIRCULACIÓN SIN PTAP | AJ44: =AJ38 -> 8.1858918e+09 | AO44: PROYECCIÓN SIN RECIRCULACIÓN | AQ44: =AQ21 -> 8.1752249e+09 | AR44: =AQ44-AQ43 -> 1.6847245e+09
AO45: PROYECCIÓN SIN RECIRCULACIÓN SIN PTAP | AQ45: =AQ38 -> 8.8535513e+09 | AR45: =AQ45-AQ43 -> 2.3630509e+09
AH47: AHORRO PROYECTADO RECIRCULANDO | AJ47: =AJ44-AJ43 -> 2.4603193e+09 | AO47: AHORRO PROYECTADO RECIRCULANDO | AQ47: =AQ45-AQ43 -> 2.3630509e+09
AO50: 30000000000 | AQ50: =AO50/AQ47 -> 12.695452
AN52: 3600 | AO52: 3400000 | AP52: cwt | AR52: =AQ4 -> 4.4846576e+09
AO53: =AO52*AN52 -> 12240000000
AR54: =AQ47+AR52 -> 6.8477085e+09
AO55: 6000000000 | AP55: Obra civil
AO56: 3000000000 | AP56: adicionales | AR56: =AO62/AR54 -> 2.7863336
AO58: 600000 | AP58: Negociación CWT | AU58: años
AO59: =AN52*AO58 -> 2160000000
AU61: Ahorro
AO62: =AO53+AO55+AO56-AO59 -> 19080000000
AU65: años
AO66: 9000000000 | AP66: Obra civil Funza | AU66: m3/día
AO67: 3000000000 | AP67: electricos | AU67: %
AN68: 4500 | AO68: 2300000 | AP68: waternext | AU68: m3/Recuperado
AO69: =AO68*AN68 -> 10350000000
AU70: Ton/Día
AU71: L/Kg

Sheet PROYECCIÓN INSUMOS QUÍMICOS
B2: COSTO PLANTA DE TRATAMIENTO DE AGUA RESIDUAL | G2: EJECUTADO PTAR AÑO 2026 BOGOTÁ
B3: Clasificación | C3: Detalle | D3: Unidad | E3: Dosificación | G3: Enero 2026 | H3: Febrero 2026 | I3: Marzo 2026 | J3: Abril 2026 | K3: Mayo 2026 | L3: Junio 2026 | M3: Julio 2026 | N3: Agosto 2026 | O3: Septiembre 2026 | P3: Octubre 2026 | Q3: Noviembre 2026 | R3: Diciembre 2026 | S3: Total general | T3: $/Kg | U3: $ Total | V3: $/M3
E4: Kg/m3 | F4: g/m3 | G4: CAUDAL PLAN MAESTRO
G5: ='PLAN MAESTRO BOGOTA RECIRCU'!F5 -> 27229 | H5: ='PLAN MAESTRO BOGOTA RECIRCU'!H5 -> 26637.416 | I5: ='PLAN MAESTRO BOGOTA RECIRCU'!J5 -> 25371.211 | J5: ='PLAN MAESTRO BOGOTA RECIRCU'!L5 -> 28996.039 | K5: ='PLAN MAESTRO BOGOTA RECIRCU'!N5 -> 31421.6 | L5: ='PLAN MAESTRO BOGOTA RECIRCU'!P5 -> 34249.301 | M5: ='PLAN MAESTRO BOGOTA RECIRCU'!R5 -> 40509.091 | N5: ='PLAN MAESTRO BOGOTA RECIRCU'!T5 -> 40285.492 | O5: ='PLAN MAESTRO BOGOTA RECIRCU'!V5 -> 43482.437 | P5: ='PLAN MAESTRO BOGOTA RECIRCU'!X5 -> 40858.186 | Q5: ='PLAN MAESTRO BOGOTA RECIRCU'!Z5 -> 26685.676 | R5: ='PLAN MAESTRO BOGOTA RECIRCU'!AB5 -> 13422.465 | S5: =SUM(G5:R5) -> 379147.92
B6: QUIMICOS (GEM + RO) | C6: ACIDO CLORHIDRICO 31,5% | D6: kg | E6: ='Resumen costos Ptar Bogotá'!U6 -> 0.013583636 | F6: =E6*1000 -> 13.583636 | G6: =$E$6*G5 -> 369.86883 | H6: =$E$6*H5 -> 361.83297 | I6: =$E$6*I5 -> 344.63331 | J6: =$E$6*J5 -> 393.87165 | K6: =$E$6*K5 -> 426.81959 | L6: =$E$6*L5 -> 465.23004 | M6: =$E$6*M5 -> 550.26077 | N6: =$E$6*N5 -> 547.22347 | ... R6: =$E$6*R5 -> 182.32589 | S6: =+SUM(G6:R6) -> 5150.2074 | T6: 1650 | U6: =S6*T6 -> 8497842.2 | V6: =U6/$S$5 -> 22.413
C7: SODIO BISULFITO | D7: kg | E7: ='Resumen costos Ptar Bogotá'!U7 -> 0.0011916667 | F7: =E7*1000 -> 1.1916667 | G7: =$E$7*G5 -> 32.447892 | H7: =$E$7*H5 -> 31.742921 | I7: =$E$7*I5 -> 30.234027 | J7: =$E$7*J5 -> 34.553613 | K7: =$E$7*K5 -> 37.444074 | L7: =$E$7*L5 -> 40.81375 | M7: =$E$7*M5 -> 48.273334 | N7: =$E$7*N5 -> 48.006878 | ... R7: =$E$7*R5 -> 15.995105 | S7: =+SUM(G7:R7) -> 451.81793 | T7: 4200 | U7: =S7*T7 -> 1897635.3 | V7: =U7/$S$5 -> 5.005
C8: NITRATO DE PLATA | D8: kg | E8: ='Resumen costos Ptar Bogotá'!U8 -> 1.8118958e-05 | F8: =E8*1000 -> 0.018118958 | G8: =$E$8*G5 -> 0.4933611 | H8: =$E$8*H5 -> 0.48264221 | I8: =$E$8*I5 -> 0.4596999 | J8: =$E$8*J5 -> 0.525378 | K8: =$E$8*K5 -> 0.56932665 | L8: =$E$8*L5 -> 0.62056163 | M8: =$E$8*M5 -> 0.73398252 | N8: =$E$8*N5 -> 0.72993113 | ... R8: =$E$8*R5 -> 0.24320108 | S8: =+SUM(G8:R8) -> 6.869765 | T8: 180000 | U8: =S8*T8 -> 1236557.7 | V8: =U8/$S$5 -> 3.2614124
C9: ACIDIFICANTE | D9: kg | E9: ='Resumen costos Ptar Bogotá'!U10 -> 0.30804068 | F9: =E9*1000 -> 308.04068 | G9: =$E$9*G5 -> 8387.6395 | H9: =$E$9*H5 -> 8205.4076 | I9: =$E$9*I5 -> 7815.3651 | J9: =$E$9*J5 -> 8931.9594 | K9: =$E$9*K5 -> 9679.131 | L9: =$E$9*L5 -> 10550.178 | M9: =$E$9*M5 -> 12478.448 | N9: =$E$9*N5 -> 12409.57 | ... R9: =$E$9*R5 -> 4134.6653 | S9: =+SUM(G9:R9) -> 116792.98 | T9: 830 | U9: =S9*T9 -> 96938173 | V9: =U9/$S$5 -> 255.67376
C10: QUIMICO FLOCULANTE PARA TRATAMIENTO DE AGUA (Catiónico) | D10: kg | E10: ='Resumen costos Ptar Bogotá'!U11 -> 0.0091306964 | F10: =E10*1000 -> 9.1306964 | G10: =$E$10*G5 -> 248.61973 | H10: =$E$10*H5 -> 243.21816 | I10: =$E$10*I5 -> 231.65683 | J10: =$E$10*J5 -> 264.75403 | K10: =$E$10*K5 -> 286.90109 | L10: =$E$10*L5 -> 312.71996 | M10: =$E$10*M5 -> 369.87621 | N10: =$E$10*N5 -> 367.8346 | ... R10: =$E$10*R5 -> 122.55646 | S10: =+SUM(G10:R10) -> 3461.8845 | T10: 22050 | U10: =S10*T10 -> 76334553 | V10: =U10/$S$5 -> 201.33185
C11: QUIMICO FLOCULANTE PARA TRATAMIENTO DE AGUA (Aniónico) | D11: kg | E11: ='Resumen costos Ptar Bogotá'!U12 -> 0.0054182543 | F11: =E11*1000 -> 5.4182543 | G11: =$E$11*G5 -> 147.53365 | H11: =$E$11*H5 -> 144.32829 | I11: =$E$11*I5 -> 137.46768 | J11: =$E$11*J5 -> 157.10791 | K11: =$E$11*K5 -> 170.25022 | L11: =$E$11*L5 -> 185.57142 | M11: =$E$11*M5 -> 219.48856 | N11: =$E$11*N5 -> 218.27704 | ... R11: =$E$11*R5 -> 72.726331 | S11: =+SUM(G11:R11) -> 2054.3198 | T11: 19050 | U11: =S11*T11 -> 39134793 | V11: =U11/$S$5 -> 103.21774
C12: QUIMICO COAGULANTE PARA TRATAMIENTO DE AGUA (Coagulante) | D12: kg | E12: ='Resumen costos Ptar Bogotá'!U13 -> 0.54180085 | F12: =E12*1000 -> 541.80085 | G12: =$E$12*G5 -> 14752.695 | H12: =$E$12*H5 -> 14432.175 | I12: =$E$12*I5 -> 13746.144 | J12: =$E$12*J5 -> 15710.079 | K12: =$E$12*K5 -> 17024.25 | L12: =$E$12*L5 -> 18556.3 | M12: =$E$12*M5 -> 21947.86 | N12: =$E$12*N5 -> 21826.714 | ... R12: =$E$12*R5 -> 7272.3033 | S12: =+SUM(G12:R12) -> 205422.66 | T12: 2818 | U12: =S12*T12 -> 5.7888107e+08 | V12: =U12/$S$5 -> 1526.7948
C13: QUIMICO COAGULANTE PARA TRATAMIENTO DE AGUA (Decolorante) | D13: kg | E13: ='Resumen costos Ptar Bogotá'!U14 -> 0.23755146 | F13: =E13*1000 -> 237.55146 | G13: =$E$13*G5 -> 6468.2888 | H13: =$E$13*H5 -> 6327.7572 | I13: =$E$13*I5 -> 6026.9684 | J13: =$E$13*J5 -> 6888.0515 | K13: =$E$13*K5 -> 7464.2471 | L13: =$E$13*L5 -> 8135.9715 | M13: =$E$13*M5 -> 9622.994 | N13: =$E$13*N5 -> 9569.8776 | ... R13: =$E$13*R5 -> 3188.5263 | S13: =+SUM(G13:R13) -> 90067.142 | T13: 6295 | U13: =S13*T13 -> 5.6697266e+08 | V13: =U13/$S$5 -> 1495.3865 | W13: OZONO
C14: HIPOCLORITO DE SODIO | D14: kg | E14: ='Resumen costos Ptar Bogotá'!U15 -> 0.0072995135 | F14: =E14*1000 -> 7.2995135 | G14: =$E$14*G5 -> 198.75845 | H14: =$E$14*H5 -> 194.44018 | I14: =$E$14*I5 -> 185.1975 | J14: =$E$14*J5 -> 211.65698 | K14: =$E$14*K5 -> 229.36239 | L14: =$E$14*L5 -> 250.00323 | M14: =$E$14*M5 -> 295.69666 | N14: =$E$14*N5 -> 294.06449 | ... R14: =$E$14*R5 -> 97.977467 | S14: =+SUM(G14:R14) -> 2767.5953 | T14: 1298 | U14: =S14*T14 -> 3592338.7 | V14: =U14/$S$5 -> 9.4747685
C15: SODA CAUSTICA LIQUI48% 90 KL | D15: kg | E15: ='Resumen costos Ptar Bogotá'!U16 -> 0.013272416 | F15: =E15*1000 -> 13.272416 | G15: =$E$15*G5 -> 361.39461 | H15: =$E$15*H5 -> 353.54286 | I15: =$E$15*I5 -> 336.73726 | J15: =$E$15*J5 -> 384.84748 | K15: =$E$15*K5 -> 417.04054 | L15: =$E$15*L5 -> 454.57095 | M15: =$E$15*M5 -> 537.6535 | N15: =$E$15*N5 -> 534.6858 | ... R15: =$E$15*R5 -> 178.14854 | S15: =+SUM(G15:R15) -> 5032.2087 | T15: 1862 | U15: =S15*T15 -> 9369972.7 | V15: =U15/$S$5 -> 24.713238
C16: QUIMICO ANTINCRUSTANTE PARA ÓSMOSIS INVERSA | D16: kg | E16: ='Resumen costos Ptar Bogotá'!U17 -> 0.013763942 | F16: =E16*1000 -> 13.763942 | G16: =$E$16*G5 -> 374.77836 | H16: =$E$16*H5 -> 366.63584 | I16: =$E$16*I5 -> 349.20787 | J16: =$E$16*J5 -> 399.09979 | K16: =$E$16*K5 -> 432.48507 | L16: =$E$16*L5 -> 471.40537 | M16: =$E$16*M5 -> 557.56477 | N16: =$E$16*N5 -> 554.48716 | ... R16: =$E$16*R5 -> 184.74603 | S16: =+SUM(G16:R16) -> 5218.5697 | T16: 36239 | U16: =S16*T16 -> 1.8911575e+08 | V16: =U16/$S$5 -> 498.79148
C17: QUIMICO PARA TRATAMIENTO CIP ALCALINO ÓSMOSIS INVERSA | D17: kg | E17: ='Resumen costos Ptar Bogotá'!U18 -> 0.00091964781 | F17: =E17*1000 -> 0.91964781 | G17: =$E$17*G5 -> 25.04109 | H17: =$E$17*H5 -> 24.497041 | I17: =$E$17*I5 -> 23.332579 | J17: =$E$17*J5 -> 26.666144 | K17: =$E$17*K5 -> 28.896806 | L17: =$E$17*L5 -> 31.497294 | M17: =$E$17*M5 -> 37.254097 | N17: =$E$17*N5 -> 37.048464 | ... R17: =$E$17*R5 -> 12.343941 | S17: =+SUM(G17:R17) -> 348.68255 | T17: 32490 | U17: =S17*T17 -> 11328696 | V17: =U17/$S$5 -> 29.879357
C18: QUIMICO PARA TRATAMIENTO BIODISPERSANTE ÓSMOSIS INVERSA | D18: kg | E18: ='Resumen costos Ptar Bogotá'!U19 -> 0.018171608 | F18: =E18*1000 -> 18.171608 | G18: =$E$18*G5 -> 494.79473 | H18: =$E$18*H5 -> 484.04469 | I18: =$E$18*I5 -> 461.03572 | J18: =$E$18*J5 -> 526.90467 | K18: =$E$18*K5 -> 570.98102 | L18: =$E$18*L5 -> 622.36488 | M18: =$E$18*M5 -> 736.11535 | N18: =$E$18*N5 -> 732.05219 | ... R18: =$E$18*R5 -> 243.90779 | S18: =+SUM(G18:R18) -> 6889.7275 | T18: 19160 | U18: =S18*T18 -> 1.3200718e+08 | V18: =U18/$S$5 -> 348.16802 | W18: TQI
C19: QUIMICO PARA TRATAMIENTO CIP ACIDO ÓSMOSIS INVERSA | D19: Kg | E19: ='Resumen costos Ptar Bogotá'!U20 -> 0.00087479088 | F19: =E19*1000 -> 0.87479088 | G19: =$E$19*G5 -> 23.819681 | H19: =$E$19*H5 -> 23.302169 | I19: =$E$19*I5 -> 22.194504 | J19: =$E$19*J5 -> 25.36547 | K19: =$E$19*K5 -> 27.487329 | L19: =$E$19*L5 -> 29.960976 | M19: =$E$19*M5 -> 35.436984 | N19: =$E$19*N5 -> 35.241381 | ... R19: =$E$19*R5 -> 11.74185 | S19: =+SUM(G19:R19) -> 331.67514 | T19: 34156 | U19: =S19*T19 -> 11328696 | V19: =U19/$S$5 -> 29.879357
C20: ACIDO CÍTRICO | D20: Kg | E20: ='Resumen costos Ptar Bogotá'!U21 -> 0.00079766595 | F20: =E20*1000 -> 0.79766595 | G20: =$E$20*G5 -> 21.719646 | H20: =$E$20*H5 -> 21.24776 | I20: =$E$20*I5 -> 20.237751 | J20: =$E$20*J5 -> 23.129153 | K20: =$E$20*K5 -> 25.063941 | L20: =$E$20*L5 -> 27.319501 | M20: =$E$20*M5 -> 32.312723 | N20: =$E$20*N5 -> 32.134365 | ... R20: =$E$20*R5 -> 10.706644 | S20: =+SUM(G20:R20) -> 302.43338 | T20: 5200 | U20: =S20*T20 -> 1572653.6 | V20: =U20/$S$5 -> 4.1478629
C21: Subtotal | T21: Total General | U21: =SUM(U6:U20) -> 1.7282086e+09 | V21: =U21/$S$5 -> 4558.1381
S22: PTAR FASE 2 (GEM + MBR) | U22: =U8+U9+U10+U11+U12+U13+U14+U20 -> 1.3646628e+09 | V22: =U22/S5 -> 3599.2887
S23: OSMOSIS INVERSA | U23: =U6+U7+U15+U16+U17+U18+U19 -> 3.6354577e+08 | V23: =U23/S5 -> 958.84945
B25: COSTO PLANTA DE TRATAMIENTO DE AGUA DE POZO PROFUNDO | G25: EJECUTADO PTAP AÑO 2026 BOGOTÁ
B26: Clasificación | C26: Detalle | D26: Unidad | E26: Dosificación | G26: Enero 2026 | H26: Febrero 2026 | I26: Marzo 2026 | J26: Abril 2026 | K26: Mayo 2026 | L26: Junio 2026 | M26: Julio 2026 | N26: Agosto 2026 | O26: Septiembre 2026 | P26: Octubre 2026 | Q26: Noviembre 2026 | R26: Diciembre 2026 | S26: Total general | T26: $/Kg | U26: $ Total | V26: $/M3
E27: Kg/m3 | F27: g/m3 | G27: CAUDAL PLAN MAESTRO
G28: ='PLAN MAESTRO BOGOTA RECIRCU'!F9 -> 5662 | H28: ='PLAN MAESTRO BOGOTA RECIRCU'!H9 -> 5537.9188 | I28: ='PLAN MAESTRO BOGOTA RECIRCU'!J9 -> 5274.6748 | J28: ='PLAN MAESTRO BOGOTA RECIRCU'!L9 -> 6028.2765 | K28: ='PLAN MAESTRO BOGOTA RECIRCU'!N9 -> 9426.4801 | L28: ='PLAN MAESTRO BOGOTA RECIRCU'!P9 -> 10274.79 | M28: ='PLAN MAESTRO BOGOTA RECIRCU'!R9 -> 9722.182 | N28: ='PLAN MAESTRO BOGOTA RECIRCU'!T9 -> 9668.5181 | O28: ='PLAN MAESTRO BOGOTA RECIRCU'!V9 -> 10000.96 | P28: ='PLAN MAESTRO BOGOTA RECIRCU'!X9 -> 10214.547 | Q28: ='PLAN MAESTRO BOGOTA RECIRCU'!Z9 -> 9339.9865 | R28: ='PLAN MAESTRO BOGOTA RECIRCU'!AB9 -> 4697.8629 | S28: =SUM(G28:R28) -> 95848.197
B29: QUIMICOS (Clarifloculador + UF) | C29: ACIDO CLORHIDRICO 31,5% | D29: kg | E29: 0.06 | F29: =E29*1000 -> 60 | G29: =$E$29*G28 -> 339.72 | H29: =$E$29*H28 -> 332.27513 | I29: =$E$29*I28 -> 316.48049 | J29: =$E$29*J28 -> 361.69659 | K29: =$E$29*K28 -> 565.58881 | L29: =$E$29*L28 -> 616.48741 | M29: =$E$29*M28 -> 583.33092 | N29: =$E$29*N28 -> 580.11108 | ... R29: =$E$29*R28 -> 281.87177 | S29: =+SUM(G29:R29) -> 5750.8918 | T29: 1650 | U29: =S29*T29 -> 9488971.5 | V29: =U29/$S$28 -> 99
C30: ACIDIFICANTE | D30: kg | E30: 0.38 | F30: =E30*1000 -> 380 | G30: =$E$30*G28 -> 2151.56 | H30: =$E$30*H28 -> 2104.4091 | I30: =$E$30*I28 -> 2004.3764 | J30: =$E$30*J28 -> 2290.7451 | K30: =$E$30*K28 -> 3582.0624 | L30: =$E$30*L28 -> 3904.4203 | M30: =$E$30*M28 -> 3694.4291 | N30: =$E$30*N28 -> 3674.0369 | ... R30: =$E$30*R28 -> 1785.1879 | S30: =+SUM(G30:R30) -> 36422.315 | T30: 830 | U30: =S30*T30 -> 30230521 | V30: =U30/$S$28 -> 315.4
C31: QUIMICO COAGULANTE PARA TRATAMIENTO DE AGUA (Coagulante) | D31: kg | E31: 0.5426 | F31: =E31*1000 -> 542.6 | G31: =$E$31*G28 -> 3072.2012 | H31: =$E$31*H28 -> 3004.8747 | I31: =$E$31*I28 -> 2862.0386 | J31: =$E$31*J28 -> 3270.9428 | K31: =$E$31*K28 -> 5114.8081 | L31: =$E$31*L28 -> 5575.1011 | M31: =$E$31*M28 -> 5275.2559 | N31: =$E$31*N28 -> 5246.1379 | ... R31: =$E$31*R28 -> 2549.0604 | S31: =+SUM(G31:R31) -> 52007.232 | T31: 2818 | U31: =S31*T31 -> 1.4655638e+08 | V31: =U31/$S$28 -> 1529.0468
C32: QUIMICO FLOCULANTE PARA TRATAMIENTO DE AGUA (Aniónico) | D32: kg | E32: 0.0054 | F32: =E32*1000 -> 5.4 | G32: =$E$32*G28 -> 30.5748 | H32: =$E$32*H28 -> 29.904761 | I32: =$E$32*I28 -> 28.483244 | J32: =$E$32*J28 -> 32.552693 | K32: =$E$32*K28 -> 50.902993 | L32: =$E$32*L28 -> 55.483867 | M32: =$E$32*M28 -> 52.499783 | N32: =$E$32*N28 -> 52.209998 | ... R32: =$E$32*R28 -> 25.36846 | S32: =+SUM(G32:R32) -> 517.58026 | T32: 19050 | U32: =S32*T32 -> 9859904 | V32: =U32/$S$28 -> 102.87
C33: HIPOCLORITO DE SODIO | D33: kg | E33: 0.125 | F33: =E33*1000 -> 125 | G33: =$E$33*G28 -> 707.75 | H33: =$E$33*H28 -> 692.23985 | I33: =$E$33*I28 -> 659.33435 | J33: =$E$33*J28 -> 753.53456 | K33: =$E$33*K28 -> 1178.31 | L33: =$E$33*L28 -> 1284.3488 | M33: =$E$33*M28 -> 1215.2727 | N33: =$E$33*N28 -> 1208.5648 | ... R33: =$E$33*R28 -> 587.23286 | S33: =+SUM(G33:R33) -> 11981.025 | T33: 1298 | U33: =S33*T33 -> 15551370 | V33: =U33/$S$28 -> 162.25
C34: SODA CAUSTICA LIQUI48% 90 KL | D34: kg | E34: 0.037 | F34: =E34*1000 -> 37 | G34: =$E$34*G28 -> 209.494 | H34: =$E$34*H28 -> 204.903 | I34: =$E$34*I28 -> 195.16297 | J34: =$E$34*J28 -> 223.04623 | K34: =$E$34*K28 -> 348.77976 | L34: =$E$34*L28 -> 380.16724 | M34: =$E$34*M28 -> 359.72073 | N34: =$E$34*N28 -> 357.73517 | ... R34: =$E$34*R28 -> 173.82093 | S34: =+SUM(G34:R34) -> 3546.3833 | T34: 1862 | U34: =S34*T34 -> 6603365.7 | V34: =U34/$S$28 -> 68.894
C35: Subtotal | T35: Total General | U35: =SUM(U29:U34) -> 2.1829051e+08 | V35: =U35/$S$28 -> 2277.4608

Sheet PROYECCIÓN RESIDUOS Y LODOS
B2: COSTO PLANTA DE TRATAMIENTO DE AGUA RESIDUAL | F2: EJECUTADO PTAR AÑO 2026 BOGOTÁ
B3: Clasificación | C3: Detalle | D3: Unidad | E3: Generación | F3: Enero 2026 | G3: Febrero 2026 | H3: Marzo 2026 | I3: Abril 2026 | J3: Mayo 2026 | K3: Junio 2026 | L3: Julio 2026 | M3: Agosto 2026 | N3: Septiembre 2026 | O3: Octubre 2026 | P3: Noviembre 2026 | Q3: Diciembre 2026 | R3: Total general | S3: $/Kg | T3: $ Total | U3: $/M3
E4: Kg/m3 | F4: CAUDAL PLAN MAESTRO
F5: ='PLAN MAESTRO BOGOTA RECIRCU'!F5 -> 27229 | G5: ='PLAN MAESTRO BOGOTA RECIRCU'!H5 -> 26637.416 | H5: ='PLAN MAESTRO BOGOTA RECIRCU'!J5 -> 25371.211 | I5: ='PLAN MAESTRO BOGOTA RECIRCU'!L5 -> 28996.039 | J5: ='PLAN MAESTRO BOGOTA RECIRCU'!N5 -> 31421.6 | K5: ='PLAN MAESTRO BOGOTA RECIRCU'!P5 -> 34249.301 | L5: ='PLAN MAESTRO BOGOTA RECIRCU'!R5 -> 40509.091 | M5: ='PLAN MAESTRO BOGOTA RECIRCU'!T5 -> 40285.492 | N5: ='PLAN MAESTRO BOGOTA RECIRCU'!V5 -> 43482.437 | O5: ='PLAN MAESTRO BOGOTA RECIRCU'!X5 -> 40858.186 | P5: ='PLAN MAESTRO BOGOTA RECIRCU'!Z5 -> 26685.676 | Q5: ='PLAN MAESTRO BOGOTA RECIRCU'!AB5 -> 13422.465 | R5: =SUM(F5:Q5) -> 379147.92
B6: RESIDUOS Y LODOS | C6: DISPOSICIÓN DE RESIDUOS (MOTA, PIEDRA, RESIDUOS DE TELA) | D6: kg | E6: 2.8 | F6: 95500 | G6: 95200 | H6: =$E$6*H5 -> 71039.392 | I6: =$E$6*I5 -> 81188.909 | J6: =$E$6*J5 -> 87980.481 | K6: =$E$6*K5 -> 95898.042 | L6: =$E$6*L5 -> 113425.46 | M6: =$E$6*M5 -> 112799.38 | N6: =$E$6*N5 -> 121750.82 | O6: =$E$6*O5 -> 114402.92 | ... Q6: =$E$6*Q5 -> 37582.903 | R6: =+SUM(F6:Q6) -> 1101488.2 | S6: 90 | T6: =R6*S6 -> 99133938 | U6: =T6/$R$5 -> 261.46507
C7: LAVADO DE TANQUES DE 2, 15, 30 Y 60 M3 | D7: $ | E7: N/A | F7: 9985500 | G7: 9985500 | H7: 9985500 | I7: 9985500 | J7: 9985500 | K7: 9985500 | L7: 9985500 | M7: 9985500 | N7: 9985500 | O7: 9985500 | P7: 9985500 | Q7: 9985500 | R7: N/A | S7: N/A | T7: =SUM(F7:Q7) -> 119826000 | U7: =T7/$R$5 -> 316.04025
C8: DISPOSICIÓN DE LODOS DESHIDRATADOS GEM | D8: kg | E8: 3.4 | F8: =$E$8*F5 -> 92578.6 | G8: =$E$8*G5 -> 90567.214 | H8: =$E$8*H5 -> 86262.118 | I8: =$E$8*I5 -> 98586.533 | J8: =$E$8*J5 -> 106833.44 | K8: =$E$8*K5 -> 116447.62 | L8: =$E$8*L5 -> 137730.91 | M8: =$E$8*M5 -> 136970.67 | ... Q8: =$E$8*Q5 -> 45636.383 | R8: =+SUM(F8:Q8) -> 1289102.9 | S8: 50 | T8: =R8*S8 -> 64455146 | U8: =T8/$R$5 -> 170
C9: TRANSPORTE DE LODOS DESHIDRATADOS | D9: Kg/Viaje Amplirrol | E9: 5500 | F9: =F8/$E$9 -> 16.832473 | G9: =G8/$E$9 -> 16.466766 | H9: =H8/$E$9 -> 15.684022 | I9: =I8/$E$9 -> 17.924824 | J9: =J8/$E$9 -> 19.424262 | K9: =K8/$E$9 -> 21.172295 | L9: =L8/$E$9 -> 25.041984 | M9: =M8/$E$9 -> 24.903759 | ... Q9: =Q8/$E$9 -> 8.2975241 | R9: =+SUM(F9:Q9) -> 234.38235 | S9: 900000 | T9: =R9*S9 -> 2.1094411e+08 | U9: =T9/$R$5 -> 556.36364
C10: Subtotal | R10: PTAR FASE 2 | T10: =SUM(T6:T9) -> 4.943592e+08 | U10: =T10/$R$5 -> 1303.869
B12: COSTO PLANTA DE TRATAMIENTO DE AGUA DE POZO PROFUNDO | F12: EJECUTADO PTAP AÑO 2026 BOGOTÁ
B13: Clasificación | C13: Detalle | D13: Unidad | E13: Generación | F13: Enero 2026 | G13: Febrero 2026 | H13: Marzo 2026 | I13: Abril 2026 | J13: Mayo 2026 | K13: Junio 2026 | L13: Julio 2026 | M13: Agosto 2026 | N13: Septiembre 2026 | O13: Octubre 2026 | P13: Noviembre 2026 | Q13: Diciembre 2026 | R13: Total general | S13: $/Kg | T13: $ Total | U13: $/M3
E14: Kg/m3 | F14: CAUDAL PLAN MAESTRO
F15: ='PROYECCIÓN INSUMOS QUÍMICOS'!G28 -> 5662 | G15: ='PROYECCIÓN INSUMOS QUÍMICOS'!H28 -> 5537.9188 | H15: ='PROYECCIÓN INSUMOS QUÍMICOS'!I28 -> 5274.6748 | I15: ='PROYECCIÓN INSUMOS QUÍMICOS'!J28 -> 6028.2765 | J15: ='PROYECCIÓN INSUMOS QUÍMICOS'!K28 -> 9426.4801 | K15: ='PROYECCIÓN INSUMOS QUÍMICOS'!L28 -> 10274.79 | L15: ='PROYECCIÓN INSUMOS QUÍMICOS'!M28 -> 9722.182 | M15: ='PROYECCIÓN INSUMOS QUÍMICOS'!N28 -> 9668.5181 | ... Q15: ='PROYECCIÓN INSUMOS QUÍMICOS'!R28 -> 4697.8629 | R15: =SUM(F15:Q15) -> 95848.197
B16: RESIDUOS Y LODOS | C16: DISPOSICIÓN DE LODOS DESHIDRATADOS GEM PTAP | D16: kg | E16: 1.7 | F16: =$E$16*F15 -> 9625.4 | G16: =$E$16*G15 -> 9414.4619 | H16: =$E$16*H15 -> 8966.9472 | I16: =$E$16*I15 -> 10248.07 | J16: =$E$16*J15 -> 16025.016 | K16: =$E$16*K15 -> 17467.143 | L16: =$E$16*L15 -> 16527.709 | M16: =$E$16*M15 -> 16436.481 | ... Q16: =$E$16*Q15 -> 7986.3669 | R16: =+SUM(F16:Q16) -> 162941.93 | S16: 50 | T16: =R16*S16 -> 8147096.7 | U16: =T16/$R$15 -> 85
C17: TRANSPORTE DE LODOS DESHIDRATADOS | D17: Viajes | E17: 5500 | F17: =F16/$E$9 -> 1.7500727 | G17: =G16/$E$9 -> 1.7117204 | H17: =H16/$E$9 -> 1.630354 | I17: =I16/$E$9 -> 1.8632855 | J17: =J16/$E$9 -> 2.9136393 | K17: =K16/$E$9 -> 3.1758442 | L17: =L16/$E$9 -> 3.0050381 | M17: =M16/$E$9 -> 2.988451 | ... Q17: =Q16/$E$9 -> 1.4520667 | R17: =+SUM(F17:Q17) -> 29.625806 | S17: 900000 | T17: =R17*S17 -> 26663226 | U17: =T17/$R$15 -> 278.18182
C18: Subtotal | R18: PTAP | T18: =SUM(T16:T17) -> 34810322 | U18: =T18/$R$15 -> 363.18182

Sheet PROYECCIÓN CONSUMIBLES PTAR
B2: COSTO PLANTA DE TRATAMIENTO DE AGUA RESIDUAL | F2: EJECUTADO PTAR AÑO 2026 BOGOTÁ
B3: Clasificación | C3: Detalle | D3: Unidad | E3: cantidad | F3: Enero 2026 | G3: Febrero 2026 | H3: Marzo 2026 | I3: Abril 2026 | J3: Mayo 2026 | K3: Junio 2026 | L3: Julio 2026 | M3: Agosto 2026 | N3: Septiembre 2026 | O3: Octubre 2026 | P3: Noviembre 2026 | Q3: Diciembre 2026 | R3: Total general | S3: $/Und | T3: $ Total | U3: $/M3
F4: CAUDAL PLAN MAESTRO
F5: ='PLAN MAESTRO BOGOTA RECIRCU'!F5 -> 27229 | G5: ='PLAN MAESTRO BOGOTA RECIRCU'!H5 -> 26637.416 | H5: ='PLAN MAESTRO BOGOTA RECIRCU'!J5 -> 25371.211 | I5: ='PLAN MAESTRO BOGOTA RECIRCU'!L5 -> 28996.039 | J5: ='PLAN MAESTRO BOGOTA RECIRCU'!N5 -> 31421.6 | K5: ='PLAN MAESTRO BOGOTA RECIRCU'!P5 -> 34249.301 | L5: ='PLAN MAESTRO BOGOTA RECIRCU'!R5 -> 40509.091 | M5: ='PLAN MAESTRO BOGOTA RECIRCU'!T5 -> 40285.492 | N5: ='PLAN MAESTRO BOGOTA RECIRCU'!V5 -> 43482.437 | O5: ='PLAN MAESTRO BOGOTA RECIRCU'!X5 -> 40858.186 | P5: ='PLAN MAESTRO BOGOTA RECIRCU'!Z5 -> 26685.676 | Q5: ='PLAN MAESTRO BOGOTA RECIRCU'!AB5 -> 13422.465 | R5: =SUM(F5:Q5) -> 379147.92
B6: CONSUMIBLES | C6: MEMBRANAS DE RO 1 | D6: Und | E6: 72 | F6: N/A | G6: N/A | H6: N/A | I6: N/A | J6: N/A | K6: N/A | L6: N/A | M6: N/A | N6: N/A | O6: N/A | P6: N/A | Q6: N/A | R6: N/A | S6: 2359000 | T6: =(E6*S6)/3 -> 56616000 | U6: =T6/R5 -> 149.32431
C7: CARTUCHOS 5 MICRAS | D7: Und | E7: 0.018 | F7: =$E$7*F5 -> 490.122 | G7: =$E$7*G5 -> 479.47349 | H7: =$E$7*H5 -> 456.6818 | I7: =$E$7*I5 -> 521.9287 | J7: =$E$7*J5 -> 565.58881 | K7: =$E$7*K5 -> 616.48741 | L7: =$E$7*L5 -> 729.16365 | M7: =$E$7*M5 -> 725.13886 | ... Q7: =$E$7*Q5 -> 241.60438 | R7: =SUM(F7:Q7) -> 6824.6625 | S7: 20900 | T7: =R7*S7 -> 1.4263545e+08 | U7: =T7/R5 -> 376.2
C8: RESINA CATIÓNICA | D8: Global | E8: N/A | F8: N/A | G8: N/A | H8: N/A | I8: N/A | J8: N/A | K8: N/A | L8: N/A | M8: N/A | N8: N/A | O8: N/A | P8: N/A | Q8: N/A | R8: 132492000 | S8: =R8/2 -> 66246000 | T8: =S8 -> 66246000 | U8: =T8/R5 -> 174.72337
C9: REACTIVOS LAB HACH | D9: Global | E9: 1 | F9: N/A | G9: N/A | H9: N/A | I9: N/A | J9: N/A | K9: N/A | L9: N/A | M9: N/A | N9: N/A | O9: N/A | P9: N/A | Q9: N/A | R9: N/A | S9: N/A | T9: =52403589*2 -> 104807178 | U9: =T9/$R$5 -> 276.42821
C10: CONSUMIBLES LAB (Buretas, erlenmeyer, vasos precipitación) | D10: Global | E10: 1 | F10: N/A | G10: N/A | H10: N/A | I10: N/A | J10: N/A | K10: N/A | L10: N/A | M10: N/A | N10: N/A | O10: N/A | P10: N/A | Q10: N/A | R10: N/A | S10: N/A | T10: 9813068 | U10: =T10/$R$5 -> 25.881899
C11: Subtotal | S11: Total General | T11: =SUM(T6:T10) -> 3.8011769e+08 | U11: =T11/$R$5 -> 1002.5578
R12: PTAR FASE 2 (GEM + MBR) | T12: =SUM(T9:T10)*70% -> 80234172 | U12: =T12/R5 -> 211.61707
R13: ÓSMOSIS INVERSA | T13: =(SUM(T9:T10)*30%)+T6+T7+T8 -> 2.9988352e+08 | U13: =T13/R5 -> 790.94071
B15: COSTO PLANTA DE TRATAMIENTO DE AGUA DE POZO PROFUNDO | F15: EJECUTADO PTAP AÑO 2026 BOGOTÁ
B16: Clasificación | C16: Detalle | D16: Unidad | E16: Dosificación | F16: Enero 2026 | G16: Febrero 2026 | H16: Marzo 2026 | I16: Abril 2026 | J16: Mayo 2026 | K16: Junio 2026 | L16: Julio 2026 | M16: Agosto 2026 | N16: Septiembre 2026 | O16: Octubre 2026 | P16: Noviembre 2026 | Q16: Diciembre 2026 | R16: Total general | S16: $/Und | T16: $ Total | U16: $/M3
E17: Und/m3 | F17: CAUDAL PLAN MAESTRO
F18: ='PROYECCIÓN RESIDUOS Y LODOS'!F15 -> 5662 | G18: ='PROYECCIÓN RESIDUOS Y LODOS'!G15 -> 5537.9188 | H18: ='PROYECCIÓN RESIDUOS Y LODOS'!H15 -> 5274.6748 | I18: ='PROYECCIÓN RESIDUOS Y LODOS'!I15 -> 6028.2765 | J18: ='PROYECCIÓN RESIDUOS Y LODOS'!J15 -> 9426.4801 | K18: ='PROYECCIÓN RESIDUOS Y LODOS'!K15 -> 10274.79 | L18: ='PROYECCIÓN RESIDUOS Y LODOS'!L15 -> 9722.182 | M18: ='PROYECCIÓN RESIDUOS Y LODOS'!M15 -> 9668.5181 | ... Q18: ='PROYECCIÓN RESIDUOS Y LODOS'!Q15 -> 4697.8629 | R18: =SUM(F18:Q18) -> 95848.197
B20: CONSUMIBLES | C20: REACTIVOS LAB HACH | D20: Global | E20: 1 | F20: N/A | G20: N/A | H20: N/A | I20: N/A | J20: N/A | K20: N/A | L20: N/A | M20: N/A | N20: N/A | O20: N/A | P20: N/A | Q20: N/A | R20: N/A | S20: N/A | T20: =T9*5% -> 5240358.9 | U20: =T20/$R$18 -> 54.673526
C21: MEMBRANAS DUPONT UF | D21: Global | E21: 1 | F21: N/A | G21: N/A | H21: N/A | I21: N/A | J21: N/A | K21: N/A | L21: N/A | M21: N/A | N21: N/A | O21: N/A | P21: N/A | Q21: N/A | R21: 186000000 | S21: N/A | T21: =186000000/5 -> 37200000 | U21: =T21/R18 -> 388.11372
C22: FILTROS MANGA | D22: Und | E22: 0.005 | F22: =F18*$E$22 -> 28.31 | G22: =G18*$E$22 -> 27.689594 | H22: =H18*$E$22 -> 26.373374 | I22: =I18*$E$22 -> 30.141383 | J22: =J18*$E$22 -> 47.132401 | K22: =K18*$E$22 -> 51.373951 | L22: =L18*$E$22 -> 48.61091 | M22: =M18*$E$22 -> 48.34259 | ... Q22: =Q18*$E$22 -> 23.489315 | R22: =SUM(F22:Q22) -> 479.24098 | S22: 28300 | T22: =R22*S22 -> 13562520 | U22: =T22/$R$18 -> 141.5
C23: Subtotal | S23: Total General | T23: =SUM(T20:T22) -> 56002879 | U23: =T23/$R$18 -> 584.28724

Sheet PROYECCIÓN CALIBR-MANTE PTAR
B2: COSTO PLANTA DE TRATAMIENTO DE AGUA RESIDUAL | F2: EJECUTADO PTAR AÑO 2026 BOGOTÁ
B3: Clasificación | C3: Detalle | D3: Unidad | E3: cantidad | F3: Enero 2026 | G3: Febrero 2026 | H3: Marzo 2026 | I3: Abril 2026 | J3: Mayo 2026 | K3: Junio 2026 | L3: Julio 2026 | M3: Agosto 2026 | N3: Septiembre 2026 | O3: Octubre 2026 | P3: Noviembre 2026 | Q3: Diciembre 2026 | R3: Total general | S3: $/Año | T3: $ Total | U3: $/M3
F4: CAUDAL PLAN MAESTRO
F5: ='PLAN MAESTRO BOGOTA RECIRCU'!F5 -> 27229 | G5: ='PLAN MAESTRO BOGOTA RECIRCU'!H5 -> 26637.416 | H5: ='PLAN MAESTRO BOGOTA RECIRCU'!J5 -> 25371.211 | I5: ='PLAN MAESTRO BOGOTA RECIRCU'!L5 -> 28996.039 | J5: ='PLAN MAESTRO BOGOTA RECIRCU'!N5 -> 31421.6 | K5: ='PLAN MAESTRO BOGOTA RECIRCU'!P5 -> 34249.301 | L5: ='PLAN MAESTRO BOGOTA RECIRCU'!R5 -> 40509.091 | M5: ='PLAN MAESTRO BOGOTA RECIRCU'!T5 -> 40285.492 | N5: ='PLAN MAESTRO BOGOTA RECIRCU'!V5 -> 43482.437 | O5: ='PLAN MAESTRO BOGOTA RECIRCU'!X5 -> 40858.186 | P5: ='PLAN MAESTRO BOGOTA RECIRCU'!Z5 -> 26685.676 | Q5: ='PLAN MAESTRO BOGOTA RECIRCU'!AB5 -> 13422.465 | R5: =SUM(F5:Q5) -> 379147.92
B6: MANTENIMIENTO | C6: CALIBRACIONES EQUIPO LAB | D6: Global | E6: 1 | F6: 1 | G6: 1 | H6: 1 | I6: 1 | J6: 1 | K6: 1 | L6: 1 | M6: 1 | N6: 1 | O6: 1 | P6: 1 | Q6: 1 | R6: N/A | S6: 19091400 | T6: =E6*S6 -> 19091400 | U6: =T6/$R$5 -> 50.353435
C7: MANTENIMIENTOS (Herramienta, materiales de mantenimiento) | D7: Global | E7: 1 | F7: 1 | G7: 1 | H7: 1 | I7: 1 | J7: 1 | K7: 1 | L7: 1 | M7: 1 | N7: 1 | O7: 1 | P7: 1 | Q7: 1 | R7: N/A | S7: =207739008 -> 207739008 | T7: =S7 -> 207739008 | U7: =T7/$R$5 -> 547.91019
C8: Suministro e instalación de bombas dosificadoras OSMOSIS INVERSA | D8: Global | E8: 1 | F8: 1 | G8: 1 | H8: 1 | I8: 1 | J8: 1 | K8: 1 | L8: 1 | M8: 1 | N8: 1 | O8: 1 | P8: 1 | Q8: 1 | R8: 108103011 | S8: =R8/2 -> 54051506 | T8: =S8 -> 54051506 | U8: =T8/$R$5 -> 142.56047
C9: Independizar CIP de la ósmosis inversa | D9: Global | E9: 1 | F9: 1 | G9: 1 | H9: 1 | I9: 1 | J9: 1 | K9: 1 | L9: 1 | M9: 1 | N9: 1 | O9: 1 | P9: 1 | Q9: 1 | R9: 27700656 | S9: =R9/15 -> 1846710.4 | T9: =S9 -> 1846710.4 | U9: =T9/$R$5 -> 4.8706859
C10: Programación y automatización de ósmosis inversa | D10: Global | E10: 1 | F10: 1 | G10: 1 | H10: 1 | I10: 1 | J10: 1 | K10: 1 | L10: 1 | M10: 1 | N10: 1 | O10: 1 | P10: 1 | Q10: 1 | R10: 140100000 | S10: =R10/3 -> 46700000 | T10: =S10 -> 46700000 | U10: =T10/$R$5 -> 123.17093
C11: Subtotal | S11: Total General | T11: =SUM(T6:T10) -> 3.2942862e+08 | U11: =T11/$R$5 -> 868.86571
S12: PTAR FASE 2 (GEM + MBR) | T12: =(T6+T7)*80% -> 1.8146433e+08 | U12: =T12/R5 -> 478.6109
S13: ÓSMOSIS INVERSA | T13: =(T10+T9+T8)+((T6+T7)*20%) -> 1.479643e+08 | U13: =T13/R5 -> 390.25481
B15: COSTO PLANTA DE TRATAMIENTO DE AGUA DE POZO PROFUNDO | F15: EJECUTADO PTAP AÑO 2026 BOGOTÁ
B16: Clasificación | C16: Detalle | D16: Unidad | E16: Dosificación | F16: Enero 2026 | G16: Febrero 2026 | H16: Marzo 2026 | I16: Abril 2026 | J16: Mayo 2026 | K16: Junio 2026 | L16: Julio 2026 | M16: Agosto 2026 | N16: Septiembre 2026 | O16: Octubre 2026 | P16: Noviembre 2026 | Q16: Diciembre 2026 | R16: Total general | S16: $/Kg | T16: $ Total | U16: $/M3
E17: Kg/m3 | F17: CAUDAL PLAN MAESTRO
F18: ='PROYECCIÓN CONSUMIBLES PTAR'!F18 -> 5662 | G18: ='PROYECCIÓN CONSUMIBLES PTAR'!G18 -> 5537.9188 | H18: ='PROYECCIÓN CONSUMIBLES PTAR'!H18 -> 5274.6748 | I18: ='PROYECCIÓN CONSUMIBLES PTAR'!I18 -> 6028.2765 | J18: ='PROYECCIÓN CONSUMIBLES PTAR'!J18 -> 9426.4801 | K18: ='PROYECCIÓN CONSUMIBLES PTAR'!K18 -> 10274.79 | L18: ='PROYECCIÓN CONSUMIBLES PTAR'!L18 -> 9722.182 | M18: ='PROYECCIÓN CONSUMIBLES PTAR'!M18 -> 9668.5181 | ... Q18: ='PROYECCIÓN CONSUMIBLES PTAR'!Q18 -> 4697.8629 | R18: =SUM(F18:Q18) -> 95848.197
B19: MANTENIMIENTO | C19: MANTENIMIENTO POZO | D19: Global | E19: 1 | F19: N/A | G19: N/A | H19: N/A | I19: N/A | J19: N/A | K19: N/A | L19: N/A | M19: N/A | N19: N/A | O19: N/A | P19: N/A | Q19: N/A | R19: N/A | S19: N/A | T19: 15140000 | U19: =T19/R18 -> 157.95811
C20: MANTENIMIENTOS (Herramienta, materiales de mantenimiento) | D20: Global | E20: 1 | F20: 1 | G20: 1 | H20: 1 | I20: 1 | J20: 1 | K20: 1 | L20: 1 | M20: 1 | N20: 1 | O20: 1 | P20: 1 | Q20: 1 | R20: N/A | S20: =S7*5% -> 10386950 | T20: =E20*S20 -> 10386950 | U20: =T20/$R$5 -> 27.39551
C21: CALIBRACIONES | D21: Global | E21: 1 | F21: N/A | G21: N/A | H21: N/A | I21: N/A | J21: N/A | K21: N/A | L21: N/A | M21: N/A | N21: N/A | O21: N/A | P21: N/A | Q21: N/A | R21: N/A | S21: N/A | T21: =T6*10% -> 1909140 | U21: =T21/R18 -> 19.918372
C22: Subtotal | S22: Total General | T22: =SUM(T19:T21) -> 27436090 | U22: =T22/R18 -> 286.24524

Sheet PROYECCIÓN NOMINA PTAR
B2: COSTO PLANTA DE TRATAMIENTO DE AGUA RESIDUAL | F2: EJECUTADO PTAR AÑO 2026 BOGOTÁ
B3: Clasificación | C3: Detalle | D3: Unidad | E3: Cantidad | F3: Enero 2026 | G3: Febrero 2026 | H3: Marzo 2026 | I3: Abril 2026 | J3: Mayo 2026 | K3: Junio 2026 | L3: Julio 2026 | M3: Agosto 2026 | N3: Septiembre 2026 | O3: Octubre 2026 | P3: Noviembre 2026 | Q3: Diciembre 2026 | R3: Total general | S3: $/Año | T3: $ Total | U3: $/M3
F4: CAUDAL PLAN MAESTRO
F5: ='PLAN MAESTRO BOGOTA RECIRCU'!F5 -> 27229 | G5: ='PLAN MAESTRO BOGOTA RECIRCU'!H5 -> 26637.416 | H5: ='PLAN MAESTRO BOGOTA RECIRCU'!J5 -> 25371.211 | I5: ='PLAN MAESTRO BOGOTA RECIRCU'!L5 -> 28996.039 | J5: ='PLAN MAESTRO BOGOTA RECIRCU'!N5 -> 31421.6 | K5: ='PLAN MAESTRO BOGOTA RECIRCU'!P5 -> 34249.301 | L5: ='PLAN MAESTRO BOGOTA RECIRCU'!R5 -> 40509.091 | M5: ='PLAN MAESTRO BOGOTA RECIRCU'!T5 -> 40285.492 | N5: ='PLAN MAESTRO BOGOTA RECIRCU'!V5 -> 43482.437 | O5: ='PLAN MAESTRO BOGOTA RECIRCU'!X5 -> 40858.186 | P5: ='PLAN MAESTRO BOGOTA RECIRCU'!Z5 -> 26685.676 | Q5: ='PLAN MAESTRO BOGOTA RECIRCU'!AB5 -> 13422.465 | R5: =SUM(F5:Q5) -> 379147.92
B6: NÓMINA | C6: PERSONAL TÉCNICO | D6: Global | E6: 1 | F6: =$G$31 -> 36784446 | G6: =$G$31 -> 36784446 | H6: =$G$31 -> 36784446 | I6: =$G$31 -> 36784446 | J6: =$G$31 -> 36784446 | K6: =$G$31 -> 36784446 | L6: =$G$31 -> 36784446 | M6: =$G$31 -> 36784446 | ... Q6: =$G$31 -> 36784446 | R6: N/A | S6: =SUM(F6:Q6) -> 4.4141335e+08 | T6: =E6*S6 -> 4.4141335e+08 | U6: =T6/$R$5 -> 1164.2246
C7: DOTACIÓN | D7: Global | E7: 1 | F7: 1 | G7: 1 | H7: 1 | I7: 1 | J7: 1 | K7: 1 | L7: 1 | M7: 1 | N7: 1 | O7: 1 | P7: 1 | Q7: 1 | R7: N/A | S7: 5389920 | T7: =E7*S7 -> 5389920 | U7: =T7/$R$5 -> 14.215877
C8: OTROS SERVICIOS (ÉXAMENES MÉDICOS) | D8: Global | E8: 1 | F8: 1 | G8: 1 | H8: 1 | I8: 1 | J8: 1 | K8: 1 | L8: 1 | M8: 1 | N8: 1 | O8: 1 | P8: 1 | Q8: 1 | R8: N/A | S8: 1593312 | T8: =E8*S8 -> 1593312 | U8: =T8/$R$5 -> 4.2023494
C9: Subtotal | S9: Total General | T9: =SUM(T6:T8) -> 4.4839658e+08 | U9: =T9/$R$5 -> 1182.6429
S10: PTAR FASE 2 (GEM + MBR) | T10: 0.7 | U10: =U9*T10 -> 827.85001
S11: ÓSMOSIS INVERSA | T11: 0.3 | U11: =U9*T11 -> 354.79286
B13: COSTO PLANTA DE TRATAMIENTO DE AGUA DE POZO PROFUNDO | F13: EJECUTADO PTAP AÑO 2026 BOGOTÁ
B14: Clasificación | C14: Detalle | D14: Unidad | E14: Cantidad | F14: Enero 2026 | G14: Febrero 2026 | H14: Marzo 2026 | I14: Abril 2026 | J14: Mayo 2026 | K14: Junio 2026 | L14: Julio 2026 | M14: Agosto 2026 | N14: Septiembre 2026 | O14: Octubre 2026 | P14: Noviembre 2026 | Q14: Diciembre 2026 | R14: Total general | S14: $/Año | T14: $ Total | U14: $/M3
F15: CAUDAL PLAN MAESTRO
F16: ='PROYECCIÓN CALIBR-MANTE PTAR'!F18 -> 5662 | G16: ='PROYECCIÓN CALIBR-MANTE PTAR'!G18 -> 5537.9188 | H16: ='PROYECCIÓN CALIBR-MANTE PTAR'!H18 -> 5274.6748 | I16: ='PROYECCIÓN CALIBR-MANTE PTAR'!I18 -> 6028.2765 | J16: ='PROYECCIÓN CALIBR-MANTE PTAR'!J18 -> 9426.4801 | K16: ='PROYECCIÓN CALIBR-MANTE PTAR'!K18 -> 10274.79 | L16: ='PROYECCIÓN CALIBR-MANTE PTAR'!L18 -> 9722.182 | M16: ='PROYECCIÓN CALIBR-MANTE PTAR'!M18 -> 9668.5181 | ... Q16: ='PROYECCIÓN CALIBR-MANTE PTAR'!Q18 -> 4697.8629 | R16: =SUM(F16:Q16) -> 95848.197
B17: NÓMINA | C17: PERSONAL TÉCNICO | D17: Global | E17: 1 | F17: =$G$32 -> 9980972.4 | G17: =$G$32 -> 9980972.4 | H17: =$G$32 -> 9980972.4 | I17: =$G$32 -> 9980972.4 | J17: =$G$32 -> 9980972.4 | K17: =$G$32 -> 9980972.4 | L17: =$G$32 -> 9980972.4 | M17: =$G$32 -> 9980972.4 | ... Q17: =$G$32 -> 9980972.4 | R17: N/A | S17: =SUM(F17:Q17)/2 -> 59885834 | T17: =E17*S17 -> 59885834 | U17: =T17/$R$16 -> 624.79876
C18: DOTACIÓN | D18: Global | E18: 1 | F18: 1 | G18: 1 | H18: 1 | I18: 1 | J18: 1 | K18: 1 | L18: 1 | M18: 1 | N18: 1 | O18: 1 | P18: 1 | Q18: 1 | R18: N/A | S18: =5389920*30% -> 1616976 | T18: =E18*S18 -> 1616976 | U18: =T18/$R$5 -> 4.264763
C19: OTROS SERVICIOS (ÉXAMENES MÉDICOS) | D19: Global | E19: 1 | F19: 1 | G19: 1 | H19: 1 | I19: 1 | J19: 1 | K19: 1 | L19: 1 | M19: 1 | N19: 1 | O19: 1 | P19: 1 | Q19: 1 | R19: N/A | S19: =1593312*30% -> 477993.6 | T19: =E19*S19 -> 477993.6 | U19: =T19/$R$5 -> 1.2607048
C20: Subtotal | S20: Total general | T20: =SUM(T17:T19) -> 61980804 | U20: =SUM(U17:U19) -> 630.32423
C22: NÓMINA PROYECTADA
C23: CARGO | D23: SALARIO | E23: NÚMERO | F23: DEDICACIÓN | G23: UBICACIÓN | H23: TOTAL ($)/Mes
C24: Auxiliar de MTTO PTAR | D24: 3172412 | E24: 3 | F24: 0.5 | G24: PTAR Bógota | H24: =D24*E24*F24 -> 4758618
C25: Técnico de MTTO PTAR | D25: 3929433 | E25: 6 | F25: 1 | G25: PTAR Bógota | H25: =D25*E25*F25 -> 23576598
C26: Coordinación PTAR/PTAP | D26: 8067188 | E26: 1 | F26: 0.7 | G26: PTAR Bógota | H26: =D26*E26*F26 -> 5647031.6
D27: 8067188 | E27: 1 | F27: 0.3 | G27: PTAP Bógota | H27: =D27*E27*F27 -> 2420156.4
C28: JEFATURA PTAR/PTAP | D28: 11208792 | E28: 1 | F28: 0.25 | G28: PTAR Bógota | H28: =D28*E28*F28 -> 2802198
D29: 11208792 | E29: 1 | F29: 0.25 | G29: PTAP Bógota | H29: =D29*E29*F29 -> 2802198
F31: Total PTAR Bógota | G31: =H24+H25+H26+H28 -> 36784446
F32: Total PTAP Bógota | G32: =H24+H27+H29 -> 9980972.4

Sheet PROYECCIÓN ELECTRICIDAD PTAR
B2: COSTO PLANTA DE TRATAMIENTO DE AGUA RESIDUAL | F2: EJECUTADO PTAR AÑO 2026 BOGOTÁ
B3: Clasificación | C3: Detalle | D3: Unidad | E3: cantidad | F3: Enero 2026 | G3: Febrero 2026 | H3: Marzo 2026 | I3: Abril 2026 | J3: Mayo 2026 | K3: Junio 2026 | L3: Julio 2026 | M3: Agosto 2026 | N3: Septiembre 2026 | O3: Octubre 2026 | P3: Noviembre 2026 | Q3: Diciembre 2026 | R3: Total general | S3: $/Año | T3: $ Total | U3: $/M3
F4: CAUDAL PLAN MAESTRO
F5: ='PLAN MAESTRO BOGOTA RECIRCU'!F5 -> 27229 | G5: ='PLAN MAESTRO BOGOTA RECIRCU'!H5 -> 26637.416 | H5: ='PLAN MAESTRO BOGOTA RECIRCU'!J5 -> 25371.211 | I5: ='PLAN MAESTRO BOGOTA RECIRCU'!L5 -> 28996.039 | J5: ='PLAN MAESTRO BOGOTA RECIRCU'!N5 -> 31421.6 | K5: ='PLAN MAESTRO BOGOTA RECIRCU'!P5 -> 34249.301 | L5: ='PLAN MAESTRO BOGOTA RECIRCU'!R5 -> 40509.091 | M5: ='PLAN MAESTRO BOGOTA RECIRCU'!T5 -> 40285.492 | N5: ='PLAN MAESTRO BOGOTA RECIRCU'!V5 -> 43482.437 | O5: ='PLAN MAESTRO BOGOTA RECIRCU'!X5 -> 40858.186 | P5: ='PLAN MAESTRO BOGOTA RECIRCU'!Z5 -> 26685.676 | Q5: ='PLAN MAESTRO BOGOTA RECIRCU'!AB5 -> 13422.465 | R5: =SUM(F5:Q5) -> 379147.92
B6: CONSUMO ELÉCTRICO | C6: CONSUMO ELÉCTRICO | D6: kW | E6: 1 | F6: 1 | G6: 1 | H6: 1 | I6: 1 | J6: 1 | K6: 1 | L6: 1 | M6: 1 | N6: 1 | O6: 1 | P6: 1 | Q6: 1 | R6: N/A | S6: =H20 -> 1728000000 | T6: =E6*S6 -> 1728000000 | U6: =T6/$R$5 -> 4557.588
C7: Subtotal | S7: Total General | T7: =SUM(T6:T6) -> 1728000000 | U7: =T7/$R$5 -> 4557.588
S8: PTAR FASE 2 (GEM + MBR) | T8: 0.8 | U8: =U7*T8 -> 3646.0704
S9: ÓSMOSIS INVERSA | T9: 0.2 | U9: =U7*T9 -> 911.51761
B11: COSTO PLANTA DE TRATAMIENTO DE AGUA DE POZO PROFUNDO | F11: EJECUTADO PTAP AÑO 2026 BOGOTÁ
B12: Clasificación | C12: Detalle | D12: Unidad | E12: Dosificación | F12: Enero 2026 | G12: Febrero 2026 | H12: Marzo 2026 | I12: Abril 2026 | J12: Mayo 2026 | K12: Junio 2026 | L12: Julio 2026 | M12: Agosto 2026 | N12: Septiembre 2026 | O12: Octubre 2026 | P12: Noviembre 2026 | Q12: Diciembre 2026 | R12: Total general | S12: $/Año | T12: $ Total | U12: $/M3
E13: Kg/m3 | F13: CAUDAL PLAN MAESTRO
F14: ='PROYECCIÓN NOMINA PTAR'!F16 -> 5662 | G14: ='PROYECCIÓN NOMINA PTAR'!G16 -> 5537.9188 | H14: ='PROYECCIÓN NOMINA PTAR'!H16 -> 5274.6748 | I14: ='PROYECCIÓN NOMINA PTAR'!I16 -> 6028.2765 | J14: ='PROYECCIÓN NOMINA PTAR'!J16 -> 9426.4801 | K14: ='PROYECCIÓN NOMINA PTAR'!K16 -> 10274.79 | L14: ='PROYECCIÓN NOMINA PTAR'!L16 -> 9722.182 | M14: ='PROYECCIÓN NOMINA PTAR'!M16 -> 9668.5181 | ... Q14: ='PROYECCIÓN NOMINA PTAR'!Q16 -> 4697.8629 | R14: =SUM(F14:Q14) -> 95848.197
B15: CONSUMO ELÉCTRICO | C15: CONSUMO ELÉCTRICO | D15: Global | E15: 1 | F15: 1 | G15: 1 | H15: 1 | I15: 1 | J15: 1 | K15: 1 | L15: 1 | M15: 1 | N15: 1 | O15: 1 | P15: 1 | Q15: 1 | R15: N/A | S15: =H21 -> 74361600 | T15: =E15*S15 -> 74361600 | U15: =T15/$R$14 -> 775.8268
C16: Subtotal | S16: Total General | T16: =T15 -> 74361600 | U16: =U15 -> 775.8268
C18: kW Proyectados y medidos
C19: Kw/h | D19: Costo ($/Kw) | E19: Costo Total ($/Hora) | F19: Costo Total ($/Día) | G19: Costo Total ($/Mes) | H19: Costo Total ($/Año)
C20: 300 | D20: 800 | E20: =D20*C20 -> 240000 | F20: =E20*24 -> 5760000 | G20: =F20*25 -> 144000000 | H20: =G20*12 -> 1728000000 | I20: PTAR
C21: 12.91 | D21: 800 | E21: =D21*C21 -> 10328 | F21: =E21*24 -> 247872 | G21: =F21*25 -> 6196800 | H21: =G21*12 -> 74361600 | I21: PTAP

Sheet PROYECCIÓN DEPRECIACIÓN PTAR
B2: COSTO PLANTA DE TRATAMIENTO DE AGUA RESIDUAL | F2: EJECUTADO PTAR AÑO 2026 BOGOTÁ
B3: Clasificación | C3: Detalle | D3: Unidad | E3: cantidad | F3: Enero 2026 | G3: Febrero 2026 | H3: Marzo 2026 | I3: Abril 2026 | J3: Mayo 2026 | K3: Junio 2026 | L3: Julio 2026 | M3: Agosto 2026 | N3: Septiembre 2026 | O3: Octubre 2026 | P3: Noviembre 2026 | Q3: Diciembre 2026 | R3: Total general | S3: $/Año | T3: $ Total | U3: $/M3
F4: CAUDAL PLAN MAESTRO
F5: ='PLAN MAESTRO BOGOTA RECIRCU'!F5 -> 27229 | G5: ='PLAN MAESTRO BOGOTA RECIRCU'!H5 -> 26637.416 | H5: ='PLAN MAESTRO BOGOTA RECIRCU'!J5 -> 25371.211 | I5: ='PLAN MAESTRO BOGOTA RECIRCU'!L5 -> 28996.039 | J5: ='PLAN MAESTRO BOGOTA RECIRCU'!N5 -> 31421.6 | K5: ='PLAN MAESTRO BOGOTA RECIRCU'!P5 -> 34249.301 | L5: ='PLAN MAESTRO BOGOTA RECIRCU'!R5 -> 40509.091 | M5: ='PLAN MAESTRO BOGOTA RECIRCU'!T5 -> 40285.492 | N5: ='PLAN MAESTRO BOGOTA RECIRCU'!V5 -> 43482.437 | O5: ='PLAN MAESTRO BOGOTA RECIRCU'!X5 -> 40858.186 | P5: ='PLAN MAESTRO BOGOTA RECIRCU'!Z5 -> 26685.676 | Q5: ='PLAN MAESTRO BOGOTA RECIRCU'!AB5 -> 13422.465 | R5: =SUM(F5:Q5) -> 379147.92
B6: Depreciación | C6: CAPEX EQUIPOS | D6: Global | E6: 1 | F6: 1 | G6: 1 | H6: 1 | I6: 1 | J6: 1 | K6: 1 | L6: 1 | M6: 1 | N6: 1 | O6: 1 | P6: 1 | Q6: 1 | R6: =L24-V25 -> 7.9709108e+09 | S6: =R6/15 -> 5.3139405e+08 | T6: =E6*S6 -> 5.3139405e+08 | U6: =T6/$R$5 -> 1401.5481
C7: CAPEX OBRA CIVIL | D7: Global | E7: 1 | F7: 1 | G7: 1 | H7: 1 | I7: 1 | J7: 1 | K7: 1 | L7: 1 | M7: 1 | N7: 1 | O7: 1 | P7: 1 | Q7: 1 | R7: =O22 -> 6.3134958e+09 | S7: =R7/30 -> 2.1044986e+08 | T7: =E7*S7 -> 2.1044986e+08 | U7: =T7/$R$5 -> 555.06005
C8: DEPRECIACIÓN | D8: Global | E8: 1 | F8: 1 | G8: 1 | H8: 1 | I8: 1 | J8: 1 | K8: 1 | L8: 1 | M8: 1 | N8: 1 | O8: 1 | P8: 1 | Q8: 1 | R8: N/A | S8: 1544735744 | T8: =E8*S8 -> 1544735744 | U8: =T8/$R$5 -> 4074.2298
C9: Subtotal | S9: Total General | T9: =SUM(T6:T7) -> 7.4184391e+08 | U9: =T9/$R$5 -> 1956.6082
S10: PTAR FASE 2 (GEM + MBR) | T10: 0.9 | U10: =U9*T10 -> 1760.9474
S11: ÓSMOSIS INVERSA | T11: =(I23*100%)/E72 -> 0.10037686 | U11: =U9*T11 -> 196.39819
B13: COSTO PLANTA DE TRATAMIENTO DE AGUA DE POZO PROFUNDO | F13: EJECUTADO PTAP AÑO 2026 BOGOTÁ
B14: Clasificación | C14: Detalle | D14: Unidad | E14: Dosificación | F14: Enero 2026 | G14: Febrero 2026 | H14: Marzo 2026 | I14: Abril 2026 | J14: Mayo 2026 | K14: Junio 2026 | L14: Julio 2026 | M14: Agosto 2026 | N14: Septiembre 2026 | O14: Octubre 2026 | P14: Noviembre 2026 | Q14: Diciembre 2026 | R14: Total general | S14: $/Año | T14: $ Total | U14: $/M3
E15: Kg/m3 | F15: CAUDAL PLAN MAESTRO
F16: ='PROYECCIÓN NOMINA PTAR'!F16 -> 5662 | G16: ='PROYECCIÓN NOMINA PTAR'!G16 -> 5537.9188 | H16: ='PROYECCIÓN NOMINA PTAR'!H16 -> 5274.6748 | I16: ='PROYECCIÓN NOMINA PTAR'!I16 -> 6028.2765 | J16: ='PROYECCIÓN NOMINA PTAR'!J16 -> 9426.4801 | K16: ='PROYECCIÓN NOMINA PTAR'!K16 -> 10274.79 | L16: ='PROYECCIÓN NOMINA PTAR'!L16 -> 9722.182 | M16: ='PROYECCIÓN NOMINA PTAR'!M16 -> 9668.5181 | ... Q16: ='PROYECCIÓN NOMINA PTAR'!Q16 -> 4697.8629 | R16: =SUM(F16:Q16) -> 95848.197
B17: Depreciación | C17: DEPRECIACIÓN | D17: Global | E17: 1 | F17: 1 | G17: 1 | H17: 1 | I17: 1 | J17: 1 | K17: 1 | L17: 1 | M17: 1 | N17: 1 | O17: 1 | P17: 1 | Q17: 1 | R17: ='PROYEC COSTO M3 PERMODA BOGOTA'!D81 -> 1527416878 | S17: =R17/10 -> 1.5274169e+08 | T17: =E17*S17 -> 1.5274169e+08 | U17: =T17/$R$5 -> 402.85514
C18: CONTRUCCIÓN POZO | D18: Global | E18: 1 | F18: 1 | G18: 1 | H18: 1 | I18: 1 | J18: 1 | K18: 1 | L18: 1 | M18: 1 | N18: 1 | O18: 1 | P18: 1 | Q18: 1 | R18: 598771671 | S18: =R18/10 -> 59877167 | T18: =E18*S18 -> 59877167 | U18: =T18/$R$5 -> 157.92561
C19: Subtotal | S19: Total General | T19: =SUM(T17:T18) -> 2.1261885e+08 | U19: =SUM(U17:U18) -> 560.78076
K20: CAPEX EQUIPOS | L20: =E72-E26 -> 1.8606404e+10
C21: 2.EQUIPOS DE SOPORTE | D21: 1.417293e+10 | E21: 1.417293e+10 | K21: 1.Caldera CBEXWW 700- 300 BHP | L21: 9.521797e+08
C22: 1.EQUIPOS PROCESOS | D22: 1.417293e+10 | E22: 1.417293e+10 | G22: EVAPORADOR | H22: 965521 | I22: =H22*3700 -> 3572427700 | K22: EVAPORADOR | L22: =I22 -> 3572427700 | N22: CAPEX OBRA CIVIL | O22: =E26 -> 6.3134958e+09 | T22: BENEFICIOS TRIBUTARIOS (25%) | U22: IVA | V22: 2936270641 | W22: =(V22*100%)/E72 -> 0.11782835
C23: 1.Caldera CBEXWW 700- 300 BHP | D23: 9.521797e+08 | E23: 9.521797e+08 | G23: ÓSMOSIS INVERSA | H23: 676049 | I23: =H23*3700 -> 2501381300 | K23: Caldera CBEXWW 700-300 BHP | L23: =E23 -> 9.521797e+08 | U23: RENTA | V23: 3174614783 | W23: =(V23*100%)/E72 -> 0.12739276
C24: 2.MAQUINARIA-A CWT | D24: 13220749871 | E24: 13220749871 | K24: CAPEX REAL EQUIPOS TOTAL | L24: =L20-L22-L23 -> 1.4081796e+10
C25: 3.ADECUACIONES Y MONTAJES | D25: 8.5483127e+09 | E25: 8.5483127e+09 | U25: TOTAL | V25: =SUM(V22:V23) -> 6110885424
C26: 1.OBRAS CIVILES | D26: 6.3134958e+09 | E26: 6.3134958e+09 | N26: COSTO TOTAL | O26: =L20+O22 -> 2.4919899e+10
C27: 2.Obras SGC | D27: 6.2502364e+09 | E27: 6.2502364e+09 | V27: =(V25*100%)/E72 -> 0.24522111
C28: 3.Obras Civil Otros | D28: 63259382 | E28: 63259382
C29: 2.MONTAJE MECANICO | D29: 1.1559096e+09 | E29: 1.1559096e+09
C30: 1.Demolicion-Method – Ozono | D30: 27305283 | E30: 27305283
C31: 10.PASAMUROS TANQUES | D31: 77659969 | E31: 77659969
C32: 11.PUENTE GRUA | D32: 143882900 | E32: 143882900
C33: 12.REJILLAS | D33: 83528753 | E33: 83528753
C34: 14. Sistema de suavización PTAR | D34: 142984383 | E34: 142984383
C35: 15. Ingeniería básica, hidráulica y eléctrica presentada por CWT | D35: 16421144 | E35: 16421144
C36: 16. Suministro e instalación de las 3 líneas y la bomba que realizarán el trasiego de los químicos | D36: 5126549.8 | E36: 5126549.8
C37: 18. Adecuaciones red de vertimiento | D37: 16880695 | E37: 16880695
C38: 19. Adecuación trasiego de químicos | D38: 35456632 | E38: 35456632
C39: 20.Elevación Swingmill - CWT | D39: 28530000 | E39: 28530000
... C72: Total presupuestal | D72: 2.4919899e+10 | E72: 2.4919899e+10

Sheet PROYECCIÓN PAGO USO POZO
B2: COSTO PLANTA DE TRATAMIENTO DE AGUA DE POZO PROFUNDO | F2: EJECUTADO PTAP AÑO 2026 BOGOTÁ
B3: Clasificación | C3: Detalle | D3: Unidad | E3: Dosificación | F3: Enero 2026 | G3: Febrero 2026 | H3: Marzo 2026 | I3: Abril 2026 | J3: Mayo 2026 | K3: Junio 2026 | L3: Julio 2026 | M3: Agosto 2026 | N3: Septiembre 2026 | O3: Octubre 2026 | P3: Noviembre 2026 | Q3: Diciembre 2026 | R3: Total general | S3: $/Año | T3: $ Total | U3: $/M3
E4: Kg/m3 | F4: CAUDAL PLAN MAESTRO
F5: ='PROYECCIÓN NOMINA PTAR'!F16 -> 5662 | G5: ='PROYECCIÓN NOMINA PTAR'!G16 -> 5537.9188 | H5: ='PROYECCIÓN NOMINA PTAR'!H16 -> 5274.6748 | I5: ='PROYECCIÓN NOMINA PTAR'!I16 -> 6028.2765 | J5: ='PROYECCIÓN NOMINA PTAR'!J16 -> 9426.4801 | K5: ='PROYECCIÓN NOMINA PTAR'!K16 -> 10274.79 | L5: ='PROYECCIÓN NOMINA PTAR'!L16 -> 9722.182 | M5: ='PROYECCIÓN NOMINA PTAR'!M16 -> 9668.5181 | ... Q5: ='PROYECCIÓN NOMINA PTAR'!Q16 -> 4697.8629 | R5: =SUM(F5:Q5) -> 95848.197
B6: TASAS | C6: TASA RETRIBUTIVA | D6: Global | E6: 1 | F6: 1 | G6: 1 | H6: 1 | I6: 1 | J6: 1 | K6: 1 | L6: 1 | M6: 1 | N6: 1 | O6: 1 | P6: 1 | Q6: 1 | R6: N/A | S6: 1514587 | T6: =E6*S6 -> 1514587 | U6: =T6/R5 -> 15.801935
C7: TASA RETRIBUTIVA | D7: Global | E7: 1 | F7: 1 | G7: 1 | H7: 1 | I7: 1 | J7: 1 | K7: 1 | L7: 1 | M7: 1 | N7: 1 | O7: 1 | P7: 1 | Q7: 1 | R7: N/A | S7: =R5*129 -> 12364417 | T7: =E7*S7 -> 12364417 | U7: =T7/R5 -> 129
C8: Subtotal | R8: Total general | T8: =SUM(T6:T7) -> 13879004 | U8: =SUM(U6:U7) -> 144.80194
