Workbook
Name ANALISTA: #REF!
Name BALANCEO: #REF!
Name ESTADO: #REF!
Name PLANTAS: #REF!
Name PRENDA: #REF!
Name PROCESO: #REF!
Name SegmentaciónDeDatos_DIA: #N/A
Name SegmentaciónDeDatos_FECHA1: #N/A
Name SegmentaciónDeDatos_FECHA2: #N/A
Name TIPO: #REF!

Sheet PROYECCIÓN INSUMOS QUÍMICO
B2: COSTO PLANTA DE TRATAMIENTO DE AGUA RESIDUAL
B3: Clasificación | C3: Detalle | D3: Unidad | E3: Dosificación | F3: ABRIL 2026 | G3: ABRIL REAL | H3: Abril 2026 | I3: Mayo 2026 | J3: Junio 2026 | K3: Julio 2026 | L3: Agosto 2026 | M3: Septiembre 2026 | N3: Octubre 2026 | O3: Noviembre 2026 | P3: Diciembre 2026 | Q3: Total general | R3: kg/m3 PROYECCION | S3: Kg/m3 REAL | T3: % CONSUMO Kg/m3 | U3: $/Kg | V3: $ Total PROYECCIÓN | W3: $ Total REAL | X3: % CONSUMO $Total | Y3: $/M3 PROYECCIÓN | Z3: $/M3 REAL | AA3: DIFERENCIAL $/M3
E4: Kg/m3
F5: 28996.039 | G5: ='DB QUIMICA'!Z8 -> 32414 | H5: ='[1]PLAN MAESTRO BOGOTA RECIRCU'!L5 -> 28996.039 | I5: ='[1]PLAN MAESTRO BOGOTA RECIRCU'!N5 -> 31421.6 | J5: ='[1]PLAN MAESTRO BOGOTA RECIRCU'!P5 -> 34249.301 | K5: ='[1]PLAN MAESTRO BOGOTA RECIRCU'!R5 -> 40509.091 | L5: ='[1]PLAN MAESTRO BOGOTA RECIRCU'!T5 -> 40285.492 | M5: ='[1]PLAN MAESTRO BOGOTA RECIRCU'!V5 -> 43482.437 | N5: ='[1]PLAN MAESTRO BOGOTA RECIRCU'!X5 -> 40858.186 | O5: ='[1]PLAN MAESTRO BOGOTA RECIRCU'!Z5 -> 26685.676 | P5: ='[1]PLAN MAESTRO BOGOTA RECIRCU'!AB5 -> 13422.465 | Q5: =SUM(F5:P5) -> 361320.33
B6: QUIMICOS (GEM + RO) | C6: ACIDO CLORHIDRICO 31,5% | D6: kg | E6: 0.013583636 | F6: 393.87165 | G6: =19*2 -> 38 | H6: =$E$6*H5 -> 393.87165 | I6: =$E$6*I5 -> 426.81959 | J6: =$E$6*J5 -> 465.23004 | K6: =$E$6*K5 -> 550.26077 | L6: =$E$6*L5 -> 547.22347 | M6: =$E$6*M5 -> 590.64961 | N6: =$E$6*N5 -> 555.00275 | O6: =$E$6*O5 -> 362.48852 | P6: =$E$6*P5 -> 182.32589 | Q6: =+SUM(F6:P6) -> 4505.7439 | R6: =F6/$F$5 -> 0.013583636 | S6: =G6/$G$5 -> 0.0011723329 | T6: =1-S6/R6 -> 0.91369521 | U6: 1650 | V6: =F6*U6 -> 649888.22 | W6: =G6*U6 -> 62700 | X6: =1-W6/V6 -> 0.90352187 | Y6: =V6/$F$5 -> 22.413 | Z6: =W6/$G$5 -> 1.9343494 | AA6: =Y6-Z6 -> 20.478651 | AC6: Por cada CIP son 19 Kg de acido aprox
C7: SODIO BISULFITO | D7: kg | E7: 0.0011916667 | F7: 34.553613 | G7: 0 | H7: =$E$7*H5 -> 34.553613 | I7: =$E$7*I5 -> 37.444074 | J7: =$E$7*J5 -> 40.81375 | K7: =$E$7*K5 -> 48.273334 | L7: =$E$7*L5 -> 48.006878 | M7: =$E$7*M5 -> 51.816571 | N7: =$E$7*N5 -> 48.689339 | O7: =$E$7*O5 -> 31.80043 | P7: =$E$7*P5 -> 15.995105 | Q7: =+SUM(F7:P7) -> 391.94671 | R7: =F7/$F$5 -> 0.0011916667 | S7: =G7/$G$5 -> 0 | T7: =1-S7/R7 -> 1 | U7: 4200 | V7: =F7*U7 -> 145125.18 | W7: =G7*U7 -> 0 | X7: =1-W7/V7 -> 1 | Y7: =V7/$F$5 -> 5.005 | Z7: =W7/$G$5 -> 0 | AA7: =Y7-Z7 -> 5.005
C8: NITRATO DE PLATA | D8: kg | E8: 1.8118958e-05 | F8: 0.525378 | G8: =120*1/1000 -> 0.12 | H8: =$E$8*H5 -> 0.525378 | I8: =$E$8*I5 -> 0.56932665 | J8: =$E$8*J5 -> 0.62056163 | K8: =$E$8*K5 -> 0.73398252 | L8: =$E$8*L5 -> 0.72993113 | M8: =$E$8*M5 -> 0.78785643 | N8: =$E$8*N5 -> 0.74030775 | O8: =$E$8*O5 -> 0.48351663 | P8: =$E$8*P5 -> 0.24320108 | Q8: =+SUM(F8:P8) -> 6.0794398 | R8: =F8/$F$5 -> 1.8118958e-05 | S8: =G8/$G$5 -> 3.702104e-06 | T8: =1-S8/R8 -> 0.79567787 | U8: 180000 | V8: =F8*U8 -> 94568.041 | W8: =G8*U8 -> 21600 | X8: =1-W8/V8 -> 0.77159303 | Y8: =V8/$F$5 -> 3.2614124 | Z8: =W8/$G$5 -> 0.66637873 | AA8: =Y8-Z8 -> 2.5950337 | AC8: 40 mL dia * 3 dias a la semana
C9: ACIDIFICANTE | D9: kg | E9: 0.30804068 | F9: 8931.9594 | G9: =GRAFICAS!S32 -> 9321 | H9: =$E$9*H5 -> 8931.9594 | I9: =$E$9*I5 -> 9679.131 | J9: =$E$9*J5 -> 10550.178 | K9: =$E$9*K5 -> 12478.448 | L9: =$E$9*L5 -> 12409.57 | M9: =$E$9*M5 -> 13394.359 | N9: =$E$9*N5 -> 12585.983 | O9: =$E$9*O5 -> 8220.2736 | P9: =$E$9*P5 -> 4134.6653 | Q9: =+SUM(F9:P9) -> 110637.53 | R9: =F9/$F$5 -> 0.30804068 | S9: =G9/$G$5 -> 0.28756093 | T9: =1-S9/R9 -> 0.066483898 | U9: 830 | V9: =F9*U9 -> 7413526.3 | W9: =G9*U9 -> 7736430 | X9: =1-W9/V9 -> -0.043556016 | Y9: =V9/$F$5 -> 255.67376 | Z9: =W9/$G$5 -> 238.67557 | AA9: =Y9-Z9 -> 16.998188
C10: QUIMICO FLOCULANTE PARA TRATAMIENTO DE AGUA (Catiónico) | D10: kg | E10: 0.0091306964 | F10: 264.75403 | G10: =GRAFICAS!R55 -> 355 | H10: =$E$10*H5 -> 264.75403 | I10: =$E$10*I5 -> 286.90109 | J10: =$E$10*J5 -> 312.71996 | K10: =$E$10*K5 -> 369.87621 | L10: =$E$10*L5 -> 367.8346 | M10: =$E$10*M5 -> 397.02493 | N10: =$E$10*N5 -> 373.06369 | O10: =$E$10*O5 -> 243.6588 | P10: =$E$10*P5 -> 122.55646 | Q10: =+SUM(F10:P10) -> 3358.1438 | R10: =F10/$F$5 -> 0.0091306964 | S10: =G10/$G$5 -> 0.010952058 | T10: =1-S10/R10 -> -0.19947672 | U10: 22050 | V10: =F10*U10 -> 5837826.3 | W10: =G10*U10 -> 7827750 | X10: =1-W10/V10 -> -0.34086723 | Y10: =V10/$F$5 -> 201.33185 | Z10: =W10/$G$5 -> 241.49287 | AA10: =Y10-Z10 -> -40.161019
C11: QUIMICO FLOCULANTE PARA TRATAMIENTO DE AGUA (Aniónico) | D11: kg | E11: 0.0054182543 | F11: 157.10791 | G11: =GRAFICAS!R44 -> 195 | H11: =$E$11*H5 -> 157.10791 | I11: =$E$11*I5 -> 170.25022 | J11: =$E$11*J5 -> 185.57142 | K11: =$E$11*K5 -> 219.48856 | L11: =$E$11*L5 -> 218.27704 | M11: =$E$11*M5 -> 235.5989 | N11: =$E$11*N5 -> 221.38004 | O11: =$E$11*O5 -> 144.58978 | P11: =$E$11*P5 -> 72.726331 | Q11: =+SUM(F11:P11) -> 1977.0981 | R11: =F11/$F$5 -> 0.0054182543 | S11: =G11/$G$5 -> 0.006015919 | T11: =1-S11/R11 -> -0.11030577 | U11: 19050 | V11: =F11*U11 -> 2992905.8 | W11: =G11*U11 -> 3714750 | X11: =1-W11/V11 -> -0.24118509 | Y11: =V11/$F$5 -> 103.21774 | Z11: =W11/$G$5 -> 114.60326 | AA11: =Y11-Z11 -> -11.385513
C12: QUIMICO COAGULANTE PARA TRATAMIENTO DE AGUA (Coagulante) | D12: kg | E12: 0.54180085 | F12: 15710.079 | G12: =GRAFICAS!S20 -> 13024.75 | H12: =$E$12*H5 -> 15710.079 | I12: =$E$12*I5 -> 17024.25 | J12: =$E$12*J5 -> 18556.3 | K12: =$E$12*K5 -> 21947.86 | L12: =$E$12*L5 -> 21826.714 | M12: =$E$12*M5 -> 23558.821 | N12: =$E$12*N5 -> 22137 | O12: =$E$12*O5 -> 14458.322 | P12: =$E$12*P5 -> 7272.3033 | Q12: =+SUM(F12:P12) -> 191226.48 | R12: =F12/$F$5 -> 0.54180085 | S12: =G12/$G$5 -> 0.40182483 | T12: =1-S12/R12 -> 0.25835328 | U12: 2818 | V12: =F12*U12 -> 44271002 | W12: =G12*U12 -> 36703746 | X12: =1-W12/V12 -> 0.17093032 | Y12: =V12/$F$5 -> 1526.7948 | Z12: =W12/$G$5 -> 1132.3424 | AA12: =Y12-Z12 -> 394.45244
C13: QUIMICO COAGULANTE PARA TRATAMIENTO DE AGUA (Decolorante) | D13: kg | E13: 0.23755146 | F13: 6888.0515 | G13: =GRAFICAS!S13 -> 4800 | H13: =$E$13*H5 -> 6888.0515 | I13: =$E$13*I5 -> 7464.2471 | J13: =$E$13*J5 -> 8135.9715 | K13: =$E$13*K5 -> 9622.994 | L13: =$E$13*L5 -> 9569.8776 | M13: =$E$13*M5 -> 10329.317 | N13: =$E$13*N5 -> 9705.922 | O13: =$E$13*O5 -> 6339.2213 | P13: =$E$13*P5 -> 3188.5263 | Q13: =+SUM(F13:P13) -> 82932.179 | R13: =F13/$F$5 -> 0.23755146 | S13: =G13/$G$5 -> 0.14808416 | T13: =1-S13/R13 -> 0.37662282 | U13: 6295 | V13: =F13*U13 -> 43360284 | W13: =G13*U13 -> 30216000 | X13: =1-W13/V13 -> 0.3031411 | Y13: =V13/$F$5 -> 1495.3865 | Z13: =W13/$G$5 -> 932.18979 | AA13: =Y13-Z13 -> 563.19667
C14: HIPOCLORITO DE SODIO | D14: kg | E14: 0.0072995135 | F14: 211.65698 | G14: 1000 | H14: =$E$14*H5 -> 211.65698 | I14: =$E$14*I5 -> 229.36239 | J14: =$E$14*J5 -> 250.00323 | K14: =$E$14*K5 -> 295.69666 | L14: =$E$14*L5 -> 294.06449 | M14: =$E$14*M5 -> 317.40063 | N14: =$E$14*N5 -> 298.24488 | O14: =$E$14*O5 -> 194.79245 | P14: =$E$14*P5 -> 97.977467 | Q14: =+SUM(F14:P14) -> 3400.8562 | R14: =F14/$F$5 -> 0.0072995135 | S14: =G14/$G$5 -> 0.030850867 | T14: =1-S14/R14 -> -3.2264278 | U14: 1298 | V14: =F14*U14 -> 274730.76 | W14: =G14*U14 -> 1298000 | X14: =1-W14/V14 -> -3.7246257 | Y14: =V14/$F$5 -> 9.4747685 | Z14: =W14/$G$5 -> 40.044425 | AA14: =Y14-Z14 -> -30.569657
C15: SODA CAUSTICA LIQUI48% 90 KL | D15: kg | E15: 0.013272416 | F15: 384.84748 | G15: 90 | H15: =$E$15*H5 -> 384.84748 | I15: =$E$15*I5 -> 417.04054 | J15: =$E$15*J5 -> 454.57095 | K15: =$E$15*K5 -> 537.6535 | L15: =$E$15*L5 -> 534.6858 | M15: =$E$15*M5 -> 577.11698 | N15: =$E$15*N5 -> 542.28683 | O15: =$E$15*O5 -> 354.18338 | P15: =$E$15*P5 -> 178.14854 | Q15: =+SUM(F15:P15) -> 4455.3815 | R15: =F15/$F$5 -> 0.013272416 | S15: =G15/$G$5 -> 0.002776578 | T15: =1-S15/R15 -> 0.79080085 | U15: 1862 | V15: =F15*U15 -> 716586.01 | W15: =G15*U15 -> 167580 | X15: =1-W15/V15 -> 0.76614112 | Y15: =V15/$F$5 -> 24.713238 | Z15: =W15/$G$5 -> 5.1699883 | AA15: =Y15-Z15 -> 19.54325 | AC15: Por cada CIP 30 Kg de soda
C16: QUIMICO ANTINCRUSTANTE PARA ÓSMOSIS INVERSA | D16: kg | E16: 0.013763942 | F16: 399.09979 | G16: 60 | H16: =$E$16*H5 -> 399.09979 | I16: =$E$16*I5 -> 432.48507 | J16: =$E$16*J5 -> 471.40537 | K16: =$E$16*K5 -> 557.56477 | L16: =$E$16*L5 -> 554.48716 | M16: =$E$16*M5 -> 598.48972 | N16: =$E$16*N5 -> 562.36969 | O16: =$E$16*O5 -> 367.30008 | P16: =$E$16*P5 -> 184.74603 | Q16: =+SUM(F16:P16) -> 4587.0475 | R16: =F16/$F$5 -> 0.013763942 | S16: =G16/$G$5 -> 0.001851052 | T16: =1-S16/R16 -> 0.86551439 | U16: 36239 | V16: =F16*U16 -> 14462977 | W16: =G16*U16 -> 2174340 | X16: =1-W16/V16 -> 0.84966166 | Y16: =V16/$F$5 -> 498.79148 | Z16: =W16/$G$5 -> 67.080274 | AA16: =Y16-Z16 -> 431.7112
C17: QUIMICO PARA TRATAMIENTO CIP ALCALINO ÓSMOSIS INVERSA | D17: kg | E17: 0.00091964781 | F17: 26.666144 | G17: 0 | H17: =$E$17*H5 -> 26.666144 | I17: =$E$17*I5 -> 28.896806 | J17: =$E$17*J5 -> 31.497294 | K17: =$E$17*K5 -> 37.254097 | L17: =$E$17*L5 -> 37.048464 | M17: =$E$17*M5 -> 39.988528 | N17: =$E$17*N5 -> 37.575141 | O17: =$E$17*O5 -> 24.541423 | P17: =$E$17*P5 -> 12.343941 | Q17: =+SUM(F17:P17) -> 302.47798 | R17: =F17/$F$5 -> 0.00091964781 | S17: =G17/$G$5 -> 0 | T17: =1-S17/R17 -> 1 | U17: 32490 | V17: =F17*U17 -> 866383.01 | W17: =G17*U17 -> 0 | X17: =1-W17/V17 -> 1 | Y17: =V17/$F$5 -> 29.879357 | Z17: =W17/$G$5 -> 0 | AA17: =Y17-Z17 -> 29.879357
C18: QUIMICO PARA TRATAMIENTO BIODISPERSANTE ÓMOSIS INVERSA | D18: kg | E18: 0.018171608 | F18: 526.90467 | G18: 80 | H18: =$E$18*H5 -> 526.90467 | I18: =$E$18*I5 -> 570.98102 | J18: =$E$18*J5 -> 622.36488 | K18: =$E$18*K5 -> 736.11535 | L18: =$E$18*L5 -> 732.05219 | M18: =$E$18*M5 -> 790.14582 | N18: =$E$18*N5 -> 742.45896 | O18: =$E$18*O5 -> 484.92165 | P18: =$E$18*P5 -> 243.90779 | Q18: =+SUM(F18:P18) -> 6056.757 | R18: =F18/$F$5 -> 0.018171608 | S18: =G18/$G$5 -> 0.0024680694 | T18: =1-S18/R18 -> 0.86417992 | U18: 19160 | V18: =F18*U18 -> 10095493 | W18: =G18*U18 -> 1532800 | X18: =1-W18/V18 -> 0.84816988 | Y18: =V18/$F$5 -> 348.16802 | Z18: =W18/$G$5 -> 47.288209 | AA18: =Y18-Z18 -> 300.87981
C19: QUIMICO PARA TRATAMIENTO CIP ACIDO ÓSMOSIS INVERSA | D19: Kg | E19: 0.00087479088 | F19: 25.36547 | G19: 0 | H19: =$E$19*H5 -> 25.36547 | I19: =$E$19*I5 -> 27.487329 | J19: =$E$19*J5 -> 29.960976 | K19: =$E$19*K5 -> 35.436984 | L19: =$E$19*L5 -> 35.241381 | M19: =$E$19*M5 -> 38.038039 | N19: =$E$19*N5 -> 35.742369 | O19: =$E$19*O5 -> 23.344386 | P19: =$E$19*P5 -> 11.74185 | Q19: =+SUM(F19:P19) -> 287.72425 | R19: =F19/$F$5 -> 0.00087479088 | S19: =G19/$G$5 -> 0 | T19: =1-S19/R19 -> 1 | U19: 34156 | V19: =F19*U19 -> 866383.01 | W19: =G19*U19 -> 0 | X19: =1-W19/V19 -> 1 | Y19: =V19/$F$5 -> 29.879357 | Z19: =W19/$G$5 -> 0 | AA19: =Y19-Z19 -> 29.879357
C20: ACIDO CÍTRICO | D20: Kg | E20: 0.00079766595 | F20: 23.129153 | G20: 0 | H20: =$E$20*H5 -> 23.129153 | I20: =$E$20*I5 -> 25.063941 | J20: =$E$20*J5 -> 27.319501 | K20: =$E$20*K5 -> 32.312723 | L20: =$E$20*L5 -> 32.134365 | M20: =$E$20*M5 -> 34.684459 | N20: =$E$20*N5 -> 32.591184 | O20: =$E$20*O5 -> 21.286255 | P20: =$E$20*P5 -> 10.706644 | Q20: =+SUM(F20:P20) -> 262.35738 | R20: =F20/$F$5 -> 0.00079766595 | S20: =G20/$G$5 -> 0 | T20: =1-S20/R20 -> 1 | U20: 5200 | V20: =F20*U20 -> 120271.6 | W20: =G20*U20 -> 0 | X20: =1-W20/V20 -> 1 | Y20: =V20/$F$5 -> 4.1478629 | Z20: =W20/$G$5 -> 0 | AA20: =Y20-Z20 -> 4.1478629
C21: Subtotal | V21: =F21*U21 -> 0 | W21: =G21*U21 -> 0
Q22: OSMOSIS INVERSA | V22: =F22*U22 -> 0 | W22: =G22*U22 -> 0
Q23: PTAR FASE 2 | V23: =F23*U23 -> 0 | W23: =G23*U23 -> 0
B25: COSTO PLANTA DE TRATAMIENTO DE AGUA DE POZO PROFUNDO
B26: Clasificación | C26: Detalle | D26: Unidad | E26: Dosificación | F26: Marzo 2026 | H26: Abril 2026 | I26: Mayo 2026 | J26: Junio 2026 | K26: Julio 2026 | L26: Agosto 2026 | M26: Septiembre 2026 | N26: Octubre 2026 | O26: Noviembre 2026 | P26: Diciembre 2026 | Q26: Total general | U26: $/Kg | V26: $ Total | W26: $/M3
E27: Kg/m3
F28: ='[1]PLAN MAESTRO BOGOTA RECIRCU'!J9 -> 5274.6748 | H28: ='[1]PLAN MAESTRO BOGOTA RECIRCU'!L9 -> 6028.2765 | I28: ='[1]PLAN MAESTRO BOGOTA RECIRCU'!N9 -> 10800 | J28: ='[1]PLAN MAESTRO BOGOTA RECIRCU'!P9 -> 10800 | K28: ='[1]PLAN MAESTRO BOGOTA RECIRCU'!R9 -> 10800 | L28: ='[1]PLAN MAESTRO BOGOTA RECIRCU'!T9 -> 10800 | M28: ='[1]PLAN MAESTRO BOGOTA RECIRCU'!V9 -> 10800 | N28: ='[1]PLAN MAESTRO BOGOTA RECIRCU'!X9 -> 10800 | O28: ='[1]PLAN MAESTRO BOGOTA RECIRCU'!Z9 -> 10800 | P28: ='[1]PLAN MAESTRO BOGOTA RECIRCU'!AB9 -> 10800 | Q28: =SUM(F28:P28) -> 97702.951
B29: QUIMICOS (GEM + RO) | C29: ACIDO CLORHIDRICO 31,5% | D29: kg | E29: 0.06 | F29: =$E$29*F28 -> 316.48049 | H29: =$E$29*H28 -> 361.69659 | I29: =$E$29*I28 -> 648 | J29: =$E$29*J28 -> 648 | K29: =$E$29*K28 -> 648 | L29: =$E$29*L28 -> 648 | M29: =$E$29*M28 -> 648 | N29: =$E$29*N28 -> 648 | O29: =$E$29*O28 -> 648 | P29: =$E$29*P28 -> 648 | Q29: =+SUM(F29:P29) -> 5862.1771 | U29: 1650 | V29: =Q29*U29 -> 9672592.2 | W29: =V29/$Q$28 -> 99
C30: ACIDIFICANTE | D30: kg | E30: 0.38 | F30: =$E$30*F28 -> 2004.3764 | H30: =$E$30*H28 -> 2290.7451 | I30: =$E$30*I28 -> 4104 | J30: =$E$30*J28 -> 4104 | K30: =$E$30*K28 -> 4104 | L30: =$E$30*L28 -> 4104 | M30: =$E$30*M28 -> 4104 | N30: =$E$30*N28 -> 4104 | O30: =$E$30*O28 -> 4104 | P30: =$E$30*P28 -> 4104 | Q30: =+SUM(F30:P30) -> 37127.122 | U30: 830 | V30: =Q30*U30 -> 30815511 | W30: =V30/$Q$28 -> 315.4
C31: QUIMICO COAGULANTE PARA TRATAMIENTO DE AGUA (Coagulante) | D31: kg | E31: 0.5426 | F31: =$E$31*F28 -> 2862.0386 | H31: =$E$31*H28 -> 3270.9428 | I31: =$E$31*I28 -> 5860.08 | J31: =$E$31*J28 -> 5860.08 | K31: =$E$31*K28 -> 5860.08 | L31: =$E$31*L28 -> 5860.08 | M31: =$E$31*M28 -> 5860.08 | N31: =$E$31*N28 -> 5860.08 | O31: =$E$31*O28 -> 5860.08 | P31: =$E$31*P28 -> 5860.08 | Q31: =+SUM(F31:P31) -> 53013.621 | U31: 2900 | V31: =Q31*U31 -> 1.537395e+08 | W31: =V31/$Q$28 -> 1573.54
C32: QUIMICO FLOCULANTE PARA TRATAMIENTO DE AGUA (Aniónico) | D32: kg | E32: 0.0054 | F32: =$E$32*F28 -> 28.483244 | H32: =$E$32*H28 -> 32.552693 | I32: =$E$32*I28 -> 58.32 | J32: =$E$32*J28 -> 58.32 | K32: =$E$32*K28 -> 58.32 | L32: =$E$32*L28 -> 58.32 | M32: =$E$32*M28 -> 58.32 | N32: =$E$32*N28 -> 58.32 | O32: =$E$32*O28 -> 58.32 | P32: =$E$32*P28 -> 58.32 | Q32: =+SUM(F32:P32) -> 527.59594 | U32: 19050 | V32: =Q32*U32 -> 10050703 | W32: =V32/$Q$28 -> 102.87
C33: HIPOCLORITO DE SODIO | D33: kg | E33: 0.125 | F33: =$E$33*F28 -> 659.33435 | H33: =$E$33*H28 -> 753.53456 | I33: =$E$33*I28 -> 1350 | J33: =$E$33*J28 -> 1350 | K33: =$E$33*K28 -> 1350 | L33: =$E$33*L28 -> 1350 | M33: =$E$33*M28 -> 1350 | N33: =$E$33*N28 -> 1350 | O33: =$E$33*O28 -> 1350 | P33: =$E$33*P28 -> 1350 | Q33: =+SUM(F33:P33) -> 12212.869 | U33: 1298 | V33: =Q33*U33 -> 15852304 | W33: =V33/$Q$28 -> 162.25
C34: SODA CAUSTICA LIQUI48% 90 KL | D34: kg | E34: 0.037 | F34: =$E$34*F28 -> 195.16297 | H34: =$E$34*H28 -> 223.04623 | I34: =$E$34*I28 -> 399.6 | J34: =$E$34*J28 -> 399.6 | K34: =$E$34*K28 -> 399.6 | L34: =$E$34*L28 -> 399.6 | M34: =$E$34*M28 -> 399.6 | N34: =$E$34*N28 -> 399.6 | O34: =$E$34*O28 -> 399.6 | P34: =$E$34*P28 -> 399.6 | Q34: =+SUM(F34:P34) -> 3615.0092 | U34: 1862 | V34: =Q34*U34 -> 6731147.1 | W34: =V34/$Q$28 -> 68.894
C35: Subtotal | Q35: PTAP | V35: =SUM(V29:V34) -> 2.2686176e+08 | W35: =V35/$Q$28 -> 2321.954

Sheet INVENTARIO Y CONSUMO GEM  
A1: FECHA | B1: DIA | C1: ANALISIS TURNO | D1: # TURNO | E1: DILIGENCIAR BITACORA | F1: FINAL ACIDO (L) | G1: FINAL COAGULANTE (L) | H1: FINAL DECOLORANTE (L) | I1: FINAL POL ANIONICO (KG) | J1: FINAL POL CATIONICO (KG) | K1: Lectura Horometro INICIAL (06:00) | L1: CAUDAL TOTAL TRATADO GEM | M1: CAUDAL DE TRATAMIENTO | N1: CONSUMO LITROS ACIDO (L) | O1: CONSUMO LITROS COAGULANTE (L) | P1: CONSUMO LITROS DECOLORANTE (L) | Q1: CONSUMO POL ANIONICO (KG) | R1: CONSUMO POL CATIONICO (KG) | S1: KG ACIDO | T1: KG COAGULANTE | U1: KG DECOLORANTE | V1: KG POL ANIONICO | W1: KG POL CATIONICO | X1: PPM ACIDO | Y1: PPM COAGULANTE | Z1: PPM DECOLORANTE | AA1: PPM POL ANIONICO | AB1: PPM POL CATIONICO | AC1: DENSIDAD ACIDO | AD1: DENSIDAD COAGULANTE | AE1: DENSIDAD DECOLORANTE | AF1: DENSIDAD ANIONICO | AG1: DENSIDAD CATIONICO | AH1: PRECIO (KG) ACIDO | AI1: PRECIO (KG) COAGULANTE | AJ1: PRECIO (KG) DECOLORANTE | AK1: PRECIO (KG) ANIONICO | AL1: PRECIO (KG) CATIONICO | AM1: COSTO OPERATIVO ACIDO | AN1: COSTO OPERATIVO COAGULANTE | AO1: COSTO OPERATIVO DECOLORANTE | AP1: COSTO OPERATIVO ANIONICO | AQ1: COSTO OPERATIVO CATIONICO | AR1: COSTO QUIMICA | AS1: LIMITE INDICADOR M3 | AT1: $ m3 | AU1: HORAS DE OPERACIÓN
A2: 46113 | B2: 1 | C2: 1 (NOCHE) | D2: 1 | E2: FINAL TURNO 3 | F2: 2780 | G2: 5720 | H2: 4280 | I2: 275 | J2: 450 | K2: 17622 | L2: =(K3-K2)*M2 -> 0 | M2: 80 | N2: =F2-F3 -> 0 | O2: =G2-G3 -> 0 | P2: =H2-H3 -> 0 | Q2: =I2-I3 -> 0 | R2: =J2-J3 -> 0 | S2: =(N2*$AC$2) -> 0 | T2: =(O2*$AD$2) -> 0 | U2: =(P2*$AE$2) -> 0 | V2: =Tabla1[[#This Row],[CONSUMO POL ANIONICO (KG)]] -> 0 | W2: =Tabla1[[#This Row],[CONSUMO POL CATIONICO (KG)]] -> 0 | X2: =(S2*1000)/L2 -> #DIV/0! | Y2: =(T2*1000)/L2 -> #DIV/0! | Z2: =(U2*1000)/L2 -> #DIV/0! | AA2: =(V2*1000)/L2 -> #DIV/0! | AB2: =(W2*1000)/L2 -> #DIV/0! | AC2: 1.3 | AD2: 1.325 | AE2: 1.25 | AF2: 2500 | AG2: 2500 | AH2: 830 | AI2: 2818 | AJ2: 6295 | AK2: 19050 | AL2: 22050 | AM2: =S2*AH2 -> 0 | AN2: =T2*AI2 -> 0 | AO2: =U2*AJ2 -> 0 | AP2: =V2*AK2 -> 0 | AQ2: =W2*AL2 -> 0 | AR2: =SUM(Tabla1[[#This Row],[COSTO OPERATIVO ACIDO]:[COSTO OPERATIVO CATIONICO]]) -> 0 | AS2: 3599 | AT2: =AR2/L2 -> #DIV/0! | AU2: =IFERROR(Tabla1[[#This Row],[CAUDAL TOTAL TRATADO GEM ]]/Tabla1[[#This Row],[CAUDAL DE TRATAMIENTO]],0) -> 0
A3: =A2 -> 46113 | B3: 1 | C3: 2 (MAÑANA) | D3: 2 | E3: FINAL TURNO 1 | F3: 2780 | G3: 5720 | H3: 4280 | I3: =+I2-0 -> 275 | J3: =+J2-0 -> 450 | K3: 17622 | L3: =(K4-K3)*M3 -> 0 | M3: 80 | N3: =F3-F4 -> 0 | O3: =G3-G4 -> 0 | P3: =H3-H4 -> 0 | Q3: =I3-I4 -> 0 | R3: =J3-J4 -> 0 | S3: =(N3*$AC$2) -> 0 | T3: =(O3*$AD$2) -> 0 | U3: =(P3*$AE$2) -> 0 | V3: =Tabla1[[#This Row],[CONSUMO POL ANIONICO (KG)]] -> 0 | W3: =Tabla1[[#This Row],[CONSUMO POL CATIONICO (KG)]] -> 0 | X3: =(S3*1000)/L3 -> #DIV/0! | Y3: =(T3*1000)/L3 -> #DIV/0! | Z3: =(U3*1000)/L3 -> #DIV/0! | AA3: =(V3*1000)/L3 -> #DIV/0! | AB3: =(W3*1000)/L3 -> #DIV/0! | AC3: 1.3 | AD3: 1.325 | AE3: 1.25 | AF3: 2500 | AG3: 2500 | AH3: 830 | AI3: 2818 | AJ3: 6295 | AK3: 19050 | AL3: 22050 | AM3: =S3*AH3 -> 0 | AN3: =T3*AI3 -> 0 | AO3: =U3*AJ3 -> 0 | AP3: =V3*AK3 -> 0 | AQ3: =W3*AL3 -> 0 | AR3: =SUM(Tabla1[[#This Row],[COSTO OPERATIVO ACIDO]:[COSTO OPERATIVO CATIONICO]]) -> 0 | AS3: 3599 | AT3: =AR3/L3 -> #DIV/0! | AU3: =IFERROR(Tabla1[[#This Row],[CAUDAL TOTAL TRATADO GEM ]]/Tabla1[[#This Row],[CAUDAL DE TRATAMIENTO]],0) -> 0
A4: =+A3 -> 46113 | B4: 1 | C4: 3(TARDE) | D4: 3 | E4: FINAL TURNO 2 | F4: 2780 | G4: 5720 | H4: 4280 | I4: =+I3-0 -> 275 | J4: =+J3-0 -> 450 | K4: 17622 | L4: =(K5-K4)*M4 -> 0 | M4: 80 | N4: =F4-F5 -> 0 | O4: =G4-G5 -> 0 | P4: =H4-H5 -> 0 | Q4: =I4-I5 -> 0 | R4: =J4-J5 -> 0 | S4: =(N4*$AC$2) -> 0 | T4: =(O4*$AD$2) -> 0 | U4: =(P4*$AE$2) -> 0 | V4: =Tabla1[[#This Row],[CONSUMO POL ANIONICO (KG)]] -> 0 | W4: =Tabla1[[#This Row],[CONSUMO POL CATIONICO (KG)]] -> 0 | X4: =(S4*1000)/L4 -> #DIV/0! | Y4: =(T4*1000)/L4 -> #DIV/0! | Z4: =(U4*1000)/L4 -> #DIV/0! | AA4: =(V4*1000)/L4 -> #DIV/0! | AB4: =(W4*1000)/L4 -> #DIV/0! | AC4: 1.3 | AD4: 1.325 | AE4: 1.25 | AF4: 2500 | AG4: 2500 | AH4: 830 | AI4: 2818 | AJ4: 6295 | AK4: 19050 | AL4: 22050 | AM4: =S4*AH4 -> 0 | AN4: =T4*AI4 -> 0 | AO4: =U4*AJ4 -> 0 | AP4: =V4*AK4 -> 0 | AQ4: =W4*AL4 -> 0 | AR4: =SUM(Tabla1[[#This Row],[COSTO OPERATIVO ACIDO]:[COSTO OPERATIVO CATIONICO]]) -> 0 | AS4: 3599 | AT4: =AR4/L4 -> #DIV/0! | AU4: =IFERROR(Tabla1[[#This Row],[CAUDAL TOTAL TRATADO GEM ]]/Tabla1[[#This Row],[CAUDAL DE TRATAMIENTO]],0) -> 0
A5: =+A4+1 -> 46114 | B5: 2 | C5: 2 (NOCHE) | D5: 4 | E5: FINAL TURNO 3 | F5: 2780 | G5: 5720 | H5: 4280 | I5: =+I4-0 -> 275 | J5: =+J4-0 -> 450 | K5: 17622 | L5: =(K6-K5)*M5 -> 480 | M5: 80 | N5: =F5-F6 -> 80 | O5: =G5-G6 -> 20 | P5: =H5-H6 -> 80 | Q5: =I5-I6 -> 5 | R5: =J5-J6 -> 5 | S5: =(N5*$AC$2) -> 104 | T5: =(O5*$AD$2) -> 26.5 | U5: =(P5*$AE$2) -> 100 | V5: =Tabla1[[#This Row],[CONSUMO POL ANIONICO (KG)]] -> 5 | W5: =Tabla1[[#This Row],[CONSUMO POL CATIONICO (KG)]] -> 5 | X5: =(S5*1000)/L5 -> 216.66667 | Y5: =(T5*1000)/L5 -> 55.208333 | Z5: =(U5*1000)/L5 -> 208.33333 | AA5: =(V5*1000)/L5 -> 10.416667 | AB5: =(W5*1000)/L5 -> 10.416667 | AC5: 1.3 | AD5: 1.325 | AE5: 1.25 | AF5: 2500 | AG5: 2500 | AH5: 830 | AI5: 2818 | AJ5: 6295 | AK5: 19050 | AL5: 22050 | AM5: =S5*AH5 -> 86320 | AN5: =T5*AI5 -> 74677 | AO5: =U5*AJ5 -> 629500 | AP5: =V5*AK5 -> 95250 | AQ5: =W5*AL5 -> 110250 | AR5: =SUM(Tabla1[[#This Row],[COSTO OPERATIVO ACIDO]:[COSTO OPERATIVO CATIONICO]]) -> 995997 | AS5: 3599 | AT5: =AR5/L5 -> 2074.9938 | AU5: =IFERROR(Tabla1[[#This Row],[CAUDAL TOTAL TRATADO GEM ]]/Tabla1[[#This Row],[CAUDAL DE TRATAMIENTO]],0) -> 6
A6: =+A5 -> 46114 | B6: 2 | C6: 3 (MAÑANA) | D6: 5 | E6: FINAL TURNO 1 | F6: 2700 | G6: 5700 | H6: 4200 | I6: =+I5-5 -> 270 | J6: =+J5-5 -> 445 | K6: 17628 | L6: =(K7-K6)*M6 -> 400 | M6: 80 | N6: =F6-F7 -> 100 | O6: =G6-G7 -> 100 | P6: =H6-H7 -> 10 | Q6: =I6-I7 -> 5 | R6: =J6-J7 -> 5 | S6: =(N6*$AC$2) -> 130 | T6: =(O6*$AD$2) -> 132.5 | U6: =(P6*$AE$2) -> 12.5 | V6: =Tabla1[[#This Row],[CONSUMO POL ANIONICO (KG)]] -> 5 | W6: =Tabla1[[#This Row],[CONSUMO POL CATIONICO (KG)]] -> 5 | X6: =(S6*1000)/L6 -> 325 | Y6: =(T6*1000)/L6 -> 331.25 | Z6: =(U6*1000)/L6 -> 31.25 | AA6: =(V6*1000)/L6 -> 12.5 | AB6: =(W6*1000)/L6 -> 12.5 | AC6: 1.3 | AD6: 1.325 | AE6: 1.25 | AF6: 2500 | AG6: 2500 | AH6: 830 | AI6: 2818 | AJ6: 6295 | AK6: 19050 | AL6: 22050 | AM6: =S6*AH6 -> 107900 | AN6: =T6*AI6 -> 373385 | AO6: =U6*AJ6 -> 78687.5 | AP6: =V6*AK6 -> 95250 | AQ6: =W6*AL6 -> 110250 | AR6: =SUM(Tabla1[[#This Row],[COSTO OPERATIVO ACIDO]:[COSTO OPERATIVO CATIONICO]]) -> 765472.5 | AS6: 3599 | AT6: =AR6/L6 -> 1913.6813 | AU6: =IFERROR(Tabla1[[#This Row],[CAUDAL TOTAL TRATADO GEM ]]/Tabla1[[#This Row],[CAUDAL DE TRATAMIENTO]],0) -> 5
A7: =+A6 -> 46114 | B7: 2 | C7: 3(TARDE) | D7: 6 | E7: FINAL TURNO 2 | F7: 2600 | G7: 5600 | H7: 4190 | I7: =+I6-5 -> 265 | J7: =+J6-5 -> 440 | K7: 17633 | L7: =(K8-K7)*M7 -> 0 | M7: 80 | N7: =F7-F8 -> 0 | O7: =G7-G8 -> 0 | P7: =H7-H8 -> 0 | Q7: =I7-I8 -> 0 | R7: =J7-J8 -> 0 | S7: =(N7*$AC$2) -> 0 | T7: =(O7*$AD$2) -> 0 | U7: =(P7*$AE$2) -> 0 | V7: =Tabla1[[#This Row],[CONSUMO POL ANIONICO (KG)]] -> 0 | W7: =Tabla1[[#This Row],[CONSUMO POL CATIONICO (KG)]] -> 0 | X7: =(S7*1000)/L7 -> #DIV/0! | Y7: =(T7*1000)/L7 -> #DIV/0! | Z7: =(U7*1000)/L7 -> #DIV/0! | AA7: =(V7*1000)/L7 -> #DIV/0! | AB7: =(W7*1000)/L7 -> #DIV/0! | AC7: 1.3 | AD7: 1.325 | AE7: 1.25 | AF7: 2500 | AG7: 2500 | AH7: 830 | AI7: 2818 | AJ7: 6295 | AK7: 19050 | AL7: 22050 | AM7: =S7*AH7 -> 0 | AN7: =T7*AI7 -> 0 | AO7: =U7*AJ7 -> 0 | AP7: =V7*AK7 -> 0 | AQ7: =W7*AL7 -> 0 | AR7: =SUM(Tabla1[[#This Row],[COSTO OPERATIVO ACIDO]:[COSTO OPERATIVO CATIONICO]]) -> 0 | AS7: 3599 | AT7: =AR7/L7 -> #DIV/0! | AU7: =IFERROR(Tabla1[[#This Row],[CAUDAL TOTAL TRATADO GEM ]]/Tabla1[[#This Row],[CAUDAL DE TRATAMIENTO]],0) -> 0
A8: =+A7+1 -> 46115 | B8: 3 | C8: 3 (NOCHE) | D8: 7 | E8: FINAL TURNO 3 | F8: 2600 | G8: 5600 | H8: 4190 | I8: =+I7-0 -> 265 | J8: =+J7-0 -> 440 | K8: 17633 | L8: =(K9-K8)*M8 -> 0 | M8: 80 | N8: =F8-F9 -> 0 | O8: =G8-G9 -> 0 | P8: =H8-H9 -> 0 | Q8: =I8-I9 -> 0 | R8: =J8-J9 -> 0 | S8: =(N8*$AC$2) -> 0 | T8: =(O8*$AD$2) -> 0 | U8: =(P8*$AE$2) -> 0 | V8: =Tabla1[[#This Row],[CONSUMO POL ANIONICO (KG)]] -> 0 | W8: =Tabla1[[#This Row],[CONSUMO POL CATIONICO (KG)]] -> 0 | X8: =(S8*1000)/L8 -> #DIV/0! | Y8: =(T8*1000)/L8 -> #DIV/0! | Z8: =(U8*1000)/L8 -> #DIV/0! | AA8: =(V8*1000)/L8 -> #DIV/0! | AB8: =(W8*1000)/L8 -> #DIV/0! | AC8: 1.3 | AD8: 1.325 | AE8: 1.25 | AF8: 2500 | AG8: 2500 | AH8: 830 | AI8: 2818 | AJ8: 6295 | AK8: 19050 | AL8: 22050 | AM8: =S8*AH8 -> 0 | AN8: =T8*AI8 -> 0 | AO8: =U8*AJ8 -> 0 | AP8: =V8*AK8 -> 0 | AQ8: =W8*AL8 -> 0 | AR8: =SUM(Tabla1[[#This Row],[COSTO OPERATIVO ACIDO]:[COSTO OPERATIVO CATIONICO]]) -> 0 | AS8: 3599 | AT8: =AR8/L8 -> #DIV/0! | AU8: =IFERROR(Tabla1[[#This Row],[CAUDAL TOTAL TRATADO GEM ]]/Tabla1[[#This Row],[CAUDAL DE TRATAMIENTO]],0) -> 0
A9: =+A8 -> 46115 | B9: 3 | C9: 4 (MAÑANA) | D9: 8 | E9: FINAL TURNO 1 | F9: 2600 | G9: 5600 | H9: 4190 | I9: =+I8-0 -> 265 | J9: =+J8-0 -> 440 | K9: 17633 | L9: =(K10-K9)*M9 -> 0 | M9: 80 | N9: =F9-F10 -> 0 | O9: =G9-G10 -> 0 | P9: =H9-H10 -> 0 | Q9: =I9-I10 -> 0 | R9: =J9-J10 -> 0 | S9: =(N9*$AC$2) -> 0 | T9: =(O9*$AD$2) -> 0 | U9: =(P9*$AE$2) -> 0 | V9: =Tabla1[[#This Row],[CONSUMO POL ANIONICO (KG)]] -> 0 | W9: =Tabla1[[#This Row],[CONSUMO POL CATIONICO (KG)]] -> 0 | X9: =(S9*1000)/L9 -> #DIV/0! | Y9: =(T9*1000)/L9 -> #DIV/0! | Z9: =(U9*1000)/L9 -> #DIV/0! | AA9: =(V9*1000)/L9 -> #DIV/0! | AB9: =(W9*1000)/L9 -> #DIV/0! | AC9: 1.3 | AD9: 1.325 | AE9: 1.25 | AF9: 2500 | AG9: 2500 | AH9: 830 | AI9: 2818 | AJ9: 6295 | AK9: 19050 | AL9: 22050 | AM9: =S9*AH9 -> 0 | AN9: =T9*AI9 -> 0 | AO9: =U9*AJ9 -> 0 | AP9: =V9*AK9 -> 0 | AQ9: =W9*AL9 -> 0 | AR9: =SUM(Tabla1[[#This Row],[COSTO OPERATIVO ACIDO]:[COSTO OPERATIVO CATIONICO]]) -> 0 | AS9: 3599 | AT9: =AR9/L9 -> #DIV/0! | AU9: =IFERROR(Tabla1[[#This Row],[CAUDAL TOTAL TRATADO GEM ]]/Tabla1[[#This Row],[CAUDAL DE TRATAMIENTO]],0) -> 0
A10: =+A9 -> 46115 | B10: 3 | C10: 3(TARDE) | D10: 9 | E10: FINAL TURNO 2 | F10: 2600 | G10: 5600 | H10: 4190 | I10: =+I9-0 -> 265 | J10: =+J9-0 -> 440 | K10: 17633 | L10: =(K11-K10)*M10 -> 0 | M10: 80 | N10: =F10-F11 -> 0 | O10: =G10-G11 -> 0 | P10: =H10-H11 -> 0 | Q10: =I10-I11 -> 0 | R10: =J10-J11 -> 0 | S10: =(N10*$AC$2) -> 0 | T10: =(O10*$AD$2) -> 0 | U10: =(P10*$AE$2) -> 0 | V10: =Tabla1[[#This Row],[CONSUMO POL ANIONICO (KG)]] -> 0 | W10: =Tabla1[[#This Row],[CONSUMO POL CATIONICO (KG)]] -> 0 | X10: =(S10*1000)/L10 -> #DIV/0! | Y10: =(T10*1000)/L10 -> #DIV/0! | Z10: =(U10*1000)/L10 -> #DIV/0! | AA10: =(V10*1000)/L10 -> #DIV/0! | AB10: =(W10*1000)/L10 -> #DIV/0! | AC10: 1.3 | AD10: 1.325 | AE10: 1.25 | AF10: 2500 | AG10: 2500 | AH10: 830 | AI10: 2818 | AJ10: 6295 | AK10: 19050 | AL10: 22050 | AM10: =S10*AH10 -> 0 | AN10: =T10*AI10 -> 0 | AO10: =U10*AJ10 -> 0 | AP10: =V10*AK10 -> 0 | AQ10: =W10*AL10 -> 0 | AR10: =SUM(Tabla1[[#This Row],[COSTO OPERATIVO ACIDO]:[COSTO OPERATIVO CATIONICO]]) -> 0 | AS10: 3599 | AT10: =AR10/L10 -> #DIV/0! | AU10: =IFERROR(Tabla1[[#This Row],[CAUDAL TOTAL TRATADO GEM ]]/Tabla1[[#This Row],[CAUDAL DE TRATAMIENTO]],0) -> 0
A11: =+A10+1 -> 46116 | B11: 4 | C11: 4 (NOCHE) | D11: 10 | E11: FINAL TURNO 3 | F11: 2600 | G11: 5600 | H11: 4190 | I11: =+I10-0 -> 265 | J11: =+J10-0 -> 440 | K11: 17633 | L11: =(K12-K11)*M11 -> 0 | M11: 80 | N11: =F11-F12 -> 0 | O11: =G11-G12 -> 0 | P11: =H11-H12 -> 0 | Q11: =I11-I12 -> 0 | R11: =J11-J12 -> 0 | S11: =(N11*$AC$2) -> 0 | T11: =(O11*$AD$2) -> 0 | U11: =(P11*$AE$2) -> 0 | V11: =Tabla1[[#This Row],[CONSUMO POL ANIONICO (KG)]] -> 0 | W11: =Tabla1[[#This Row],[CONSUMO POL CATIONICO (KG)]] -> 0 | X11: =(S11*1000)/L11 -> #DIV/0! | Y11: =(T11*1000)/L11 -> #DIV/0! | Z11: =(U11*1000)/L11 -> #DIV/0! | AA11: =(V11*1000)/L11 -> #DIV/0! | AB11: =(W11*1000)/L11 -> #DIV/0! | AC11: 1.3 | AD11: 1.325 | AE11: 1.25 | AF11: 2500 | AG11: 2500 | AH11: 830 | AI11: 2818 | AJ11: 6295 | AK11: 19050 | AL11: 22050 | AM11: =S11*AH11 -> 0 | AN11: =T11*AI11 -> 0 | AO11: =U11*AJ11 -> 0 | AP11: =V11*AK11 -> 0 | AQ11: =W11*AL11 -> 0 | AR11: =SUM(Tabla1[[#This Row],[COSTO OPERATIVO ACIDO]:[COSTO OPERATIVO CATIONICO]]) -> 0 | AS11: 3599 | AT11: =AR11/L11 -> #DIV/0! | AU11: =IFERROR(Tabla1[[#This Row],[CAUDAL TOTAL TRATADO GEM ]]/Tabla1[[#This Row],[CAUDAL DE TRATAMIENTO]],0) -> 0
A12: =+A11 -> 46116 | B12: 4 | C12: 5 (MAÑANA) | D12: 11 | E12: FINAL TURNO 1 | F12: 2600 | G12: 5600 | H12: 4190 | I12: =+I11-0 -> 265 | J12: =+J11-0 -> 440 | K12: 17633 | L12: =(K13-K12)*M12 -> 0 | M12: 80 | N12: =F12-F13 -> 0 | O12: =G12-G13 -> 0 | P12: =H12-H13 -> 0 | Q12: =I12-I13 -> 0 | R12: =J12-J13 -> 0 | S12: =(N12*$AC$2) -> 0 | T12: =(O12*$AD$2) -> 0 | U12: =(P12*$AE$2) -> 0 | V12: =Tabla1[[#This Row],[CONSUMO POL ANIONICO (KG)]] -> 0 | W12: =Tabla1[[#This Row],[CONSUMO POL CATIONICO (KG)]] -> 0 | X12: =(S12*1000)/L12 -> #DIV/0! | Y12: =(T12*1000)/L12 -> #DIV/0! | Z12: =(U12*1000)/L12 -> #DIV/0! | AA12: =(V12*1000)/L12 -> #DIV/0! | AB12: =(W12*1000)/L12 -> #DIV/0! | AC12: 1.3 | AD12: 1.325 | AE12: 1.25 | AF12: 2500 | AG12: 2500 | AH12: 830 | AI12: 2818 | AJ12: 6295 | AK12: 19050 | AL12: 22050 | AM12: =S12*AH12 -> 0 | AN12: =T12*AI12 -> 0 | AO12: =U12*AJ12 -> 0 | AP12: =V12*AK12 -> 0 | AQ12: =W12*AL12 -> 0 | AR12: =SUM(Tabla1[[#This Row],[COSTO OPERATIVO ACIDO]:[COSTO OPERATIVO CATIONICO]]) -> 0 | AS12: 3599 | AT12: =AR12/L12 -> #DIV/0! | AU12: =IFERROR(Tabla1[[#This Row],[CAUDAL TOTAL TRATADO GEM ]]/Tabla1[[#This Row],[CAUDAL DE TRATAMIENTO]],0) -> 0
A13: =+A12 -> 46116 | B13: 4 | C13: 3(TARDE) | D13: 12 | E13: FINAL TURNO 2 | F13: 2600 | G13: 5600 | H13: 4190 | I13: =+I12-0 -> 265 | J13: =+J12-0 -> 440 | K13: 17633 | L13: =(K14-K13)*M13 -> 0 | M13: 80 | N13: =F13-F14 -> 0 | O13: =G13-G14 -> 0 | P13: =H13-H14 -> 0 | Q13: =I13-I14 -> 0 | R13: =J13-J14 -> 0 | S13: =(N13*$AC$2) -> 0 | T13: =(O13*$AD$2) -> 0 | U13: =(P13*$AE$2) -> 0 | V13: =Tabla1[[#This Row],[CONSUMO POL ANIONICO (KG)]] -> 0 | W13: =Tabla1[[#This Row],[CONSUMO POL CATIONICO (KG)]] -> 0 | X13: =(S13*1000)/L13 -> #DIV/0! | Y13: =(T13*1000)/L13 -> #DIV/0! | Z13: =(U13*1000)/L13 -> #DIV/0! | AA13: =(V13*1000)/L13 -> #DIV/0! | AB13: =(W13*1000)/L13 -> #DIV/0! | AC13: 1.3 | AD13: 1.325 | AE13: 1.25 | AF13: 2500 | AG13: 2500 | AH13: 830 | AI13: 2818 | AJ13: 6295 | AK13: 19050 | AL13: 22050 | AM13: =S13*AH13 -> 0 | AN13: =T13*AI13 -> 0 | AO13: =U13*AJ13 -> 0 | AP13: =V13*AK13 -> 0 | AQ13: =W13*AL13 -> 0 | AR13: =SUM(Tabla1[[#This Row],[COSTO OPERATIVO ACIDO]:[COSTO OPERATIVO CATIONICO]]) -> 0 | AS13: 3599 | AT13: =AR13/L13 -> #DIV/0! | AU13: =IFERROR(Tabla1[[#This Row],[CAUDAL TOTAL TRATADO GEM ]]/Tabla1[[#This Row],[CAUDAL DE TRATAMIENTO]],0) -> 0
A14: =+A13+1 -> 46117 | B14: 5 | C14: 5 (NOCHE) | D14: 13 | E14: FINAL TURNO 3 | F14: 2600 | G14: 5600 | H14: 4190 | I14: =+I13-0 -> 265 | J14: =+J13-0 -> 440 | K14: 17633 | L14: =(K15-K14)*M14 -> 0 | M14: 80 | N14: =F14-F15 -> 0 | O14: =G14-G15 -> 0 | P14: =H14-H15 -> 0 | Q14: =I14-I15 -> 0 | R14: =J14-J15 -> 0 | S14: =(N14*$AC$2) -> 0 | T14: =(O14*$AD$2) -> 0 | U14: =(P14*$AE$2) -> 0 | V14: =Tabla1[[#This Row],[CONSUMO POL ANIONICO (KG)]] -> 0 | W14: =Tabla1[[#This Row],[CONSUMO POL CATIONICO (KG)]] -> 0 | X14: =(S14*1000)/L14 -> #DIV/0! | Y14: =(T14*1000)/L14 -> #DIV/0! | Z14: =(U14*1000)/L14 -> #DIV/0! | AA14: =(V14*1000)/L14 -> #DIV/0! | AB14: =(W14*1000)/L14 -> #DIV/0! | AC14: 1.3 | AD14: 1.325 | AE14: 1.25 | AF14: 2500 | AG14: 2500 | AH14: 830 | AI14: 2818 | AJ14: 6295 | AK14: 19050 | AL14: 22050 | AM14: =S14*AH14 -> 0 | AN14: =T14*AI14 -> 0 | AO14: =U14*AJ14 -> 0 | AP14: =V14*AK14 -> 0 | AQ14: =W14*AL14 -> 0 | AR14: =SUM(Tabla1[[#This Row],[COSTO OPERATIVO ACIDO]:[COSTO OPERATIVO CATIONICO]]) -> 0 | AS14: 3599 | AT14: =AR14/L14 -> #DIV/0! | AU14: =IFERROR(Tabla1[[#This Row],[CAUDAL TOTAL TRATADO GEM ]]/Tabla1[[#This Row],[CAUDAL DE TRATAMIENTO]],0) -> 0
A15: =+A14 -> 46117 | B15: 5 | C15: 6 (MAÑANA) | D15: 14 | E15: FINAL TURNO 1 | F15: 2600 | G15: 5600 | H15: 4190 | I15: =+I14-0 -> 265 | J15: =+J14-0 -> 440 | K15: 17633 | L15: =(K16-K15)*M15 -> 0 | M15: 80 | N15: =F15-F16 -> 0 | O15: =G15-G16 -> 0 | P15: =H15-H16 -> 0 | Q15: =I15-I16 -> 0 | R15: =J15-J16 -> 0 | S15: =(N15*$AC$2) -> 0 | T15: =(O15*$AD$2) -> 0 | U15: =(P15*$AE$2) -> 0 | V15: =Tabla1[[#This Row],[CONSUMO POL ANIONICO (KG)]] -> 0 | W15: =Tabla1[[#This Row],[CONSUMO POL CATIONICO (KG)]] -> 0 | X15: =(S15*1000)/L15 -> #DIV/0! | Y15: =(T15*1000)/L15 -> #DIV/0! | Z15: =(U15*1000)/L15 -> #DIV/0! | AA15: =(V15*1000)/L15 -> #DIV/0! | AB15: =(W15*1000)/L15 -> #DIV/0! | AC15: 1.3 | AD15: 1.325 | AE15: 1.25 | AF15: 2500 | AG15: 2500 | AH15: 830 | AI15: 2818 | AJ15: 6295 | AK15: 19050 | AL15: 22050 | AM15: =S15*AH15 -> 0 | AN15: =T15*AI15 -> 0 | AO15: =U15*AJ15 -> 0 | AP15: =V15*AK15 -> 0 | AQ15: =W15*AL15 -> 0 | AR15: =SUM(Tabla1[[#This Row],[COSTO OPERATIVO ACIDO]:[COSTO OPERATIVO CATIONICO]]) -> 0 | AS15: 3599 | AT15: =AR15/L15 -> #DIV/0! | AU15: =IFERROR(Tabla1[[#This Row],[CAUDAL TOTAL TRATADO GEM ]]/Tabla1[[#This Row],[CAUDAL DE TRATAMIENTO]],0) -> 0
A16: =+A15 -> 46117 | B16: 5 | C16: 3(TARDE) | D16: 15 | E16: FINAL TURNO 2 | F16: 2600 | G16: 5600 | H16: 4190 | I16: =+I15-0 -> 265 | J16: =J15-0 -> 440 | K16: 17633 | L16: =(K17-K16)*M16 -> 0 | M16: 80 | N16: =F16-F17 -> 0 | O16: =G16-G17 -> 0 | P16: =H16-H17 -> 0 | Q16: =I16-I17 -> 0 | R16: =J16-J17 -> 0 | S16: =(N16*$AC$2) -> 0 | T16: =(O16*$AD$2) -> 0 | U16: =(P16*$AE$2) -> 0 | V16: =Tabla1[[#This Row],[CONSUMO POL ANIONICO (KG)]] -> 0 | W16: =Tabla1[[#This Row],[CONSUMO POL CATIONICO (KG)]] -> 0 | X16: =(S16*1000)/L16 -> #DIV/0! | Y16: =(T16*1000)/L16 -> #DIV/0! | Z16: =(U16*1000)/L16 -> #DIV/0! | AA16: =(V16*1000)/L16 -> #DIV/0! | AB16: =(W16*1000)/L16 -> #DIV/0! | AC16: 1.3 | AD16: 1.325 | AE16: 1.25 | AF16: 2500 | AG16: 2500 | AH16: 830 | AI16: 2818 | AJ16: 6295 | AK16: 19050 | AL16: 22050 | AM16: =S16*AH16 -> 0 | AN16: =T16*AI16 -> 0 | AO16: =U16*AJ16 -> 0 | AP16: =V16*AK16 -> 0 | AQ16: =W16*AL16 -> 0 | AR16: =SUM(Tabla1[[#This Row],[COSTO OPERATIVO ACIDO]:[COSTO OPERATIVO CATIONICO]]) -> 0 | AS16: 3599 | AT16: =AR16/L16 -> #DIV/0! | AU16: =IFERROR(Tabla1[[#This Row],[CAUDAL TOTAL TRATADO GEM ]]/Tabla1[[#This Row],[CAUDAL DE TRATAMIENTO]],0) -> 0
A17: =+A16+1 -> 46118 | B17: 6 | C17: 6 (NOCHE) | D17: 16 | E17: FINAL TURNO 3 | F17: 2600 | G17: 5600 | H17: 4190 | I17: =+I16-0 -> 265 | J17: =+J16-0 -> 440 | K17: 17633 | L17: =(K18-K17)*M17 -> 160 | M17: 80 | N17: =F17-F18 -> 20 | O17: =G17-G18+4000 -> 110 | P17: =H17-H18 -> 0 | Q17: =I17-I18 -> 0 | R17: =J17-J18 -> 0 | S17: =(N17*$AC$2) -> 26 | T17: =(O17*$AD$2) -> 145.75 | U17: =(P17*$AE$2) -> 0 | V17: =Tabla1[[#This Row],[CONSUMO POL ANIONICO (KG)]] -> 0 | W17: =Tabla1[[#This Row],[CONSUMO POL CATIONICO (KG)]] -> 0 | X17: =(S17*1000)/L17 -> 162.5 | Y17: =(T17*1000)/L17 -> 910.9375 | Z17: =(U17*1000)/L17 -> 0 | AA17: =(V17*1000)/L17 -> 0 | AB17: =(W17*1000)/L17 -> 0 | AC17: 1.3 | AD17: 1.325 | AE17: 1.25 | AF17: 2500 | AG17: 2500 | AH17: 830 | AI17: 2818 | AJ17: 6295 | AK17: 19050 | AL17: 22050 | AM17: =S17*AH17 -> 21580 | AN17: =T17*AI17 -> 410723.5 | AO17: =U17*AJ17 -> 0 | AP17: =V17*AK17 -> 0 | AQ17: =W17*AL17 -> 0 | AR17: =SUM(Tabla1[[#This Row],[COSTO OPERATIVO ACIDO]:[COSTO OPERATIVO CATIONICO]]) -> 432303.5 | AS17: 3599 | AT17: =AR17/L17 -> 2701.8969 | AU17: =IFERROR(Tabla1[[#This Row],[CAUDAL TOTAL TRATADO GEM ]]/Tabla1[[#This Row],[CAUDAL DE TRATAMIENTO]],0) -> 2
A18: =+A17 -> 46118 | B18: 6 | C18: 7 (MAÑANA) | D18: 17 | E18: FINAL TURNO 1 | F18: 2580 | G18: 9490 | H18: 4190 | I18: =+I17-0 -> 265 | J18: =+J17-0 -> 440 | K18: 17635 | L18: =(K19-K18)*M18 -> 480 | M18: 80 | N18: =F18-F19 -> 20 | O18: =G18-G19-150 -> 140 | P18: =H18-H19 -> 40 | Q18: =I18-I19 -> 5 | R18: =J18-J19 -> 10 | S18: =(N18*$AC$2) -> 26 | T18: =(O18*$AD$2) -> 185.5 | U18: =(P18*$AE$2) -> 50 | V18: =Tabla1[[#This Row],[CONSUMO POL ANIONICO (KG)]] -> 5 | W18: =Tabla1[[#This Row],[CONSUMO POL CATIONICO (KG)]] -> 10 | X18: =(S18*1000)/L18 -> 54.166667 | Y18: =(T18*1000)/L18 -> 386.45833 | Z18: =(U18*1000)/L18 -> 104.16667 | AA18: =(V18*1000)/L18 -> 10.416667 | AB18: =(W18*1000)/L18 -> 20.833333 | AC18: 1.3 | AD18: 1.325 | AE18: 1.25 | AF18: 2500 | AG18: 2500 | AH18: 830 | AI18: 2818 | AJ18: 6295 | AK18: 19050 | AL18: 22050 | AM18: =S18*AH18 -> 21580 | AN18: =T18*AI18 -> 522739 | AO18: =U18*AJ18 -> 314750 | AP18: =V18*AK18 -> 95250 | AQ18: =W18*AL18 -> 220500 | AR18: =SUM(Tabla1[[#This Row],[COSTO OPERATIVO ACIDO]:[COSTO OPERATIVO CATIONICO]]) -> 1174819 | AS18: 3599 | AT18: =AR18/L18 -> 2447.5396 | AU18: =IFERROR(Tabla1[[#This Row],[CAUDAL TOTAL TRATADO GEM ]]/Tabla1[[#This Row],[CAUDAL DE TRATAMIENTO]],0) -> 6
A19: =+A18 -> 46118 | B19: 6 | C19: 3(TARDE) | D19: 18 | E19: FINAL TURNO 2 | F19: 2560 | G19: 9200 | H19: 4150 | I19: =+I18-5 -> 260 | J19: =+J18-10 -> 430 | K19: 17641 | L19: =(K20-K19)*M19 -> 400 | M19: 80 | N19: =F19-F20 -> 110 | O19: =G19-G20 -> 180 | P19: =H19-H20 -> 30 | Q19: =I19-I20 -> 0 | R19: =J19-J20 -> 5 | S19: =(N19*$AC$2) -> 143 | T19: =(O19*$AD$2) -> 238.5 | U19: =(P19*$AE$2) -> 37.5 | V19: =Tabla1[[#This Row],[CONSUMO POL ANIONICO (KG)]] -> 0 | W19: =Tabla1[[#This Row],[CONSUMO POL CATIONICO (KG)]] -> 5 | X19: =(S19*1000)/L19 -> 357.5 | Y19: =(T19*1000)/L19 -> 596.25 | Z19: =(U19*1000)/L19 -> 93.75 | AA19: =(V19*1000)/L19 -> 0 | AB19: =(W19*1000)/L19 -> 12.5 | AC19: 1.3 | AD19: 1.325 | AE19: 1.25 | AF19: 2500 | AG19: 2500 | AH19: 830 | AI19: 2818 | AJ19: 6295 | AK19: 19050 | AL19: 22050 | AM19: =S19*AH19 -> 118690 | AN19: =T19*AI19 -> 672093 | AO19: =U19*AJ19 -> 236062.5 | AP19: =V19*AK19 -> 0 | AQ19: =W19*AL19 -> 110250 | AR19: =SUM(Tabla1[[#This Row],[COSTO OPERATIVO ACIDO]:[COSTO OPERATIVO CATIONICO]]) -> 1137095.5 | AS19: 3599 | AT19: =AR19/L19 -> 2842.7387 | AU19: =IFERROR(Tabla1[[#This Row],[CAUDAL TOTAL TRATADO GEM ]]/Tabla1[[#This Row],[CAUDAL DE TRATAMIENTO]],0) -> 5
A20: =+A19+1 -> 46119 | B20: 7 | C20: 7 (NOCHE) | D20: 19 | E20: FINAL TURNO 3 | F20: 2450 | G20: 9020 | H20: 4120 | I20: =+I19-0 -> 260 | J20: =+J19-5 -> 425 | K20: 17646 | L20: =(K21-K20)*M20 -> 498 | M20: 83 | N20: =F20-F21 -> 50 | O20: =G20-G21 -> 90 | P20: =H20-H21 -> 20 | Q20: =I20-I21 -> 0 | R20: =J20-J21 -> 0 | S20: =(N20*$AC$2) -> 65 | T20: =(O20*$AD$2) -> 119.25 | U20: =(P20*$AE$2) -> 25 | V20: =Tabla1[[#This Row],[CONSUMO POL ANIONICO (KG)]] -> 0 | W20: =Tabla1[[#This Row],[CONSUMO POL CATIONICO (KG)]] -> 0 | X20: =(S20*1000)/L20 -> 130.52209 | Y20: =(T20*1000)/L20 -> 239.45783 | Z20: =(U20*1000)/L20 -> 50.200803 | AA20: =(V20*1000)/L20 -> 0 | AB20: =(W20*1000)/L20 -> 0 | AC20: 1.3 | AD20: 1.325 | AE20: 1.25 | AF20: 2500 | AG20: 2500 | AH20: 830 | AI20: 2818 | AJ20: 6295 | AK20: 19050 | AL20: 22050 | AM20: =S20*AH20 -> 53950 | AN20: =T20*AI20 -> 336046.5 | AO20: =U20*AJ20 -> 157375 | AP20: =V20*AK20 -> 0 | AQ20: =W20*AL20 -> 0 | AR20: =SUM(Tabla1[[#This Row],[COSTO OPERATIVO ACIDO]:[COSTO OPERATIVO CATIONICO]]) -> 547371.5 | AS20: 3599 | AT20: =AR20/L20 -> 1099.1396 | AU20: =IFERROR(Tabla1[[#This Row],[CAUDAL TOTAL TRATADO GEM ]]/Tabla1[[#This Row],[CAUDAL DE TRATAMIENTO]],0) -> 6
A21: =+A20 -> 46119 | B21: 7 | C21: 8 (MAÑANA) | D21: 20 | E21: FINAL TURNO 1 | F21: 2400 | G21: 8930 | H21: 4100 | I21: =+I20-0 -> 260 | J21: =+J20-0 -> 425 | K21: 17652 | L21: =(K22-K21)*M21 -> 249 | M21: 83 | N21: =F21-F22 -> 0 | O21: =G21-G22 -> 170 | P21: =H21-H22 -> 30 | Q21: =I21-I22 -> 0 | R21: =J21-J22 -> 5 | S21: =(N21*$AC$2) -> 0 | T21: =(O21*$AD$2) -> 225.25 | U21: =(P21*$AE$2) -> 37.5 | V21: =Tabla1[[#This Row],[CONSUMO POL ANIONICO (KG)]] -> 0 | W21: =Tabla1[[#This Row],[CONSUMO POL CATIONICO (KG)]] -> 5 | X21: =(S21*1000)/L21 -> 0 | Y21: =(T21*1000)/L21 -> 904.61847 | Z21: =(U21*1000)/L21 -> 150.60241 | AA21: =(V21*1000)/L21 -> 0 | AB21: =(W21*1000)/L21 -> 20.080321 | AC21: 1.3 | AD21: 1.325 | AE21: 1.25 | AF21: 2500 | AG21: 2500 | AH21: 830 | AI21: 2818 | AJ21: 6295 | AK21: 19050 | AL21: 22050 | AM21: =S21*AH21 -> 0 | AN21: =T21*AI21 -> 634754.5 | AO21: =U21*AJ21 -> 236062.5 | AP21: =V21*AK21 -> 0 | AQ21: =W21*AL21 -> 110250 | AR21: =SUM(Tabla1[[#This Row],[COSTO OPERATIVO ACIDO]:[COSTO OPERATIVO CATIONICO]]) -> 981067 | AS21: 3599 | AT21: =AR21/L21 -> 3940.0281 | AU21: =IFERROR(Tabla1[[#This Row],[CAUDAL TOTAL TRATADO GEM ]]/Tabla1[[#This Row],[CAUDAL DE TRATAMIENTO]],0) -> 3
A22: =+A21 -> 46119 | B22: 7 | C22: 3(TARDE) | D22: 21 | E22: FINAL TURNO 2 | F22: 2400 | G22: 8760 | H22: 4070 | I22: =+I21-0 -> 260 | J22: =+J21-5 -> 420 | K22: 17655 | L22: =(K23-K22)*M22 -> 332 | M22: 83 | N22: =F22-F23 -> 100 | O22: =G22-G23-150 -> 160 | P22: =H22-H23 -> 70 | Q22: =I22-I23 -> 5 | R22: =J22-J23 -> 5 | S22: =(N22*$AC$2) -> 130 | T22: =(O22*$AD$2) -> 212 | U22: =(P22*$AE$2) -> 87.5 | V22: =Tabla1[[#This Row],[CONSUMO POL ANIONICO (KG)]] -> 5 | W22: =Tabla1[[#This Row],[CONSUMO POL CATIONICO (KG)]] -> 5 | X22: =(S22*1000)/L22 -> 391.56627 | Y22: =(T22*1000)/L22 -> 638.55422 | Z22: =(U22*1000)/L22 -> 263.55422 | AA22: =(V22*1000)/L22 -> 15.060241 | AB22: =(W22*1000)/L22 -> 15.060241 | AC22: 1.3 | AD22: 1.325 | AE22: 1.25 | AF22: 2500 | AG22: 2500 | AH22: 830 | AI22: 2818 | AJ22: 6295 | AK22: 19050 | AL22: 22050 | AM22: =S22*AH22 -> 107900 | AN22: =T22*AI22 -> 597416 | AO22: =U22*AJ22 -> 550812.5 | AP22: =V22*AK22 -> 95250 | AQ22: =W22*AL22 -> 110250 | AR22: =SUM(Tabla1[[#This Row],[COSTO OPERATIVO ACIDO]:[COSTO OPERATIVO CATIONICO]]) -> 1461628.5 | AS22: 3599 | AT22: =AR22/L22 -> 4402.4955 | AU22: =IFERROR(Tabla1[[#This Row],[CAUDAL TOTAL TRATADO GEM ]]/Tabla1[[#This Row],[CAUDAL DE TRATAMIENTO]],0) -> 4
A23: =+A22+1 -> 46120 | B23: 8 | C23: 8 (NOCHE) | D23: 22 | E23: FINAL TURNO 3 | F23: 2300 | G23: 8450 | H23: 4000 | I23: =+I22-5 -> 255 | J23: =+J22-5 -> 415 | K23: 17659 | L23: =(K24-K23)*M23 -> 400 | M23: 80 | N23: =F23-F24 -> 150 | O23: =G23-G24 -> 110 | P23: =H23-H24 -> 60 | Q23: =I23-I24 -> 0 | R23: =J23-J24 -> 0 | S23: =(N23*$AC$2) -> 195 | T23: =(O23*$AD$2) -> 145.75 | U23: =(P23*$AE$2) -> 75 | V23: =Tabla1[[#This Row],[CONSUMO POL ANIONICO (KG)]] -> 0 | W23: =Tabla1[[#This Row],[CONSUMO POL CATIONICO (KG)]] -> 0 | X23: =(S23*1000)/L23 -> 487.5 | Y23: =(T23*1000)/L23 -> 364.375 | Z23: =(U23*1000)/L23 -> 187.5 | AA23: =(V23*1000)/L23 -> 0 | AB23: =(W23*1000)/L23 -> 0 | AC23: 1.3 | AD23: 1.325 | AE23: 1.25 | AF23: 2500 | AG23: 2500 | AH23: 830 | AI23: 2818 | AJ23: 6295 | AK23: 19050 | AL23: 22050 | AM23: =S23*AH23 -> 161850 | AN23: =T23*AI23 -> 410723.5 | AO23: =U23*AJ23 -> 472125 | AP23: =V23*AK23 -> 0 | AQ23: =W23*AL23 -> 0 | AR23: =SUM(Tabla1[[#This Row],[COSTO OPERATIVO ACIDO]:[COSTO OPERATIVO CATIONICO]]) -> 1044698.5 | AS23: 3599 | AT23: =AR23/L23 -> 2611.7463 | AU23: =IFERROR(Tabla1[[#This Row],[CAUDAL TOTAL TRATADO GEM ]]/Tabla1[[#This Row],[CAUDAL DE TRATAMIENTO]],0) -> 5
A24: =+A23 -> 46120 | B24: 8 | C24: 9 (MAÑANA) | D24: 23 | E24: FINAL TURNO 1 | F24: 2150 | G24: =+AVERAGE(G23,G25) -> 8340 | H24: 3940 | I24: =+I23-0 -> 255 | J24: =J23-0 -> 415 | K24: 17664 | L24: =(K25-K24)*M24 -> 240 | M24: 80 | N24: =F24-F25+2000 -> 130 | O24: =G24-G25 -> 110 | P24: =H24-H25+1000 -> 10 | Q24: =I24-I25 -> 0 | R24: =J24-J25 -> 5 | S24: =(N24*$AC$2) -> 169 | T24: =(O24*$AD$2) -> 145.75 | U24: =(P24*$AE$2) -> 12.5 | V24: =Tabla1[[#This Row],[CONSUMO POL ANIONICO (KG)]] -> 0 | W24: =Tabla1[[#This Row],[CONSUMO POL CATIONICO (KG)]] -> 5 | X24: =(S24*1000)/L24 -> 704.16667 | Y24: =(T24*1000)/L24 -> 607.29167 | Z24: =(U24*1000)/L24 -> 52.083333 | AA24: =(V24*1000)/L24 -> 0 | AB24: =(W24*1000)/L24 -> 20.833333 | AC24: 1.3 | AD24: 1.325 | AE24: 1.25 | AF24: 2500 | AG24: 2500 | AH24: 830 | AI24: 2818 | AJ24: 6295 | AK24: 19050 | AL24: 22050 | AM24: =S24*AH24 -> 140270 | AN24: =T24*AI24 -> 410723.5 | AO24: =U24*AJ24 -> 78687.5 | AP24: =V24*AK24 -> 0 | AQ24: =W24*AL24 -> 110250 | AR24: =SUM(Tabla1[[#This Row],[COSTO OPERATIVO ACIDO]:[COSTO OPERATIVO CATIONICO]]) -> 739931 | AS24: 3599 | AT24: =AR24/L24 -> 3083.0458 | AU24: =IFERROR(Tabla1[[#This Row],[CAUDAL TOTAL TRATADO GEM ]]/Tabla1[[#This Row],[CAUDAL DE TRATAMIENTO]],0) -> 3
A25: =+A24 -> 46120 | B25: 8 | C25: 3(TARDE) | D25: 24 | E25: FINAL TURNO 2 | F25: 4020 | G25: 8230 | H25: 4930 | I25: =+I24-0 -> 255 | J25: =+J24-5 -> 410 | K25: 17667 | L25: =(K26-K25)*M25 -> 560 | M25: 80 | N25: =F25-F26 -> 90 | O25: =G25-G26 -> 120 | P25: =H25-H26 -> 30 | Q25: =I25-I26 -> 5 | R25: =J25-J26 -> 5 | S25: =(N25*$AC$2) -> 117 | T25: =(O25*$AD$2) -> 159 | U25: =(P25*$AE$2) -> 37.5 | V25: =Tabla1[[#This Row],[CONSUMO POL ANIONICO (KG)]] -> 5 | W25: =Tabla1[[#This Row],[CONSUMO POL CATIONICO (KG)]] -> 5 | X25: =(S25*1000)/L25 -> 208.92857 | Y25: =(T25*1000)/L25 -> 283.92857 | Z25: =(U25*1000)/L25 -> 66.964286 | AA25: =(V25*1000)/L25 -> 8.9285714 | AB25: =(W25*1000)/L25 -> 8.9285714 | AC25: 1.3 | AD25: 1.325 | AE25: 1.25 | AF25: 2500 | AG25: 2500 | AH25: 830 | AI25: 2818 | AJ25: 6295 | AK25: 19050 | AL25: 22050 | AM25: =S25*AH25 -> 97110 | AN25: =T25*AI25 -> 448062 | AO25: =U25*AJ25 -> 236062.5 | AP25: =V25*AK25 -> 95250 | AQ25: =W25*AL25 -> 110250 | AR25: =SUM(Tabla1[[#This Row],[COSTO OPERATIVO ACIDO]:[COSTO OPERATIVO CATIONICO]]) -> 986734.5 | AS25: 3599 | AT25: =AR25/L25 -> 1762.0259 | AU25: =IFERROR(Tabla1[[#This Row],[CAUDAL TOTAL TRATADO GEM ]]/Tabla1[[#This Row],[CAUDAL DE TRATAMIENTO]],0) -> 7
A26: =+A25+1 -> 46121 | B26: 9 | C26: 9 (NOCHE) | D26: 25 | E26: FINAL TURNO 3 | F26: 3930 | G26: 8110 | H26: 4900 | I26: =+I25-5 -> 250 | J26: =+J25-5 -> 405 | K26: 17674 | L26: =(K27-K26)*M26 -> 560 | M26: 80 | N26: =F26-F27 -> 70 | O26: =G26-G27 -> 100 | P26: =H26-H27 -> 10 | Q26: =I26-I27 -> 5 | R26: =J26-J27 -> 5 | S26: =(N26*$AC$2) -> 91 | T26: =(O26*$AD$2) -> 132.5 | U26: =(P26*$AE$2) -> 12.5 | V26: =Tabla1[[#This Row],[CONSUMO POL ANIONICO (KG)]] -> 5 | W26: =Tabla1[[#This Row],[CONSUMO POL CATIONICO (KG)]] -> 5 | X26: =(S26*1000)/L26 -> 162.5 | Y26: =(T26*1000)/L26 -> 236.60714 | Z26: =(U26*1000)/L26 -> 22.321429 | AA26: =(V26*1000)/L26 -> 8.9285714 | AB26: =(W26*1000)/L26 -> 8.9285714 | AC26: 1.3 | AD26: 1.325 | AE26: 1.25 | AF26: 2500 | AG26: 2500 | AH26: 830 | AI26: 2818 | AJ26: 6295 | AK26: 19050 | AL26: 22050 | AM26: =S26*AH26 -> 75530 | AN26: =T26*AI26 -> 373385 | AO26: =U26*AJ26 -> 78687.5 | AP26: =V26*AK26 -> 95250 | AQ26: =W26*AL26 -> 110250 | AR26: =SUM(Tabla1[[#This Row],[COSTO OPERATIVO ACIDO]:[COSTO OPERATIVO CATIONICO]]) -> 733102.5 | AS26: 3599 | AT26: =AR26/L26 -> 1309.1116 | AU26: =IFERROR(Tabla1[[#This Row],[CAUDAL TOTAL TRATADO GEM ]]/Tabla1[[#This Row],[CAUDAL DE TRATAMIENTO]],0) -> 7
A27: =+A26 -> 46121 | B27: 9 | C27: 10 (MAÑANA) | D27: 26 | E27: FINAL TURNO 1 | F27: 3860 | G27: 8010 | H27: 4890 | I27: =+I26-5 -> 245 | J27: =+J26-5 -> 400 | K27: 17681 | L27: =(K28-K27)*M27 -> 240 | M27: 80 | N27: =F27-F28 -> 160 | O27: =G27-G28-50 -> 60 | P27: =H27-H28 -> 30 | Q27: =I27-I28 -> 5 | R27: =J27-J28 -> 5 | S27: =(N27*$AC$2) -> 208 | T27: =(O27*$AD$2) -> 79.5 | U27: =(P27*$AE$2) -> 37.5 | V27: =Tabla1[[#This Row],[CONSUMO POL ANIONICO (KG)]] -> 5 | W27: =Tabla1[[#This Row],[CONSUMO POL CATIONICO (KG)]] -> 5 | X27: =(S27*1000)/L27 -> 866.66667 | Y27: =(T27*1000)/L27 -> 331.25 | Z27: =(U27*1000)/L27 -> 156.25 | AA27: =(V27*1000)/L27 -> 20.833333 | AB27: =(W27*1000)/L27 -> 20.833333 | AC27: 1.3 | AD27: 1.325 | AE27: 1.25 | AF27: 2500 | AG27: 2500 | AH27: 830 | AI27: 2818 | AJ27: 6295 | AK27: 19050 | AL27: 22050 | AM27: =S27*AH27 -> 172640 | AN27: =T27*AI27 -> 224031 | AO27: =U27*AJ27 -> 236062.5 | AP27: =V27*AK27 -> 95250 | AQ27: =W27*AL27 -> 110250 | AR27: =SUM(Tabla1[[#This Row],[COSTO OPERATIVO ACIDO]:[COSTO OPERATIVO CATIONICO]]) -> 838233.5 | AS27: 3599 | AT27: =AR27/L27 -> 3492.6396 | AU27: =IFERROR(Tabla1[[#This Row],[CAUDAL TOTAL TRATADO GEM ]]/Tabla1[[#This Row],[CAUDAL DE TRATAMIENTO]],0) -> 3
A28: =+A27 -> 46121 | B28: 9 | C28: 3(TARDE) | D28: 27 | E28: FINAL TURNO 2 | F28: 3700 | G28: 7900 | H28: 4860 | I28: =+I27-5 -> 240 | J28: =+J27-5 -> 395 | K28: 17684 | L28: =(K29-K28)*M28 -> 480 | M28: 80 | N28: =F28-F29 -> 200 | O28: =G28-G29-50 -> 50 | P28: =H28-H29 -> 30 | Q28: =I28-I29 -> 0 | R28: =J28-J29 -> 5 | S28: =(N28*$AC$2) -> 260 | T28: =(O28*$AD$2) -> 66.25 | U28: =(P28*$AE$2) -> 37.5 | V28: =Tabla1[[#This Row],[CONSUMO POL ANIONICO (KG)]] -> 0 | W28: =Tabla1[[#This Row],[CONSUMO POL CATIONICO (KG)]] -> 5 | X28: =(S28*1000)/L28 -> 541.66667 | Y28: =(T28*1000)/L28 -> 138.02083 | Z28: =(U28*1000)/L28 -> 78.125 | AA28: =(V28*1000)/L28 -> 0 | AB28: =(W28*1000)/L28 -> 10.416667 | AC28: 1.3 | AD28: 1.325 | AE28: 1.25 | AF28: 2500 | AG28: 2500 | AH28: 830 | AI28: 2818 | AJ28: 6295 | AK28: 19050 | AL28: 22050 | AM28: =S28*AH28 -> 215800 | AN28: =T28*AI28 -> 186692.5 | AO28: =U28*AJ28 -> 236062.5 | AP28: =V28*AK28 -> 0 | AQ28: =W28*AL28 -> 110250 | AR28: =SUM(Tabla1[[#This Row],[COSTO OPERATIVO ACIDO]:[COSTO OPERATIVO CATIONICO]]) -> 748805 | AS28: 3599 | AT28: =AR28/L28 -> 1560.0104 | AU28: =IFERROR(Tabla1[[#This Row],[CAUDAL TOTAL TRATADO GEM ]]/Tabla1[[#This Row],[CAUDAL DE TRATAMIENTO]],0) -> 6
A29: =+A28+1 -> 46122 | B29: 10 | C29: 10 (NOCHE) | D29: 28 | E29: FINAL TURNO 3 | F29: 3500 | G29: 7800 | H29: 4830 | I29: =+I28-0 -> 240 | J29: =+J28-5 -> 390 | K29: 17690 | L29: =(K30-K29)*M29 -> 480 | M29: 80 | N29: =F29-F30 -> 10 | O29: =G29-G30 -> 10 | P29: =H29-H30 -> 60 | Q29: =I29-I30 -> 5 | R29: =J29-J30 -> 5 | S29: =(N29*$AC$2) -> 13 | T29: =(O29*$AD$2) -> 13.25 | U29: =(P29*$AE$2) -> 75 | V29: =Tabla1[[#This Row],[CONSUMO POL ANIONICO (KG)]] -> 5 | W29: =Tabla1[[#This Row],[CONSUMO POL CATIONICO (KG)]] -> 5 | X29: =(S29*1000)/L29 -> 27.083333 | Y29: =(T29*1000)/L29 -> 27.604167 | Z29: =(U29*1000)/L29 -> 156.25 | AA29: =(V29*1000)/L29 -> 10.416667 | AB29: =(W29*1000)/L29 -> 10.416667 | AC29: 1.3 | AD29: 1.325 | AE29: 1.25 | AF29: 2500 | AG29: 2500 | AH29: 830 | AI29: 2818 | AJ29: 6295 | AK29: 19050 | AL29: 22050 | AM29: =S29*AH29 -> 10790 | AN29: =T29*AI29 -> 37338.5 | AO29: =U29*AJ29 -> 472125 | AP29: =V29*AK29 -> 95250 | AQ29: =W29*AL29 -> 110250 | AR29: =SUM(Tabla1[[#This Row],[COSTO OPERATIVO ACIDO]:[COSTO OPERATIVO CATIONICO]]) -> 725753.5 | AS29: 3599 | AT29: =AR29/L29 -> 1511.9865 | AU29: =IFERROR(Tabla1[[#This Row],[CAUDAL TOTAL TRATADO GEM ]]/Tabla1[[#This Row],[CAUDAL DE TRATAMIENTO]],0) -> 6
A30: =+A29 -> 46122 | B30: 10 | C30: 11 (MAÑANA) | D30: 29 | E30: FINAL TURNO 1 | F30: 3490 | G30: 7790 | H30: 4770 | I30: =+I29-5 -> 235 | J30: =+J29-5 -> 385 | K30: 17696 | L30: =(K31-K30)*M30 -> 400 | M30: 80 | N30: =F30-F31-70 -> 80 | O30: =G30-G31 -> 190 | P30: =H30-H31 -> 20 | Q30: =I30-I31 -> 0 | R30: =J30-J31 -> 5 | S30: =(N30*$AC$2) -> 104 | T30: =(O30*$AD$2) -> 251.75 | U30: =(P30*$AE$2) -> 25 | V30: =Tabla1[[#This Row],[CONSUMO POL ANIONICO (KG)]] -> 0 | W30: =Tabla1[[#This Row],[CONSUMO POL CATIONICO (KG)]] -> 5 | X30: =(S30*1000)/L30 -> 260 | Y30: =(T30*1000)/L30 -> 629.375 | Z30: =(U30*1000)/L30 -> 62.5 | AA30: =(V30*1000)/L30 -> 0 | AB30: =(W30*1000)/L30 -> 12.5 | AC30: 1.3 | AD30: 1.325 | AE30: 1.25 | AF30: 2500 | AG30: 2500 | AH30: 830 | AI30: 2818 | AJ30: 6295 | AK30: 19050 | AL30: 22050 | AM30: =S30*AH30 -> 86320 | AN30: =T30*AI30 -> 709431.5 | AO30: =U30*AJ30 -> 157375 | AP30: =V30*AK30 -> 0 | AQ30: =W30*AL30 -> 110250 | AR30: =SUM(Tabla1[[#This Row],[COSTO OPERATIVO ACIDO]:[COSTO OPERATIVO CATIONICO]]) -> 1063376.5 | AS30: 3599 | AT30: =AR30/L30 -> 2658.4412 | AU30: =IFERROR(Tabla1[[#This Row],[CAUDAL TOTAL TRATADO GEM ]]/Tabla1[[#This Row],[CAUDAL DE TRATAMIENTO]],0) -> 5
A31: =+A30 -> 46122 | B31: 10 | C31: 3(TARDE) | D31: 30 | E31: FINAL TURNO 2 | F31: 3340 | G31: 7600 | H31: 4750 | I31: =+I30-0 -> 235 | J31: =+J30-5 -> 380 | K31: 17701 | L31: =(K32-K31)*M31 -> 640 | M31: 80 | N31: =F31-F32 -> 110 | O31: =G31-G32-210 -> 220 | P31: =H31-H32 -> 60 | Q31: =I31-I32 -> 5 | R31: =J31-J32 -> 5 | S31: =(N31*$AC$2) -> 143 | T31: =(O31*$AD$2) -> 291.5 | U31: =(P31*$AE$2) -> 75 | V31: =Tabla1[[#This Row],[CONSUMO POL ANIONICO (KG)]] -> 5 | W31: =Tabla1[[#This Row],[CONSUMO POL CATIONICO (KG)]] -> 5 | X31: =(S31*1000)/L31 -> 223.4375 | Y31: =(T31*1000)/L31 -> 455.46875 | Z31: =(U31*1000)/L31 -> 117.1875 | AA31: =(V31*1000)/L31 -> 7.8125 | AB31: =(W31*1000)/L31 -> 7.8125 | AC31: 1.3 | AD31: 1.325 | AE31: 1.25 | AF31: 2500 | AG31: 2500 | AH31: 830 | AI31: 2818 | AJ31: 6295 | AK31: 19050 | AL31: 22050 | AM31: =S31*AH31 -> 118690 | AN31: =T31*AI31 -> 821447 | AO31: =U31*AJ31 -> 472125 | AP31: =V31*AK31 -> 95250 | AQ31: =W31*AL31 -> 110250 | AR31: =SUM(Tabla1[[#This Row],[COSTO OPERATIVO ACIDO]:[COSTO OPERATIVO CATIONICO]]) -> 1617762 | AS31: 3599 | AT31: =AR31/L31 -> 2527.7531 | AU31: =IFERROR(Tabla1[[#This Row],[CAUDAL TOTAL TRATADO GEM ]]/Tabla1[[#This Row],[CAUDAL DE TRATAMIENTO]],0) -> 8
A32: =+A31+1 -> 46123 | B32: 11 | C32: 11 (NOCHE) | D32: 31 | E32: FINAL TURNO 3 | F32: 3230 | G32: 7170 | H32: 4690 | I32: =+I31-5 -> 230 | J32: =+J31-5 -> 375 | K32: 17709 | L32: =(K33-K32)*M32 -> 400 | M32: 80 | N32: =F32-F33 -> 110 | O32: =G32-G33 -> 100 | P32: =H32-H33 -> 90 | Q32: =I32-I33 -> 0 | R32: =J32-J33 -> 5 | S32: =(N32*$AC$2) -> 143 | T32: =(O32*$AD$2) -> 132.5 | U32: =(P32*$AE$2) -> 112.5 | V32: =Tabla1[[#This Row],[CONSUMO POL ANIONICO (KG)]] -> 0 | W32: =Tabla1[[#This Row],[CONSUMO POL CATIONICO (KG)]] -> 5 | X32: =(S32*1000)/L32 -> 357.5 | Y32: =(T32*1000)/L32 -> 331.25 | Z32: =(U32*1000)/L32 -> 281.25 | AA32: =(V32*1000)/L32 -> 0 | AB32: =(W32*1000)/L32 -> 12.5 | AC32: 1.3 | AD32: 1.325 | AE32: 1.25 | AF32: 2500 | AG32: 2500 | AH32: 830 | AI32: 2818 | AJ32: 6295 | AK32: 19050 | AL32: 22050 | AM32: =S32*AH32 -> 118690 | AN32: =T32*AI32 -> 373385 | AO32: =U32*AJ32 -> 708187.5 | AP32: =V32*AK32 -> 0 | AQ32: =W32*AL32 -> 110250 | AR32: =SUM(Tabla1[[#This Row],[COSTO OPERATIVO ACIDO]:[COSTO OPERATIVO CATIONICO]]) -> 1310512.5 | AS32: 3599 | AT32: =AR32/L32 -> 3276.2812 | AU32: =IFERROR(Tabla1[[#This Row],[CAUDAL TOTAL TRATADO GEM ]]/Tabla1[[#This Row],[CAUDAL DE TRATAMIENTO]],0) -> 5
A33: =+A32 -> 46123 | B33: 11 | C33: 12 (MAÑANA) | D33: 32 | E33: FINAL TURNO 1 | F33: 3120 | G33: 7070 | H33: 4600 | I33: =+I32-0 -> 230 | J33: =+J32-5 -> 370 | K33: 17714 | L33: =(K34-K33)*M33 -> 320 | M33: 80 | N33: =F33-F34 -> 20 | O33: =G33-G34 -> 170 | P33: =H33-H34 -> 50 | Q33: =I33-I34 -> 0 | R33: =J33-J34 -> 0 | S33: =(N33*$AC$2) -> 26 | T33: =(O33*$AD$2) -> 225.25 | U33: =(P33*$AE$2) -> 62.5 | V33: =Tabla1[[#This Row],[CONSUMO POL ANIONICO (KG)]] -> 0 | W33: =Tabla1[[#This Row],[CONSUMO POL CATIONICO (KG)]] -> 0 | X33: =(S33*1000)/L33 -> 81.25 | Y33: =(T33*1000)/L33 -> 703.90625 | Z33: =(U33*1000)/L33 -> 195.3125 | AA33: =(V33*1000)/L33 -> 0 | AB33: =(W33*1000)/L33 -> 0 | AC33: 1.3 | AD33: 1.325 | AE33: 1.25 | AF33: 2500 | AG33: 2500 | AH33: 830 | AI33: 2818 | AJ33: 6295 | AK33: 19050 | AL33: 22050 | AM33: =S33*AH33 -> 21580 | AN33: =T33*AI33 -> 634754.5 | AO33: =U33*AJ33 -> 393437.5 | AP33: =V33*AK33 -> 0 | AQ33: =W33*AL33 -> 0 | AR33: =SUM(Tabla1[[#This Row],[COSTO OPERATIVO ACIDO]:[COSTO OPERATIVO CATIONICO]]) -> 1049772 | AS33: 3599 | AT33: =AR33/L33 -> 3280.5375 | AU33: =IFERROR(Tabla1[[#This Row],[CAUDAL TOTAL TRATADO GEM ]]/Tabla1[[#This Row],[CAUDAL DE TRATAMIENTO]],0) -> 4
A34: =+A33 -> 46123 | B34: 11 | C34: 3(TARDE) | D34: 33 | E34: FINAL TURNO 2 | F34: 3100 | G34: 6900 | H34: 4550 | I34: =+I33-0 -> 230 | J34: =+J33-0 -> 370 | K34: 17718 | L34: =(K35-K34)*M34 -> 320 | M34: 80 | N34: =F34-F35 -> 50 | O34: =G34-G35 -> 100 | P34: =H34-H35 -> 50 | Q34: =I34-I35 -> 0 | R34: =J34-J35 -> 5 | S34: =(N34*$AC$2) -> 65 | T34: =(O34*$AD$2) -> 132.5 | U34: =(P34*$AE$2) -> 62.5 | V34: =Tabla1[[#This Row],[CONSUMO POL ANIONICO (KG)]] -> 0 | W34: =Tabla1[[#This Row],[CONSUMO POL CATIONICO (KG)]] -> 5 | X34: =(S34*1000)/L34 -> 203.125 | Y34: =(T34*1000)/L34 -> 414.0625 | Z34: =(U34*1000)/L34 -> 195.3125 | AA34: =(V34*1000)/L34 -> 0 | AB34: =(W34*1000)/L34 -> 15.625 | AC34: 1.3 | AD34: 1.325 | AE34: 1.25 | AF34: 2500 | AG34: 2500 | AH34: 830 | AI34: 2818 | AJ34: 6295 | AK34: 19050 | AL34: 22050 | AM34: =S34*AH34 -> 53950 | AN34: =T34*AI34 -> 373385 | AO34: =U34*AJ34 -> 393437.5 | AP34: =V34*AK34 -> 0 | AQ34: =W34*AL34 -> 110250 | AR34: =SUM(Tabla1[[#This Row],[COSTO OPERATIVO ACIDO]:[COSTO OPERATIVO CATIONICO]]) -> 931022.5 | AS34: 3599 | AT34: =AR34/L34 -> 2909.4453 | AU34: =IFERROR(Tabla1[[#This Row],[CAUDAL TOTAL TRATADO GEM ]]/Tabla1[[#This Row],[CAUDAL DE TRATAMIENTO]],0) -> 4
A35: =+A34+1 -> 46124 | B35: 12 | C35: 12 (NOCHE) | D35: 34 | E35: FINAL TURNO 3 | F35: 3050 | G35: 6800 | H35: 4500 | I35: =+I34-0 -> 230 | J35: =+J34-5 -> 365 | K35: 17722 | L35: =(K36-K35)*M35 -> 0 | M35: 80 | N35: =F35-F36 -> 0 | O35: =G35-G36 -> 0 | P35: =H35-H36 -> 0 | Q35: =I35-I36 -> 0 | R35: =J35-J36 -> 0 | S35: =(N35*$AC$2) -> 0 | T35: =(O35*$AD$2) -> 0 | U35: =(P35*$AE$2) -> 0 | V35: =Tabla1[[#This Row],[CONSUMO POL ANIONICO (KG)]] -> 0 | W35: =Tabla1[[#This Row],[CONSUMO POL CATIONICO (KG)]] -> 0 | X35: =(S35*1000)/L35 -> #DIV/0! | Y35: =(T35*1000)/L35 -> #DIV/0! | Z35: =(U35*1000)/L35 -> #DIV/0! | AA35: =(V35*1000)/L35 -> #DIV/0! | AB35: =(W35*1000)/L35 -> #DIV/0! | AC35: 1.3 | AD35: 1.325 | AE35: 1.25 | AF35: 2500 | AG35: 2500 | AH35: 830 | AI35: 2818 | AJ35: 6295 | AK35: 19050 | AL35: 22050 | AM35: =S35*AH35 -> 0 | AN35: =T35*AI35 -> 0 | AO35: =U35*AJ35 -> 0 | AP35: =V35*AK35 -> 0 | AQ35: =W35*AL35 -> 0 | AR35: =SUM(Tabla1[[#This Row],[COSTO OPERATIVO ACIDO]:[COSTO OPERATIVO CATIONICO]]) -> 0 | AS35: 3599 | AT35: =AR35/L35 -> #DIV/0! | AU35: =IFERROR(Tabla1[[#This Row],[CAUDAL TOTAL TRATADO GEM ]]/Tabla1[[#This Row],[CAUDAL DE TRATAMIENTO]],0) -> 0
A36: =+A35 -> 46124 | B36: 12 | C36: 13 (MAÑANA) | D36: 35 | E36: FINAL TURNO 1 | F36: 3050 | G36: 6800 | H36: 4500 | I36: =+I35-0 -> 230 | J36: =+J35-0 -> 365 | K36: 17722 | L36: =(K37-K36)*M36 -> 0 | M36: 80 | N36: =F36-F37 -> 0 | O36: =G36-G37 -> 0 | P36: =H36-H37 -> 0 | Q36: =I36-I37 -> 0 | R36: =J36-J37 -> 0 | S36: =(N36*$AC$2) -> 0 | T36: =(O36*$AD$2) -> 0 | U36: =(P36*$AE$2) -> 0 | V36: =Tabla1[[#This Row],[CONSUMO POL ANIONICO (KG)]] -> 0 | W36: =Tabla1[[#This Row],[CONSUMO POL CATIONICO (KG)]] -> 0 | X36: =(S36*1000)/L36 -> #DIV/0! | Y36: =(T36*1000)/L36 -> #DIV/0! | Z36: =(U36*1000)/L36 -> #DIV/0! | AA36: =(V36*1000)/L36 -> #DIV/0! | AB36: =(W36*1000)/L36 -> #DIV/0! | AC36: 1.3 | AD36: 1.325 | AE36: 1.25 | AF36: 2500 | AG36: 2500 | AH36: 830 | AI36: 2818 | AJ36: 6295 | AK36: 19050 | AL36: 22050 | AM36: =S36*AH36 -> 0 | AN36: =T36*AI36 -> 0 | AO36: =U36*AJ36 -> 0 | AP36: =V36*AK36 -> 0 | AQ36: =W36*AL36 -> 0 | AR36: =SUM(Tabla1[[#This Row],[COSTO OPERATIVO ACIDO]:[COSTO OPERATIVO CATIONICO]]) -> 0 | AS36: 3599 | AT36: =AR36/L36 -> #DIV/0! | AU36: =IFERROR(Tabla1[[#This Row],[CAUDAL TOTAL TRATADO GEM ]]/Tabla1[[#This Row],[CAUDAL DE TRATAMIENTO]],0) -> 0
A37: =+A36 -> 46124 | B37: 12 | C37: 3(TARDE) | D37: 36 | E37: FINAL TURNO 2 | F37: 3050 | G37: 6800 | H37: 4500 | I37: =+I36-0 -> 230 | J37: =+J36-0 -> 365 | K37: 17722 | L37: =(K38-K37)*M37 -> 0 | M37: 80 | N37: =F37-F38 -> 0 | O37: =G37-G38 -> 0 | P37: =H37-H38 -> 0 | Q37: =I37-I38 -> 0 | R37: =J37-J38 -> 0 | S37: =(N37*$AC$2) -> 0 | T37: =(O37*$AD$2) -> 0 | U37: =(P37*$AE$2) -> 0 | V37: =Tabla1[[#This Row],[CONSUMO POL ANIONICO (KG)]] -> 0 | W37: =Tabla1[[#This Row],[CONSUMO POL CATIONICO (KG)]] -> 0 | X37: =(S37*1000)/L37 -> #DIV/0! | Y37: =(T37*1000)/L37 -> #DIV/0! | Z37: =(U37*1000)/L37 -> #DIV/0! | AA37: =(V37*1000)/L37 -> #DIV/0! | AB37: =(W37*1000)/L37 -> #DIV/0! | AC37: 1.3 | AD37: 1.325 | AE37: 1.25 | AF37: 2500 | AG37: 2500 | AH37: 830 | AI37: 2818 | AJ37: 6295 | AK37: 19050 | AL37: 22050 | AM37: =S37*AH37 -> 0 | AN37: =T37*AI37 -> 0 | AO37: =U37*AJ37 -> 0 | AP37: =V37*AK37 -> 0 | AQ37: =W37*AL37 -> 0 | AR37: =SUM(Tabla1[[#This Row],[COSTO OPERATIVO ACIDO]:[COSTO OPERATIVO CATIONICO]]) -> 0 | AS37: 3599 | AT37: =AR37/L37 -> #DIV/0! | AU37: =IFERROR(Tabla1[[#This Row],[CAUDAL TOTAL TRATADO GEM ]]/Tabla1[[#This Row],[CAUDAL DE TRATAMIENTO]],0) -> 0
A38: =+A37+1 -> 46125 | B38: 13 | C38: 13 (NOCHE) | D38: 37 | E38: FINAL TURNO 3 | F38: 3050 | G38: 6800 | H38: 4500 | I38: =+I37-0 -> 230 | J38: =+J37-0 -> 365 | K38: 17722 | L38: =(K39-K38)*M38 -> 480 | M38: 80 | N38: =F38-F39 -> 150 | O38: =G38-G39 -> 100 | P38: =H38-H39 -> 20 | Q38: =I38-I39 -> 0 | R38: =J38-J39 -> 10 | S38: =(N38*$AC$2) -> 195 | T38: =(O38*$AD$2) -> 132.5 | U38: =(P38*$AE$2) -> 25 | V38: =Tabla1[[#This Row],[CONSUMO POL ANIONICO (KG)]] -> 0 | W38: =Tabla1[[#This Row],[CONSUMO POL CATIONICO (KG)]] -> 10 | X38: =(S38*1000)/L38 -> 406.25 | Y38: =(T38*1000)/L38 -> 276.04167 | Z38: =(U38*1000)/L38 -> 52.083333 | AA38: =(V38*1000)/L38 -> 0 | AB38: =(W38*1000)/L38 -> 20.833333 | AC38: 1.3 | AD38: 1.325 | AE38: 1.25 | AF38: 2500 | AG38: 2500 | AH38: 830 | AI38: 2818 | AJ38: 6295 | AK38: 19050 | AL38: 22050 | AM38: =S38*AH38 -> 161850 | AN38: =T38*AI38 -> 373385 | AO38: =U38*AJ38 -> 157375 | AP38: =V38*AK38 -> 0 | AQ38: =W38*AL38 -> 220500 | AR38: =SUM(Tabla1[[#This Row],[COSTO OPERATIVO ACIDO]:[COSTO OPERATIVO CATIONICO]]) -> 913110 | AS38: 3599 | AT38: =AR38/L38 -> 1902.3125 | AU38: =IFERROR(Tabla1[[#This Row],[CAUDAL TOTAL TRATADO GEM ]]/Tabla1[[#This Row],[CAUDAL DE TRATAMIENTO]],0) -> 6
A39: =+A38 -> 46125 | B39: 13 | C39: 14 (MAÑANA) | D39: 38 | E39: FINAL TURNO 1 | F39: 2900 | G39: 6700 | H39: 4480 | I39: =+I38-0 -> 230 | J39: =+J38-10 -> 355 | K39: 17728 | L39: =(K40-K39)*M39 -> 400 | M39: 80 | N39: =F39-F40 -> 100 | O39: =G39-G40 -> 100 | P39: =H39-H40 -> 30 | Q39: =I39-I40 -> 5 | R39: =J39-J40 -> 5 | S39: =(N39*$AC$2) -> 130 | T39: =(O39*$AD$2) -> 132.5 | U39: =(P39*$AE$2) -> 37.5 | V39: =Tabla1[[#This Row],[CONSUMO POL ANIONICO (KG)]] -> 5 | W39: =Tabla1[[#This Row],[CONSUMO POL CATIONICO (KG)]] -> 5 | X39: =(S39*1000)/L39 -> 325 | Y39: =(T39*1000)/L39 -> 331.25 | Z39: =(U39*1000)/L39 -> 93.75 | AA39: =(V39*1000)/L39 -> 12.5 | AB39: =(W39*1000)/L39 -> 12.5 | AC39: 1.3 | AD39: 1.325 | AE39: 1.25 | AF39: 2500 | AG39: 2500 | AH39: 830 | AI39: 2818 | AJ39: 6295 | AK39: 19050 | AL39: 22050 | AM39: =S39*AH39 -> 107900 | AN39: =T39*AI39 -> 373385 | AO39: =U39*AJ39 -> 236062.5 | AP39: =V39*AK39 -> 95250 | AQ39: =W39*AL39 -> 110250 | AR39: =SUM(Tabla1[[#This Row],[COSTO OPERATIVO ACIDO]:[COSTO OPERATIVO CATIONICO]]) -> 922847.5 | AS39: 3599 | AT39: =AR39/L39 -> 2307.1188 | AU39: =IFERROR(Tabla1[[#This Row],[CAUDAL TOTAL TRATADO GEM ]]/Tabla1[[#This Row],[CAUDAL DE TRATAMIENTO]],0) -> 5
A40: =+A39 -> 46125 | B40: 13 | C40: 3(TARDE) | D40: 39 | E40: FINAL TURNO 2 | F40: 2800 | G40: 6600 | H40: 4450 | I40: =+I39-5 -> 225 | J40: =+J39-5 -> 350 | K40: 17733 | L40: =(K41-K40)*M40 -> 480 | M40: 80 | N40: =F40-F41 -> 100 | O40: =G40-G41 -> 100 | P40: =H40-H41 -> 100 | Q40: =I40-I41 -> 0 | R40: =J40-J41 -> 5 | S40: =(N40*$AC$2) -> 130 | T40: =(O40*$AD$2) -> 132.5 | U40: =(P40*$AE$2) -> 125 | V40: =Tabla1[[#This Row],[CONSUMO POL ANIONICO (KG)]] -> 0 | W40: =Tabla1[[#This Row],[CONSUMO POL CATIONICO (KG)]] -> 5 | X40: =(S40*1000)/L40 -> 270.83333 | Y40: =(T40*1000)/L40 -> 276.04167 | Z40: =(U40*1000)/L40 -> 260.41667 | AA40: =(V40*1000)/L40 -> 0 | AB40: =(W40*1000)/L40 -> 10.416667 | AC40: 1.3 | AD40: 1.325 | AE40: 1.25 | AF40: 2500 | AG40: 2500 | AH40: 830 | AI40: 2818 | AJ40: 6295 | AK40: 19050 | AL40: 22050 | AM40: =S40*AH40 -> 107900 | AN40: =T40*AI40 -> 373385 | AO40: =U40*AJ40 -> 786875 | AP40: =V40*AK40 -> 0 | AQ40: =W40*AL40 -> 110250 | AR40: =SUM(Tabla1[[#This Row],[COSTO OPERATIVO ACIDO]:[COSTO OPERATIVO CATIONICO]]) -> 1378410 | AS40: 3599 | AT40: =AR40/L40 -> 2871.6875 | AU40: =IFERROR(Tabla1[[#This Row],[CAUDAL TOTAL TRATADO GEM ]]/Tabla1[[#This Row],[CAUDAL DE TRATAMIENTO]],0) -> 6
A41: =+A40+1 -> 46126 | B41: 14 | C41: 14 (NOCHE) | D41: 40 | E41: FINAL TURNO 3 | F41: 2700 | G41: 6500 | H41: 4350 | I41: =+I40-0 -> 225 | J41: =+J40-5 -> 345 | K41: 17739 | L41: =(K42-K41)*M41 -> 560 | M41: 80 | N41: =F41-F42 -> 100 | O41: =G41-G42 -> 200 | P41: =H41-H42 -> 70 | Q41: =I41-I42 -> 5 | R41: =J41-J42 -> 10 | S41: =(N41*$AC$2) -> 130 | T41: =(O41*$AD$2) -> 265 | U41: =(P41*$AE$2) -> 87.5 | V41: =Tabla1[[#This Row],[CONSUMO POL ANIONICO (KG)]] -> 5 | W41: =Tabla1[[#This Row],[CONSUMO POL CATIONICO (KG)]] -> 10 | X41: =(S41*1000)/L41 -> 232.14286 | Y41: =(T41*1000)/L41 -> 473.21429 | Z41: =(U41*1000)/L41 -> 156.25 | AA41: =(V41*1000)/L41 -> 8.9285714 | AB41: =(W41*1000)/L41 -> 17.857143 | AC41: 1.3 | AD41: 1.325 | AE41: 1.25 | AF41: 2500 | AG41: 2500 | AH41: 830 | AI41: 2818 | AJ41: 6295 | AK41: 19050 | AL41: 22050 | AM41: =S41*AH41 -> 107900 | AN41: =T41*AI41 -> 746770 | AO41: =U41*AJ41 -> 550812.5 | AP41: =V41*AK41 -> 95250 | AQ41: =W41*AL41 -> 220500 | AR41: =SUM(Tabla1[[#This Row],[COSTO OPERATIVO ACIDO]:[COSTO OPERATIVO CATIONICO]]) -> 1721232.5 | AS41: 3599 | AT41: =AR41/L41 -> 3073.6295 | AU41: =IFERROR(Tabla1[[#This Row],[CAUDAL TOTAL TRATADO GEM ]]/Tabla1[[#This Row],[CAUDAL DE TRATAMIENTO]],0) -> 7
A42: =+A41 -> 46126 | B42: 14 | C42: 15 (MAÑANA) | D42: 41 | E42: FINAL TURNO 1 | F42: 2600 | G42: 6300 | H42: 4280 | I42: =+I41-5 -> 220 | J42: =+J41-10 -> 335 | K42: 17746 | L42: =(K43-K42)*M42 -> 240 | M42: 80 | N42: =F42-F43 -> 60 | O42: =G42-G43 -> 140 | P42: =H42-H43 -> 30 | Q42: =I42-I43 -> 5 | R42: =J42-J43 -> 5 | S42: =(N42*$AC$2) -> 78 | T42: =(O42*$AD$2) -> 185.5 | U42: =(P42*$AE$2) -> 37.5 | V42: =Tabla1[[#This Row],[CONSUMO POL ANIONICO (KG)]] -> 5 | W42: =Tabla1[[#This Row],[CONSUMO POL CATIONICO (KG)]] -> 5 | X42: =(S42*1000)/L42 -> 325 | Y42: =(T42*1000)/L42 -> 772.91667 | Z42: =(U42*1000)/L42 -> 156.25 | AA42: =(V42*1000)/L42 -> 20.833333 | AB42: =(W42*1000)/L42 -> 20.833333 | AC42: 1.3 | AD42: 1.325 | AE42: 1.25 | AF42: 2500 | AG42: 2500 | AH42: 830 | AI42: 2818 | AJ42: 6295 | AK42: 19050 | AL42: 22050 | AM42: =S42*AH42 -> 64740 | AN42: =T42*AI42 -> 522739 | AO42: =U42*AJ42 -> 236062.5 | AP42: =V42*AK42 -> 95250 | AQ42: =W42*AL42 -> 110250 | AR42: =SUM(Tabla1[[#This Row],[COSTO OPERATIVO ACIDO]:[COSTO OPERATIVO CATIONICO]]) -> 1029041.5 | AS42: 3599 | AT42: =AR42/L42 -> 4287.6729 | AU42: =IFERROR(Tabla1[[#This Row],[CAUDAL TOTAL TRATADO GEM ]]/Tabla1[[#This Row],[CAUDAL DE TRATAMIENTO]],0) -> 3
A43: =+A42 -> 46126 | B43: 14 | C43: 3(TARDE) | D43: 42 | E43: FINAL TURNO 2 | F43: 2540 | G43: 6160 | H43: 4250 | I43: =+I42-5 -> 215 | J43: =+J42-5 -> 330 | K43: 17749 | L43: =(K44-K43)*M43 -> 480 | M43: 80 | N43: =F43-F44 -> 40 | O43: =G43-G44 -> 230 | P43: =H43-H44 -> 20 | Q43: =I43-I44 -> 5 | R43: =J43-J44 -> 5 | S43: =(N43*$AC$2) -> 52 | T43: =(O43*$AD$2) -> 304.75 | U43: =(P43*$AE$2) -> 25 | V43: =Tabla1[[#This Row],[CONSUMO POL ANIONICO (KG)]] -> 5 | W43: =Tabla1[[#This Row],[CONSUMO POL CATIONICO (KG)]] -> 5 | X43: =(S43*1000)/L43 -> 108.33333 | Y43: =(T43*1000)/L43 -> 634.89583 | Z43: =(U43*1000)/L43 -> 52.083333 | AA43: =(V43*1000)/L43 -> 10.416667 | AB43: =(W43*1000)/L43 -> 10.416667 | AC43: 1.3 | AD43: 1.325 | AE43: 1.25 | AF43: 2500 | AG43: 2500 | AH43: 830 | AI43: 2818 | AJ43: 6295 | AK43: 19050 | AL43: 22050 | AM43: =S43*AH43 -> 43160 | AN43: =T43*AI43 -> 858785.5 | AO43: =U43*AJ43 -> 157375 | AP43: =V43*AK43 -> 95250 | AQ43: =W43*AL43 -> 110250 | AR43: =SUM(Tabla1[[#This Row],[COSTO OPERATIVO ACIDO]:[COSTO OPERATIVO CATIONICO]]) -> 1264820.5 | AS43: 3599 | AT43: =AR43/L43 -> 2635.0427 | AU43: =IFERROR(Tabla1[[#This Row],[CAUDAL TOTAL TRATADO GEM ]]/Tabla1[[#This Row],[CAUDAL DE TRATAMIENTO]],0) -> 6
A44: =+A43+1 -> 46127 | B44: 15 | C44: 15 (NOCHE) | D44: 43 | E44: FINAL TURNO 3 | F44: 2500 | G44: 5930 | H44: 4230 | I44: =+I43-5 -> 210 | J44: =+J43-5 -> 325 | K44: 17755 | L44: =(K45-K44)*M44 -> 480 | M44: 80 | N44: =F44-F45 -> 170 | O44: =G44-G45 -> 200 | P44: =H44-H45 -> 80 | Q44: =I44-I45 -> 0 | R44: =J44-J45 -> 5 | S44: =(N44*$AC$2) -> 221 | T44: =(O44*$AD$2) -> 265 | U44: =(P44*$AE$2) -> 100 | V44: =Tabla1[[#This Row],[CONSUMO POL ANIONICO (KG)]] -> 0 | W44: =Tabla1[[#This Row],[CONSUMO POL CATIONICO (KG)]] -> 5 | X44: =(S44*1000)/L44 -> 460.41667 | Y44: =(T44*1000)/L44 -> 552.08333 | Z44: =(U44*1000)/L44 -> 208.33333 | AA44: =(V44*1000)/L44 -> 0 | AB44: =(W44*1000)/L44 -> 10.416667 | AC44: 1.3 | AD44: 1.325 | AE44: 1.25 | AF44: 2500 | AG44: 2500 | AH44: 830 | AI44: 2818 | AJ44: 6295 | AK44: 19050 | AL44: 22050 | AM44: =S44*AH44 -> 183430 | AN44: =T44*AI44 -> 746770 | AO44: =U44*AJ44 -> 629500 | AP44: =V44*AK44 -> 0 | AQ44: =W44*AL44 -> 110250 | AR44: =SUM(Tabla1[[#This Row],[COSTO OPERATIVO ACIDO]:[COSTO OPERATIVO CATIONICO]]) -> 1669950 | AS44: 3599 | AT44: =AR44/L44 -> 3479.0625 | AU44: =IFERROR(Tabla1[[#This Row],[CAUDAL TOTAL TRATADO GEM ]]/Tabla1[[#This Row],[CAUDAL DE TRATAMIENTO]],0) -> 6
A45: =+A44 -> 46127 | B45: 15 | C45: 16 (MAÑANA) | D45: 44 | E45: FINAL TURNO 1 | F45: 2330 | G45: 5730 | H45: 4150 | I45: =+I44-0 -> 210 | J45: =+J44-5 -> 320 | K45: 17761 | L45: =(K46-K45)*M45 -> 400 | M45: 80 | N45: =F45-F46 -> 30 | O45: =G45-G46 -> 130 | P45: =H45-H46 -> 50 | Q45: =I45-I46 -> 0 | R45: =J45-J46 -> 10 | S45: =(N45*$AC$2) -> 39 | T45: =(O45*$AD$2) -> 172.25 | U45: =(P45*$AE$2) -> 62.5 | V45: =Tabla1[[#This Row],[CONSUMO POL ANIONICO (KG)]] -> 0 | W45: =Tabla1[[#This Row],[CONSUMO POL CATIONICO (KG)]] -> 10 | X45: =(S45*1000)/L45 -> 97.5 | Y45: =(T45*1000)/L45 -> 430.625 | Z45: =(U45*1000)/L45 -> 156.25 | AA45: =(V45*1000)/L45 -> 0 | AB45: =(W45*1000)/L45 -> 25 | AC45: 1.3 | AD45: 1.325 | AE45: 1.25 | AF45: 2500 | AG45: 2500 | AH45: 830 | AI45: 2818 | AJ45: 6295 | AK45: 19050 | AL45: 22050 | AM45: =S45*AH45 -> 32370 | AN45: =T45*AI45 -> 485400.5 | AO45: =U45*AJ45 -> 393437.5 | AP45: =V45*AK45 -> 0 | AQ45: =W45*AL45 -> 220500 | AR45: =SUM(Tabla1[[#This Row],[COSTO OPERATIVO ACIDO]:[COSTO OPERATIVO CATIONICO]]) -> 1131708 | AS45: 3599 | AT45: =AR45/L45 -> 2829.27 | AU45: =IFERROR(Tabla1[[#This Row],[CAUDAL TOTAL TRATADO GEM ]]/Tabla1[[#This Row],[CAUDAL DE TRATAMIENTO]],0) -> 5
A46: =+A45 -> 46127 | B46: 15 | C46: 3(TARDE) | D46: 45 | E46: FINAL TURNO 2 | F46: 2300 | G46: 5600 | H46: 4100 | I46: =+I45-0 -> 210 | J46: =+J45-10 -> 310 | K46: 17766 | L46: =(K47-K46)*M46 -> 320 | M46: 80 | N46: =F46-F47+2000 -> 0 | O46: =G46-G47+2000 -> 20 | P46: =H46-H47 -> 50 | Q46: =I46-I47 -> 5 | R46: =J46-J47 -> 5 | S46: =(N46*$AC$2) -> 0 | T46: =(O46*$AD$2) -> 26.5 | U46: =(P46*$AE$2) -> 62.5 | V46: =Tabla1[[#This Row],[CONSUMO POL ANIONICO (KG)]] -> 5 | W46: =Tabla1[[#This Row],[CONSUMO POL CATIONICO (KG)]] -> 5 | X46: =(S46*1000)/L46 -> 0 | Y46: =(T46*1000)/L46 -> 82.8125 | Z46: =(U46*1000)/L46 -> 195.3125 | AA46: =(V46*1000)/L46 -> 15.625 | AB46: =(W46*1000)/L46 -> 15.625 | AC46: 1.3 | AD46: 1.325 | AE46: 1.25 | AF46: 2500 | AG46: 2500 | AH46: 830 | AI46: 2818 | AJ46: 6295 | AK46: 19050 | AL46: 22050 | AM46: =S46*AH46 -> 0 | AN46: =T46*AI46 -> 74677 | AO46: =U46*AJ46 -> 393437.5 | AP46: =V46*AK46 -> 95250 | AQ46: =W46*AL46 -> 110250 | AR46: =SUM(Tabla1[[#This Row],[COSTO OPERATIVO ACIDO]:[COSTO OPERATIVO CATIONICO]]) -> 673614.5 | AS46: 3599 | AT46: =AR46/L46 -> 2105.0453 | AU46: =IFERROR(Tabla1[[#This Row],[CAUDAL TOTAL TRATADO GEM ]]/Tabla1[[#This Row],[CAUDAL DE TRATAMIENTO]],0) -> 4
A47: =+A46+1 -> 46128 | B47: 16 | C47: 16 (NOCHE) | D47: 46 | E47: FINAL TURNO 3 | F47: 4300 | G47: 7580 | H47: 4050 | I47: =+I46-5 -> 205 | J47: =+J46-5 -> 305 | K47: 17770 | L47: =(K48-K47)*M47 -> 560 | M47: 80 | N47: =F47-F48 -> 100 | O47: =G47-G48 -> 220 | P47: =H47-H48 -> 80 | Q47: =I47-I48 -> 5 | R47: =J47-J48 -> 5 | S47: =(N47*$AC$2) -> 130 | T47: =(O47*$AD$2) -> 291.5 | U47: =(P47*$AE$2) -> 100 | V47: =Tabla1[[#This Row],[CONSUMO POL ANIONICO (KG)]] -> 5 | W47: =Tabla1[[#This Row],[CONSUMO POL CATIONICO (KG)]] -> 5 | X47: =(S47*1000)/L47 -> 232.14286 | Y47: =(T47*1000)/L47 -> 520.53571 | Z47: =(U47*1000)/L47 -> 178.57143 | AA47: =(V47*1000)/L47 -> 8.9285714 | AB47: =(W47*1000)/L47 -> 8.9285714 | AC47: 1.3 | AD47: 1.325 | AE47: 1.25 | AF47: 2500 | AG47: 2500 | AH47: 830 | AI47: 2818 | AJ47: 6295 | AK47: 19050 | AL47: 22050 | AM47: =S47*AH47 -> 107900 | AN47: =T47*AI47 -> 821447 | AO47: =U47*AJ47 -> 629500 | AP47: =V47*AK47 -> 95250 | AQ47: =W47*AL47 -> 110250 | AR47: =SUM(Tabla1[[#This Row],[COSTO OPERATIVO ACIDO]:[COSTO OPERATIVO CATIONICO]]) -> 1764347 | AS47: 3599 | AT47: =AR47/L47 -> 3150.6196 | AU47: =IFERROR(Tabla1[[#This Row],[CAUDAL TOTAL TRATADO GEM ]]/Tabla1[[#This Row],[CAUDAL DE TRATAMIENTO]],0) -> 7
A48: =+A47 -> 46128 | B48: 16 | C48: 17 (MAÑANA) | D48: 47 | E48: FINAL TURNO 1 | F48: 4200 | G48: 7360 | H48: 3970 | I48: =+I47-5 -> 200 | J48: =+J47-5 -> 300 | K48: 17777 | L48: =(K49-K48)*M48 -> 560 | M48: 80 | N48: =F48-F49 -> 90 | O48: =G48-G49 -> 140 | P48: =H48-H49 -> 50 | Q48: =I48-I49 -> 0 | R48: =J48-J49 -> 0 | S48: =(N48*$AC$2) -> 117 | T48: =(O48*$AD$2) -> 185.5 | U48: =(P48*$AE$2) -> 62.5 | V48: =Tabla1[[#This Row],[CONSUMO POL ANIONICO (KG)]] -> 0 | W48: =Tabla1[[#This Row],[CONSUMO POL CATIONICO (KG)]] -> 0 | X48: =(S48*1000)/L48 -> 208.92857 | Y48: =(T48*1000)/L48 -> 331.25 | Z48: =(U48*1000)/L48 -> 111.60714 | AA48: =(V48*1000)/L48 -> 0 | AB48: =(W48*1000)/L48 -> 0 | AC48: 1.3 | AD48: 1.325 | AE48: 1.25 | AF48: 2500 | AG48: 2500 | AH48: 830 | AI48: 2818 | AJ48: 6295 | AK48: 19050 | AL48: 22050 | AM48: =S48*AH48 -> 97110 | AN48: =T48*AI48 -> 522739 | AO48: =U48*AJ48 -> 393437.5 | AP48: =V48*AK48 -> 0 | AQ48: =W48*AL48 -> 0 | AR48: =SUM(Tabla1[[#This Row],[COSTO OPERATIVO ACIDO]:[COSTO OPERATIVO CATIONICO]]) -> 1013286.5 | AS48: 3599 | AT48: =AR48/L48 -> 1809.4402 | AU48: =IFERROR(Tabla1[[#This Row],[CAUDAL TOTAL TRATADO GEM ]]/Tabla1[[#This Row],[CAUDAL DE TRATAMIENTO]],0) -> 7
A49: =+A48 -> 46128 | B49: 16 | C49: 3(TARDE) | D49: 48 | E49: FINAL TURNO 2 | F49: 4110 | G49: 7220 | H49: 3920 | I49: =+I48-0 -> 200 | J49: =+J48-0 -> 300 | K49: 17784 | L49: =(K50-K49)*M49 -> 480 | M49: 80 | N49: =F49-F50 -> 130 | O49: =G49-G50+2000-150 -> 150 | P49: =H49-H50 -> 70 | Q49: =I49-I50 -> 5 | R49: =J49-J50 -> 5 | S49: =(N49*$AC$2) -> 169 | T49: =(O49*$AD$2) -> 198.75 | U49: =(P49*$AE$2) -> 87.5 | V49: =Tabla1[[#This Row],[CONSUMO POL ANIONICO (KG)]] -> 5 | W49: =Tabla1[[#This Row],[CONSUMO POL CATIONICO (KG)]] -> 5 | X49: =(S49*1000)/L49 -> 352.08333 | Y49: =(T49*1000)/L49 -> 414.0625 | Z49: =(U49*1000)/L49 -> 182.29167 | AA49: =(V49*1000)/L49 -> 10.416667 | AB49: =(W49*1000)/L49 -> 10.416667 | AC49: 1.3 | AD49: 1.325 | AE49: 1.25 | AF49: 2500 | AG49: 2500 | AH49: 830 | AI49: 2818 | AJ49: 6295 | AK49: 19050 | AL49: 22050 | AM49: =S49*AH49 -> 140270 | AN49: =T49*AI49 -> 560077.5 | AO49: =U49*AJ49 -> 550812.5 | AP49: =V49*AK49 -> 95250 | AQ49: =W49*AL49 -> 110250 | AR49: =SUM(Tabla1[[#This Row],[COSTO OPERATIVO ACIDO]:[COSTO OPERATIVO CATIONICO]]) -> 1456660 | AS49: 3599 | AT49: =AR49/L49 -> 3034.7083 | AU49: =IFERROR(Tabla1[[#This Row],[CAUDAL TOTAL TRATADO GEM ]]/Tabla1[[#This Row],[CAUDAL DE TRATAMIENTO]],0) -> 6
A50: =+A49+1 -> 46129 | B50: 17 | C50: 17 (NOCHE) | D50: 49 | E50: FINAL TURNO 3 | F50: 3980 | G50: 8920 | H50: 3850 | I50: =+I49-5 -> 195 | J50: =+J49-5 -> 295 | K50: 17790 | L50: =(K51-K50)*M50 -> 560 | M50: 80 | N50: =F50-F51 -> 100 | O50: =G50-G51 -> 190 | P50: =H50-H51 -> 90 | Q50: =I50-I51 -> 0 | R50: =J50-J51 -> 10 | S50: =(N50*$AC$2) -> 130 | T50: =(O50*$AD$2) -> 251.75 | U50: =(P50*$AE$2) -> 112.5 | V50: =Tabla1[[#This Row],[CONSUMO POL ANIONICO (KG)]] -> 0 | W50: =Tabla1[[#This Row],[CONSUMO POL CATIONICO (KG)]] -> 10 | X50: =(S50*1000)/L50 -> 232.14286 | Y50: =(T50*1000)/L50 -> 449.55357 | Z50: =(U50*1000)/L50 -> 200.89286 | AA50: =(V50*1000)/L50 -> 0 | AB50: =(W50*1000)/L50 -> 17.857143 | AC50: 1.3 | AD50: 1.325 | AE50: 1.25 | AF50: 2500 | AG50: 2500 | AH50: 830 | AI50: 2818 | AJ50: 6295 | AK50: 19050 | AL50: 22050 | AM50: =S50*AH50 -> 107900 | AN50: =T50*AI50 -> 709431.5 | AO50: =U50*AJ50 -> 708187.5 | AP50: =V50*AK50 -> 0 | AQ50: =W50*AL50 -> 220500 | AR50: =SUM(Tabla1[[#This Row],[COSTO OPERATIVO ACIDO]:[COSTO OPERATIVO CATIONICO]]) -> 1746019 | AS50: 3599 | AT50: =AR50/L50 -> 3117.8911 | AU50: =IFERROR(Tabla1[[#This Row],[CAUDAL TOTAL TRATADO GEM ]]/Tabla1[[#This Row],[CAUDAL DE TRATAMIENTO]],0) -> 7
A51: =+A50 -> 46129 | B51: 17 | C51: 18 (MAÑANA) | D51: 50 | E51: FINAL TURNO 1 | F51: 3880 | G51: 8730 | H51: 3760 | I51: =+I50-0 -> 195 | J51: =+J50-10 -> 285 | K51: 17797 | L51: =(K52-K51)*M51 -> 320 | M51: 80 | N51: =F51-F52 -> 200 | O51: =G51-G52 -> 180 | P51: =H51-H52 -> 70 | Q51: =I51-I52 -> 0 | R51: =J51-J52 -> 0 | S51: =(N51*$AC$2) -> 260 | T51: =(O51*$AD$2) -> 238.5 | U51: =(P51*$AE$2) -> 87.5 | V51: =Tabla1[[#This Row],[CONSUMO POL ANIONICO (KG)]] -> 0 | W51: =Tabla1[[#This Row],[CONSUMO POL CATIONICO (KG)]] -> 0 | X51: =(S51*1000)/L51 -> 812.5 | Y51: =(T51*1000)/L51 -> 745.3125 | Z51: =(U51*1000)/L51 -> 273.4375 | AA51: =(V51*1000)/L51 -> 0 | AB51: =(W51*1000)/L51 -> 0 | AC51: 1.3 | AD51: 1.325 | AE51: 1.25 | AF51: 2500 | AG51: 2500 | AH51: 830 | AI51: 2818 | AJ51: 6295 | AK51: 19050 | AL51: 22050 | AM51: =S51*AH51 -> 215800 | AN51: =T51*AI51 -> 672093 | AO51: =U51*AJ51 -> 550812.5 | AP51: =V51*AK51 -> 0 | AQ51: =W51*AL51 -> 0 | AR51: =SUM(Tabla1[[#This Row],[COSTO OPERATIVO ACIDO]:[COSTO OPERATIVO CATIONICO]]) -> 1438705.5 | AS51: 3599 | AT51: =AR51/L51 -> 4495.9547 | AU51: =IFERROR(Tabla1[[#This Row],[CAUDAL TOTAL TRATADO GEM ]]/Tabla1[[#This Row],[CAUDAL DE TRATAMIENTO]],0) -> 4
A52: =+A51 -> 46129 | B52: 17 | C52: 3(TARDE) | D52: 51 | E52: FINAL TURNO 2 | F52: 3680 | G52: 8550 | H52: 3690 | I52: =+I51-0 -> 195 | J52: =+J51-0 -> 285 | K52: 17801 | L52: =(K53-K52)*M52 -> 560 | M52: 80 | N52: =F52-F53 -> 260 | O52: =G52-G53 -> 170 | P52: =H52-H53 -> 90 | Q52: =I52-I53 -> 5 | R52: =J52-J53 -> 5 | S52: =(N52*$AC$2) -> 338 | T52: =(O52*$AD$2) -> 225.25 | U52: =(P52*$AE$2) -> 112.5 | V52: =Tabla1[[#This Row],[CONSUMO POL ANIONICO (KG)]] -> 5 | W52: =Tabla1[[#This Row],[CONSUMO POL CATIONICO (KG)]] -> 5 | X52: =(S52*1000)/L52 -> 603.57143 | Y52: =(T52*1000)/L52 -> 402.23214 | Z52: =(U52*1000)/L52 -> 200.89286 | AA52: =(V52*1000)/L52 -> 8.9285714 | AB52: =(W52*1000)/L52 -> 8.9285714 | AC52: 1.3 | AD52: 1.325 | AE52: 1.25 | AF52: 2500 | AG52: 2500 | AH52: 830 | AI52: 2818 | AJ52: 6295 | AK52: 19050 | AL52: 22050 | AM52: =S52*AH52 -> 280540 | AN52: =T52*AI52 -> 634754.5 | AO52: =U52*AJ52 -> 708187.5 | AP52: =V52*AK52 -> 95250 | AQ52: =W52*AL52 -> 110250 | AR52: =SUM(Tabla1[[#This Row],[COSTO OPERATIVO ACIDO]:[COSTO OPERATIVO CATIONICO]]) -> 1828982 | AS52: 3599 | AT52: =AR52/L52 -> 3266.0393 | AU52: =IFERROR(Tabla1[[#This Row],[CAUDAL TOTAL TRATADO GEM ]]/Tabla1[[#This Row],[CAUDAL DE TRATAMIENTO]],0) -> 7
A53: =+A52+1 -> 46130 | B53: 18 | C53: 18 (NOCHE) | D53: 52 | E53: FINAL TURNO 3 | F53: 3420 | G53: 8380 | H53: 3600 | I53: =+I52-5 -> 190 | J53: =+J52-5 -> 280 | K53: 17808 | L53: =(K54-K53)*M53 -> 640 | M53: 80 | N53: =F53-F54 -> 120 | O53: =G53-G54-150 -> 170 | P53: =H53-H54 -> 60 | Q53: =I53-I54 -> 0 | R53: =J53-J54 -> 10 | S53: =(N53*$AC$2) -> 156 | T53: =(O53*$AD$2) -> 225.25 | U53: =(P53*$AE$2) -> 75 | V53: =Tabla1[[#This Row],[CONSUMO POL ANIONICO (KG)]] -> 0 | W53: =Tabla1[[#This Row],[CONSUMO POL CATIONICO (KG)]] -> 10 | X53: =(S53*1000)/L53 -> 243.75 | Y53: =(T53*1000)/L53 -> 351.95312 | Z53: =(U53*1000)/L53 -> 117.1875 | AA53: =(V53*1000)/L53 -> 0 | AB53: =(W53*1000)/L53 -> 15.625 | AC53: 1.3 | AD53: 1.325 | AE53: 1.25 | AF53: 2500 | AG53: 2500 | AH53: 830 | AI53: 2818 | AJ53: 6295 | AK53: 19050 | AL53: 22050 | AM53: =S53*AH53 -> 129480 | AN53: =T53*AI53 -> 634754.5 | AO53: =U53*AJ53 -> 472125 | AP53: =V53*AK53 -> 0 | AQ53: =W53*AL53 -> 220500 | AR53: =SUM(Tabla1[[#This Row],[COSTO OPERATIVO ACIDO]:[COSTO OPERATIVO CATIONICO]]) -> 1456859.5 | AS53: 3599 | AT53: =AR53/L53 -> 2276.343 | AU53: =IFERROR(Tabla1[[#This Row],[CAUDAL TOTAL TRATADO GEM ]]/Tabla1[[#This Row],[CAUDAL DE TRATAMIENTO]],0) -> 8
A54: =+A53 -> 46130 | B54: 18 | C54: 19 (MAÑANA) | D54: 53 | E54: FINAL TURNO 1 | F54: 3300 | G54: 8060 | H54: 3540 | I54: =+I53-0 -> 190 | J54: =+J53-10 -> 270 | K54: 17816 | L54: =(K55-K54)*M54 -> 640 | M54: 80 | N54: =F54-F55 -> 300 | O54: =G54-G55 -> 180 | P54: =H54-H55 -> 140 | Q54: =I54-I55 -> 0 | R54: =J54-J55 -> 0 | S54: =(N54*$AC$2) -> 390 | T54: =(O54*$AD$2) -> 238.5 | U54: =(P54*$AE$2) -> 175 | V54: =Tabla1[[#This Row],[CONSUMO POL ANIONICO (KG)]] -> 0 | W54: =Tabla1[[#This Row],[CONSUMO POL CATIONICO (KG)]] -> 0 | X54: =(S54*1000)/L54 -> 609.375 | Y54: =(T54*1000)/L54 -> 372.65625 | Z54: =(U54*1000)/L54 -> 273.4375 | AA54: =(V54*1000)/L54 -> 0 | AB54: =(W54*1000)/L54 -> 0 | AC54: 1.3 | AD54: 1.325 | AE54: 1.25 | AF54: 2500 | AG54: 2500 | AH54: 830 | AI54: 2818 | AJ54: 6295 | AK54: 19050 | AL54: 22050 | AM54: =S54*AH54 -> 323700 | AN54: =T54*AI54 -> 672093 | AO54: =U54*AJ54 -> 1101625 | AP54: =V54*AK54 -> 0 | AQ54: =W54*AL54 -> 0 | AR54: =SUM(Tabla1[[#This Row],[COSTO OPERATIVO ACIDO]:[COSTO OPERATIVO CATIONICO]]) -> 2097418 | AS54: 3599 | AT54: =AR54/L54 -> 3277.2156 | AU54: =IFERROR(Tabla1[[#This Row],[CAUDAL TOTAL TRATADO GEM ]]/Tabla1[[#This Row],[CAUDAL DE TRATAMIENTO]],0) -> 8
A55: =+A54 -> 46130 | B55: 18 | C55: 3(TARDE) | D55: 54 | E55: FINAL TURNO 2 | F55: 3000 | G55: 7880 | H55: 3400 | I55: =+I54-0 -> 190 | J55: =+J54-0 -> 270 | K55: 17824 | L55: =(K56-K55)*M55 -> 400 | M55: 80 | N55: =F55-F56 -> 35 | O55: =G55-G56 -> 150 | P55: =H55-H56 -> 105 | Q55: =I55-I56 -> 5 | R55: =J55-J56 -> 5 | S55: =(N55*$AC$2) -> 45.5 | T55: =(O55*$AD$2) -> 198.75 | U55: =(P55*$AE$2) -> 131.25 | V55: =Tabla1[[#This Row],[CONSUMO POL ANIONICO (KG)]] -> 5 | W55: =Tabla1[[#This Row],[CONSUMO POL CATIONICO (KG)]] -> 5 | X55: =(S55*1000)/L55 -> 113.75 | Y55: =(T55*1000)/L55 -> 496.875 | Z55: =(U55*1000)/L55 -> 328.125 | AA55: =(V55*1000)/L55 -> 12.5 | AB55: =(W55*1000)/L55 -> 12.5 | AC55: 1.3 | AD55: 1.325 | AE55: 1.25 | AF55: 2500 | AG55: 2500 | AH55: 830 | AI55: 2818 | AJ55: 6295 | AK55: 19050 | AL55: 22050 | AM55: =S55*AH55 -> 37765 | AN55: =T55*AI55 -> 560077.5 | AO55: =U55*AJ55 -> 826218.75 | AP55: =V55*AK55 -> 95250 | AQ55: =W55*AL55 -> 110250 | AR55: =SUM(Tabla1[[#This Row],[COSTO OPERATIVO ACIDO]:[COSTO OPERATIVO CATIONICO]]) -> 1629561.2 | AS55: 3599 | AT55: =AR55/L55 -> 4073.9031 | AU55: =IFERROR(Tabla1[[#This Row],[CAUDAL TOTAL TRATADO GEM ]]/Tabla1[[#This Row],[CAUDAL DE TRATAMIENTO]],0) -> 5
A56: =+A55+1 -> 46131 | B56: 19 | C56: 19 (NOCHE) | D56: 55 | E56: FINAL TURNO 3 | F56: =+AVERAGE(F55,F60) -> 2965 | G56: =+AVERAGE(G55,G60) -> 7730 | H56: =+AVERAGE(H55,H60) -> 3295 | I56: =+I55-5 -> 185 | J56: =+J55-5 -> 265 | K56: 17829 | L56: =(K57-K56)*M56 -> 0 | M56: 80 | N56: =F56-F57 -> 0 | O56: =G56-G57 -> 0 | P56: =H56-H57 -> 0 | Q56: =I56-I57 -> 0 | R56: =J56-J57 -> 10 | S56: =(N56*$AC$2) -> 0 | T56: =(O56*$AD$2) -> 0 | U56: =(P56*$AE$2) -> 0 | V56: =Tabla1[[#This Row],[CONSUMO POL ANIONICO (KG)]] -> 0 | W56: =Tabla1[[#This Row],[CONSUMO POL CATIONICO (KG)]] -> 10 | X56: =(S56*1000)/L56 -> #DIV/0! | Y56: =(T56*1000)/L56 -> #DIV/0! | Z56: =(U56*1000)/L56 -> #DIV/0! | AA56: =(V56*1000)/L56 -> #DIV/0! | AB56: =(W56*1000)/L56 -> #DIV/0! | AC56: 1.3 | AD56: 1.325 | AE56: 1.25 | AF56: 2500 | AG56: 2500 | AH56: 830 | AI56: 2818 | AJ56: 6295 | AK56: 19050 | AL56: 22050 | AM56: =S56*AH56 -> 0 | AN56: =T56*AI56 -> 0 | AO56: =U56*AJ56 -> 0 | AP56: =V56*AK56 -> 0 | AQ56: =W56*AL56 -> 220500 | AR56: =SUM(Tabla1[[#This Row],[COSTO OPERATIVO ACIDO]:[COSTO OPERATIVO CATIONICO]]) -> 220500 | AS56: 3599 | AT56: =AR56/L56 -> #DIV/0! | AU56: =IFERROR(Tabla1[[#This Row],[CAUDAL TOTAL TRATADO GEM ]]/Tabla1[[#This Row],[CAUDAL DE TRATAMIENTO]],0) -> 0
A57: =+A56 -> 46131 | B57: 19 | C57: 20 (MAÑANA) | D57: 56 | E57: FINAL TURNO 1 | F57: 2965 | G57: 7730 | H57: 3295 | I57: =+I56-0 -> 185 | J57: =+J56-10 -> 255 | K57: 17829 | L57: =(K58-K57)*M57 -> 0 | M57: 80 | N57: =F57-F58 -> 0 | O57: =G57-G58 -> 0 | P57: =H57-H58 -> 0 | Q57: =I57-I58 -> 0 | R57: =J57-J58 -> 0 | S57: =(N57*$AC$2) -> 0 | T57: =(O57*$AD$2) -> 0 | U57: =(P57*$AE$2) -> 0 | V57: =Tabla1[[#This Row],[CONSUMO POL ANIONICO (KG)]] -> 0 | W57: =Tabla1[[#This Row],[CONSUMO POL CATIONICO (KG)]] -> 0 | X57: =(S57*1000)/L57 -> #DIV/0! | Y57: =(T57*1000)/L57 -> #DIV/0! | Z57: =(U57*1000)/L57 -> #DIV/0! | AA57: =(V57*1000)/L57 -> #DIV/0! | AB57: =(W57*1000)/L57 -> #DIV/0! | AC57: 1.3 | AD57: 1.325 | AE57: 1.25 | AF57: 2500 | AG57: 2500 | AH57: 830 | AI57: 2818 | AJ57: 6295 | AK57: 19050 | AL57: 22050 | AM57: =S57*AH57 -> 0 | AN57: =T57*AI57 -> 0 | AO57: =U57*AJ57 -> 0 | AP57: =V57*AK57 -> 0 | AQ57: =W57*AL57 -> 0 | AR57: =SUM(Tabla1[[#This Row],[COSTO OPERATIVO ACIDO]:[COSTO OPERATIVO CATIONICO]]) -> 0 | AS57: 3599 | AT57: =AR57/L57 -> #DIV/0! | AU57: =IFERROR(Tabla1[[#This Row],[CAUDAL TOTAL TRATADO GEM ]]/Tabla1[[#This Row],[CAUDAL DE TRATAMIENTO]],0) -> 0
A58: =+A57 -> 46131 | B58: 19 | C58: 3(TARDE) | D58: 57 | E58: FINAL TURNO 2 | F58: 2965 | G58: 7730 | H58: 3295 | I58: =+I57-0 -> 185 | J58: =+J57-0 -> 255 | K58: 17829 | L58: =(K59-K58)*M58 -> 0 | M58: 80 | N58: =F58-F59 -> 0 | O58: =G58-G59 -> 0 | P58: =H58-H59 -> 0 | Q58: =I58-I59 -> 0 | R58: =J58-J59 -> 5 | S58: =(N58*$AC$2) -> 0 | T58: =(O58*$AD$2) -> 0 | U58: =(P58*$AE$2) -> 0 | V58: =Tabla1[[#This Row],[CONSUMO POL ANIONICO (KG)]] -> 0 | W58: =Tabla1[[#This Row],[CONSUMO POL CATIONICO (KG)]] -> 5 | X58: =(S58*1000)/L58 -> #DIV/0! | Y58: =(T58*1000)/L58 -> #DIV/0! | Z58: =(U58*1000)/L58 -> #DIV/0! | AA58: =(V58*1000)/L58 -> #DIV/0! | AB58: =(W58*1000)/L58 -> #DIV/0! | AC58: 1.3 | AD58: 1.325 | AE58: 1.25 | AF58: 2500 | AG58: 2500 | AH58: 830 | AI58: 2818 | AJ58: 6295 | AK58: 19050 | AL58: 22050 | AM58: =S58*AH58 -> 0 | AN58: =T58*AI58 -> 0 | AO58: =U58*AJ58 -> 0 | AP58: =V58*AK58 -> 0 | AQ58: =W58*AL58 -> 110250 | AR58: =SUM(Tabla1[[#This Row],[COSTO OPERATIVO ACIDO]:[COSTO OPERATIVO CATIONICO]]) -> 110250 | AS58: 3599 | AT58: =AR58/L58 -> #DIV/0! | AU58: =IFERROR(Tabla1[[#This Row],[CAUDAL TOTAL TRATADO GEM ]]/Tabla1[[#This Row],[CAUDAL DE TRATAMIENTO]],0) -> 0
A59: =+A58+1 -> 46132 | B59: 20 | C59: 20 (NOCHE) | D59: 58 | E59: FINAL TURNO 3 | F59: 2965 | G59: 7730 | H59: 3295 | I59: =+I58-0 -> 185 | J59: =+J58-5 -> 250 | K59: 17829 | L59: =(K60-K59)*M59 -> 400 | M59: 80 | N59: =F59-F60 -> 35 | O59: =G59-G60 -> 150 | P59: =H59-H60 -> 105 | Q59: =I59-I60 -> 0 | R59: =J59-J60 -> 0 | S59: =(N59*$AC$2) -> 45.5 | T59: =(O59*$AD$2) -> 198.75 | U59: =(P59*$AE$2) -> 131.25 | V59: =Tabla1[[#This Row],[CONSUMO POL ANIONICO (KG)]] -> 0 | W59: =Tabla1[[#This Row],[CONSUMO POL CATIONICO (KG)]] -> 0 | X59: =(S59*1000)/L59 -> 113.75 | Y59: =(T59*1000)/L59 -> 496.875 | Z59: =(U59*1000)/L59 -> 328.125 | AA59: =(V59*1000)/L59 -> 0 | AB59: =(W59*1000)/L59 -> 0 | AC59: 1.3 | AD59: 1.325 | AE59: 1.25 | AF59: 2500 | AG59: 2500 | AH59: 830 | AI59: 2818 | AJ59: 6295 | AK59: 19050 | AL59: 22050 | AM59: =S59*AH59 -> 37765 | AN59: =T59*AI59 -> 560077.5 | AO59: =U59*AJ59 -> 826218.75 | AP59: =V59*AK59 -> 0 | AQ59: =W59*AL59 -> 0 | AR59: =SUM(Tabla1[[#This Row],[COSTO OPERATIVO ACIDO]:[COSTO OPERATIVO CATIONICO]]) -> 1424061.2 | AS59: 3599 | AT59: =AR59/L59 -> 3560.1531 | AU59: =IFERROR(Tabla1[[#This Row],[CAUDAL TOTAL TRATADO GEM ]]/Tabla1[[#This Row],[CAUDAL DE TRATAMIENTO]],0) -> 5
A60: =+A59 -> 46132 | B60: 20 | C60: 21 (MAÑANA) | D60: 59 | E60: FINAL TURNO 1 | F60: 2930 | G60: 7580 | H60: 3190 | I60: =+I59-0 -> 185 | J60: =+J59-0 -> 250 | K60: 17834 | L60: =(K61-K60)*M60 -> 640 | M60: 80 | N60: =F60-F61 -> 30 | O60: =G60-G61 -> 180 | P60: =H60-H61 -> 50 | Q60: =I60-I61 -> 5 | R60: =J60-J61 -> 5 | S60: =(N60*$AC$2) -> 39 | T60: =(O60*$AD$2) -> 238.5 | U60: =(P60*$AE$2) -> 62.5 | V60: =Tabla1[[#This Row],[CONSUMO POL ANIONICO (KG)]] -> 5 | W60: =Tabla1[[#This Row],[CONSUMO POL CATIONICO (KG)]] -> 5 | X60: =(S60*1000)/L60 -> 60.9375 | Y60: =(T60*1000)/L60 -> 372.65625 | Z60: =(U60*1000)/L60 -> 97.65625 | AA60: =(V60*1000)/L60 -> 7.8125 | AB60: =(W60*1000)/L60 -> 7.8125 | AC60: 1.3 | AD60: 1.325 | AE60: 1.25 | AF60: 2500 | AG60: 2500 | AH60: 830 | AI60: 2818 | AJ60: 6295 | AK60: 19050 | AL60: 22050 | AM60: =S60*AH60 -> 32370 | AN60: =T60*AI60 -> 672093 | AO60: =U60*AJ60 -> 393437.5 | AP60: =V60*AK60 -> 95250 | AQ60: =W60*AL60 -> 110250 | AR60: =SUM(Tabla1[[#This Row],[COSTO OPERATIVO ACIDO]:[COSTO OPERATIVO CATIONICO]]) -> 1303400.5 | AS60: 3599 | AT60: =AR60/L60 -> 2036.5633 | AU60: =IFERROR(Tabla1[[#This Row],[CAUDAL TOTAL TRATADO GEM ]]/Tabla1[[#This Row],[CAUDAL DE TRATAMIENTO]],0) -> 8
A61: =+A60 -> 46132 | B61: 20 | C61: 3(TARDE) | D61: 60 | E61: FINAL TURNO 2 | F61: 2900 | G61: 7400 | H61: 3140 | I61: =+I60-5 -> 180 | J61: =+J60-5 -> 245 | K61: 17842 | L61: =(K62-K61)*M61 -> 560 | M61: 80 | N61: =F61-F62 -> 10 | O61: =G61-G62 -> 100 | P61: =H61-H62 -> 20 | Q61: =I61-I62 -> 0 | R61: =J61-J62 -> 10 | S61: =(N61*$AC$2) -> 13 | T61: =(O61*$AD$2) -> 132.5 | U61: =(P61*$AE$2) -> 25 | V61: =Tabla1[[#This Row],[CONSUMO POL ANIONICO (KG)]] -> 0 | W61: =Tabla1[[#This Row],[CONSUMO POL CATIONICO (KG)]] -> 10 | X61: =(S61*1000)/L61 -> 23.214286 | Y61: =(T61*1000)/L61 -> 236.60714 | Z61: =(U61*1000)/L61 -> 44.642857 | AA61: =(V61*1000)/L61 -> 0 | AB61: =(W61*1000)/L61 -> 17.857143 | AC61: 1.3 | AD61: 1.325 | AE61: 1.25 | AF61: 2500 | AG61: 2500 | AH61: 830 | AI61: 2818 | AJ61: 6295 | AK61: 19050 | AL61: 22050 | AM61: =S61*AH61 -> 10790 | AN61: =T61*AI61 -> 373385 | AO61: =U61*AJ61 -> 157375 | AP61: =V61*AK61 -> 0 | AQ61: =W61*AL61 -> 220500 | AR61: =SUM(Tabla1[[#This Row],[COSTO OPERATIVO ACIDO]:[COSTO OPERATIVO CATIONICO]]) -> 762050 | AS61: 3599 | AT61: =AR61/L61 -> 1360.8036 | AU61: =IFERROR(Tabla1[[#This Row],[CAUDAL TOTAL TRATADO GEM ]]/Tabla1[[#This Row],[CAUDAL DE TRATAMIENTO]],0) -> 7
A62: =+A61+1 -> 46133 | B62: 21 | C62: 21 (NOCHE) | D62: 61 | E62: FINAL TURNO 3 | F62: 2890 | G62: 7300 | H62: 3120 | I62: =+I61-0 -> 180 | J62: =+J61-10 -> 235 | K62: 17849 | L62: =(K63-K62)*M62 -> 400 | M62: 80 | N62: =F62-F63 -> 90 | O62: =G62-G63-120 -> 150 | P62: =H62-H63 -> 120 | Q62: =I62-I63 -> 5 | R62: =J62-J63 -> 5 | S62: =(N62*$AC$2) -> 117 | T62: =(O62*$AD$2) -> 198.75 | U62: =(P62*$AE$2) -> 150 | V62: =Tabla1[[#This Row],[CONSUMO POL ANIONICO (KG)]] -> 5 | W62: =Tabla1[[#This Row],[CONSUMO POL CATIONICO (KG)]] -> 5 | X62: =(S62*1000)/L62 -> 292.5 | Y62: =(T62*1000)/L62 -> 496.875 | Z62: =(U62*1000)/L62 -> 375 | AA62: =(V62*1000)/L62 -> 12.5 | AB62: =(W62*1000)/L62 -> 12.5 | AC62: 1.3 | AD62: 1.325 | AE62: 1.25 | AF62: 2500 | AG62: 2500 | AH62: 830 | AI62: 2818 | AJ62: 6295 | AK62: 19050 | AL62: 22050 | AM62: =S62*AH62 -> 97110 | AN62: =T62*AI62 -> 560077.5 | AO62: =U62*AJ62 -> 944250 | AP62: =V62*AK62 -> 95250 | AQ62: =W62*AL62 -> 110250 | AR62: =SUM(Tabla1[[#This Row],[COSTO OPERATIVO ACIDO]:[COSTO OPERATIVO CATIONICO]]) -> 1806937.5 | AS62: 3599 | AT62: =AR62/L62 -> 4517.3438 | AU62: =IFERROR(Tabla1[[#This Row],[CAUDAL TOTAL TRATADO GEM ]]/Tabla1[[#This Row],[CAUDAL DE TRATAMIENTO]],0) -> 5
A63: =+A62 -> 46133 | B63: 21 | C63: 22 (MAÑANA) | D63: 62 | E63: FINAL TURNO 1 | F63: 2800 | G63: 7030 | H63: 3000 | I63: =+I62-5 -> 175 | J63: =+J62-5 -> 230 | K63: 17854 | L63: =(K64-K63)*M63 -> 480 | M63: 80 | N63: =F63-F64 -> 130 | O63: =G63-G64 -> 150 | P63: =H63-H64 -> 50 | Q63: =I63-I64 -> 0 | R63: =J63-J64 -> 5 | S63: =(N63*$AC$2) -> 169 | T63: =(O63*$AD$2) -> 198.75 | U63: =(P63*$AE$2) -> 62.5 | V63: =Tabla1[[#This Row],[CONSUMO POL ANIONICO (KG)]] -> 0 | W63: =Tabla1[[#This Row],[CONSUMO POL CATIONICO (KG)]] -> 5 | X63: =(S63*1000)/L63 -> 352.08333 | Y63: =(T63*1000)/L63 -> 414.0625 | Z63: =(U63*1000)/L63 -> 130.20833 | AA63: =(V63*1000)/L63 -> 0 | AB63: =(W63*1000)/L63 -> 10.416667 | AC63: 1.3 | AD63: 1.325 | AE63: 1.25 | AF63: 2500 | AG63: 2500 | AH63: 830 | AI63: 2818 | AJ63: 6295 | AK63: 19050 | AL63: 22050 | AM63: =S63*AH63 -> 140270 | AN63: =T63*AI63 -> 560077.5 | AO63: =U63*AJ63 -> 393437.5 | AP63: =V63*AK63 -> 0 | AQ63: =W63*AL63 -> 110250 | AR63: =SUM(Tabla1[[#This Row],[COSTO OPERATIVO ACIDO]:[COSTO OPERATIVO CATIONICO]]) -> 1204035 | AS63: 3599 | AT63: =AR63/L63 -> 2508.4062 | AU63: =IFERROR(Tabla1[[#This Row],[CAUDAL TOTAL TRATADO GEM ]]/Tabla1[[#This Row],[CAUDAL DE TRATAMIENTO]],0) -> 6
A64: =+A63 -> 46133 | B64: 21 | C64: 3(TARDE) | D64: 63 | E64: FINAL TURNO 2 | F64: 2670 | G64: 6880 | H64: 2950 | I64: =+I63-0 -> 175 | J64: =+J63-5 -> 225 | K64: 17860 | L64: =(K65-K64)*M64 -> 480 | M64: 80 | N64: =F64-F65 -> 60 | O64: =G64-G65 -> 80 | P64: =H64-H65 -> 20 | Q64: =I64-I65 -> 5 | R64: =J64-J65 -> 5 | S64: =(N64*$AC$2) -> 78 | T64: =(O64*$AD$2) -> 106 | U64: =(P64*$AE$2) -> 25 | V64: =Tabla1[[#This Row],[CONSUMO POL ANIONICO (KG)]] -> 5 | W64: =Tabla1[[#This Row],[CONSUMO POL CATIONICO (KG)]] -> 5 | X64: =(S64*1000)/L64 -> 162.5 | Y64: =(T64*1000)/L64 -> 220.83333 | Z64: =(U64*1000)/L64 -> 52.083333 | AA64: =(V64*1000)/L64 -> 10.416667 | AB64: =(W64*1000)/L64 -> 10.416667 | AC64: 1.3 | AD64: 1.325 | AE64: 1.25 | AF64: 2500 | AG64: 2500 | AH64: 830 | AI64: 2818 | AJ64: 6295 | AK64: 19050 | AL64: 22050 | AM64: =S64*AH64 -> 64740 | AN64: =T64*AI64 -> 298708 | AO64: =U64*AJ64 -> 157375 | AP64: =V64*AK64 -> 95250 | AQ64: =W64*AL64 -> 110250 | AR64: =SUM(Tabla1[[#This Row],[COSTO OPERATIVO ACIDO]:[COSTO OPERATIVO CATIONICO]]) -> 726323 | AS64: 3599 | AT64: =AR64/L64 -> 1513.1729 | AU64: =IFERROR(Tabla1[[#This Row],[CAUDAL TOTAL TRATADO GEM ]]/Tabla1[[#This Row],[CAUDAL DE TRATAMIENTO]],0) -> 6
A65: =+A64+1 -> 46134 | B65: 22 | C65: 22 (NOCHE) | D65: 64 | E65: FINAL TURNO 3 | F65: 2610 | G65: 6800 | H65: 2930 | I65: =+I64-5 -> 170 | J65: =+J64-5 -> 220 | K65: 17866 | L65: =(K66-K65)*M65 -> 480 | M65: 80 | N65: =F65-F66 -> 110 | O65: =G65-G66 -> 250 | P65: =H65-H66 -> 130 | Q65: =I65-I66 -> 5 | R65: =J65-J66 -> 5 | S65: =(N65*$AC$2) -> 143 | T65: =(O65*$AD$2) -> 331.25 | U65: =(P65*$AE$2) -> 162.5 | V65: =Tabla1[[#This Row],[CONSUMO POL ANIONICO (KG)]] -> 5 | W65: =Tabla1[[#This Row],[CONSUMO POL CATIONICO (KG)]] -> 5 | X65: =(S65*1000)/L65 -> 297.91667 | Y65: =(T65*1000)/L65 -> 690.10417 | Z65: =(U65*1000)/L65 -> 338.54167 | AA65: =(V65*1000)/L65 -> 10.416667 | AB65: =(W65*1000)/L65 -> 10.416667 | AC65: 1.3 | AD65: 1.325 | AE65: 1.25 | AF65: 2500 | AG65: 2500 | AH65: 830 | AI65: 2818 | AJ65: 6295 | AK65: 19050 | AL65: 22050 | AM65: =S65*AH65 -> 118690 | AN65: =T65*AI65 -> 933462.5 | AO65: =U65*AJ65 -> 1022937.5 | AP65: =V65*AK65 -> 95250 | AQ65: =W65*AL65 -> 110250 | AR65: =SUM(Tabla1[[#This Row],[COSTO OPERATIVO ACIDO]:[COSTO OPERATIVO CATIONICO]]) -> 2280590 | AS65: 3599 | AT65: =AR65/L65 -> 4751.2292 | AU65: =IFERROR(Tabla1[[#This Row],[CAUDAL TOTAL TRATADO GEM ]]/Tabla1[[#This Row],[CAUDAL DE TRATAMIENTO]],0) -> 6
A66: =+A65 -> 46134 | B66: 22 | C66: 23 (MAÑANA) | D66: 65 | E66: FINAL TURNO 1 | F66: 2500 | G66: 6550 | H66: 2800 | I66: =+I65-5 -> 165 | J66: =+J65-5 -> 215 | K66: 17872 | L66: =(K67-K66)*M66 -> 400 | M66: 80 | N66: =F66-F67-70 -> 180 | O66: =G66-G67 -> 200 | P66: =H66-H67 -> 80 | Q66: =I66-I67 -> 0 | R66: =J66-J67 -> 5 | S66: =(N66*$AC$2) -> 234 | T66: =(O66*$AD$2) -> 265 | U66: =(P66*$AE$2) -> 100 | V66: =Tabla1[[#This Row],[CONSUMO POL ANIONICO (KG)]] -> 0 | W66: =Tabla1[[#This Row],[CONSUMO POL CATIONICO (KG)]] -> 5 | X66: =(S66*1000)/L66 -> 585 | Y66: =(T66*1000)/L66 -> 662.5 | Z66: =(U66*1000)/L66 -> 250 | AA66: =(V66*1000)/L66 -> 0 | AB66: =(W66*1000)/L66 -> 12.5 | AC66: 1.3 | AD66: 1.325 | AE66: 1.25 | AF66: 2500 | AG66: 2500 | AH66: 830 | AI66: 2818 | AJ66: 6295 | AK66: 19050 | AL66: 22050 | AM66: =S66*AH66 -> 194220 | AN66: =T66*AI66 -> 746770 | AO66: =U66*AJ66 -> 629500 | AP66: =V66*AK66 -> 0 | AQ66: =W66*AL66 -> 110250 | AR66: =SUM(Tabla1[[#This Row],[COSTO OPERATIVO ACIDO]:[COSTO OPERATIVO CATIONICO]]) -> 1680740 | AS66: 3599 | AT66: =AR66/L66 -> 4201.85 | AU66: =IFERROR(Tabla1[[#This Row],[CAUDAL TOTAL TRATADO GEM ]]/Tabla1[[#This Row],[CAUDAL DE TRATAMIENTO]],0) -> 5
A67: =+A66 -> 46134 | B67: 22 | C67: 3(TARDE) | D67: 66 | E67: FINAL TURNO 2 | F67: 2250 | G67: 6350 | H67: 2720 | I67: =+I66-0 -> 165 | J67: =+J66-5 -> 210 | K67: 17877 | L67: =(K68-K67)*M67 -> 640 | M67: 80 | N67: =F67-F68 -> 20 | O67: =G67-G68-150 -> 200 | P67: =H67-H68 -> 80 | Q67: =I67-I68 -> 5 | R67: =J67-J68 -> 5 | S67: =(N67*$AC$2) -> 26 | T67: =(O67*$AD$2) -> 265 | U67: =(P67*$AE$2) -> 100 | V67: =Tabla1[[#This Row],[CONSUMO POL ANIONICO (KG)]] -> 5 | W67: =Tabla1[[#This Row],[CONSUMO POL CATIONICO (KG)]] -> 5 | X67: =(S67*1000)/L67 -> 40.625 | Y67: =(T67*1000)/L67 -> 414.0625 | Z67: =(U67*1000)/L67 -> 156.25 | AA67: =(V67*1000)/L67 -> 7.8125 | AB67: =(W67*1000)/L67 -> 7.8125 | AC67: 1.3 | AD67: 1.325 | AE67: 1.25 | AF67: 2500 | AG67: 2500 | AH67: 830 | AI67: 2818 | AJ67: 6295 | AK67: 19050 | AL67: 22050 | AM67: =S67*AH67 -> 21580 | AN67: =T67*AI67 -> 746770 | AO67: =U67*AJ67 -> 629500 | AP67: =V67*AK67 -> 95250 | AQ67: =W67*AL67 -> 110250 | AR67: =SUM(Tabla1[[#This Row],[COSTO OPERATIVO ACIDO]:[COSTO OPERATIVO CATIONICO]]) -> 1603350 | AS67: 3599 | AT67: =AR67/L67 -> 2505.2344 | AU67: =IFERROR(Tabla1[[#This Row],[CAUDAL TOTAL TRATADO GEM ]]/Tabla1[[#This Row],[CAUDAL DE TRATAMIENTO]],0) -> 8
A68: =+A67+1 -> 46135 | B68: 23 | C68: 23 (NOCHE) | D68: 67 | E68: FINAL TURNO 3 | F68: 2230 | G68: 6000 | H68: 2640 | I68: =+I67-5 -> 160 | J68: =+J67-5 -> 205 | K68: 17885 | L68: =(K69-K68)*M68 -> 595 | M68: 85 | N68: =F68-F69 -> 20 | O68: =G68-G69 -> 150 | P68: =H68-H69 -> 80 | Q68: =I68-I69 -> 5 | R68: =J68-J69 -> 10 | S68: =(N68*$AC$2) -> 26 | T68: =(O68*$AD$2) -> 198.75 | U68: =(P68*$AE$2) -> 100 | V68: =Tabla1[[#This Row],[CONSUMO POL ANIONICO (KG)]] -> 5 | W68: =Tabla1[[#This Row],[CONSUMO POL CATIONICO (KG)]] -> 10 | X68: =(S68*1000)/L68 -> 43.697479 | Y68: =(T68*1000)/L68 -> 334.03361 | Z68: =(U68*1000)/L68 -> 168.06723 | AA68: =(V68*1000)/L68 -> 8.4033613 | AB68: =(W68*1000)/L68 -> 16.806723 | AC68: 1.3 | AD68: 1.325 | AE68: 1.25 | AF68: 2500 | AG68: 2500 | AH68: 830 | AI68: 2818 | AJ68: 6295 | AK68: 19050 | AL68: 22050 | AM68: =S68*AH68 -> 21580 | AN68: =T68*AI68 -> 560077.5 | AO68: =U68*AJ68 -> 629500 | AP68: =V68*AK68 -> 95250 | AQ68: =W68*AL68 -> 220500 | AR68: =SUM(Tabla1[[#This Row],[COSTO OPERATIVO ACIDO]:[COSTO OPERATIVO CATIONICO]]) -> 1526907.5 | AS68: 3599 | AT68: =AR68/L68 -> 2566.2311 | AU68: =IFERROR(Tabla1[[#This Row],[CAUDAL TOTAL TRATADO GEM ]]/Tabla1[[#This Row],[CAUDAL DE TRATAMIENTO]],0) -> 7
A69: =+A68 -> 46135 | B69: 23 | C69: 24 (MAÑANA) | D69: 68 | E69: FINAL TURNO 1 | F69: 2210 | G69: 5850 | H69: 2560 | I69: =+I68-5 -> 155 | J69: =+J68-10 -> 195 | K69: 17892 | L69: =(K70-K69)*M69 -> 450 | M69: 90 | N69: =F69-F70 -> 190 | O69: =G69-G70 -> 120 | P69: =H69-H70 -> 60 | Q69: =I69-I70 -> 0 | R69: =J69-J70 -> 0 | S69: =(N69*$AC$2) -> 247 | T69: =(O69*$AD$2) -> 159 | U69: =(P69*$AE$2) -> 75 | V69: =Tabla1[[#This Row],[CONSUMO POL ANIONICO (KG)]] -> 0 | W69: =Tabla1[[#This Row],[CONSUMO POL CATIONICO (KG)]] -> 0 | X69: =(S69*1000)/L69 -> 548.88889 | Y69: =(T69*1000)/L69 -> 353.33333 | Z69: =(U69*1000)/L69 -> 166.66667 | AA69: =(V69*1000)/L69 -> 0 | AB69: =(W69*1000)/L69 -> 0 | AC69: 1.3 | AD69: 1.325 | AE69: 1.25 | AF69: 2500 | AG69: 2500 | AH69: 830 | AI69: 2818 | AJ69: 6295 | AK69: 19050 | AL69: 22050 | AM69: =S69*AH69 -> 205010 | AN69: =T69*AI69 -> 448062 | AO69: =U69*AJ69 -> 472125 | AP69: =V69*AK69 -> 0 | AQ69: =W69*AL69 -> 0 | AR69: =SUM(Tabla1[[#This Row],[COSTO OPERATIVO ACIDO]:[COSTO OPERATIVO CATIONICO]]) -> 1125197 | AS69: 3599 | AT69: =AR69/L69 -> 2500.4378 | AU69: =IFERROR(Tabla1[[#This Row],[CAUDAL TOTAL TRATADO GEM ]]/Tabla1[[#This Row],[CAUDAL DE TRATAMIENTO]],0) -> 5
A70: =+A69 -> 46135 | B70: 23 | C70: 3(TARDE) | D70: 69 | E70: FINAL TURNO 2 | F70: 2020 | G70: 5730 | H70: 2500 | I70: =+I69-0 -> 155 | J70: =+J69-0 -> 195 | K70: 17897 | L70: =(K71-K70)*M70 -> 450 | M70: 90 | N70: =F70-F71 -> 110 | O70: =G70-G71-160 -> 90 | P70: =H70-H71 -> 10 | Q70: =I70-I71 -> 5 | R70: =J70-J71 -> 10 | S70: =(N70*$AC$2) -> 143 | T70: =(O70*$AD$2) -> 119.25 | U70: =(P70*$AE$2) -> 12.5 | V70: =Tabla1[[#This Row],[CONSUMO POL ANIONICO (KG)]] -> 5 | W70: =Tabla1[[#This Row],[CONSUMO POL CATIONICO (KG)]] -> 10 | X70: =(S70*1000)/L70 -> 317.77778 | Y70: =(T70*1000)/L70 -> 265 | Z70: =(U70*1000)/L70 -> 27.777778 | AA70: =(V70*1000)/L70 -> 11.111111 | AB70: =(W70*1000)/L70 -> 22.222222 | AC70: 1.3 | AD70: 1.325 | AE70: 1.25 | AF70: 2500 | AG70: 2500 | AH70: 830 | AI70: 2818 | AJ70: 6295 | AK70: 19050 | AL70: 22050 | AM70: =S70*AH70 -> 118690 | AN70: =T70*AI70 -> 336046.5 | AO70: =U70*AJ70 -> 78687.5 | AP70: =V70*AK70 -> 95250 | AQ70: =W70*AL70 -> 220500 | AR70: =SUM(Tabla1[[#This Row],[COSTO OPERATIVO ACIDO]:[COSTO OPERATIVO CATIONICO]]) -> 849174 | AS70: 3599 | AT70: =AR70/L70 -> 1887.0533 | AU70: =IFERROR(Tabla1[[#This Row],[CAUDAL TOTAL TRATADO GEM ]]/Tabla1[[#This Row],[CAUDAL DE TRATAMIENTO]],0) -> 5
A71: =+A70+1 -> 46136 | B71: 24 | C71: 24 (NOCHE) | D71: 70 | E71: FINAL TURNO 3 | F71: 1910 | G71: 5480 | H71: 2490 | I71: =+I70-5 -> 150 | J71: =+J70-10 -> 185 | K71: 17902 | L71: =(K72-K71)*M71 -> 560 | M71: 80 | N71: =F71-F72 -> 160 | O71: =G71-G72 -> 120 | P71: =H71-H72 -> 40 | Q71: =I71-I72 -> 5 | R71: =J71-J72 -> 5 | S71: =(N71*$AC$2) -> 208 | T71: =(O71*$AD$2) -> 159 | U71: =(P71*$AE$2) -> 50 | V71: =Tabla1[[#This Row],[CONSUMO POL ANIONICO (KG)]] -> 5 | W71: =Tabla1[[#This Row],[CONSUMO POL CATIONICO (KG)]] -> 5 | X71: =(S71*1000)/L71 -> 371.42857 | Y71: =(T71*1000)/L71 -> 283.92857 | Z71: =(U71*1000)/L71 -> 89.285714 | AA71: =(V71*1000)/L71 -> 8.9285714 | AB71: =(W71*1000)/L71 -> 8.9285714 | AC71: 1.3 | AD71: 1.325 | AE71: 1.25 | AF71: 2500 | AG71: 2500 | AH71: 830 | AI71: 2818 | AJ71: 6295 | AK71: 19050 | AL71: 22050 | AM71: =S71*AH71 -> 172640 | AN71: =T71*AI71 -> 448062 | AO71: =U71*AJ71 -> 314750 | AP71: =V71*AK71 -> 95250 | AQ71: =W71*AL71 -> 110250 | AR71: =SUM(Tabla1[[#This Row],[COSTO OPERATIVO ACIDO]:[COSTO OPERATIVO CATIONICO]]) -> 1140952 | AS71: 3599 | AT71: =AR71/L71 -> 2037.4143 | AU71: =IFERROR(Tabla1[[#This Row],[CAUDAL TOTAL TRATADO GEM ]]/Tabla1[[#This Row],[CAUDAL DE TRATAMIENTO]],0) -> 7
A72: =+A71 -> 46136 | B72: 24 | C72: 25 (MAÑANA) | D72: 71 | E72: FINAL TURNO 1 | F72: 1750 | G72: 5360 | H72: 2450 | I72: =+I71-5 -> 145 | J72: =+J71-5 -> 180 | K72: 17909 | L72: =(K73-K72)*M72 -> 320 | M72: 80 | N72: =F72-F73+2000 -> 70 | O72: =G72-G73+1000 -> 110 | P72: =H72-H73 -> 10 | Q72: =I72-I73 -> 0 | R72: =J72-J73 -> 0 | S72: =(N72*$AC$2) -> 91 | T72: =(O72*$AD$2) -> 145.75 | U72: =(P72*$AE$2) -> 12.5 | V72: =Tabla1[[#This Row],[CONSUMO POL ANIONICO (KG)]] -> 0 | W72: =Tabla1[[#This Row],[CONSUMO POL CATIONICO (KG)]] -> 0 | X72: =(S72*1000)/L72 -> 284.375 | Y72: =(T72*1000)/L72 -> 455.46875 | Z72: =(U72*1000)/L72 -> 39.0625 | AA72: =(V72*1000)/L72 -> 0 | AB72: =(W72*1000)/L72 -> 0 | AC72: 1.3 | AD72: 1.325 | AE72: 1.25 | AF72: 2500 | AG72: 2500 | AH72: 830 | AI72: 2818 | AJ72: 6295 | AK72: 19050 | AL72: 22050 | AM72: =S72*AH72 -> 75530 | AN72: =T72*AI72 -> 410723.5 | AO72: =U72*AJ72 -> 78687.5 | AP72: =V72*AK72 -> 0 | AQ72: =W72*AL72 -> 0 | AR72: =SUM(Tabla1[[#This Row],[COSTO OPERATIVO ACIDO]:[COSTO OPERATIVO CATIONICO]]) -> 564941 | AS72: 3599 | AT72: =AR72/L72 -> 1765.4406 | AU72: =IFERROR(Tabla1[[#This Row],[CAUDAL TOTAL TRATADO GEM ]]/Tabla1[[#This Row],[CAUDAL DE TRATAMIENTO]],0) -> 4
A73: =+A72 -> 46136 | B73: 24 | C73: 3(TARDE) | D73: 72 | E73: FINAL TURNO 2 | F73: 3680 | G73: 6250 | H73: 2440 | I73: =+I72-0 -> 145 | J73: =+J72-0 -> 180 | K73: 17913 | L73: =(K74-K73)*M73 -> 480 | M73: 80 | N73: =F73-F74 -> 80 | O73: =G73-G74 -> 80 | P73: =H73-H74 -> 100 | Q73: =I73-I74 -> 0 | R73: =J73-J74 -> 0 | S73: =(N73*$AC$2) -> 104 | T73: =(O73*$AD$2) -> 106 | U73: =(P73*$AE$2) -> 125 | V73: =Tabla1[[#This Row],[CONSUMO POL ANIONICO (KG)]] -> 0 | W73: =Tabla1[[#This Row],[CONSUMO POL CATIONICO (KG)]] -> 0 | X73: =(S73*1000)/L73 -> 216.66667 | Y73: =(T73*1000)/L73 -> 220.83333 | Z73: =(U73*1000)/L73 -> 260.41667 | AA73: =(V73*1000)/L73 -> 0 | AB73: =(W73*1000)/L73 -> 0 | AC73: 1.3 | AD73: 1.325 | AE73: 1.25 | AF73: 2500 | AG73: 2500 | AH73: 830 | AI73: 2818 | AJ73: 6295 | AK73: 19050 | AL73: 22050 | AM73: =S73*AH73 -> 86320 | AN73: =T73*AI73 -> 298708 | AO73: =U73*AJ73 -> 786875 | AP73: =V73*AK73 -> 0 | AQ73: =W73*AL73 -> 0 | AR73: =SUM(Tabla1[[#This Row],[COSTO OPERATIVO ACIDO]:[COSTO OPERATIVO CATIONICO]]) -> 1171903 | AS73: 3599 | AT73: =AR73/L73 -> 2441.4646 | AU73: =IFERROR(Tabla1[[#This Row],[CAUDAL TOTAL TRATADO GEM ]]/Tabla1[[#This Row],[CAUDAL DE TRATAMIENTO]],0) -> 6
A74: =+A73+1 -> 46137 | B74: 25 | C74: 25 (NOCHE) | D74: 73 | E74: FINAL TURNO 3 | F74: 3600 | G74: 6170 | H74: 2340 | I74: =+I73-0 -> 145 | J74: =+J73-0 -> 180 | K74: 17919 | L74: =(K75-K74)*M74 -> 480 | M74: 80 | N74: =F74-F75 -> 110 | O74: =G74-G75 -> 190 | P74: =H74-H75 -> 40 | Q74: =I74-I75 -> 5 | R74: =J74-J75 -> 5 | S74: =(N74*$AC$2) -> 143 | T74: =(O74*$AD$2) -> 251.75 | U74: =(P74*$AE$2) -> 50 | V74: =Tabla1[[#This Row],[CONSUMO POL ANIONICO (KG)]] -> 5 | W74: =Tabla1[[#This Row],[CONSUMO POL CATIONICO (KG)]] -> 5 | X74: =(S74*1000)/L74 -> 297.91667 | Y74: =(T74*1000)/L74 -> 524.47917 | Z74: =(U74*1000)/L74 -> 104.16667 | AA74: =(V74*1000)/L74 -> 10.416667 | AB74: =(W74*1000)/L74 -> 10.416667 | AC74: 1.3 | AD74: 1.325 | AE74: 1.25 | AF74: 2500 | AG74: 2500 | AH74: 830 | AI74: 2818 | AJ74: 6295 | AK74: 19050 | AL74: 22050 | AM74: =S74*AH74 -> 118690 | AN74: =T74*AI74 -> 709431.5 | AO74: =U74*AJ74 -> 314750 | AP74: =V74*AK74 -> 95250 | AQ74: =W74*AL74 -> 110250 | AR74: =SUM(Tabla1[[#This Row],[COSTO OPERATIVO ACIDO]:[COSTO OPERATIVO CATIONICO]]) -> 1348371.5 | AS74: 3599 | AT74: =AR74/L74 -> 2809.1073 | AU74: =IFERROR(Tabla1[[#This Row],[CAUDAL TOTAL TRATADO GEM ]]/Tabla1[[#This Row],[CAUDAL DE TRATAMIENTO]],0) -> 6
A75: =+A74 -> 46137 | B75: 25 | C75: 26 (MAÑANA) | D75: 74 | E75: FINAL TURNO 1 | F75: 3490 | G75: 5980 | H75: 2300 | I75: =+I74-5 -> 140 | J75: =+J74-5 -> 175 | K75: 17925 | L75: =(K76-K75)*M75 -> 480 | M75: 80 | N75: =F75-F76 -> 160 | O75: =G75-G76 -> 80 | P75: =H75-H76 -> 15 | Q75: =I75-I76 -> 0 | R75: =J75-J76 -> 5 | S75: =(N75*$AC$2) -> 208 | T75: =(O75*$AD$2) -> 106 | U75: =(P75*$AE$2) -> 18.75 | V75: =Tabla1[[#This Row],[CONSUMO POL ANIONICO (KG)]] -> 0 | W75: =Tabla1[[#This Row],[CONSUMO POL CATIONICO (KG)]] -> 5 | X75: =(S75*1000)/L75 -> 433.33333 | Y75: =(T75*1000)/L75 -> 220.83333 | Z75: =(U75*1000)/L75 -> 39.0625 | AA75: =(V75*1000)/L75 -> 0 | AB75: =(W75*1000)/L75 -> 10.416667 | AC75: 1.3 | AD75: 1.325 | AE75: 1.25 | AF75: 2500 | AG75: 2500 | AH75: 830 | AI75: 2818 | AJ75: 6295 | AK75: 19050 | AL75: 22050 | AM75: =S75*AH75 -> 172640 | AN75: =T75*AI75 -> 298708 | AO75: =U75*AJ75 -> 118031.25 | AP75: =V75*AK75 -> 0 | AQ75: =W75*AL75 -> 110250 | AR75: =SUM(Tabla1[[#This Row],[COSTO OPERATIVO ACIDO]:[COSTO OPERATIVO CATIONICO]]) -> 699629.25 | AS75: 3599 | AT75: =AR75/L75 -> 1457.5609 | AU75: =IFERROR(Tabla1[[#This Row],[CAUDAL TOTAL TRATADO GEM ]]/Tabla1[[#This Row],[CAUDAL DE TRATAMIENTO]],0) -> 6
A76: =+A75 -> 46137 | B76: 25 | C76: 3(TARDE) | D76: 75 | E76: FINAL TURNO 2 | F76: 3330 | G76: 5900 | H76: 2285 | I76: =+I75-0 -> 140 | J76: =+J75-5 -> 170 | K76: 17931 | L76: =(K77-K76)*M76 -> 400 | M76: 80 | N76: =F76-F77 -> 30 | O76: =G76-G77 -> 140 | P76: =H76-H77 -> 85 | Q76: =I76-I77 -> 0 | R76: =J76-J77 -> 5 | S76: =(N76*$AC$2) -> 39 | T76: =(O76*$AD$2) -> 185.5 | U76: =(P76*$AE$2) -> 106.25 | V76: =Tabla1[[#This Row],[CONSUMO POL ANIONICO (KG)]] -> 0 | W76: =Tabla1[[#This Row],[CONSUMO POL CATIONICO (KG)]] -> 5 | X76: =(S76*1000)/L76 -> 97.5 | Y76: =(T76*1000)/L76 -> 463.75 | Z76: =(U76*1000)/L76 -> 265.625 | AA76: =(V76*1000)/L76 -> 0 | AB76: =(W76*1000)/L76 -> 12.5 | AC76: 1.3 | AD76: 1.325 | AE76: 1.25 | AF76: 2500 | AG76: 2500 | AH76: 830 | AI76: 2818 | AJ76: 6295 | AK76: 19050 | AL76: 22050 | AM76: =S76*AH76 -> 32370 | AN76: =T76*AI76 -> 522739 | AO76: =U76*AJ76 -> 668843.75 | AP76: =V76*AK76 -> 0 | AQ76: =W76*AL76 -> 110250 | AR76: =SUM(Tabla1[[#This Row],[COSTO OPERATIVO ACIDO]:[COSTO OPERATIVO CATIONICO]]) -> 1334202.8 | AS76: 3599 | AT76: =AR76/L76 -> 3335.5069 | AU76: =IFERROR(Tabla1[[#This Row],[CAUDAL TOTAL TRATADO GEM ]]/Tabla1[[#This Row],[CAUDAL DE TRATAMIENTO]],0) -> 5
A77: =+A76+1 -> 46138 | B77: 26 | C77: 26 (NOCHE) | D77: 76 | E77: FINAL TURNO 3 | F77: 3300 | G77: 5760 | H77: 2200 | I77: =+I76-0 -> 140 | J77: =+J76-5 -> 165 | K77: 17936 | L77: =(K78-K77)*M77 -> 0 | M77: 80 | N77: =F77-F78 -> 0 | O77: =G77-G78 -> 0 | P77: =H77-H78 -> 0 | Q77: =I77-I78 -> 0 | R77: =J77-J78 -> 0 | S77: =(N77*$AC$2) -> 0 | T77: =(O77*$AD$2) -> 0 | U77: =(P77*$AE$2) -> 0 | V77: =Tabla1[[#This Row],[CONSUMO POL ANIONICO (KG)]] -> 0 | W77: =Tabla1[[#This Row],[CONSUMO POL CATIONICO (KG)]] -> 0 | X77: =(S77*1000)/L77 -> #DIV/0! | Y77: =(T77*1000)/L77 -> #DIV/0! | Z77: =(U77*1000)/L77 -> #DIV/0! | AA77: =(V77*1000)/L77 -> #DIV/0! | AB77: =(W77*1000)/L77 -> #DIV/0! | AC77: 1.3 | AD77: 1.325 | AE77: 1.25 | AF77: 2500 | AG77: 2500 | AH77: 830 | AI77: 2818 | AJ77: 6295 | AK77: 19050 | AL77: 22050 | AM77: =S77*AH77 -> 0 | AN77: =T77*AI77 -> 0 | AO77: =U77*AJ77 -> 0 | AP77: =V77*AK77 -> 0 | AQ77: =W77*AL77 -> 0 | AR77: =SUM(Tabla1[[#This Row],[COSTO OPERATIVO ACIDO]:[COSTO OPERATIVO CATIONICO]]) -> 0 | AS77: 3599 | AT77: =AR77/L77 -> #DIV/0! | AU77: =IFERROR(Tabla1[[#This Row],[CAUDAL TOTAL TRATADO GEM ]]/Tabla1[[#This Row],[CAUDAL DE TRATAMIENTO]],0) -> 0
A78: =+A77 -> 46138 | B78: 26 | C78: 27 (MAÑANA) | D78: 77 | E78: FINAL TURNO 1 | F78: =+AVERAGE(F77,F79) -> 3300 | G78: 5760 | H78: =+AVERAGE(H77,H79) -> 2200 | I78: =+I77-0 -> 140 | J78: =+J77-0 -> 165 | K78: 17936 | L78: =(K79-K78)*M78 -> 320 | M78: 80 | N78: =F78-F79 -> 0 | O78: =G78-G79 -> 40 | P78: =H78-H79 -> 0 | Q78: =I78-I79 -> 5 | R78: =J78-J79 -> 5 | S78: =(N78*$AC$2) -> 0 | T78: =(O78*$AD$2) -> 53 | U78: =(P78*$AE$2) -> 0 | V78: =Tabla1[[#This Row],[CONSUMO POL ANIONICO (KG)]] -> 5 | W78: =Tabla1[[#This Row],[CONSUMO POL CATIONICO (KG)]] -> 5 | X78: =(S78*1000)/L78 -> 0 | Y78: =(T78*1000)/L78 -> 165.625 | Z78: =(U78*1000)/L78 -> 0 | AA78: =(V78*1000)/L78 -> 15.625 | AB78: =(W78*1000)/L78 -> 15.625 | AC78: 1.3 | AD78: 1.325 | AE78: 1.25 | AF78: 2500 | AG78: 2500 | AH78: 830 | AI78: 2818 | AJ78: 6295 | AK78: 19050 | AL78: 22050 | AM78: =S78*AH78 -> 0 | AN78: =T78*AI78 -> 149354 | AO78: =U78*AJ78 -> 0 | AP78: =V78*AK78 -> 95250 | AQ78: =W78*AL78 -> 110250 | AR78: =SUM(Tabla1[[#This Row],[COSTO OPERATIVO ACIDO]:[COSTO OPERATIVO CATIONICO]]) -> 354854 | AS78: 3599 | AT78: =AR78/L78 -> 1108.9188 | AU78: =IFERROR(Tabla1[[#This Row],[CAUDAL TOTAL TRATADO GEM ]]/Tabla1[[#This Row],[CAUDAL DE TRATAMIENTO]],0) -> 4
A79: =+A78 -> 46138 | B79: 26 | C79: 3(TARDE) | D79: 78 | E79: FINAL TURNO 2 | F79: 3300 | G79: 5720 | H79: 2200 | I79: =+I78-5 -> 135 | J79: =+J78-5 -> 160 | K79: 17940 | L79: =(K80-K79)*M79 -> 480 | M79: 80 | N79: =F79-F80-70 -> 230 | O79: =G79-G80 -> 60 | P79: =H79-H80 -> 30 | Q79: =I79-I80 -> 0 | R79: =J79-J80 -> 5 | S79: =(N79*$AC$2) -> 299 | T79: =(O79*$AD$2) -> 79.5 | U79: =(P79*$AE$2) -> 37.5 | V79: =Tabla1[[#This Row],[CONSUMO POL ANIONICO (KG)]] -> 0 | W79: =Tabla1[[#This Row],[CONSUMO POL CATIONICO (KG)]] -> 5 | X79: =(S79*1000)/L79 -> 622.91667 | Y79: =(T79*1000)/L79 -> 165.625 | Z79: =(U79*1000)/L79 -> 78.125 | AA79: =(V79*1000)/L79 -> 0 | AB79: =(W79*1000)/L79 -> 10.416667 | AC79: 1.3 | AD79: 1.325 | AE79: 1.25 | AF79: 2500 | AG79: 2500 | AH79: 830 | AI79: 2818 | AJ79: 6295 | AK79: 19050 | AL79: 22050 | AM79: =S79*AH79 -> 248170 | AN79: =T79*AI79 -> 224031 | AO79: =U79*AJ79 -> 236062.5 | AP79: =V79*AK79 -> 0 | AQ79: =W79*AL79 -> 110250 | AR79: =SUM(Tabla1[[#This Row],[COSTO OPERATIVO ACIDO]:[COSTO OPERATIVO CATIONICO]]) -> 818513.5 | AS79: 3599 | AT79: =AR79/L79 -> 1705.2365 | AU79: =IFERROR(Tabla1[[#This Row],[CAUDAL TOTAL TRATADO GEM ]]/Tabla1[[#This Row],[CAUDAL DE TRATAMIENTO]],0) -> 6
A80: =+A79+1 -> 46139 | B80: 27 | C80: 27 (NOCHE) | D80: 79 | E80: FINAL TURNO 3 | F80: 3000 | G80: 5660 | H80: 2170 | I80: =+I79-0 -> 135 | J80: =+J79-5 -> 155 | K80: 17946 | L80: =(K81-K80)*M80 -> 640 | M80: 80 | N80: =F80-F81 -> 200 | O80: =G80-G81-120 -> 220 | P80: =H80-H81 -> 90 | Q80: =I80-I81 -> 5 | R80: =J80-J81 -> 5 | S80: =(N80*$AC$2) -> 260 | T80: =(O80*$AD$2) -> 291.5 | U80: =(P80*$AE$2) -> 112.5 | V80: =Tabla1[[#This Row],[CONSUMO POL ANIONICO (KG)]] -> 5 | W80: =Tabla1[[#This Row],[CONSUMO POL CATIONICO (KG)]] -> 5 | X80: =(S80*1000)/L80 -> 406.25 | Y80: =(T80*1000)/L80 -> 455.46875 | Z80: =(U80*1000)/L80 -> 175.78125 | AA80: =(V80*1000)/L80 -> 7.8125 | AB80: =(W80*1000)/L80 -> 7.8125 | AC80: 1.3 | AD80: 1.325 | AE80: 1.25 | AF80: 2500 | AG80: 2500 | AH80: 830 | AI80: 2818 | AJ80: 6295 | AK80: 19050 | AL80: 22050 | AM80: =S80*AH80 -> 215800 | AN80: =T80*AI80 -> 821447 | AO80: =U80*AJ80 -> 708187.5 | AP80: =V80*AK80 -> 95250 | AQ80: =W80*AL80 -> 110250 | AR80: =SUM(Tabla1[[#This Row],[COSTO OPERATIVO ACIDO]:[COSTO OPERATIVO CATIONICO]]) -> 1950934.5 | AS80: 3599 | AT80: =AR80/L80 -> 3048.3352 | AU80: =IFERROR(Tabla1[[#This Row],[CAUDAL TOTAL TRATADO GEM ]]/Tabla1[[#This Row],[CAUDAL DE TRATAMIENTO]],0) -> 8
A81: =+A80 -> 46139 | B81: 27 | C81: 28 (MAÑANA) | D81: 80 | E81: FINAL TURNO 1 | F81: 2800 | G81: 5320 | H81: 2080 | I81: =+I80-5 -> 130 | J81: =+J80-5 -> 150 | K81: 17954 | L81: =(K82-K81)*M81 -> 400 | M81: 80 | N81: =F81-F82 -> 120 | O81: =G81-G82-150 -> 120 | P81: =H81-H82 -> 10 | Q81: =I81-I82 -> 5 | R81: =J81-J82 -> 5 | S81: =(N81*$AC$2) -> 156 | T81: =(O81*$AD$2) -> 159 | U81: =(P81*$AE$2) -> 12.5 | V81: =Tabla1[[#This Row],[CONSUMO POL ANIONICO (KG)]] -> 5 | W81: =Tabla1[[#This Row],[CONSUMO POL CATIONICO (KG)]] -> 5 | X81: =(S81*1000)/L81 -> 390 | Y81: =(T81*1000)/L81 -> 397.5 | Z81: =(U81*1000)/L81 -> 31.25 | AA81: =(V81*1000)/L81 -> 12.5 | AB81: =(W81*1000)/L81 -> 12.5 | AC81: 1.3 | AD81: 1.325 | AE81: 1.25 | AF81: 2500 | AG81: 2500 | AH81: 830 | AI81: 2818 | AJ81: 6295 | AK81: 19050 | AL81: 22050 | AM81: =S81*AH81 -> 129480 | AN81: =T81*AI81 -> 448062 | AO81: =U81*AJ81 -> 78687.5 | AP81: =V81*AK81 -> 95250 | AQ81: =W81*AL81 -> 110250 | AR81: =SUM(Tabla1[[#This Row],[COSTO OPERATIVO ACIDO]:[COSTO OPERATIVO CATIONICO]]) -> 861729.5 | AS81: 3599 | AT81: =AR81/L81 -> 2154.3238 | AU81: =IFERROR(Tabla1[[#This Row],[CAUDAL TOTAL TRATADO GEM ]]/Tabla1[[#This Row],[CAUDAL DE TRATAMIENTO]],0) -> 5
A82: =+A81 -> 46139 | B82: 27 | C82: 3(TARDE) | D82: 81 | E82: FINAL TURNO 2 | F82: 2680 | G82: 5050 | H82: 2070 | I82: =+I81-5 -> 125 | J82: =+J81-5 -> 145 | K82: 17959 | L82: =(K83-K82)*M82 -> 480 | M82: 80 | N82: =F82-F83 -> 160 | O82: =G82-G83 -> 100 | P82: =H82-H83 -> 40 | Q82: =I82-I83 -> 5 | R82: =J82-J83 -> 10 | S82: =(N82*$AC$2) -> 208 | T82: =(O82*$AD$2) -> 132.5 | U82: =(P82*$AE$2) -> 50 | V82: =Tabla1[[#This Row],[CONSUMO POL ANIONICO (KG)]] -> 5 | W82: =Tabla1[[#This Row],[CONSUMO POL CATIONICO (KG)]] -> 10 | X82: =(S82*1000)/L82 -> 433.33333 | Y82: =(T82*1000)/L82 -> 276.04167 | Z82: =(U82*1000)/L82 -> 104.16667 | AA82: =(V82*1000)/L82 -> 10.416667 | AB82: =(W82*1000)/L82 -> 20.833333 | AC82: 1.3 | AD82: 1.325 | AE82: 1.25 | AF82: 2500 | AG82: 2500 | AH82: 830 | AI82: 2818 | AJ82: 6295 | AK82: 19050 | AL82: 22050 | AM82: =S82*AH82 -> 172640 | AN82: =T82*AI82 -> 373385 | AO82: =U82*AJ82 -> 314750 | AP82: =V82*AK82 -> 95250 | AQ82: =W82*AL82 -> 220500 | AR82: =SUM(Tabla1[[#This Row],[COSTO OPERATIVO ACIDO]:[COSTO OPERATIVO CATIONICO]]) -> 1176525 | AS82: 3599 | AT82: =AR82/L82 -> 2451.0938 | AU82: =IFERROR(Tabla1[[#This Row],[CAUDAL TOTAL TRATADO GEM ]]/Tabla1[[#This Row],[CAUDAL DE TRATAMIENTO]],0) -> 6
A83: =+A82+1 -> 46140 | B83: 28 | C83: 28 (NOCHE) | D83: 82 | E83: FINAL TURNO 3 | F83: 2520 | G83: 4950 | H83: 2030 | I83: =+I82-5 -> 120 | J83: =+J82-10 -> 135 | K83: 17965 | L83: =(K84-K83)*M83 -> 640 | M83: 80 | N83: =F83-F84 -> 195 | O83: =G83-G84 -> 210 | P83: =H83-H84 -> 50 | Q83: =I83-I84 -> 0 | R83: =J83-J84 -> 0 | S83: =(N83*$AC$2) -> 253.5 | T83: =(O83*$AD$2) -> 278.25 | U83: =(P83*$AE$2) -> 62.5 | V83: =Tabla1[[#This Row],[CONSUMO POL ANIONICO (KG)]] -> 0 | W83: =Tabla1[[#This Row],[CONSUMO POL CATIONICO (KG)]] -> 0 | X83: =(S83*1000)/L83 -> 396.09375 | Y83: =(T83*1000)/L83 -> 434.76562 | Z83: =(U83*1000)/L83 -> 97.65625 | AA83: =(V83*1000)/L83 -> 0 | AB83: =(W83*1000)/L83 -> 0 | AC83: 1.3 | AD83: 1.325 | AE83: 1.25 | AF83: 2500 | AG83: 2500 | AH83: 830 | AI83: 2818 | AJ83: 6295 | AK83: 19050 | AL83: 22050 | AM83: =S83*AH83 -> 210405 | AN83: =T83*AI83 -> 784108.5 | AO83: =U83*AJ83 -> 393437.5 | AP83: =V83*AK83 -> 0 | AQ83: =W83*AL83 -> 0 | AR83: =SUM(Tabla1[[#This Row],[COSTO OPERATIVO ACIDO]:[COSTO OPERATIVO CATIONICO]]) -> 1387951 | AS83: 3599 | AT83: =AR83/L83 -> 2168.6734 | AU83: =IFERROR(Tabla1[[#This Row],[CAUDAL TOTAL TRATADO GEM ]]/Tabla1[[#This Row],[CAUDAL DE TRATAMIENTO]],0) -> 8
A84: =+A83 -> 46140 | B84: 28 | C84: 29 (MAÑANA) | D84: 83 | E84: FINAL TURNO 1 | F84: =+AVERAGE(F83,F85) -> 2325 | G84: =+AVERAGE(G83,G85) -> 4740 | H84: =+AVERAGE(H83,H85) -> 1980 | I84: =+I83-0 -> 120 | J84: =+J83-0 -> 135 | K84: 17973 | L84: =(K85-K84)*M84 -> 480 | M84: 80 | N84: =F84-F85 -> 195 | O84: =G84-G85 -> 210 | P84: =H84-H85 -> 50 | Q84: =I84-I85 -> 5 | R84: =J84-J85 -> 5 | S84: =(N84*$AC$2) -> 253.5 | T84: =(O84*$AD$2) -> 278.25 | U84: =(P84*$AE$2) -> 62.5 | V84: =Tabla1[[#This Row],[CONSUMO POL ANIONICO (KG)]] -> 5 | W84: =Tabla1[[#This Row],[CONSUMO POL CATIONICO (KG)]] -> 5 | X84: =(S84*1000)/L84 -> 528.125 | Y84: =(T84*1000)/L84 -> 579.6875 | Z84: =(U84*1000)/L84 -> 130.20833 | AA84: =(V84*1000)/L84 -> 10.416667 | AB84: =(W84*1000)/L84 -> 10.416667 | AC84: 1.3 | AD84: 1.325 | AE84: 1.25 | AF84: 2500 | AG84: 2500 | AH84: 830 | AI84: 2818 | AJ84: 6295 | AK84: 19050 | AL84: 22050 | AM84: =S84*AH84 -> 210405 | AN84: =T84*AI84 -> 784108.5 | AO84: =U84*AJ84 -> 393437.5 | AP84: =V84*AK84 -> 95250 | AQ84: =W84*AL84 -> 110250 | AR84: =SUM(Tabla1[[#This Row],[COSTO OPERATIVO ACIDO]:[COSTO OPERATIVO CATIONICO]]) -> 1593451 | AS84: 3599 | AT84: =AR84/L84 -> 3319.6896 | AU84: =IFERROR(Tabla1[[#This Row],[CAUDAL TOTAL TRATADO GEM ]]/Tabla1[[#This Row],[CAUDAL DE TRATAMIENTO]],0) -> 6
A85: =+A84 -> 46140 | B85: 28 | C85: 3(TARDE) | D85: 84 | E85: FINAL TURNO 2 | F85: 2130 | G85: 4530 | H85: 1930 | I85: =+I84-5 -> 115 | J85: =+J84-5 -> 130 | K85: 17979 | L85: =(K86-K85)*M85 -> 480 | M85: 80 | N85: =F85-F86 -> 130 | O85: =G85-G86 -> 190 | P85: =H85-H86 -> 80 | Q85: =I85-I86 -> 5 | R85: =J85-J86 -> 5 | S85: =(N85*$AC$2) -> 169 | T85: =(O85*$AD$2) -> 251.75 | U85: =(P85*$AE$2) -> 100 | V85: =Tabla1[[#This Row],[CONSUMO POL ANIONICO (KG)]] -> 5 | W85: =Tabla1[[#This Row],[CONSUMO POL CATIONICO (KG)]] -> 5 | X85: =(S85*1000)/L85 -> 352.08333 | Y85: =(T85*1000)/L85 -> 524.47917 | Z85: =(U85*1000)/L85 -> 208.33333 | AA85: =(V85*1000)/L85 -> 10.416667 | AB85: =(W85*1000)/L85 -> 10.416667 | AC85: 1.3 | AD85: 1.325 | AE85: 1.25 | AF85: 2500 | AG85: 2500 | AH85: 830 | AI85: 2818 | AJ85: 6295 | AK85: 19050 | AL85: 22050 | AM85: =S85*AH85 -> 140270 | AN85: =T85*AI85 -> 709431.5 | AO85: =U85*AJ85 -> 629500 | AP85: =V85*AK85 -> 95250 | AQ85: =W85*AL85 -> 110250 | AR85: =SUM(Tabla1[[#This Row],[COSTO OPERATIVO ACIDO]:[COSTO OPERATIVO CATIONICO]]) -> 1684701.5 | AS85: 3599 | AT85: =AR85/L85 -> 3509.7948 | AU85: =IFERROR(Tabla1[[#This Row],[CAUDAL TOTAL TRATADO GEM ]]/Tabla1[[#This Row],[CAUDAL DE TRATAMIENTO]],0) -> 6
A86: =+A85+1 -> 46141 | B86: 29 | C86: 29 (NOCHE) | D86: 85 | E86: FINAL TURNO 3 | F86: 2000 | G86: 4340 | H86: 1850 | I86: =+I85-5 -> 110 | J86: =+J85-5 -> 125 | K86: 17985 | L86: =(K87-K86)*M86 -> 560 | M86: 80 | N86: =F86-F87 -> 190 | O86: =G86-G87 -> 230 | P86: =H86-H87 -> 90 | Q86: =I86-I87 -> 5 | R86: =J86-J87 -> 5 | S86: =(N86*$AC$2) -> 247 | T86: =(O86*$AD$2) -> 304.75 | U86: =(P86*$AE$2) -> 112.5 | V86: =Tabla1[[#This Row],[CONSUMO POL ANIONICO (KG)]] -> 5 | W86: =Tabla1[[#This Row],[CONSUMO POL CATIONICO (KG)]] -> 5 | X86: =(S86*1000)/L86 -> 441.07143 | Y86: =(T86*1000)/L86 -> 544.19643 | Z86: =(U86*1000)/L86 -> 200.89286 | AA86: =(V86*1000)/L86 -> 8.9285714 | AB86: =(W86*1000)/L86 -> 8.9285714 | AC86: 1.3 | AD86: 1.325 | AE86: 1.25 | AF86: 2500 | AG86: 2500 | AH86: 830 | AI86: 2818 | AJ86: 6295 | AK86: 19050 | AL86: 22050 | AM86: =S86*AH86 -> 205010 | AN86: =T86*AI86 -> 858785.5 | AO86: =U86*AJ86 -> 708187.5 | AP86: =V86*AK86 -> 95250 | AQ86: =W86*AL86 -> 110250 | AR86: =SUM(Tabla1[[#This Row],[COSTO OPERATIVO ACIDO]:[COSTO OPERATIVO CATIONICO]]) -> 1977483 | AS86: 3599 | AT86: =AR86/L86 -> 3531.2196 | AU86: =IFERROR(Tabla1[[#This Row],[CAUDAL TOTAL TRATADO GEM ]]/Tabla1[[#This Row],[CAUDAL DE TRATAMIENTO]],0) -> 7
A87: =+A86 -> 46141 | B87: 29 | C87: 30 (MAÑANA) | D87: 86 | E87: FINAL TURNO 1 | F87: 1810 | G87: 4110 | H87: 1760 | I87: =+I86-5 -> 105 | J87: =+J86-5 -> 120 | K87: 17992 | L87: =(K88-K87)*M87 -> 560 | M87: 80 | N87: =F87-F88 -> 10 | O87: =G87-G88 -> 110 | P87: =H87-H88 -> 100 | Q87: =I87-I88 -> 5 | R87: =J87-J88 -> 5 | S87: =(N87*$AC$2) -> 13 | T87: =(O87*$AD$2) -> 145.75 | U87: =(P87*$AE$2) -> 125 | V87: =Tabla1[[#This Row],[CONSUMO POL ANIONICO (KG)]] -> 5 | W87: =Tabla1[[#This Row],[CONSUMO POL CATIONICO (KG)]] -> 5 | X87: =(S87*1000)/L87 -> 23.214286 | Y87: =(T87*1000)/L87 -> 260.26786 | Z87: =(U87*1000)/L87 -> 223.21429 | AA87: =(V87*1000)/L87 -> 8.9285714 | AB87: =(W87*1000)/L87 -> 8.9285714 | AC87: 1.3 | AD87: 1.325 | AE87: 1.25 | AF87: 2500 | AG87: 2500 | AH87: 830 | AI87: 2818 | AJ87: 6295 | AK87: 19050 | AL87: 22050 | AM87: =S87*AH87 -> 10790 | AN87: =T87*AI87 -> 410723.5 | AO87: =U87*AJ87 -> 786875 | AP87: =V87*AK87 -> 95250 | AQ87: =W87*AL87 -> 110250 | AR87: =SUM(Tabla1[[#This Row],[COSTO OPERATIVO ACIDO]:[COSTO OPERATIVO CATIONICO]]) -> 1413888.5 | AS87: 3599 | AT87: =AR87/L87 -> 2524.8009 | AU87: =IFERROR(Tabla1[[#This Row],[CAUDAL TOTAL TRATADO GEM ]]/Tabla1[[#This Row],[CAUDAL DE TRATAMIENTO]],0) -> 7
A88: =+A87 -> 46141 | B88: 29 | C88: 3(TARDE) | D88: 87 | E88: FINAL TURNO 2 | F88: 1800 | G88: 4000 | H88: 1660 | I88: =+I87-5 -> 100 | J88: =+J87-5 -> 115 | K88: 17999 | L88: =(K89-K88)*M88 -> 560 | M88: 80 | N88: =F88-F89 -> 60 | O88: =G88-G89 -> 190 | P88: =H88-H89 -> 60 | Q88: =I88-I89 -> 5 | R88: =J88-J89 -> 5 | S88: =(N88*$AC$2) -> 78 | T88: =(O88*$AD$2) -> 251.75 | U88: =(P88*$AE$2) -> 75 | V88: =Tabla1[[#This Row],[CONSUMO POL ANIONICO (KG)]] -> 5 | W88: =Tabla1[[#This Row],[CONSUMO POL CATIONICO (KG)]] -> 5 | X88: =(S88*1000)/L88 -> 139.28571 | Y88: =(T88*1000)/L88 -> 449.55357 | Z88: =(U88*1000)/L88 -> 133.92857 | AA88: =(V88*1000)/L88 -> 8.9285714 | AB88: =(W88*1000)/L88 -> 8.9285714 | AC88: 1.3 | AD88: 1.325 | AE88: 1.25 | AF88: 2500 | AG88: 2500 | AH88: 830 | AI88: 2818 | AJ88: 6295 | AK88: 19050 | AL88: 22050 | AM88: =S88*AH88 -> 64740 | AN88: =T88*AI88 -> 709431.5 | AO88: =U88*AJ88 -> 472125 | AP88: =V88*AK88 -> 95250 | AQ88: =W88*AL88 -> 110250 | AR88: =SUM(Tabla1[[#This Row],[COSTO OPERATIVO ACIDO]:[COSTO OPERATIVO CATIONICO]]) -> 1451796.5 | AS88: 3599 | AT88: =AR88/L88 -> 2592.4938 | AU88: =IFERROR(Tabla1[[#This Row],[CAUDAL TOTAL TRATADO GEM ]]/Tabla1[[#This Row],[CAUDAL DE TRATAMIENTO]],0) -> 7
A89: =+A88+1 -> 46142 | B89: 30 | C89: 30 (NOCHE) | D89: 88 | E89: FINAL TURNO 3 | F89: 1740 | G89: 3810 | H89: 1600 | I89: =+I88-5 -> 95 | J89: =+J88-5 -> 110 | K89: 18006 | L89: =(K90-K89)*M89 -> 560 | M89: 80 | N89: =F89-F90 -> 130 | O89: =G89-G90-100 -> 200 | P89: =H89-H90 -> 50 | Q89: =I89-I90 -> 5 | R89: =J89-J90 -> 5 | S89: =(N89*$AC$2) -> 169 | T89: =(O89*$AD$2) -> 265 | U89: =(P89*$AE$2) -> 62.5 | V89: =Tabla1[[#This Row],[CONSUMO POL ANIONICO (KG)]] -> 5 | W89: =Tabla1[[#This Row],[CONSUMO POL CATIONICO (KG)]] -> 5 | X89: =(S89*1000)/L89 -> 301.78571 | Y89: =(T89*1000)/L89 -> 473.21429 | Z89: =(U89*1000)/L89 -> 111.60714 | AA89: =(V89*1000)/L89 -> 8.9285714 | AB89: =(W89*1000)/L89 -> 8.9285714 | AC89: 1.3 | AD89: 1.325 | AE89: 1.25 | AF89: 2500 | AG89: 2500 | AH89: 830 | AI89: 2818 | AJ89: 6295 | AK89: 19050 | AL89: 22050 | AM89: =S89*AH89 -> 140270 | AN89: =T89*AI89 -> 746770 | AO89: =U89*AJ89 -> 393437.5 | AP89: =V89*AK89 -> 95250 | AQ89: =W89*AL89 -> 110250 | AR89: =SUM(Tabla1[[#This Row],[COSTO OPERATIVO ACIDO]:[COSTO OPERATIVO CATIONICO]]) -> 1485977.5 | AS89: 3599 | AT89: =AR89/L89 -> 2653.5312 | AU89: =IFERROR(Tabla1[[#This Row],[CAUDAL TOTAL TRATADO GEM ]]/Tabla1[[#This Row],[CAUDAL DE TRATAMIENTO]],0) -> 7
A90: =+A89 -> 46142 | B90: 30 | C90: 31 (MAÑANA) | D90: 89 | E90: FINAL TURNO 1 | F90: 1610 | G90: 3510 | H90: 1550 | I90: =+I89-5 -> 90 | J90: =+J89-5 -> 105 | K90: 18013 | L90: =(K91-K90)*M90 -> 560 | M90: 80 | N90: =F90-F91 -> 130 | O90: =G90-G91 -> 210 | P90: =H90-H91 -> 50 | Q90: =I90-I91 -> 5 | R90: =J90-J91 -> 5 | S90: =(N90*$AC$2) -> 169 | T90: =(O90*$AD$2) -> 278.25 | U90: =(P90*$AE$2) -> 62.5 | V90: =Tabla1[[#This Row],[CONSUMO POL ANIONICO (KG)]] -> 5 | W90: =Tabla1[[#This Row],[CONSUMO POL CATIONICO (KG)]] -> 5 | X90: =(S90*1000)/L90 -> 301.78571 | Y90: =(T90*1000)/L90 -> 496.875 | Z90: =(U90*1000)/L90 -> 111.60714 | AA90: =(V90*1000)/L90 -> 8.9285714 | AB90: =(W90*1000)/L90 -> 8.9285714 | AC90: 1.3 | AD90: 1.325 | AE90: 1.25 | AF90: 2500 | AG90: 2500 | AH90: 830 | AI90: 2818 | AJ90: 6295 | AK90: 19050 | AL90: 22050 | AM90: =S90*AH90 -> 140270 | AN90: =T90*AI90 -> 784108.5 | AO90: =U90*AJ90 -> 393437.5 | AP90: =V90*AK90 -> 95250 | AQ90: =W90*AL90 -> 110250 | AR90: =SUM(Tabla1[[#This Row],[COSTO OPERATIVO ACIDO]:[COSTO OPERATIVO CATIONICO]]) -> 1523316 | AS90: 3599 | AT90: =AR90/L90 -> 2720.2071 | AU90: =IFERROR(Tabla1[[#This Row],[CAUDAL TOTAL TRATADO GEM ]]/Tabla1[[#This Row],[CAUDAL DE TRATAMIENTO]],0) -> 7
A91: =+A90 -> 46142 | B91: 30 | C91: 3(TARDE) | D91: 90 | E91: FINAL TURNO 2 | F91: 1480 | G91: 3300 | H91: 1500 | I91: =+I90-5 -> 85 | J91: =+J90-5 -> 100 | K91: 18020 | L91: =(K92-K91)*M91 -> 400 | M91: 80 | N91: =F91-F92 -> 80 | O91: =G91-G92 -> 120 | P91: =H91-H92 -> 60 | Q91: =I91-I92 -> 5 | R91: =J91-J92 -> 5 | S91: =(N91*$AC$2) -> 104 | T91: =(O91*$AD$2) -> 159 | U91: =(P91*$AE$2) -> 75 | V91: =Tabla1[[#This Row],[CONSUMO POL ANIONICO (KG)]] -> 5 | W91: =Tabla1[[#This Row],[CONSUMO POL CATIONICO (KG)]] -> 5 | X91: =(S91*1000)/L91 -> 260 | Y91: =(T91*1000)/L91 -> 397.5 | Z91: =(U91*1000)/L91 -> 187.5 | AA91: =(V91*1000)/L91 -> 12.5 | AB91: =(W91*1000)/L91 -> 12.5 | AC91: 1.3 | AD91: 1.325 | AE91: 1.25 | AF91: 2500 | AG91: 2500 | AH91: 830 | AI91: 2818 | AJ91: 6295 | AK91: 19050 | AL91: 22050 | AM91: =S91*AH91 -> 86320 | AN91: =T91*AI91 -> 448062 | AO91: =U91*AJ91 -> 472125 | AP91: =V91*AK91 -> 95250 | AQ91: =W91*AL91 -> 110250 | AR91: =SUM(Tabla1[[#This Row],[COSTO OPERATIVO ACIDO]:[COSTO OPERATIVO CATIONICO]]) -> 1212007 | AS91: 3599 | AT91: =AR91/L91 -> 3030.0175 | AU91: =IFERROR(Tabla1[[#This Row],[CAUDAL TOTAL TRATADO GEM ]]/Tabla1[[#This Row],[CAUDAL DE TRATAMIENTO]],0) -> 5
A92: =+A91+1 -> 46143 | B92: 31 | C92: 31 (NOCHE) | D92: 91 | E92: FINAL TURNO 3 | F92: 1400 | G92: 3180 | H92: 1440 | I92: =+I91-5 -> 80 | J92: =+J91-5 -> 95 | K92: 18025 | L92: =(K93-K92)*M92 -> -1442000 | M92: 80 | N92: =F92-F93 -> 1400 | O92: =G92-G93 -> 3180 | P92: =H92-H93 -> 1440 | Q92: =I92-I93 -> 80 | R92: =J92-J93 -> 95 | S92: =(N92*$AC$2) -> 1820 | T92: =(O92*$AD$2) -> 4213.5 | U92: =(P92*$AE$2) -> 1800 | V92: =Tabla1[[#This Row],[CONSUMO POL ANIONICO (KG)]] -> 80 | W92: =Tabla1[[#This Row],[CONSUMO POL CATIONICO (KG)]] -> 95 | X92: =(S92*1000)/L92 -> -1.2621359 | Y92: =(T92*1000)/L92 -> -2.9219834 | Z92: =(U92*1000)/L92 -> -1.2482663 | AA92: =(V92*1000)/L92 -> -0.055478502 | AB92: =(W92*1000)/L92 -> -0.065880721 | AC92: 1.3 | AD92: 1.325 | AE92: 1.25 | AF92: 2500 | AG92: 2500 | AH92: 830 | AI92: 2818 | AJ92: 6295 | AK92: 19050 | AL92: 22050 | AM92: =S92*AH92 -> 1510600 | AN92: =T92*AI92 -> 11873643 | AO92: =U92*AJ92 -> 11331000 | AP92: =V92*AK92 -> 1524000 | AQ92: =W92*AL92 -> 2094750 | AR92: =SUM(Tabla1[[#This Row],[COSTO OPERATIVO ACIDO]:[COSTO OPERATIVO CATIONICO]]) -> 28333993 | AS92: 3599 | AT92: =AR92/L92 -> -19.649094 | AU92: =IFERROR(Tabla1[[#This Row],[CAUDAL TOTAL TRATADO GEM ]]/Tabla1[[#This Row],[CAUDAL DE TRATAMIENTO]],0) -> -18025
A93: =+A92 -> 46143 | B93: 31 | C93: 32 (MAÑANA) | D93: 92 | E93: FINAL TURNO 1 | L93: =(K94-K93)*M93 -> 0 | M93: 80 | N93: =F93-F94 -> 0 | O93: =G93-G94 -> 0 | P93: =H93-H94 -> 0 | Q93: =I93-I94 -> 0 | R93: =J93-J94 -> 0 | S93: =(N93*$AC$2) -> 0 | T93: =(O93*$AD$2) -> 0 | U93: =(P93*$AE$2) -> 0 | V93: =Tabla1[[#This Row],[CONSUMO POL ANIONICO (KG)]] -> 0 | W93: =Tabla1[[#This Row],[CONSUMO POL CATIONICO (KG)]] -> 0 | X93: =(S93*1000)/L93 -> #DIV/0! | Y93: =(T93*1000)/L93 -> #DIV/0! | Z93: =(U93*1000)/L93 -> #DIV/0! | AA93: =(V93*1000)/L93 -> #DIV/0! | AB93: =(W93*1000)/L93 -> #DIV/0! | AC93: 1.3 | AD93: 1.325 | AE93: 1.25 | AF93: 2500 | AG93: 2500 | AH93: 830 | AI93: 2818 | AJ93: 6295 | AK93: 19050 | AL93: 22050 | AM93: =S93*AH93 -> 0 | AN93: =T93*AI93 -> 0 | AO93: =U93*AJ93 -> 0 | AP93: =V93*AK93 -> 0 | AQ93: =W93*AL93 -> 0 | AR93: =SUM(Tabla1[[#This Row],[COSTO OPERATIVO ACIDO]:[COSTO OPERATIVO CATIONICO]]) -> 0 | AS93: 3599 | AT93: =AR93/L93 -> #DIV/0! | AU93: =IFERROR(Tabla1[[#This Row],[CAUDAL TOTAL TRATADO GEM ]]/Tabla1[[#This Row],[CAUDAL DE TRATAMIENTO]],0) -> 0
A94: =+A93 -> 46143 | B94: 31 | C94: 3(TARDE) | D94: 93 | E94: FINAL TURNO 2 | L94: =(K95-K94)*M94 -> 0 | M94: 80 | N94: =F94-F95 -> 0 | O94: =G94-G95 -> 0 | P94: =H94-H95 -> 0 | Q94: =I94-I95 -> 0 | R94: =J94-J95 -> 0 | S94: =(N94*$AC$2) -> 0 | T94: =(O94*$AD$2) -> 0 | U94: =(P94*$AE$2) -> 0 | V94: =Tabla1[[#This Row],[CONSUMO POL ANIONICO (KG)]] -> 0 | W94: =Tabla1[[#This Row],[CONSUMO POL CATIONICO (KG)]] -> 0 | X94: =(S94*1000)/L94 -> #DIV/0! | Y94: =(T94*1000)/L94 -> #DIV/0! | Z94: =(U94*1000)/L94 -> #DIV/0! | AA94: =(V94*1000)/L94 -> #DIV/0! | AB94: =(W94*1000)/L94 -> #DIV/0! | AC94: 1.3 | AD94: 1.325 | AE94: 1.25 | AF94: 2500 | AG94: 2500 | AH94: 830 | AI94: 2818 | AJ94: 6295 | AK94: 19050 | AL94: 22050 | AM94: =S94*AH94 -> 0 | AN94: =T94*AI94 -> 0 | AO94: =U94*AJ94 -> 0 | AP94: =V94*AK94 -> 0 | AQ94: =W94*AL94 -> 0 | AR94: =SUM(Tabla1[[#This Row],[COSTO OPERATIVO ACIDO]:[COSTO OPERATIVO CATIONICO]]) -> 0 | AS94: 3599 | AT94: =AR94/L94 -> #DIV/0! | AU94: =IFERROR(Tabla1[[#This Row],[CAUDAL TOTAL TRATADO GEM ]]/Tabla1[[#This Row],[CAUDAL DE TRATAMIENTO]],0) -> 0
L95: =(K96-K95)*M95 -> 0 | N95: =F95-F96 -> 0 | Q95: =I95-I96 -> 0 | S95: =(N95*$AC$2) -> 0 | T95: =(O95*$AD$2) -> 0 | U95: =(P95*$AE$2) -> 0 | V95: =Tabla1[[#This Row],[CONSUMO POL ANIONICO (KG)]] -> 0 | W95: =Tabla1[[#This Row],[CONSUMO POL CATIONICO (KG)]] -> 0 | X95: =(S95*1000)/L95 -> #DIV/0! | Y95: =(T95*1000)/L95 -> #DIV/0! | Z95: =(U95*1000)/L95 -> #DIV/0! | AA95: =(V95*1000)/L95 -> #DIV/0! | AB95: =(W95*1000)/L95 -> #DIV/0! | AM95: =S95*AH95 -> 0 | AN95: =T95*AI95 -> 0 | AO95: =U95*AJ95 -> 0 | AP95: =V95*AK95 -> 0 | AQ95: =W95*AL95 -> 0 | AR95: =SUM(Tabla1[[#This Row],[COSTO OPERATIVO ACIDO]:[COSTO OPERATIVO CATIONICO]]) -> 0 | AT95: =AR95/L95 -> #DIV/0! | AU95: =IFERROR(Tabla1[[#This Row],[CAUDAL TOTAL TRATADO GEM ]]/Tabla1[[#This Row],[CAUDAL DE TRATAMIENTO]],0) -> 0
L96: =(K97-K96)*M96 -> 0 | N96: =F96-F97 -> -2160 | Q96: =I96-I97 -> -205 | S96: =(N96*$AC$2) -> -2808 | T96: =(O96*$AD$2) -> 0 | U96: =(P96*$AE$2) -> 0 | V96: =Tabla1[[#This Row],[CONSUMO POL ANIONICO (KG)]] -> -205 | W96: =Tabla1[[#This Row],[CONSUMO POL CATIONICO (KG)]] -> 0 | X96: =(S96*1000)/L96 -> #DIV/0! | Y96: =(T96*1000)/L96 -> #DIV/0! | Z96: =(U96*1000)/L96 -> #DIV/0! | AA96: =(V96*1000)/L96 -> #DIV/0! | AB96: =(W96*1000)/L96 -> #DIV/0! | AM96: =S96*AH96 -> 0 | AN96: =T96*AI96 -> 0 | AO96: =U96*AJ96 -> 0 | AP96: =V96*AK96 -> 0 | AQ96: =W96*AL96 -> 0 | AR96: =SUM(Tabla1[[#This Row],[COSTO OPERATIVO ACIDO]:[COSTO OPERATIVO CATIONICO]]) -> 0 | AT96: =AR96/L96 -> #DIV/0! | AU96: =IFERROR(Tabla1[[#This Row],[CAUDAL TOTAL TRATADO GEM ]]/Tabla1[[#This Row],[CAUDAL DE TRATAMIENTO]],0) -> 0
F97: 2.160 | G97: 2.100 | H97: 1.670 | I97: 205 | J97: 105 | M97: 80 | AM97: =S97*AH97 -> 0 | AN97: =T97*AI97 -> 0 | AO97: =U97*AJ97 -> 0 | AP97: =V97*AK97 -> 0 | AQ97: =W97*AL97 -> 0 | AS97: =SUM(AS2:AS37) -> 129564
L98: =+SUM(L2:L13) -> 880 | N98: =+SUM(N2:N44) -> 2380 | O98: =+SUM(O2:O44) -> 3380 | P98: =+SUM(P2:P44) -> 1130 | Q98: =+SUM(Q2:Q44) -> 65 | R98: =+SUM(R2:R44) -> 130 | S98: =+SUM(S2:S93) -> 11141 | T98: =+SUM(T2:T93) -> 17238.25 | U98: =+SUM(U2:U93) -> 6600 | V98: =+SUM(V2:V93) -> 275 | W98: =+SUM(W2:W93) -> 450 | AN98: =+SUM(AN2:AN96) -> 48577388 | AO98: =+SUM(AO2:AO96) -> 41547000 | AP98: =+SUM(AP2:AP96) -> 5238750 | AQ98: =+SUM(AQ2:AQ96) -> 9922500 | AR98: =+SUM(AR2:AR96) -> 1.1453267e+08
L99: =+SUM(L2:L13) -> 880 | P99: =+MEDIAN(P2:P78)+2000 -> 2030 | AS99: =+SUM(AS2:AS13) -> 43188
N100: =+N98*1.3 -> 3094 | O100: =+O98*1.325 -> 4478.5 | P100: =+P98*1.25 -> 1412.5 | AR100: =+SUM(AR2:AR46) -> 29990193
...

Sheet DB QUIMICA
A1: CONSUMO DE QUIMICO | AJ1: TABLA GRAFICA 2. COSTO CONSUMO QUIMICO VS $M3 | AT1: TABLA GRAFICA 3. RO COSTO CONSUMO QUIMICO VS $M3
A2: GEM | B2: COSTO TTO - CAUDAL TRATADP GEM Vs $M3
Z4: CONSOLIDADO COSTO TTO - CAUDAL TRATADP GEM Vs $M3 | AJ4: DIA | AK4: CAUDAL TOTAL TRATADO GEM | AL4: INDICADOR $m3 | AM4: 2025 $m3 GEM | AP4: DIA | AQ4: VOLUMEN TRATADO GEM (m3) | AR4: HORAS DE OPERACIÓN | AT4: DÍA | AU4: VOLUMEN ENVIADO A RO (m3) | AV4: LIMITE INDICADOR M3 | AW4: INDICADOR $m3 RO | AY4: Etiquetas de fila | AZ4: VOLUMEN ENVIADO A RO (m3) | BA4: TIEMPO DE OPERACIÓN | BC4: Etiquetas de fila | BD4: VOLUMEN ENVIADO A RO (m3) | BE4: TIEMPO DE OPERACIÓN | BF4: COSTO QUIMICA | BH4: DIA | BI4: VOLUMEN TRATADO GEM (m3) | BJ4: COSTO QUIMICA GEM
AJ5: 1 | AK5: 0 | AL5: 0 | AM5: 3599 | AP5: 1 | AQ5: 0 | AR5: 0 | AT5: 1 | AU5: 0 | AV5: 1000 | AW5: 0 | AY5: 1 | AZ5: 0 | BA5: #DIV/0! | BC5: 1 | BD5: 0 | BE5: #DIV/0! | BF5: 0 | BH5: 1 | BI5: 0 | BJ5: 0
Z6: PANORAMA OPERATIVO GEM | AJ6: 2 | AK6: 880 | AL6: 2001.6699 | AM6: 3599 | AP6: 2 | AQ6: 880 | AR6: 11 | AT6: 2 | AU6: 0 | AV6: 1000 | AW6: 0 | AY6: 2 | AZ6: 0 | BA6: #DIV/0! | BC6: 2 | BD6: 0 | BE6: #DIV/0! | BF6: 0 | BH6: 2 | BI6: 880 | BJ6: 1761469.5
Z7: VOLUMEN TRATADO GEM (m3) | AA7: $m3 | AB7: HORAS | AC7: $ HORA DE TRATAMIENTO GEM | AD7: $ CONSOLIDADO | AJ7: 3 | AK7: 0 | AL7: 0 | AM7: 3599 | AP7: 3 | AQ7: 0 | AR7: 0 | AT7: 3 | AU7: 0 | AV7: 1000 | AW7: 0 | AY7: 3 | AZ7: 0 | BA7: #DIV/0! | BC7: 3 | BD7: 0 | BE7: #DIV/0! | BF7: 0 | BH7: 3 | BI7: 0 | BJ7: 0
Z8: =GETPIVOTDATA(" CAUDAL TOTAL TRATADO GEM ",$AJ$4) -> 32414 | AA8: =AD8/Z8 -> 2659.3039 | AB8: =Z8/80 -> 405.175 | AC8: =AD8/AB8 -> 212744.31 | AD8: =GETPIVOTDATA("COSTO QUIMICA GEM",$BH$4) -> 86198676 | AJ8: 4 | AK8: 0 | AL8: 0 | AM8: 3599 | AP8: 4 | AQ8: 0 | AR8: 0 | AT8: 4 | AU8: 0 | AV8: 1000 | AW8: 0 | AY8: 4 | AZ8: 0 | BA8: #DIV/0! | BC8: 4 | BD8: 0 | BE8: #DIV/0! | BF8: 0 | BH8: 4 | BI8: 0 | BJ8: 0
AJ9: 5 | AK9: 0 | AL9: 0 | AM9: 3599 | AP9: 5 | AQ9: 0 | AR9: 0 | AT9: 5 | AU9: 0 | AV9: 1000 | AW9: 0 | AY9: 5 | AZ9: 0 | BA9: #DIV/0! | BC9: 5 | BD9: 0 | BE9: #DIV/0! | BF9: 0 | BH9: 5 | BI9: 0 | BJ9: 0
AJ10: 6 | AK10: 1040 | AL10: 2638.6712 | AM10: 3599 | AP10: 6 | AQ10: 1040 | AR10: 13 | AT10: 6 | AU10: 388.574 | AV10: 1000 | AW10: 105 | AY10: 6 | AZ10: 388.574 | BA10: 9.3115389 | BC10: 6 | BD10: 388.574 | BE10: 9.3115389 | BF10: 40800.27 | BH10: 6 | BI10: 1040 | BJ10: 2744218
AJ11: 7 | AK11: 1079 | AL11: 2771.1464 | AM11: 3599 | AP11: 7 | AQ11: 1079 | AR11: 13 | AT11: 7 | AU11: 983.598 | AV11: 1000 | AW11: 105 | AY11: 7 | AZ11: 983.598 | BA11: 24.578781 | BC11: 7 | BD11: 983.598 | BE11: 24.578781 | BF11: 103277.79 | BH11: 7 | BI11: 1079 | BJ11: 2990067
AJ12: 8 | AK12: 1200 | AL12: 2309.47 | AM12: 3599 | AP12: 8 | AQ12: 1200 | AR12: 15 | AT12: 8 | AU12: 892.843 | AV12: 1000 | AW12: 105 | AY12: 8 | AZ12: 892.843 | BA12: 23.008721 | BC12: 8 | BD12: 892.843 | BE12: 23.008721 | BF12: 93748.515 | BH12: 8 | BI12: 1200 | BJ12: 2771364
AJ13: 9 | AK13: 1280 | AL13: 1812.6102 | AM13: 3599 | AP13: 9 | AQ13: 1280 | AR13: 16 | AT13: 9 | AU13: 825.066 | AV13: 1000 | AW13: 105 | AY13: 9 | AZ13: 825.066 | BA13: 20.789156 | BC13: 9 | BD13: 825.066 | BE13: 20.789156 | BF13: 86631.93 | BH13: 9 | BI13: 1280 | BJ13: 2320141
AJ14: 10 | AK14: 1520 | AL14: 2241.3763 | AM14: 3599 | AP14: 10 | AQ14: 1520 | AR14: 19 | AT14: 10 | AU14: 863.92 | AV14: 1000 | AW14: 105 | AY14: 10 | AZ14: 863.92 | BA14: 22.351823 | BC14: 10 | BD14: 863.92 | BE14: 22.351823 | BF14: 90711.6 | BH14: 10 | BI14: 1520 | BJ14: 3406892
AJ15: 11 | AK15: 1040 | AL15: 3164.7183 | AM15: 3599 | AP15: 11 | AQ15: 1040 | AR15: 13 | AT15: 11 | AU15: 404.333 | AV15: 1000 | AW15: 105 | AY15: 11 | AZ15: 404.333 | BA15: 10.939228 | BC15: 11 | BD15: 404.333 | BE15: 10.939228 | BF15: 42454.965 | BH15: 11 | BI15: 1040 | BJ15: 3291307
AJ16: 12 | AK16: 0 | AL16: 0 | AM16: 3599 | AP16: 12 | AQ16: 0 | AR16: 0 | AT16: 12 | AU16: 0 | AV16: 1000 | AW16: 0 | AY16: 12 | AZ16: 0 | BA16: 0 | BC16: 12 | BD16: 0 | BE16: 0 | BF16: 0 | BH16: 12 | BI16: 0 | BJ16: 0
AJ17: 13 | AK17: 1360 | AL17: 2363.5055 | AM17: 3599 | AP17: 13 | AQ17: 1360 | AR17: 17 | AT17: 13 | AU17: 402.163 | AV17: 1000 | AW17: 105 | AY17: 13 | AZ17: 402.163 | BA17: 9.8088537 | BC17: 13 | BD17: 402.163 | BE17: 9.8088537 | BF17: 42227.115 | BH17: 13 | BI17: 1360 | BJ17: 3214367.5
AJ18: 14 | AK18: 1280 | AL18: 3136.7926 | AM18: 3599 | AP18: 14 | AQ18: 1280 | AR18: 16 | AT18: 14 | AU18: 897.921 | AV18: 1000 | AW18: 105 | AY18: 14 | AZ18: 897.921 | BA18: 22.13617 | BC18: 14 | BD18: 897.921 | BE18: 22.13617 | BF18: 94281.705 | BH18: 14 | BI18: 1280 | BJ18: 4015094.5
A19: OSMOSIS INVERSA | AJ19: 15 | AK19: 1200 | AL19: 2896.0604 | AM19: 3599 | AP19: 15 | AQ19: 1200 | AR19: 15 | AT19: 15 | AU19: 944.207 | AV19: 1000 | AW19: 105 | AY19: 15 | AZ19: 944.207 | BA19: 21.768512 | BC19: 15 | BD19: 944.207 | BE19: 21.768512 | BF19: 99141.735 | BH19: 15 | BI19: 1200 | BJ19: 3475272.5
AJ20: 16 | AK20: 1600 | AL20: 2646.4334 | AM20: 3599 | AP20: 16 | AQ20: 1600 | AR20: 20 | AT20: 16 | AU20: 987.576 | AV20: 1000 | AW20: 105 | AY20: 16 | AZ20: 987.576 | BA20: 23.532731 | BC20: 16 | BD20: 987.576 | BE20: 23.532731 | BF20: 103695.48 | BH20: 16 | BI20: 1600 | BJ20: 4234293.5
Z21: CONSOLIDADO COSTO TTO - CAUDAL TRATADP RO Vs $M3 | AJ21: 17 | AK21: 1440 | AL21: 3481.7406 | AM21: 3599 | AP21: 17 | AQ21: 1440 | AR21: 18 | AT21: 17 | AU21: 755.365 | AV21: 1000 | AW21: 105 | AY21: 17 | AZ21: 755.365 | BA21: #DIV/0! | BC21: 17 | BD21: 755.365 | BE21: #DIV/0! | BF21: 79313.325 | BH21: 17 | BI21: 1440 | BJ21: 5013706.5
AJ22: 18 | AK22: 1680 | AL22: 3085.6183 | AM22: 3599 | AP22: 18 | AQ22: 1680 | AR22: 21 | AT22: 18 | AU22: 688.209 | AV22: 1000 | AW22: 105 | AY22: 18 | AZ22: 688.209 | BA22: #DIV/0! | BC22: 18 | BD22: 688.209 | BE22: #DIV/0! | BF22: 72261.945 | BH22: 18 | BI22: 1680 | BJ22: 5183838.8
Z23: PANORAMA OPERATIVO RO | AJ23: 19 | AK23: 0 | AL23: 0 | AM23: 3599 | AP23: 19 | AQ23: 0 | AR23: 0 | AT23: 19 | AU23: 0 | AV23: 1000 | AW23: 0 | AY23: 19 | AZ23: 0 | BA23: #DIV/0! | BC23: 19 | BD23: 0 | BE23: #DIV/0! | BF23: 0 | BH23: 19 | BI23: 0 | BJ23: 330750
Z24: TOTAL CAUDAL TRATADO RO | AA24: $m3 | AB24: HORAS | AC24: $ HORA DE TRATAMIENTO RO | AD24: $ CONSOLIDADO | AJ24: 20 | AK24: 1600 | AL24: 2180.9448 | AM24: 3599 | AP24: 20 | AQ24: 1600 | AR24: 20 | AT24: 20 | AU24: 829.347 | AV24: 1000 | AW24: 105 | AY24: 20 | AZ24: 829.347 | BA24: #DIV/0! | BC24: 20 | BD24: 829.347 | BE24: #DIV/0! | BF24: 87081.435 | BH24: 20 | BI24: 1600 | BJ24: 3489511.8
Z25: =+GETPIVOTDATA(" VOLUMEN ENVIADO A RO (m3)",$AT$4) -> 17694.769 | AA25: =+AD25/Z25 -> 105 | AB25: =GETPIVOTDATA("TIEMPO DE OPERACIÓN",$AY$4) -> #DIV/0! | AC25: =AD25/AB25 -> #DIV/0! | AD25: =GETPIVOTDATA("COSTO QUIMICA ",$BC$4) -> 1857950.7 | AJ25: 21 | AK25: 1360 | AL25: 2748.0114 | AM25: 3599 | AP25: 21 | AQ25: 1360 | AR25: 17 | AT25: 21 | AU25: 909.375 | AV25: 1000 | AW25: 105 | AY25: 21 | AZ25: 909.375 | BA25: #DIV/0! | BC25: 21 | BD25: 909.375 | BE25: #DIV/0! | BF25: 95484.375 | BH25: 21 | BI25: 1360 | BJ25: 3737295.5
AJ26: 22 | AK26: 1520 | AL26: 3660.9737 | AM26: 3599 | AP26: 22 | AQ26: 1520 | AR26: 19 | AT26: 22 | AU26: 872.694 | AV26: 1000 | AW26: 105 | AY26: 22 | AZ26: 872.694 | BA26: #DIV/0! | BC26: 22 | BD26: 872.694 | BE26: #DIV/0! | BF26: 91632.87 | BH26: 22 | BI26: 1520 | BJ26: 5564680
AJ27: 23 | AK27: 1495 | AL27: 2341.9923 | AM27: 3599 | AP27: 23 | AQ27: 1495 | AR27: 17 | AT27: 23 | AU27: 839.555 | AV27: 1000 | AW27: 105 | AY27: 23 | AZ27: 839.555 | BA27: #DIV/0! | BC27: 23 | BD27: 839.555 | BE27: #DIV/0! | BF27: 88153.275 | BH27: 23 | BI27: 1495 | BJ27: 3501278.5
AJ28: 24 | AK28: 1360 | AL28: 2116.0265 | AM28: 3599 | AP28: 24 | AQ28: 1360 | AR28: 17 | AT28: 24 | AU28: 825.554 | AV28: 1000 | AW28: 105 | AY28: 24 | AZ28: 825.554 | BA28: #DIV/0! | BC28: 24 | BD28: 825.554 | BE28: #DIV/0! | BF28: 86683.17 | BH28: 24 | BI28: 1360 | BJ28: 2877796
AJ29: 25 | AK29: 1360 | AL29: 2486.9143 | AM29: 3599 | AP29: 25 | AQ29: 1360 | AR29: 17 | AT29: 25 | AU29: 622.582 | AV29: 1000 | AW29: 105 | AY29: 25 | AZ29: 622.582 | BA29: #DIV/0! | BC29: 25 | BD29: 622.582 | BE29: #DIV/0! | BF29: 65371.11 | BH29: 25 | BI29: 1360 | BJ29: 3382203.5
AJ30: 26 | AK30: 800 | AL30: 1466.7094 | AM30: 3599 | AP30: 26 | AQ30: 800 | AR30: 10 | AT30: 26 | AU30: 125.733 | AV30: 1000 | AW30: 105 | AY30: 26 | AZ30: 125.733 | BA30: #DIV/0! | BC30: 26 | BD30: 125.733 | BE30: #DIV/0! | BF30: 13201.965 | BH30: 26 | BI30: 800 | BJ30: 1173367.5
AJ31: 27 | AK31: 1520 | AL31: 2624.4664 | AM31: 3599 | AP31: 27 | AQ31: 1520 | AR31: 19 | AT31: 27 | AU31: 940.945 | AV31: 1000 | AW31: 105 | AY31: 27 | AZ31: 940.945 | BA31: #DIV/0! | BC31: 27 | BD31: 940.945 | BE31: #DIV/0! | BF31: 98799.225 | BH31: 27 | BI31: 1520 | BJ31: 3989189
AJ32: 28 | AK32: 1600 | AL32: 2916.3147 | AM32: 3599 | AP32: 28 | AQ32: 1600 | AR32: 20 | AT32: 28 | AU32: 940.332 | AV32: 1000 | AW32: 105 | AY32: 28 | AZ32: 940.332 | BA32: #DIV/0! | BC32: 28 | BD32: 940.332 | BE32: #DIV/0! | BF32: 98734.86 | BH32: 28 | BI32: 1600 | BJ32: 4666103.5
AJ33: 29 | AK33: 1680 | AL33: 2882.8381 | AM33: 3599 | AP33: 29 | AQ33: 1680 | AR33: 21 | AT33: 29 | AU33: 1045.816 | AV33: 1000 | AW33: 105 | AY33: 29 | AZ33: 1045.816 | BA33: #DIV/0! | BC33: 29 | BD33: 1045.816 | BE33: #DIV/0! | BF33: 109810.68 | BH33: 29 | BI33: 1680 | BJ33: 4843168
AJ34: 30 | AK34: 1520 | AL34: 2777.1714 | AM34: 3599 | AP34: 30 | AQ34: 1520 | AR34: 19 | AT34: 30 | AU34: 709.061 | AV34: 1000 | AW34: 105 | AY34: 30 | AZ34: 709.061 | BA34: #DIV/0! | BC34: 30 | BD34: 709.061 | BE34: #DIV/0! | BF34: 74451.405 | BH34: 30 | BI34: 1520 | BJ34: 4221300.5
AJ35: Total general | AK35: 32414 | AL35: 2659.3039 | AM35: 3599 | AP35: Total general | AQ35: 32414 | AR35: 403 | AT35: Total general | AU35: 17694.769 | AV35: 1000 | AW35: 105 | AY35: Total general | AZ35: 17694.769 | BA35: #DIV/0! | BC35: Total general | BD35: 17694.769 | BE35: #DIV/0! | BF35: 1857950.7 | BH35: Total general | BI35: 32414 | BJ35: 86198676

Sheet GRAFICAS
V1: FECHA | W1: (Varios elementos) | AD1: FECHA | AE1: (Varios elementos) | AL1: FECHA | AM1: (Varios elementos) | AV1: PRECIO (KG) ACIDO | AW1: PRECIO (KG) COAGULANTE | AX1: PRECIO (KG) DECOLORANTE | AY1: PRECIO (KG) ANIONICO | AZ1: PRECIO (KG) CATIONICO
AV2: 830 | AW2: 2900 | AX2: 6295 | AY2: 19050 | AZ2: 22050
V3: DIA | W3: COF 494 - PPM POL CATIONICO | X3: COF 440 - PPM POL ANIONICO | Y3: COF 280 - PPM ACIDO | Z3: COF 235 - PPM COAGULANTE | AA3: COF 255 - PPM DECOLORANTE | AB3: INDICADOR $m3 | AD3: DIA | AE3: CONSUMO POL CATIONICO (KG) | AF3: CONSUMO POL ANIONICO (KG) | AG3: CONSUMO LITROS ACIDO (L) | AH3: CONSUMO LITROS COAGULANTE (L) | AI3: CONSUMO LITROS DECOLORANTE (L) | AJ3: INDICADOR $m3 | AL3: DIA | AM3: KG POL CATIONICO | AN3: KG POL ANIONICO | AO3: KG ACIDO | AP3: KG COAGULANTE | AQ3: KG DECOLORANTE | AR3: INDICADOR $m3 | AT3: DIA | AU3: INDICADOR $m3 | AV3: INDICADOR $ACIDO/M3 | AW3: INDICADOR $COAGULANTE/M3 | AX3: INDICADOR $DECOLORANTE/M3 | AY3: INDICADOR $POL ANIONICO/ M3 | AZ3: INDICADOR $POL CATIONICO / M3
P4: COF 255 - DECOLORANTE | V4: 1 | W4: 0 | X4: 0 | Y4: 0 | Z4: 0 | AA4: 0 | AB4: 0 | AD4: 1 | AE4: 0 | AF4: 0 | AG4: 0 | AH4: 0 | AI4: 0 | AJ4: 0 | AL4: 1 | AM4: 0 | AN4: 0 | AO4: 0 | AP4: 0 | AQ4: 0 | AR4: 0 | AT4: 1 | AU4: 0 | AV4: 0 | AW4: 0 | AX4: 0 | AY4: 0 | AZ4: 0
Q5: PPM | R5: L/DIA | S5: KG/DIA | T5: $ | V5: 2 | W5: 2.8409091 | X5: 2.8409091 | Y5: 204.54545 | Z5: 136.36364 | AA5: 102.27273 | AB5: 2001.6699 | AD5: 2 | AE5: 10 | AF5: 10 | AG5: 180 | AH5: 120 | AI5: 90 | AJ5: 2001.6699 | AL5: 2 | AM5: 10 | AN5: 10 | AO5: 234 | AP5: 159 | AQ5: 112.5 | AR5: 2001.6699 | AT5: 2 | AU5: 2001.6699 | AV5: 220.70455 | AW5: 509.16136 | AX5: 804.75852 | AY5: 216.47727 | AZ5: 250.56818
P6: MINIMO | Q6: =_xlfn.MINIFS(AA4:AA30,AA4:AA30,"<>0") -> 37.5 | R6: =_xlfn.MINIFS(AI4:AI30,AI4:AI30,"<>0") -> 30 | S6: =_xlfn.MINIFS(AQ4:AQ30,AQ4:AQ30,"<>0") -> 37.5 | T6: =_xlfn.MINIFS(AX4:AX30,AX4:AX30,"<>0") -> 295.07812 | V6: 3 | W6: 0 | X6: 0 | Y6: 0 | Z6: 0 | AA6: 0 | AB6: 0 | AD6: 3 | AE6: 0 | AF6: 0 | AG6: 0 | AH6: 0 | AI6: 0 | AJ6: 0 | AL6: 3 | AM6: 0 | AN6: 0 | AO6: 0 | AP6: 0 | AQ6: 0 | AR6: 0 | AT6: 3 | AU6: 0 | AV6: 0 | AW6: 0 | AX6: 0 | AY6: 0 | AZ6: 0
P7: MAXIMO | Q7: =MAX(AA4:AA30) -> 190.78947 | R7: =MAX(AI4:AI30) -> 305 | S7: =MAX(AQ4:AQ30) -> 381.25 | T7: =MAX(AX4:AX30) -> 1501.2747 | V7: 4 | W7: 0 | X7: 0 | Y7: 0 | Z7: 0 | AA7: 0 | AB7: 0 | AD7: 4 | AE7: 0 | AF7: 0 | AG7: 0 | AH7: 0 | AI7: 0 | AJ7: 0 | AL7: 4 | AM7: 0 | AN7: 0 | AO7: 0 | AP7: 0 | AQ7: 0 | AR7: 0 | AT7: 4 | AU7: 0 | AV7: 0 | AW7: 0 | AX7: 0 | AY7: 0 | AZ7: 0
P8: PROMEDIO | Q8: =AVERAGEIF(AA4:AA30,"<>0") -> 114.80291 | R8: =AVERAGEIF(AI4:AI30,"<>0") -> 154.7619 | S8: =AVERAGEIF(AQ4:AQ30,"<>0") -> 193.45238 | T8: =AVERAGEIF(AX4:AX30,"<>0") -> 903.3554 | V8: 5 | W8: 0 | X8: 0 | Y8: 0 | Z8: 0 | AA8: 0 | AB8: 0 | AD8: 5 | AE8: 0 | AF8: 0 | AG8: 0 | AH8: 0 | AI8: 0 | AJ8: 0 | AL8: 5 | AM8: 0 | AN8: 0 | AO8: 0 | AP8: 0 | AQ8: 0 | AR8: 0 | AT8: 5 | AU8: 0 | AV8: 0 | AW8: 0 | AX8: 0 | AY8: 0 | AZ8: 0
P9: TOTAL CONSUMIDO | R9: =GETPIVOTDATA("CONSUMO LITROS DECOLORANTE (L) ",$AD$3) -> 3840 | S9: =GETPIVOTDATA("KG DECOLORANTE ",$AL$3) -> 4800 | T9: =S9*AX2 -> 30216000 | V9: 6 | W9: 3.6057692 | X9: 1.2019231 | Y9: 144.23077 | Z9: 413.46154 | AA9: 67.307692 | AB9: 2638.6712 | AD9: 6 | AE9: 15 | AF9: 5 | AG9: 150 | AH9: 430 | AI9: 70 | AJ9: 2638.6712 | AL9: 6 | AM9: 15 | AN9: 5 | AO9: 195 | AP9: 569.75 | AQ9: 87.5 | AR9: 2638.6712 | AT9: 6 | AU9: 2638.6712 | AV9: 155.625 | AW9: 1543.8034 | AX9: 529.6274 | AY9: 91.586538 | AZ9: 318.02885
P10: PROYECCIÓN Kg/M3 | S10: 0.23755146 | T10: 1495.4 | V10: 7 | W10: 2.3169601 | X10: 1.1584801 | Y10: 139.01761 | Z10: 389.2493 | AA10: 111.21409 | AB10: 2771.1464 | AD10: 7 | AE10: 10 | AF10: 5 | AG10: 150 | AH10: 420 | AI10: 120 | AJ10: 2771.1464 | AL10: 7 | AM10: 10 | AN10: 5 | AO10: 195 | AP10: 556.5 | AQ10: 150 | AR10: 2771.1464 | AT10: 7 | AU10: 2771.1464 | AV10: 150 | AW10: 1453.3985 | AX10: 875.11585 | AY10: 88.276182 | AZ10: 204.35589
P11: REAL Kg/ M3 | S11: =S9/F82 -> 0.14808416 | T11: =T9/F82 -> 932.18979 | V11: 8 | W11: 2.0833333 | X11: 1.0416667 | Y11: 308.33333 | Z11: 283.33333 | AA11: 83.333333 | AB11: 2309.47 | AD11: 8 | AE11: 10 | AF11: 5 | AG11: 370 | AH11: 340 | AI11: 100 | AJ11: 2309.47 | AL11: 8 | AM11: 10 | AN11: 5 | AO11: 481 | AP11: 450.5 | AQ11: 125 | AR11: 2309.47 | AT11: 8 | AU11: 2309.47 | AV11: 332.69167 | AW11: 1057.9242 | AX11: 655.72917 | AY11: 79.375 | AZ11: 183.75
P12: PROYECCIÓN CONSUMO Kg | S12: 6027 | T12: 37939766 | V12: 9 | W12: 2.9296875 | X12: 1.953125 | Y12: 335.9375 | Z12: 164.0625 | AA12: 54.6875 | AB12: 1812.6102 | AD12: 9 | AE12: 15 | AF12: 10 | AG12: 430 | AH12: 210 | AI12: 70 | AJ12: 1812.6102 | AL12: 9 | AM12: 15 | AN12: 10 | AO12: 559 | AP12: 278.25 | AQ12: 87.5 | AR12: 1812.6102 | AT12: 9 | AU12: 1812.6102 | AV12: 362.47656 | AW12: 612.58477 | AX12: 430.32227 | AY12: 148.82812 | AZ12: 258.39844
P13: CONSOLIDADO CONSUMO Kg | S13: =+S9 -> 4800 | T13: =+T9 -> 30216000 | V13: 10 | W13: 2.4671053 | X13: 1.6447368 | Y13: 131.57895 | Z13: 276.31579 | AA13: 92.105263 | AB13: 2241.3763 | AD13: 10 | AE13: 15 | AF13: 10 | AG13: 200 | AH13: 420 | AI13: 140 | AJ13: 2241.3763 | AL13: 10 | AM13: 15 | AN13: 10 | AO13: 260 | AP13: 556.5 | AQ13: 175 | AR13: 2241.3763 | AT13: 10 | AU13: 2241.3763 | AV13: 141.97368 | AW13: 1031.7217 | AX13: 724.75329 | AY13: 125.32895 | AZ13: 217.59868
V14: 11 | W14: 2.4038462 | X14: 0 | Y14: 173.07692 | Z14: 355.76923 | AA14: 182.69231 | AB14: 3164.7183 | AD14: 11 | AE14: 10 | AF14: 0 | AG14: 180 | AH14: 370 | AI14: 190 | AJ14: 3164.7183 | AL14: 11 | AM14: 10 | AN14: 0 | AO14: 234 | AP14: 490.25 | AQ14: 237.5 | AR14: 3164.7183 | AT14: 11 | AU14: 3164.7183 | AV14: 186.75 | AW14: 1328.3889 | AX14: 1437.5601 | AY14: 0 | AZ14: 212.01923
P15: COF 235 - COAGULANTE | V15: 12 | W15: 0 | X15: 0 | Y15: 0 | Z15: 0 | AA15: 0 | AB15: 0 | AD15: 12 | AE15: 0 | AF15: 0 | AG15: 0 | AH15: 0 | AI15: 0 | AJ15: 0 | AL15: 12 | AM15: 0 | AN15: 0 | AO15: 0 | AP15: 0 | AQ15: 0 | AR15: 0 | AT15: 12 | AU15: 0 | AV15: 0 | AW15: 0 | AX15: 0 | AY15: 0 | AZ15: 0
Q16: PPM | R16: L/DIA | S16: KG/DIA | T16: $ | V16: 13 | W16: 3.6764706 | X16: 0.91911765 | Y16: 257.35294 | Z16: 220.58824 | AA16: 110.29412 | AB16: 2363.5055 | AD16: 13 | AE16: 20 | AF16: 5 | AG16: 350 | AH16: 300 | AI16: 150 | AJ16: 2363.5055 | AL16: 13 | AM16: 20 | AN16: 5 | AO16: 455 | AP16: 397.5 | AQ16: 187.5 | AR16: 2363.5055 | AT16: 13 | AU16: 2363.5055 | AV16: 277.68382 | AW16: 823.64338 | AX16: 867.87684 | AY16: 70.036765 | AZ16: 324.26471
P17: MINIMO | Q17: =_xlfn.MINIFS(Z4:Z30,Z4:Z30,"<>0") -> 125 | R17: =_xlfn.MINIFS(AH4:AH30,AH4:AH30,"<>0") -> 100 | S17: =_xlfn.MINIFS(AP4:AP30,AP4:AP30,"<>0") -> 132.5 | T17: =_xlfn.MINIFS(AW4:AW30,AW4:AW30,"<>0") -> 466.73125 | V17: 14 | W17: 3.90625 | X17: 2.9296875 | Y17: 156.25 | Z17: 445.3125 | AA17: 93.75 | AB17: 3136.7926 | AD17: 14 | AE17: 20 | AF17: 15 | AG17: 200 | AH17: 570 | AI17: 120 | AJ17: 3136.7926 | AL17: 14 | AM17: 20 | AN17: 15 | AO17: 260 | AP17: 755.25 | AQ17: 150 | AR17: 3136.7926 | AT17: 14 | AU17: 3136.7926 | AV17: 168.59375 | AW17: 1662.7301 | AX17: 737.69531 | AY17: 223.24219 | AZ17: 344.53125
P18: MAXIMO | Q18: =MAX(Z4:Z30) -> 445.3125 | R18: =MAX(AH4:AH30) -> 650 | S18: =MAX(AP4:AP30) -> 861.25 | T18: =MAX(AW4:AW30) -> 1662.7301 | V18: 15 | W18: 4.1666667 | X18: 1.0416667 | Y18: 166.66667 | Z18: 291.66667 | AA18: 150 | AB18: 2896.0604 | AD18: 15 | AE18: 20 | AF18: 5 | AG18: 200 | AH18: 350 | AI18: 180 | AJ18: 2896.0604 | AL18: 15 | AM18: 20 | AN18: 5 | AO18: 260 | AP18: 463.75 | AQ18: 225 | AR18: 2896.0604 | AT18: 15 | AU18: 2896.0604 | AV18: 179.83333 | AW18: 1089.0396 | AX18: 1180.3125 | AY18: 79.375 | AZ18: 367.5
P19: PROMEDIO | Q19: =AVERAGEIF(Z4:Z30,"<>0") -> 291.80825 | R19: =AVERAGEIF(AH4:AH30,"<>0") -> 388.57143 | S19: =AVERAGEIF(AP4:AP30,"<>0") -> 514.85714 | T19: =AVERAGEIF(AW4:AW30,"<>0") -> 1089.5682 | V19: 16 | W19: 1.5625 | X19: 1.5625 | Y19: 200 | Z19: 318.75 | AA19: 125 | AB19: 2646.4334 | AD19: 16 | AE19: 10 | AF19: 10 | AG19: 320 | AH19: 510 | AI19: 200 | AJ19: 2646.4334 | AL19: 16 | AM19: 10 | AN19: 10 | AO19: 416 | AP19: 675.75 | AQ19: 250 | AR19: 2646.4334 | AT19: 16 | AU19: 2646.4334 | AV19: 215.8 | AW19: 1190.1647 | AX19: 983.59375 | AY19: 119.0625 | AZ19: 137.8125
P20: TOTAL CONSUMIDO | R20: =GETPIVOTDATA("CONSUMO LITROS COAGULANTE (L) ",$AD$3) -> 9830 | S20: =GETPIVOTDATA("KG COAGULANTE ",$AL$3) -> 13024.75 | T20: =S20*AW2 -> 37771775 | V20: 17 | W20: 2.6041667 | X20: 0.86805556 | Y20: 388.88889 | Z20: 375 | AA20: 173.61111 | AB20: 3481.7406 | AD20: 17 | AE20: 15 | AF20: 5 | AG20: 560 | AH20: 540 | AI20: 250 | AJ20: 3481.7406 | AL20: 17 | AM20: 15 | AN20: 5 | AO20: 728 | AP20: 715.5 | AQ20: 312.5 | AR20: 3481.7406 | AT20: 17 | AU20: 3481.7406 | AV20: 419.61111 | AW20: 1400.1937 | AX20: 1366.1024 | AY20: 66.145833 | AZ20: 229.6875
P21: PROYECCIÓN Kg/M3 | S21: 0.54180085 | T21: 1571.2 | V21: 18 | W21: 2.2321429 | X21: 0.74404762 | Y21: 270.83333 | Z21: 297.61905 | AA21: 181.54762 | AB21: 3085.6183 | AD21: 18 | AE21: 15 | AF21: 5 | AG21: 455 | AH21: 500 | AI21: 305 | AJ21: 3085.6183 | AL21: 18 | AM21: 15 | AN21: 5 | AO21: 591.5 | AP21: 662.5 | AQ21: 381.25 | AR21: 3085.6183 | AT21: 18 | AU21: 3085.6183 | AV21: 292.22917 | AW21: 1111.2649 | AX21: 1428.5528 | AY21: 56.696429 | AZ21: 196.875
P22: REAL Kg/ M3 | S22: =S20/F82 -> 0.40182483 | T22: =T20/F82 -> 1165.292 | V22: 19 | W22: 0 | X22: 0 | Y22: 0 | Z22: 0 | AA22: 0 | AB22: 0 | AD22: 19 | AE22: 15 | AF22: 0 | AG22: 0 | AH22: 0 | AI22: 0 | AJ22: 0 | AL22: 19 | AM22: 15 | AN22: 0 | AO22: 0 | AP22: 0 | AQ22: 0 | AR22: 0 | AT22: 19 | AU22: 0 | AV22: 0 | AW22: 0 | AX22: 0 | AY22: 0 | AZ22: 0
P23: PROYECCIÓN CONSUMO Kg | S23: 13746 | T23: 39863818 | V23: 20 | W23: 2.34375 | X23: 0.78125 | Y23: 46.875 | Z23: 268.75 | AA23: 109.375 | AB23: 2180.9448 | AD23: 20 | AE23: 15 | AF23: 5 | AG23: 75 | AH23: 430 | AI23: 175 | AJ23: 2180.9448 | AL23: 20 | AM23: 15 | AN23: 5 | AO23: 97.5 | AP23: 569.75 | AQ23: 218.75 | AR23: 2180.9448 | AT23: 20 | AU23: 2180.9448 | AV23: 50.578125 | AW23: 1003.4722 | AX23: 860.64453 | AY23: 59.53125 | AZ23: 206.71875
P24: CONSOLIDADO CONSUMO Kg | S24: =+S20 -> 13024.75 | T24: =+T20 -> 37771775 | V24: 21 | W24: 2.7573529 | X24: 1.8382353 | Y24: 205.88235 | Z24: 279.41176 | AA24: 139.70588 | AB24: 2748.0114 | AD24: 21 | AE24: 15 | AF24: 10 | AG24: 280 | AH24: 380 | AI24: 190 | AJ24: 2748.0114 | AL24: 21 | AM24: 15 | AN24: 10 | AO24: 364 | AP24: 503.5 | AQ24: 237.5 | AR24: 2748.0114 | AT24: 21 | AU24: 2748.0114 | AV24: 222.14706 | AW24: 1043.2816 | AX24: 1099.3107 | AY24: 140.07353 | AZ24: 243.19853
V25: 22 | W25: 2.4671053 | X25: 1.6447368 | Y25: 203.94737 | Z25: 427.63158 | AA25: 190.78947 | AB25: 3660.9737 | AD25: 22 | AE25: 15 | AF25: 10 | AG25: 310 | AH25: 650 | AI25: 290 | AJ25: 3660.9737 | AL25: 22 | AM25: 15 | AN25: 10 | AO25: 403 | AP25: 861.25 | AQ25: 362.5 | AR25: 3660.9737 | AT25: 22 | AU25: 3660.9737 | AV25: 220.05921 | AW25: 1596.7122 | AX25: 1501.2747 | AY25: 125.32895 | AZ25: 217.59868
V26: 23 | W26: 3.3444816 | X26: 1.6722408 | Y26: 214.04682 | Z26: 240.80268 | AA26: 100.33445 | AB26: 2341.9923 | AD26: 23 | AE26: 20 | AF26: 10 | AG26: 320 | AH26: 360 | AI26: 150 | AJ26: 2341.9923 | AL26: 23 | AM26: 20 | AN26: 10 | AO26: 416 | AP26: 477 | AQ26: 187.5 | AR26: 2341.9923 | AT26: 23 | AU26: 2341.9923 | AV26: 230.95652 | AW26: 899.12107 | AX26: 789.50669 | AY26: 127.42475 | AZ26: 294.98328
P27: COF 280 - ACIDIFICANTE | V27: 24 | W27: 0.91911765 | X27: 0.91911765 | Y27: 227.94118 | Z27: 227.94118 | AA27: 110.29412 | AB27: 2116.0265 | AD27: 24 | AE27: 5 | AF27: 5 | AG27: 310 | AH27: 310 | AI27: 150 | AJ27: 2116.0265 | AL27: 24 | AM27: 5 | AN27: 5 | AO27: 403 | AP27: 410.75 | AQ27: 187.5 | AR27: 2116.0265 | AT27: 24 | AU27: 2116.0265 | AV27: 245.94853 | AW27: 851.09816 | AX27: 867.87684 | AY27: 70.036765 | AZ27: 81.066176
Q28: PPM | R28: L/DIA | S28: KG/DIA | T28: $ | V28: 25 | W28: 2.7573529 | X28: 0.91911765 | Y28: 220.58824 | Z28: 301.47059 | AA28: 102.94118 | AB28: 2486.9143 | AD28: 25 | AE28: 15 | AF28: 5 | AG28: 300 | AH28: 410 | AI28: 140 | AJ28: 2486.9143 | AL28: 25 | AM28: 15 | AN28: 5 | AO28: 390 | AP28: 543.25 | AQ28: 175 | AR28: 2486.9143 | AT28: 25 | AU28: 2486.9143 | AV28: 238.01471 | AW28: 1125.646 | AX28: 810.01838 | AY28: 70.036765 | AZ28: 243.19853
P29: MINIMO | Q29: =_xlfn.MINIFS(Y4:Y30,Y4:Y30,"<>0") -> 46.875 | R29: =_xlfn.MINIFS(AG4:AG30,AG4:AG30,"<>0") -> 75 | S29: =_xlfn.MINIFS(AO4:AO30,AO4:AO30,"<>0") -> 97.5 | T29: =_xlfn.MINIFS(AV4:AV30,AV4:AV30,"<>0") -> 50.578125 | V29: 26 | W29: 3.125 | X29: 1.5625 | Y29: 287.5 | Z29: 125 | AA29: 37.5 | AB29: 1466.7094 | AD29: 26 | AE29: 10 | AF29: 5 | AG29: 230 | AH29: 100 | AI29: 30 | AJ29: 1466.7094 | AL29: 26 | AM29: 10 | AN29: 5 | AO29: 299 | AP29: 132.5 | AQ29: 37.5 | AR29: 1466.7094 | AT29: 26 | AU29: 1466.7094 | AV29: 310.2125 | AW29: 466.73125 | AX29: 295.07812 | AY29: 119.0625 | AZ29: 275.625
P30: MAXIMO | Q30: =MAX(Y4:Y30) -> 388.88889 | R30: =MAX(AG4:AG30) -> 560 | S30: =MAX(AO4:AO30) -> 728 | T30: =MAX(AV4:AV30) -> 419.61111 | V30: 27 | W30: 3.2894737 | X30: 2.4671053 | Y30: 315.78947 | Z30: 289.47368 | AA30: 92.105263 | AB30: 2624.4664 | AD30: 27 | AE30: 20 | AF30: 15 | AG30: 480 | AH30: 440 | AI30: 140 | AJ30: 2624.4664 | AL30: 27 | AM30: 20 | AN30: 15 | AO30: 624 | AP30: 583 | AQ30: 175 | AR30: 2624.4664 | AT30: 27 | AU30: 2624.4664 | AV30: 340.73684 | AW30: 1080.8513 | AX30: 724.75329 | AY30: 187.99342 | AZ30: 290.13158
P31: PROMEDIO | Q31: =AVERAGEIF(Y4:Y30,"<>0") -> 219.01347 | R31: =AVERAGEIF(AG4:AG30,"<>0") -> 288.09524 | S31: =AVERAGEIF(AO4:AO30,"<>0") -> 374.52381 | T31: =AVERAGEIF(AV4:AV30,"<>0") -> 236.31553 | V31: 28 | W31: 1.5625 | X31: 1.5625 | Y31: 325 | Z31: 381.25 | AA31: 112.5 | AB31: 2916.3147 | AD31: 28 | AE31: 10 | AF31: 10 | AG31: 520 | AH31: 610 | AI31: 180 | AJ31: 2916.3147 | AL31: 28 | AM31: 10 | AN31: 10 | AO31: 676 | AP31: 808.25 | AQ31: 225 | AR31: 2916.3147 | AT31: 28 | AU31: 2916.3147 | AV31: 350.675 | AW31: 1423.5303 | AX31: 885.23438 | AY31: 119.0625 | AZ31: 137.8125
P32: TOTAL CONSUMIDO | R32: =GETPIVOTDATA("CONSUMO LITROS ACIDO (L) ",$AD$3) -> 7170 | S32: =GETPIVOTDATA("KG ACIDO ",$AL$3) -> 9321 | T32: =AV2*S32 -> 7736430 | V32: 29 | W32: 2.2321429 | X32: 2.2321429 | Y32: 154.7619 | Z32: 315.47619 | AA32: 148.80952 | AB32: 2882.8381 | AD32: 29 | AE32: 15 | AF32: 15 | AG32: 260 | AH32: 530 | AI32: 250 | AJ32: 2882.8381 | AL32: 29 | AM32: 15 | AN32: 15 | AO32: 338 | AP32: 702.25 | AQ32: 312.5 | AR32: 2882.8381 | AT32: 29 | AU32: 2882.8381 | AV32: 166.9881 | AW32: 1177.9408 | AX32: 1170.9449 | AY32: 170.08929 | AZ32: 196.875
P33: PROYECCIÓN Kg/M3 | S33: 0.30804068 | T33: 255.7 | V33: 30 | W33: 2.4671053 | X33: 2.4671053 | Y33: 223.68421 | Z33: 348.68421 | AA33: 105.26316 | AB33: 2777.1714 | AD33: 30 | AE33: 15 | AF33: 15 | AG33: 340 | AH33: 530 | AI33: 160 | AJ33: 2777.1714 | AL33: 30 | AM33: 15 | AN33: 15 | AO33: 442 | AP33: 702.25 | AQ33: 200 | AR33: 2777.1714 | AT33: 30 | AU33: 2777.1714 | AV33: 241.35526 | AW33: 1301.9345 | AX33: 828.28947 | AY33: 187.99342 | AZ33: 217.59868
P34: REAL Kg/ M3 | S34: =+S32/F82 -> 0.28756093 | T34: =T32/F82 -> 238.67557 | V34: Total general | W34: 2.7380144 | X34: 1.5039798 | Y34: 221.20072 | Z34: 303.26402 | AA34: 118.46733 | AB34: 2659.3039 | AD34: Total general | AE34: 355 | AF34: 195 | AG34: 7170 | AH34: 9830 | AI34: 3840 | AJ34: 2659.3039 | AL34: Total general | AM34: 355 | AN34: 195 | AO34: 9321 | AP34: 13024.75 | AQ34: 4800 | AR34: 2659.3039 | AT34: Total general | AU34: 2659.3039 | AV34: 238.67557 | AW34: 1132.3424 | AX34: 932.18979 | AY34: 114.60326 | AZ34: 241.49287
P35: PROYECCIÓN CONSUMO Kg | S35: 7815 | T35: 6486753
P36: CONSOLIDADO CONSUMO Kg | S36: =S32 -> 9321 | T36: =+T32 -> 7736430
P39: COF 440 - POLIMERO ANIONICO
Q40: PPM | R40: KG/DIA | S40: $
P41: MINIMO | Q41: =_xlfn.MINIFS(X4:X30,X4:X30,"<>0") -> 0.74404762 | R41: =_xlfn.MINIFS(AN4:AN30,AN4:AN30,"<>0") -> 5 | S41: =_xlfn.MINIFS(AY4:AY30,AY4:AY30,"<>0") -> 56.696429
P42: MAXIMO | Q42: =MAX(X4:X30) -> 2.9296875 | R42: =MAX(AN4:AN30) -> 15 | S42: =MAX(AY4:AY30) -> 223.24219
P43: PROMEDIO | Q43: =AVERAGEIF(X4:X30,"<>0") -> 1.485511 | R43: =AVERAGEIF(AN4:AN30,"<>0") -> 7.75 | S43: =AVERAGEIF(AY4:AY30,"<>0") -> 113.19594
P44: TOTAL CONSUMIDO | R44: =GETPIVOTDATA("KG POL ANIONICO ",$AL$3) -> 195 | S44: =R44*AY2 -> 3714750
P45: PROYECCIÓN Kg/M3 | R45: 0.0054182543 | S45: 103.2
P46: REAL Kg/ M3 | Q46: REAL Kg/ M3 | R46: =R44/F82 -> 0.006015919 | S46: =+S44/F82 -> 114.60326
P47: PROYECCIÓN CONSUMO Kg | Q47: PROYECCIÓN CONSUMO Kg | R47: 137 | S47: 2618759
P48: CONSOLIDADO CONSUMO Kg | Q48: CONSOLIDADO CONSUMO Kg | R48: =+R44 -> 195 | S48: 762000
P50: COF 494 - POLIMERO CATIONICO
Q51: PPM | R51: KG/DIA | S51: $
P52: MINIMO | Q52: =_xlfn.MINIFS(W4:W30,W4:W30,"<>0") -> 0.91911765 | R52: =_xlfn.MINIFS(AM4:AM30,AM4:AM30,"<>0") -> 5 | S52: =_xlfn.MINIFS(AZ4:AZ30,AZ4:AZ30,"<>0") -> 81.066176
P53: MAXIMO | Q53: =MAX(W4:W30) -> 4.1666667 | R53: =MAX(AM4:AM30) -> 20 | S53: =MAX(AZ4:AZ30) -> 367.5
P54: PROMEDIO | Q54: =AVERAGEIF(W4:W30,"<>0") -> 2.7523544 | R54: =AVERAGEIF(AM4:AM30,"<>0") -> 14.318182 | S54: =AVERAGEIF(AZ4:AZ30,"<>0") -> 242.75765
P55: TOTAL CONSUMIDO | R55: =GETPIVOTDATA("KG POL CATIONICO ",$AL$3) -> 355 | S55: =R55*AZ2 -> 7827750
P56: PROYECCIÓN Kg/M3 | Q56: PROYECCIÓN Kg/M3 | R56: 0.0091306964 | S56: 201.3
P57: REAL Kg/ M3 | Q57: REAL Kg/ M3 | R57: =+R55/F82 -> 0.010952058 | S57: =+S55/F82 -> 241.49287
P58: PROYECCIÓN CONSUMO Kg | Q58: PROYECCIÓN CONSUMO Kg | R58: 232 | S58: 5108033
P59: CONSOLIDADO CONSUMO Kg | Q59: CONSOLIDADO CONSUMO Kg | R59: =+R55 -> 355 | S59: 2094750
B80: REMOCIÓN DQO mg/L
B81: DQO INICIAL (mg/L) | C81: DQO SALIDA (mg/L) | D81: DQO REMOMOVIDA (mg/L) | E81: KG REMOVIDOS DQO / M3 | F81: M3 TRATADOS | G81: TOTAL KG DQO REMOVIDOS | H81: $TRATAMIENTO | I81: $ REMOVER KG DQO
B82: =E97 -> 1326 | C82: =F97 -> 652 | D82: =+B82-C82 -> 674 | E82: =(D82/1000000)*1000 -> 0.674 | F82: ='DB QUIMICA'!Z8 -> 32414 | G82: =+F82*E82 -> 21847.036 | H82: ='DB QUIMICA'!AD8 -> 86198676 | I82: =H82/G82 -> 3945.5547
B84: REMOCIÓN SST mg/L
B85: SST INICIAL (mg/L) | C85: SST SALIDA (mg/L) | D85: SST REMOVIDOS (mg/L) | E85: KG REMOVIDOS SST / M3 | F85: M3 TRATADOS | G85: TOTAL KG DQO REMOVIDOS | H85: $TRATAMIENTO | I85: $ REMOVER KG SST
B86: =E102 -> 558 | C86: =F102 -> 44 | D86: =+B86-C86 -> 514 | E86: =(D86/1000000)*1000 -> 0.514 | F86: =+F82 -> 32414 | G86: =+F86*E86 -> 16660.796 | H86: =H82 -> 86198676 | I86: =H86/D86 -> 167701.7
B91: KPIs | E91: ENTRADA GEM | F91: SALIDA GEM
B92: COLOR
B93: PROMEDIO | E93: 5807 | F93: 878
B94: PERCENTIL 90 | E94: 8104 | F94: 1218
B95: INDICE DE ESTABILIDAD DEL AFLUENTE - EFLUENTE (CV%) | E95: 0.2981 | F95: 0.2946
B96: DQO
B97: PROMEDIO | E97: 1326 | F97: 652
B98: PERCENTIL 90 | E98: 1417 | F98: 803.9
B99: INDICE DE ESTABILIDAD DEL AFLUENTE - EFLUENTE (CV%) | E99: 0.0777 | F99: 0.2053
B100: CARGA REMOVIDA KG/DIA DQO | E100: =+G82 -> 21847.036
B101: SST
B102: PROMEDIO | E102: 558 | F102: 44
B103: PERCENTIL 90 | E103: 879.5 | F103: 63.9
B104: INDICE DE ESTABILIDAD DEL AFLUENTE - EFLUENTE (CV%) | E104: 0.3576 | F104: 0.3312
B105: CARGA REMOVIDA KG/DIA SST | E105: =+G86 -> 16660.796
G106: 25

Sheet INFORME CALIDAD
A1: CALIDAD DE AGUA Vs COSTOS
A2: PANORAMA OPERATIVO
A13: PANORAMA OPERATIVO
A24: 1. COSTO Vs CONSUMO DE PRODUCTOS QUIMICOS
A68: CALIDAD DE AGUA
A86: CALIDAD DE AGUA
A104: $ REMOCIÓN DQO

Sheet CONSUMO QUÍMICA-CAUDALES GEM  
A1: CONSOLIDADO CONSUMO DIARIO QUÍMICA (Litros)
B2: DIAS
A3: PRODUCTOS QUÍMICOS | B3: 1 | C3: 2 | D3: 3 | E3: 4 | F3: 5 | G3: 6 | H3: 7 | I3: 8 | J3: 9 | K3: 10 | L3: 11 | M3: 12 | N3: 13 | O3: 14 | P3: 15 | Q3: 16 | R3: 17 | S3: 18 | T3: 19 | U3: 20 | V3: 21 | W3: 22 | X3: 23 | Y3: 24 | Z3: 25 | AA3: 26 | AB3: 27 | AC3: 28 | AD3: 29 | AE3: 30 | AF3: Total general
A4: COF 280 ACIDO (L) | B4: 0 | C4: 180 | D4: 0 | E4: 0 | F4: 0 | G4: 150 | H4: 150 | I4: 370 | J4: 430 | K4: 200 | L4: 180 | M4: 0 | N4: 350 | O4: 200 | P4: 200 | Q4: 320 | R4: 560 | S4: 455 | T4: 0 | U4: 75 | V4: 280 | W4: 310 | X4: 320 | Y4: 310 | Z4: 300 | AA4: 230 | AB4: 480 | AC4: 520 | AD4: 260 | AE4: 340 | AF4: 7170
A5: COF 235 COAGULANTE (L) | B5: 0 | C5: 120 | D5: 0 | E5: 0 | F5: 0 | G5: 430 | H5: 420 | I5: 340 | J5: 210 | K5: 420 | L5: 370 | M5: 0 | N5: 300 | O5: 570 | P5: 350 | Q5: 510 | R5: 540 | S5: 500 | T5: 0 | U5: 430 | V5: 380 | W5: 650 | X5: 360 | Y5: 310 | Z5: 410 | AA5: 100 | AB5: 440 | AC5: 610 | AD5: 530 | AE5: 530 | AF5: 9830
A6: COF 255 DECOLORANTE (L) | B6: 0 | C6: 90 | D6: 0 | E6: 0 | F6: 0 | G6: 70 | H6: 120 | I6: 100 | J6: 70 | K6: 140 | L6: 190 | M6: 0 | N6: 150 | O6: 120 | P6: 180 | Q6: 200 | R6: 250 | S6: 305 | T6: 0 | U6: 175 | V6: 190 | W6: 290 | X6: 150 | Y6: 150 | Z6: 140 | AA6: 30 | AB6: 140 | AC6: 180 | AD6: 250 | AE6: 160 | AF6: 3840
A7: COF 440 POL ANIONICO (KG) | B7: 0 | C7: 10 | D7: 0 | E7: 0 | F7: 0 | G7: 5 | H7: 5 | I7: 5 | J7: 10 | K7: 10 | L7: 0 | M7: 0 | N7: 5 | O7: 15 | P7: 5 | Q7: 10 | R7: 5 | S7: 5 | T7: 0 | U7: 5 | V7: 10 | W7: 10 | X7: 10 | Y7: 5 | Z7: 5 | AA7: 5 | AB7: 15 | AC7: 10 | AD7: 15 | AE7: 15 | AF7: 195
A8: COF 494 POL CATIONICO (KG) | B8: 0 | C8: 10 | D8: 0 | E8: 0 | F8: 0 | G8: 15 | H8: 10 | I8: 10 | J8: 15 | K8: 15 | L8: 10 | M8: 0 | N8: 20 | O8: 20 | P8: 20 | Q8: 10 | R8: 15 | S8: 15 | T8: 15 | U8: 15 | V8: 15 | W8: 15 | X8: 20 | Y8: 5 | Z8: 15 | AA8: 10 | AB8: 20 | AC8: 10 | AD8: 15 | AE8: 15 | AF8: 355
A9: CAUDAL TOTAL TRATADO GEM | B9: 0 | C9: 880 | D9: 0 | E9: 0 | F9: 0 | G9: 1040 | H9: 1079 | I9: 1200 | J9: 1280 | K9: 1520 | L9: 1040 | M9: 0 | N9: 1360 | O9: 1280 | P9: 1200 | Q9: 1600 | R9: 1440 | S9: 1680 | T9: 0 | U9: 1600 | V9: 1360 | W9: 1520 | X9: 1495 | Y9: 1360 | Z9: 1360 | AA9: 800 | AB9: 1520 | AC9: 1600 | AD9: 1680 | AE9: 1520 | AF9: 32414
A10: INDICADOR $m3 | B10: 0 | C10: 2001.6699 | D10: 0 | E10: 0 | F10: 0 | G10: 2638.6712 | H10: 2771.1464 | I10: 2309.47 | J10: 1812.6102 | K10: 2241.3763 | L10: 3164.7183 | M10: 0 | N10: 2363.5055 | O10: 3136.7926 | P10: 2896.0604 | Q10: 2646.4334 | R10: 3481.7406 | S10: 3085.6183 | T10: 0 | U10: 2180.9448 | V10: 2748.0114 | W10: 3660.9737 | X10: 2341.9923 | Y10: 2116.0265 | Z10: 2486.9143 | AA10: 1466.7094 | AB10: 2624.4664 | AC10: 2916.3147 | AD10: 2882.8381 | AE10: 2777.1714 | AF10: 2659.3039
A12: CONSOLIDADO CONSUMO DIARIO QUÍMICA (Kg)
B13: DIAS
A14: PRODUCTOS QUÍMICOS | B14: 1 | C14: 2 | D14: 3 | E14: 4 | F14: 5 | G14: 6 | H14: 7 | I14: 8 | J14: 9 | K14: 10 | L14: 11 | M14: 12 | N14: 13 | O14: 14 | P14: 15 | Q14: 16 | R14: 17 | S14: 18 | T14: 19 | U14: 20 | V14: 21 | W14: 22 | X14: 23 | Y14: 24 | Z14: 25 | AA14: 26 | AB14: 27 | AC14: 28 | AD14: 29 | AE14: 30 | AF14: Total general
A15: COF 280 - KG ACIDO | B15: 0 | C15: 234 | D15: 0 | E15: 0 | F15: 0 | G15: 195 | H15: 195 | I15: 481 | J15: 559 | K15: 260 | L15: 234 | M15: 0 | N15: 455 | O15: 260 | P15: 260 | Q15: 416 | R15: 728 | S15: 591.5 | T15: 0 | U15: 97.5 | V15: 364 | W15: 403 | X15: 416 | Y15: 403 | Z15: 390 | AA15: 299 | AB15: 624 | AC15: 676 | AD15: 338 | AE15: 442 | AF15: 9321
A16: COF 235 - KG COAGULANTE | B16: 0 | C16: 159 | D16: 0 | E16: 0 | F16: 0 | G16: 569.75 | H16: 556.5 | I16: 450.5 | J16: 278.25 | K16: 556.5 | L16: 490.25 | M16: 0 | N16: 397.5 | O16: 755.25 | P16: 463.75 | Q16: 675.75 | R16: 715.5 | S16: 662.5 | T16: 0 | U16: 569.75 | V16: 503.5 | W16: 861.25 | X16: 477 | Y16: 410.75 | Z16: 543.25 | AA16: 132.5 | AB16: 583 | AC16: 808.25 | AD16: 702.25 | AE16: 702.25 | AF16: 13024.75
A17: COF 255 - KG DECOLORANTE | B17: 0 | C17: 112.5 | D17: 0 | E17: 0 | F17: 0 | G17: 87.5 | H17: 150 | I17: 125 | J17: 87.5 | K17: 175 | L17: 237.5 | M17: 0 | N17: 187.5 | O17: 150 | P17: 225 | Q17: 250 | R17: 312.5 | S17: 381.25 | T17: 0 | U17: 218.75 | V17: 237.5 | W17: 362.5 | X17: 187.5 | Y17: 187.5 | Z17: 175 | AA17: 37.5 | AB17: 175 | AC17: 225 | AD17: 312.5 | AE17: 200 | AF17: 4800
A18: COF 440 - KG POL ANIONICO | B18: 0 | C18: 10 | D18: 0 | E18: 0 | F18: 0 | G18: 5 | H18: 5 | I18: 5 | J18: 10 | K18: 10 | L18: 0 | M18: 0 | N18: 5 | O18: 15 | P18: 5 | Q18: 10 | R18: 5 | S18: 5 | T18: 0 | U18: 5 | V18: 10 | W18: 10 | X18: 10 | Y18: 5 | Z18: 5 | AA18: 5 | AB18: 15 | AC18: 10 | AD18: 15 | AE18: 15 | AF18: 195
A19: COF 494 - KG POL CATIONICO | B19: 0 | C19: 10 | D19: 0 | E19: 0 | F19: 0 | G19: 15 | H19: 10 | I19: 10 | J19: 15 | K19: 15 | L19: 10 | M19: 0 | N19: 20 | O19: 20 | P19: 20 | Q19: 10 | R19: 15 | S19: 15 | T19: 15 | U19: 15 | V19: 15 | W19: 15 | X19: 20 | Y19: 5 | Z19: 15 | AA19: 10 | AB19: 20 | AC19: 10 | AD19: 15 | AE19: 15 | AF19: 355
A20: CAUDAL TOTAL TRATADO GEM | B20: 0 | C20: 880 | D20: 0 | E20: 0 | F20: 0 | G20: 1040 | H20: 1079 | I20: 1200 | J20: 1280 | K20: 1520 | L20: 1040 | M20: 0 | N20: 1360 | O20: 1280 | P20: 1200 | Q20: 1600 | R20: 1440 | S20: 1680 | T20: 0 | U20: 1600 | V20: 1360 | W20: 1520 | X20: 1495 | Y20: 1360 | Z20: 1360 | AA20: 800 | AB20: 1520 | AC20: 1600 | AD20: 1680 | AE20: 1520 | AF20: 32414
A21: INDICADOR $m3 | B21: #DIV/0! | C21: 2001.6699 | D21: #DIV/0! | E21: #DIV/0! | F21: #DIV/0! | G21: 2638.6712 | H21: 2771.1464 | I21: 2309.47 | J21: 1812.6102 | K21: 2241.3763 | L21: 3164.7183 | M21: #DIV/0! | N21: 2363.5055 | O21: 3136.7926 | P21: 2896.0604 | Q21: 2646.4334 | R21: 3481.7406 | S21: 3085.6183 | T21: #DIV/0! | U21: 2180.9448 | V21: 2748.0114 | W21: 3660.9737 | X21: 2341.9923 | Y21: 2116.0265 | Z21: 2486.9143 | AA21: 1466.7094 | AB21: 2624.4664 | AC21: 2916.3147 | AD21: 2882.8381 | AE21: 2777.1714 | AF21: 2659.3039
A24: CONSOLIDADO DOSIFICACIÓN QUÍMICA PPM (mg/L)
B25: DIAS
A26: PRODUCTOS QUÍMICOS | B26: 1 | C26: 2 | D26: 3 | E26: 4 | F26: 5 | G26: 6 | H26: 7 | I26: 8 | J26: 9 | K26: 10 | L26: 11 | M26: 12 | N26: 13 | O26: 14 | P26: 15 | Q26: 16 | R26: 17 | S26: 18 | T26: 19 | U26: 20 | V26: 21 | W26: 22 | X26: 23 | Y26: 24 | Z26: 25 | AA26: 26 | AB26: 27 | AC26: 28 | AD26: 29 | AE26: 30
A27: COF 280 - PPM ACIDO | B27: #DIV/0! | C27: 204.54545 | D27: #DIV/0! | E27: #DIV/0! | F27: #DIV/0! | G27: 144.23077 | H27: 139.01761 | I27: 308.33333 | J27: 335.9375 | K27: 131.57895 | L27: 173.07692 | M27: #DIV/0! | N27: 257.35294 | O27: 156.25 | P27: 166.66667 | Q27: 200 | R27: 388.88889 | S27: 270.83333 | T27: #DIV/0! | U27: 46.875 | V27: 205.88235 | W27: 203.94737 | X27: 214.04682 | Y27: 227.94118 | Z27: 220.58824 | AA27: 287.5 | AB27: 315.78947 | AC27: 325 | AD27: 154.7619 | AE27: 223.68421
A28: COF 235 - PPM COAGULANTE | B28: #DIV/0! | C28: 136.36364 | D28: #DIV/0! | E28: #DIV/0! | F28: #DIV/0! | G28: 413.46154 | H28: 389.2493 | I28: 283.33333 | J28: 164.0625 | K28: 276.31579 | L28: 355.76923 | M28: #DIV/0! | N28: 220.58824 | O28: 445.3125 | P28: 291.66667 | Q28: 318.75 | R28: 375 | S28: 297.61905 | T28: #DIV/0! | U28: 268.75 | V28: 279.41176 | W28: 427.63158 | X28: 240.80268 | Y28: 227.94118 | Z28: 301.47059 | AA28: 125 | AB28: 289.47368 | AC28: 381.25 | AD28: 315.47619 | AE28: 348.68421
A29: COF 255 - PPM DECOLORANTE | B29: #DIV/0! | C29: 102.27273 | D29: #DIV/0! | E29: #DIV/0! | F29: #DIV/0! | G29: 67.307692 | H29: 111.21409 | I29: 83.333333 | J29: 54.6875 | K29: 92.105263 | L29: 182.69231 | M29: #DIV/0! | N29: 110.29412 | O29: 93.75 | P29: 150 | Q29: 125 | R29: 173.61111 | S29: 181.54762 | T29: #DIV/0! | U29: 109.375 | V29: 139.70588 | W29: 190.78947 | X29: 100.33445 | Y29: 110.29412 | Z29: 102.94118 | AA29: 37.5 | AB29: 92.105263 | AC29: 112.5 | AD29: 148.80952 | AE29: 105.26316
A30: COF 440 - PPM POL ANIONICO | B30: #DIV/0! | C30: 2.8409091 | D30: #DIV/0! | E30: #DIV/0! | F30: #DIV/0! | G30: 1.2019231 | H30: 1.1584801 | I30: 1.0416667 | J30: 1.953125 | K30: 1.6447368 | L30: 0 | M30: #DIV/0! | N30: 0.91911765 | O30: 2.9296875 | P30: 1.0416667 | Q30: 1.5625 | R30: 0.86805556 | S30: 0.74404762 | T30: #DIV/0! | U30: 0.78125 | V30: 1.8382353 | W30: 1.6447368 | X30: 1.6722408 | Y30: 0.91911765 | Z30: 0.91911765 | AA30: 1.5625 | AB30: 2.4671053 | AC30: 1.5625 | AD30: 2.2321429 | AE30: 2.4671053
A31: COF 494 - PPM POL CATIONICO | B31: #DIV/0! | C31: 2.8409091 | D31: #DIV/0! | E31: #DIV/0! | F31: #DIV/0! | G31: 3.6057692 | H31: 2.3169601 | I31: 2.0833333 | J31: 2.9296875 | K31: 2.4671053 | L31: 2.4038462 | M31: #DIV/0! | N31: 3.6764706 | O31: 3.90625 | P31: 4.1666667 | Q31: 1.5625 | R31: 2.6041667 | S31: 2.2321429 | T31: #DIV/0! | U31: 2.34375 | V31: 2.7573529 | W31: 2.4671053 | X31: 3.3444816 | Y31: 0.91911765 | Z31: 2.7573529 | AA31: 3.125 | AB31: 3.2894737 | AC31: 1.5625 | AD31: 2.2321429 | AE31: 2.4671053
A32: CAUDAL TOTAL TRATADO GEM | B32: 0 | C32: 880 | D32: 0 | E32: 0 | F32: 0 | G32: 1040 | H32: 1079 | I32: 1200 | J32: 1280 | K32: 1520 | L32: 1040 | M32: 0 | N32: 1360 | O32: 1280 | P32: 1200 | Q32: 1600 | R32: 1440 | S32: 1680 | T32: 0 | U32: 1600 | V32: 1360 | W32: 1520 | X32: 1495 | Y32: 1360 | Z32: 1360 | AA32: 800 | AB32: 1520 | AC32: 1600 | AD32: 1680 | AE32: 1520
A33: INDICADOR $m3 | B33: #DIV/0! | C33: 2001.6699 | D33: #DIV/0! | E33: #DIV/0! | F33: #DIV/0! | G33: 2638.6712 | H33: 2771.1464 | I33: 2309.47 | J33: 1812.6102 | K33: 2241.3763 | L33: 3164.7183 | M33: #DIV/0! | N33: 2363.5055 | O33: 3136.7926 | P33: 2896.0604 | Q33: 2646.4334 | R33: 3481.7406 | S33: 3085.6183 | T33: #DIV/0! | U33: 2180.9448 | V33: 2748.0114 | W33: 3660.9737 | X33: 2341.9923 | Y33: 2116.0265 | Z33: 2486.9143 | AA33: 1466.7094 | AB33: 2624.4664 | AC33: 2916.3147 | AD33: 2882.8381 | AE33: 2777.1714
B35: DIAS
B36: 1 | C36: 2 | D36: 3 | E36: 4 | F36: 5 | G36: 6 | H36: 7 | I36: 8 | J36: 9 | K36: 10 | L36: 11 | M36: 12 | N36: 13 | O36: 14 | P36: 15 | Q36: 16 | R36: 17 | S36: 18 | T36: 19 | U36: 20 | V36: 21 | W36: 22 | X36: 23 | Y36: 24 | Z36: 25 | AA36: 26 | AB36: 27 | AC36: 28 | AD36: 29 | AE36: 30 | AF36: Total general
A37: CAUDAL TOTAL TRATADO GEM | B37: 0 | C37: 880 | D37: 0 | E37: 0 | F37: 0 | G37: 1040 | H37: 1079 | I37: 1200 | J37: 1280 | K37: 1520 | L37: 1040 | M37: 0 | N37: 1360 | O37: 1280 | P37: 1200 | Q37: 1600 | R37: 1440 | S37: 1680 | T37: 0 | U37: 1600 | V37: 1360 | W37: 1520 | X37: 1495 | Y37: 1360 | Z37: 1360 | AA37: 800 | AB37: 1520 | AC37: 1600 | AD37: 1680 | AE37: 1520 | AF37: 32414

Sheet INVENTARIO INSUMOS QUÍMICOS GEM
B2: PRODUCTOS QUÍMICOS | C2: Densidad (g/ml) | D2: INVENTARIO INICIO DE MES | F2: CONSOLIDADO CONSUMO QUÍMICA MENSUAL | H2: TOTAL SUMINISTRO QUÍMICOS (PROVEEDOR) | J2: INVENTARIO ACTUALIZADO | L2: TOTAL EXTRA PROVEDOR | N2: INVENTARIO ACTUALIZADO REAL
D3: Litros | E3: Kg | F3: Litros | G3: Kg | H3: Litros | I3: Kg | J3: Litros | K3: Kg | L3: Litros | M3: Kg | N3: Litros | O3: Kg
B4: Ácido COF280 | C4: 1.24 | D4: 1.500 | E4: =D4*C4 -> 1860 | F4: =GETPIVOTDATA("COF 280 ACIDO (L)",'CONSUMO QUÍMICA-CAUDALES GEM '!$A$2) -> 7170 | G4: =GETPIVOTDATA("COF 280 - KG ACIDO",'CONSUMO QUÍMICA-CAUDALES GEM '!$A$13) -> 9321 | H4: =(+C15+E15+G15+I15+K15+M15+O15+Q15+S15) -> 8387.1613 | I4: =H4*C4 -> 10400.08 | J4: =(D4+H4)-F4 -> 2717.1613 | K4: =J4*$C4 -> 3369.28 | L4: =97+48+97 -> 242 | M4: =L4*$C4 -> 300.08 | N4: =J4-L4-1000 -> 1475.1613 | O4: =N4*$C4 -> 1829.2
B5: Coagulante COF235 | C5: 1.325 | D5: 3500 | E5: =D5*C5 -> 4637.5 | F5: =GETPIVOTDATA("COF 235 COAGULANTE (L)",'CONSUMO QUÍMICA-CAUDALES GEM '!$A$2) -> 9830 | G5: =GETPIVOTDATA("COF 235 - KG COAGULANTE",'CONSUMO QUÍMICA-CAUDALES GEM '!$A$13) -> 13024.75 | H5: =(+C16+E16+G16+I16+K16+M16+O16+Q16+S16) -> 13000 | I5: =H5*C5 -> 17225 | J5: =(D5+H5)-F5 -> 6670 | K5: =J5*$C5 -> 8837.75 | L5: 0 | M5: =L5*$C5 -> 0 | N5: =J5-L5 -> 6670 | O5: =N5*$C5 -> 8837.75
B6: Decolorante COF255 | C6: 1.1 | D6: 420 | E6: =D6*C6 -> 462 | F6: =GETPIVOTDATA("COF 255 DECOLORANTE (L)",'CONSUMO QUÍMICA-CAUDALES GEM '!$A$2) -> 3840 | G6: =GETPIVOTDATA("COF 255 - KG DECOLORANTE ",'CONSUMO QUÍMICA-CAUDALES GEM '!$A$13) -> 4800 | H6: =(+C17+E17+G17+I17+K17+M17+O17+Q17+S17) -> 7681.7273 | I6: =H6*C6 -> 8449.9 | J6: =(D6+H6)-F6 -> 4261.7273 | K6: =J6*$C6 -> 4687.9 | L6: =273+273+273+409+136 -> 1364 | M6: =L6*$C6 -> 1500.4 | N6: =J6-L6 -> 2897.7273 | O6: =N6*$C6 -> 3187.5
B7: Polimero COF440 (Aniónico) | C7: 0.0025 | D7: 140 | E7: =D7*C7 -> 0.35 | F7: =(GETPIVOTDATA("COF 440 POL ANIONICO (KG)",'CONSUMO QUÍMICA-CAUDALES GEM '!$A$2)/C7) -> 78000 | G7: =GETPIVOTDATA("COF 440 - KG POL ANIONICO ",'CONSUMO QUÍMICA-CAUDALES GEM '!$A$13) -> 195 | H7: =(+C18+E18+G18+I18+K18+M18+O18+Q18+S18) -> 30000 | I7: =H7*C7 -> 75 | J7: =(D7+H7)-F7 -> -47860 | K7: =J7*$C7 -> -119.65 | L7: 0 | M7: =L7*$C7 -> 0 | N7: =J7-L7 -> -47860 | O7: =N7*$C7 -> -119.65
B8: Polimero COF494 (Cátionico) | C8: 0.0025 | D8: 155 | E8: =D8*C8 -> 0.3875 | F8: 150000 | G8: =GETPIVOTDATA("COF 494 - KG POL CATIONICO ",'CONSUMO QUÍMICA-CAUDALES GEM '!$A$13) -> 355 | H8: =(+C19+E19+G19+I19+K19+M19+O19+Q19+S19) -> 40000 | I8: =H8*C8 -> 100 | J8: =(D8+H8)-F8 -> -109845 | K8: =J8*$C8 -> -274.6125 | L8: 0 | M8: =L8*$C8 -> 0 | N8: =J8-L8 -> -109845 | O8: =N8*$C8 -> -274.6125
B10: PRODUCTOS QUÍMICOS | C10: ENTREGAS DE INSUMOS QUÍMICOS PROVEEEDOR COFAI (FECHA)
C11: 45660 | E11: 3/01/2025 - 4/01/2025 | G11: 45672 | I11: 45674
C12: REM No | D12: O T | E12: REM No | F12: O T | G12: REM No | H12: O T | I12: REM No | J12: O T | K12: REM No | L12: O T | M12: REM No | N12: O T | O12: REM No | P12: O T | Q12: REM No | R12: O T | S12: REM No | T12: O T
C14: Litros | D14: Kg | E14: Litros | F14: Kg | G14: Litros | H14: Kg | I14: Litros | J14: Kg | K14: Litros | L14: Kg | M14: Litros | N14: Kg | O14: Litros | P14: Kg | Q14: Litros | R14: Kg | S14: Litros | T14: Kg
B15: Ácido COF280 | C15: 0 | D15: =C15*$C$4 -> 0 | E15: 2097 | F15: =E15*$C$4 -> 2600.28 | G15: 3145 | H15: =G15*$C$4 -> 3899.8 | I15: 3145.1613 | J15: =I15*$C$4 -> 3900
B16: Coagulante COF235 | C16: 1000 | D16: =+C16*$C$5 -> 1325 | E16: 3000 | F16: =+E16*$C$5 -> 3975 | G16: 4000 | H16: =+G16*$C$5 -> 5300 | I16: 5000 | J16: =+I16*$C$5 -> 6625
B17: Decolorante COF255 | C17: 1136 | D17: =+C17*$C$6 -> 1249.6 | E17: 2273 | F17: =+E17*$C$6 -> 2500.3 | G17: 2000 | H17: =+G17*$C$6 -> 2200 | I17: 2272.7273 | J17: =+I17*$C$6 -> 2500
B18: Polimero COF440 (Aniónico) | C18: 30000 | D18: =+C18*$C$7 -> 75 | E18: 0 | F18: =+E18*$C$7 -> 0 | G18: 0 | H18: =+G18*$C$7 -> 0 | I18: 0 | J18: =+I18*$C$7 -> 0
B19: Polimero COF494 (Cátionico) | C19: 0 | D19: =+C19*$C$8 -> 0 | E19: 0 | F19: =+E19*$C$8 -> 0 | G19: 0 | H19: =+G19*$C$8 -> 0 | I19: 40000 | J19: =+I19*$C$8 -> 100
B22: PRODUCTOS QUÍMICOS | C22: REGISTRO DENSIDADES DE INSUMOS QUÍMICOS PROVEEEDOR COFAI (FECHA)
C23: 2 | F23: 3 | I23: 4 | L23: 45667 | O23: 45668 | R23: 45670 | U23: 45672 | X23: 45673 | AA23: 45674 | AD23: 45677
C24: Litros | D24: Densidad (g/ml) | E24: Kg | F24: Litros | G24: Densidad (g/ml) | H24: Kg | I24: Litros | J24: Densidad (g/ml) | K24: Kg | L24: Litros | M24: Densidad (g/ml) | N24: Kg | O24: Litros | P24: Densidad (g/ml) | Q24: Kg | R24: Litros | S24: Densidad (g/ml) | T24: Kg | U24: Litros | V24: Densidad (g/ml) | W24: Kg | X24: Litros | Y24: Densidad (g/ml) | Z24: Kg | AA24: Litros | AB24: Densidad (g/ml) | AC24: Kg | AD24: Litros | AE24: Densidad (g/ml) | AF24: Kg
B25: Ácido COF280 | E25: =C25*D25 -> 0 | F25: 1 | H25: =F25*G25 -> 0 | I25: 1 | K25: =I25*J25 -> 0 | L25: 2 | N25: =L25*M25 -> 0 | Q25: =O25*P25 -> 0 | R25: 1 | T25: =R25*S25 -> 0 | W25: =U25*V25 -> 0 | X25: 3 | Z25: =X25*Y25 -> 0 | AC25: =AA25*AB25 -> 0 | AF25: =AD25*AE25 -> 0
B26: Coagulante COF235 | C26: 1 | E26: =C26*D26 -> 0 | F26: 1 | H26: =F26*G26 -> 0 | I26: 2 | K26: =I26*J26 -> 0 | N26: =L26*M26 -> 0 | O26: 3 | Q26: =O26*P26 -> 0 | T26: =R26*S26 -> 0 | U26: 3 | W26: =U26*V26 -> 0 | Z26: =X26*Y26 -> 0 | AA26: 3 | AC26: =AA26*AB26 -> 0 | AF26: =AD26*AE26 -> 0
B27: Decolorante COF255 | E27: =C27*D27 -> 0 | F27: 2 | H27: =F27*G27 -> 0 | K27: =I27*J27 -> 0 | L27: 1 | N27: =L27*M27 -> 0 | O27: 1 | Q27: =O27*P27 -> 0 | T27: =R27*S27 -> 0 | U27: 1 | W27: =U27*V27 -> 0 | X27: 1 | Z27: =X27*Y27 -> 0 | AC27: =AA27*AB27 -> 0 | AD27: 3 | AF27: =AD27*AE27 -> 0
B28: Polimero COF440 (Aniónico) | E28: =C28*D28 -> 0 | H28: =F28*G28 -> 0 | K28: =I28*J28 -> 0 | N28: =L28*M28 -> 0 | Q28: =O28*P28 -> 0 | T28: =R28*S28 -> 0 | W28: =U28*V28 -> 0 | Z28: =X28*Y28 -> 0 | AC28: =AA28*AB28 -> 0 | AF28: =AD28*AE28 -> 0
B29: Polimero COF494 (Cátionico) | E29: =C29*D29 -> 0 | H29: =F29*G29 -> 0 | K29: =I29*J29 -> 0 | N29: =L29*M29 -> 0 | Q29: =O29*P29 -> 0 | T29: =R29*S29 -> 0 | W29: =U29*V29 -> 0 | X29: 100 | Z29: =X29*Y29 -> 0 | AC29: =AA29*AB29 -> 0 | AF29: =AD29*AE29 -> 0

Sheet REGISTRO RO
A1: FECHA | B1: DIA | C1: TURNO | D1: HCL (10%) | E1: KURIVERTER IK-220 (Biocida) | F1: VITEC 7000 (Antiincrustante) | G1: Hidróxido de Sodio (NaOH) | H1: Bisulfito de sodio | I1: TIEMPO DE OPERACIÓN (minutos) | J1: VOLUMEN ENVIADO A RO (m3) | K1: Q DE OPERACIÓN (m3/h) | L1: cm HCL (10%) | M1: cm IK-220 (Biocida) | N1: cm Vitec 7000/4000 | O1: cm NaOH | P1: cm Bisulfito de sodio | Q1: (INV- L) - HCL (10%) | R1: (INV -L) - KURIVERTER IK-220 (Biocida) | S1: (INV -L) - VITEC 7000 (Antiincrustante) | T1: (INV -L) - Hidróxido de Sodio (NaOH) | U1: (INV -L) Bisulfito de sodio | V1: CONSUMO (L) HCL (10%)2 | W1: CONSUMO (L) KURIVERTER IK-220 (Biocida) | X1: CONSUMO (L) VITEC 7000 (Antiincrustante) | Y1: CONSUMO (L) Hidróxido de Sodio (NaOH) | Z1: CONSUMO (L) Bisulfito de sodio | AA1: DENSIDAD HCL (10%) | AB1: DENSIDAD KURIVERTER IK-220 (Biocida) | AC1: DENSIDAD VITEC 7000 (Antiincrustante) | AD1: DENSIDAD Hidróxido de Sodio (NaOH) | AE1: DENSIDAD Bisulfito de sodio | AF1: CONSUMO (Kg) HCL (10%)22 | AG1: CONSUMO (Kg) KURIVERTER IK-220 (Biocida) | AH1: CONSUMO (Kg) VITEC 7000 (Antiincrustante) | AI1: CONSUMO (Kg) Hidróxido de Sodio (NaOH) | AJ1: CONSUMO (Kg) Bisulfito de sodio6 | AK1: PPM HCL (10%) | AL1: PPM KURIVERTER IK-220 (Biocida) | AM1: PPM VITEC 7000 (Antiincrustante) | AN1: PPM Hidróxido de Sodio (NaOH) | AO1: PPM Bisulfito de sodio | AP1: PRECIO HCL (10%) | AQ1: PRECIO KURIVERTER IK-220 (Biocida) | AR1: PRECIO VITEC 7000 (Antiincrustante) | AS1: PRECIO Hidróxido de Sodio (NaOH) | AT1: PRECIO Bisulfito de sodio | AU1: COSTO OPERATIVO HCL (10%) | AV1: COSTO OPERATIVO KURIVERTER IK-220 (Biocida) | AW1: COSTO OPERATIVO VITEC 7000 (Antiincrustante) | AX1: COSTO OPERATIVO Hidróxido de Sodio (NaOH) | AY1: COSTO OPERATIVO Bisulfito de sodio | AZ1: COSTO QUIMICA | BA1: LIMITE INDICADOR M3 | BB1: $m3 ENVIADO A RO (m3)
A2: 46113 | B2: =DAY(Tabla2[[#This Row],[FECHA]]) -> 1 | C2: 1 (NOCHE) | I2: =Tabla2[[#This Row],[VOLUMEN ENVIADO A RO (m3)]]/Tabla2[[#This Row],[Q DE OPERACIÓN (m3/h)]] -> #DIV/0! | J2: 0 | K2: 0 | L2: 0 | M2: 0 | N2: 0 | O2: 0 | P2: 0 | Q2: =L2*(1000/114) -> 0 | R2: =M2*(1000/114) -> 0 | S2: =N2*(1000/114) -> 0 | T2: =O2*(1000/114) -> 0 | U2: =P2*(1000/114) -> 0 | V2: =Q2-Q3 -> 0 | W2: =R2-R3 -> 0 | X2: =S2-S3 -> 0 | Y2: =T2-T3 -> 0 | Z2: =U2-U3 -> 0 | AA2: 1.18 | AB2: 1.28 | AC2: 1.2 | AD2: 1.53 | AE2: 1.2 | AF2: =V2*AA2 -> 0 | AG2: =W2*AB2 -> 0 | AH2: =X2*AC2 -> 0 | AI2: =Y2*AD2 -> 0 | AJ2: =Z2*AE2 -> 0 | AK2: =(AF2*1000)/$J2 -> #DIV/0! | AL2: =(AG2*1000)/$J2 -> #DIV/0! | AM2: =(AH2*1000)/$J2 -> #DIV/0! | AN2: =(AI2*1000)/$J2 -> #DIV/0! | AO2: =(AJ2*1000)/$J2 -> #DIV/0! | AP2: 1650 | AQ2: 19160 | AR2: 36239 | AS2: 1298 | AT2: 4200 | AU2: =AP2*(AG2*0.8) -> 0 | AV2: =AQ2*(AH2*0.012) -> 0 | AW2: =AR2*(AI2*0.044) -> 0 | AX2: =AS2*AJ2 -> 0 | AY2: =AT2*(J2*0.025) -> 0 | AZ2: =AU2+AV2+AW2+AX2+AY2 -> 0 | BA2: 1000 | BB2: =+Tabla2[[#This Row],[COSTO QUIMICA ]]/Tabla2[[#This Row],[VOLUMEN ENVIADO A RO (m3)]] -> #DIV/0!
A3: =+A2 -> 46113 | B3: =DAY(Tabla2[[#This Row],[FECHA]]) -> 1 | C3: 2 (MAÑANA) | I3: =Tabla2[[#This Row],[VOLUMEN ENVIADO A RO (m3)]]/Tabla2[[#This Row],[Q DE OPERACIÓN (m3/h)]] -> #DIV/0! | J3: 0 | K3: 0 | L3: 0 | M3: 0 | N3: 0 | O3: 0 | P3: 0 | Q3: =L3*(1000/114) -> 0 | R3: =M3*(1000/114) -> 0 | S3: =N3*(1000/114) -> 0 | T3: =O3*(1000/114) -> 0 | U3: =P3*(1000/114) -> 0 | V3: =Q3-Q4 -> 0 | W3: =R3-R4 -> 0 | X3: =S3-S4 -> 0 | Y3: =T3-T4 -> 0 | Z3: =U3-U4 -> 0 | AA3: 1.18 | AB3: 1.28 | AC3: 1.2 | AD3: 1.53 | AE3: 1.2 | AF3: =V3*AA3 -> 0 | AG3: =W3*AB3 -> 0 | AH3: =X3*AC3 -> 0 | AI3: =Y3*AD3 -> 0 | AJ3: =Z3*AE3 -> 0 | AK3: =(AF3*1000)/$J3 -> #DIV/0! | AL3: =(AG3*1000)/$J3 -> #DIV/0! | AM3: =(AH3*1000)/$J3 -> #DIV/0! | AN3: =(AI3*1000)/$J3 -> #DIV/0! | AO3: =(AJ3*1000)/$J3 -> #DIV/0! | AP3: =AP2 -> 1650 | AQ3: =AQ2 -> 19160 | AR3: =AR2 -> 36239 | AS3: =AS2 -> 1298 | AT3: =AT2 -> 4200 | AU3: =AP3*(AG3*0.8) -> 0 | AV3: =AQ3*(AH3*0.012) -> 0 | AW3: =AR3*(AI3*0.044) -> 0 | AX3: =AS3*AJ3 -> 0 | AY3: =AT3*(J3*0.025) -> 0 | AZ3: =AU3+AV3+AW3+AX3+AY3 -> 0 | BA3: 1000 | BB3: =+Tabla2[[#This Row],[COSTO QUIMICA ]]/Tabla2[[#This Row],[VOLUMEN ENVIADO A RO (m3)]] -> #DIV/0!
A4: =+A3 -> 46113 | B4: =DAY(Tabla2[[#This Row],[FECHA]]) -> 1 | C4: 3(TARDE) | I4: =Tabla2[[#This Row],[VOLUMEN ENVIADO A RO (m3)]]/Tabla2[[#This Row],[Q DE OPERACIÓN (m3/h)]] -> #DIV/0! | J4: 0 | K4: 0 | L4: 0 | M4: 0 | N4: 0 | O4: 0 | P4: 0 | Q4: =L4*(1000/114) -> 0 | R4: =M4*(1000/114) -> 0 | S4: =N4*(1000/114) -> 0 | T4: =O4*(1000/114) -> 0 | U4: =P4*(1000/114) -> 0 | V4: =Q4-Q5 -> 0 | W4: =R4-R5 -> 0 | X4: =S4-S5 -> 0 | Y4: =T4-T5 -> 0 | Z4: =U4-U5 -> 0 | AA4: 1.18 | AB4: 1.28 | AC4: 1.2 | AD4: 1.53 | AE4: 1.2 | AF4: =V4*AA4 -> 0 | AG4: =W4*AB4 -> 0 | AH4: =X4*AC4 -> 0 | AI4: =Y4*AD4 -> 0 | AJ4: =Z4*AE4 -> 0 | AK4: =(AF4*1000)/$J4 -> #DIV/0! | AL4: =(AG4*1000)/$J4 -> #DIV/0! | AM4: =(AH4*1000)/$J4 -> #DIV/0! | AN4: =(AI4*1000)/$J4 -> #DIV/0! | AO4: =(AJ4*1000)/$J4 -> #DIV/0! | AP4: =AP3 -> 1650 | AQ4: =AQ3 -> 19160 | AR4: =AR3 -> 36239 | AS4: =AS3 -> 1298 | AT4: =AT3 -> 4200 | AU4: =AP4*(AG4*0.8) -> 0 | AV4: =AQ4*(AH4*0.012) -> 0 | AW4: =AR4*(AI4*0.044) -> 0 | AX4: =AS4*AJ4 -> 0 | AY4: =AT4*(J4*0.025) -> 0 | AZ4: =AU4+AV4+AW4+AX4+AY4 -> 0 | BA4: 1000 | BB4: =+Tabla2[[#This Row],[COSTO QUIMICA ]]/Tabla2[[#This Row],[VOLUMEN ENVIADO A RO (m3)]] -> #DIV/0!
A5: =+A4+1 -> 46114 | B5: =DAY(Tabla2[[#This Row],[FECHA]]) -> 2 | C5: 1 (NOCHE) | I5: =Tabla2[[#This Row],[VOLUMEN ENVIADO A RO (m3)]]/Tabla2[[#This Row],[Q DE OPERACIÓN (m3/h)]] -> #DIV/0! | J5: 0 | K5: 0 | L5: 0 | M5: 0 | N5: 0 | O5: 0 | P5: 0 | Q5: =L5*(1000/114) -> 0 | R5: =M5*(1000/114) -> 0 | S5: =N5*(1000/114) -> 0 | T5: =O5*(1000/114) -> 0 | U5: =P5*(1000/114) -> 0 | V5: =Q5-Q6 -> 0 | W5: =R5-R6 -> 0 | X5: =S5-S6 -> 0 | Y5: =T5-T6 -> 0 | Z5: =U5-U6 -> 0 | AA5: 1.18 | AB5: 1.28 | AC5: 1.2 | AD5: 1.53 | AE5: 1.2 | AF5: =V5*AA5 -> 0 | AG5: =W5*AB5 -> 0 | AH5: =X5*AC5 -> 0 | AI5: =Y5*AD5 -> 0 | AJ5: =Z5*AE5 -> 0 | AK5: =(AF5*1000)/$J5 -> #DIV/0! | AL5: =(AG5*1000)/$J5 -> #DIV/0! | AM5: =(AH5*1000)/$J5 -> #DIV/0! | AN5: =(AI5*1000)/$J5 -> #DIV/0! | AO5: =(AJ5*1000)/$J5 -> #DIV/0! | AP5: =AP4 -> 1650 | AQ5: =AQ4 -> 19160 | AR5: =AR4 -> 36239 | AS5: =AS4 -> 1298 | AT5: =AT4 -> 4200 | AU5: =AP5*(AG5*0.8) -> 0 | AV5: =AQ5*(AH5*0.012) -> 0 | AW5: =AR5*(AI5*0.044) -> 0 | AX5: =AS5*AJ5 -> 0 | AY5: =AT5*(J5*0.025) -> 0 | AZ5: =AU5+AV5+AW5+AX5+AY5 -> 0 | BA5: 1000 | BB5: =+Tabla2[[#This Row],[COSTO QUIMICA ]]/Tabla2[[#This Row],[VOLUMEN ENVIADO A RO (m3)]] -> #DIV/0!
A6: =+A5 -> 46114 | B6: =DAY(Tabla2[[#This Row],[FECHA]]) -> 2 | C6: 2 (MAÑANA) | I6: =Tabla2[[#This Row],[VOLUMEN ENVIADO A RO (m3)]]/Tabla2[[#This Row],[Q DE OPERACIÓN (m3/h)]] -> #DIV/0! | J6: 0 | K6: 0 | L6: 0 | M6: 0 | N6: 0 | O6: 0 | P6: 0 | Q6: =L6*(1000/114) -> 0 | R6: =M6*(1000/114) -> 0 | S6: =N6*(1000/114) -> 0 | T6: =O6*(1000/114) -> 0 | U6: =P6*(1000/114) -> 0 | V6: =Q6-Q7 -> 0 | W6: =R6-R7 -> 0 | X6: =S6-S7 -> 0 | Y6: =T6-T7 -> 0 | Z6: =U6-U7 -> 0 | AA6: 1.18 | AB6: 1.28 | AC6: 1.2 | AD6: 1.53 | AE6: 1.2 | AF6: =V6*AA6 -> 0 | AG6: =W6*AB6 -> 0 | AH6: =X6*AC6 -> 0 | AI6: =Y6*AD6 -> 0 | AJ6: =Z6*AE6 -> 0 | AK6: =(AF6*1000)/$J6 -> #DIV/0! | AL6: =(AG6*1000)/$J6 -> #DIV/0! | AM6: =(AH6*1000)/$J6 -> #DIV/0! | AN6: =(AI6*1000)/$J6 -> #DIV/0! | AO6: =(AJ6*1000)/$J6 -> #DIV/0! | AP6: =AP5 -> 1650 | AQ6: =AQ5 -> 19160 | AR6: =AR5 -> 36239 | AS6: =AS5 -> 1298 | AT6: =AT5 -> 4200 | AU6: =AP6*(AG6*0.8) -> 0 | AV6: =AQ6*(AH6*0.012) -> 0 | AW6: =AR6*(AI6*0.044) -> 0 | AX6: =AS6*AJ6 -> 0 | AY6: =AT6*(J6*0.025) -> 0 | AZ6: =AU6+AV6+AW6+AX6+AY6 -> 0 | BA6: 1000 | BB6: =+Tabla2[[#This Row],[COSTO QUIMICA ]]/Tabla2[[#This Row],[VOLUMEN ENVIADO A RO (m3)]] -> #DIV/0!
A7: =+A6 -> 46114 | B7: =DAY(Tabla2[[#This Row],[FECHA]]) -> 2 | C7: 3(TARDE) | I7: =Tabla2[[#This Row],[VOLUMEN ENVIADO A RO (m3)]]/Tabla2[[#This Row],[Q DE OPERACIÓN (m3/h)]] -> #DIV/0! | J7: 0 | K7: 0 | L7: 0 | M7: 0 | N7: 0 | O7: 0 | P7: 0 | Q7: =L7*(1000/114) -> 0 | R7: =M7*(1000/114) -> 0 | S7: =N7*(1000/114) -> 0 | T7: =O7*(1000/114) -> 0 | U7: =P7*(1000/114) -> 0 | V7: =Q7-Q8 -> 0 | W7: =R7-R8 -> 0 | X7: =S7-S8 -> 0 | Y7: =T7-T8 -> 0 | Z7: =U7-U8 -> 0 | AA7: 1.18 | AB7: 1.28 | AC7: 1.2 | AD7: 1.53 | AE7: 1.2 | AF7: =V7*AA7 -> 0 | AG7: =W7*AB7 -> 0 | AH7: =X7*AC7 -> 0 | AI7: =Y7*AD7 -> 0 | AJ7: =Z7*AE7 -> 0 | AK7: =(AF7*1000)/$J7 -> #DIV/0! | AL7: =(AG7*1000)/$J7 -> #DIV/0! | AM7: =(AH7*1000)/$J7 -> #DIV/0! | AN7: =(AI7*1000)/$J7 -> #DIV/0! | AO7: =(AJ7*1000)/$J7 -> #DIV/0! | AP7: =AP6 -> 1650 | AQ7: =AQ6 -> 19160 | AR7: =AR6 -> 36239 | AS7: =AS6 -> 1298 | AT7: =AT6 -> 4200 | AU7: =AP7*(AG7*0.8) -> 0 | AV7: =AQ7*(AH7*0.012) -> 0 | AW7: =AR7*(AI7*0.044) -> 0 | AX7: =AS7*AJ7 -> 0 | AY7: =AT7*(J7*0.025) -> 0 | AZ7: =AU7+AV7+AW7+AX7+AY7 -> 0 | BA7: 1000 | BB7: =+Tabla2[[#This Row],[COSTO QUIMICA ]]/Tabla2[[#This Row],[VOLUMEN ENVIADO A RO (m3)]] -> #DIV/0!
A8: =+A7+1 -> 46115 | B8: =DAY(Tabla2[[#This Row],[FECHA]]) -> 3 | C8: 1 (NOCHE) | I8: =Tabla2[[#This Row],[VOLUMEN ENVIADO A RO (m3)]]/Tabla2[[#This Row],[Q DE OPERACIÓN (m3/h)]] -> #DIV/0! | J8: 0 | K8: 0 | L8: 0 | M8: 0 | N8: 0 | O8: 0 | P8: 0 | Q8: =L8*(1000/114) -> 0 | R8: =M8*(1000/114) -> 0 | S8: =N8*(1000/114) -> 0 | T8: =O8*(1000/114) -> 0 | U8: =P8*(1000/114) -> 0 | V8: =Q8-Q9 -> 0 | W8: =R8-R9 -> 0 | X8: =S8-S9 -> 0 | Y8: =T8-T9 -> 0 | Z8: =U8-U9 -> 0 | AA8: 1.18 | AB8: 1.28 | AC8: 1.2 | AD8: 1.53 | AE8: 1.2 | AF8: =V8*AA8 -> 0 | AG8: =W8*AB8 -> 0 | AH8: =X8*AC8 -> 0 | AI8: =Y8*AD8 -> 0 | AJ8: =Z8*AE8 -> 0 | AK8: =(AF8*1000)/$J8 -> #DIV/0! | AL8: =(AG8*1000)/$J8 -> #DIV/0! | AM8: =(AH8*1000)/$J8 -> #DIV/0! | AN8: =(AI8*1000)/$J8 -> #DIV/0! | AO8: =(AJ8*1000)/$J8 -> #DIV/0! | AP8: =AP7 -> 1650 | AQ8: =AQ7 -> 19160 | AR8: =AR7 -> 36239 | AS8: =AS7 -> 1298 | AT8: =AT7 -> 4200 | AU8: =AP8*(AG8*0.8) -> 0 | AV8: =AQ8*(AH8*0.012) -> 0 | AW8: =AR8*(AI8*0.044) -> 0 | AX8: =AS8*AJ8 -> 0 | AY8: =AT8*(J8*0.025) -> 0 | AZ8: =AU8+AV8+AW8+AX8+AY8 -> 0 | BA8: 1000 | BB8: =+Tabla2[[#This Row],[COSTO QUIMICA ]]/Tabla2[[#This Row],[VOLUMEN ENVIADO A RO (m3)]] -> #DIV/0!
A9: =+A8 -> 46115 | B9: =DAY(Tabla2[[#This Row],[FECHA]]) -> 3 | C9: 2 (MAÑANA) | I9: =Tabla2[[#This Row],[VOLUMEN ENVIADO A RO (m3)]]/Tabla2[[#This Row],[Q DE OPERACIÓN (m3/h)]] -> #DIV/0! | J9: 0 | K9: 0 | L9: 0 | M9: 0 | N9: 0 | O9: 0 | P9: 0 | Q9: =L9*(1000/114) -> 0 | R9: =M9*(1000/114) -> 0 | S9: =N9*(1000/114) -> 0 | T9: =O9*(1000/114) -> 0 | U9: =P9*(1000/114) -> 0 | V9: =Q9-Q10 -> 0 | W9: =R9-R10 -> 0 | X9: =S9-S10 -> 0 | Y9: =T9-T10 -> 0 | Z9: =U9-U10 -> 0 | AA9: 1.18 | AB9: 1.28 | AC9: 1.2 | AD9: 1.53 | AE9: 1.2 | AF9: =V9*AA9 -> 0 | AG9: =W9*AB9 -> 0 | AH9: =X9*AC9 -> 0 | AI9: =Y9*AD9 -> 0 | AJ9: =Z9*AE9 -> 0 | AK9: =(AF9*1000)/$J9 -> #DIV/0! | AL9: =(AG9*1000)/$J9 -> #DIV/0! | AM9: =(AH9*1000)/$J9 -> #DIV/0! | AN9: =(AI9*1000)/$J9 -> #DIV/0! | AO9: =(AJ9*1000)/$J9 -> #DIV/0! | AP9: =AP8 -> 1650 | AQ9: =AQ8 -> 19160 | AR9: =AR8 -> 36239 | AS9: =AS8 -> 1298 | AT9: =AT8 -> 4200 | AU9: =AP9*(AG9*0.8) -> 0 | AV9: =AQ9*(AH9*0.012) -> 0 | AW9: =AR9*(AI9*0.044) -> 0 | AX9: =AS9*AJ9 -> 0 | AY9: =AT9*(J9*0.025) -> 0 | AZ9: =AU9+AV9+AW9+AX9+AY9 -> 0 | BA9: 1000 | BB9: =+Tabla2[[#This Row],[COSTO QUIMICA ]]/Tabla2[[#This Row],[VOLUMEN ENVIADO A RO (m3)]] -> #DIV/0!
A10: =+A9 -> 46115 | B10: =DAY(Tabla2[[#This Row],[FECHA]]) -> 3 | C10: 3(TARDE) | I10: =Tabla2[[#This Row],[VOLUMEN ENVIADO A RO (m3)]]/Tabla2[[#This Row],[Q DE OPERACIÓN (m3/h)]] -> #DIV/0! | J10: 0 | K10: 0 | L10: 0 | M10: 0 | N10: 0 | O10: 0 | P10: 0 | Q10: =L10*(1000/114) -> 0 | R10: =M10*(1000/114) -> 0 | S10: =N10*(1000/114) -> 0 | T10: =O10*(1000/114) -> 0 | U10: =P10*(1000/114) -> 0 | V10: =Q10-Q11 -> 0 | W10: =R10-R11 -> 0 | X10: =S10-S11 -> 0 | Y10: =T10-T11 -> 0 | Z10: =U10-U11 -> 0 | AA10: 1.18 | AB10: 1.28 | AC10: 1.2 | AD10: 1.53 | AE10: 1.2 | AF10: =V10*AA10 -> 0 | AG10: =W10*AB10 -> 0 | AH10: =X10*AC10 -> 0 | AI10: =Y10*AD10 -> 0 | AJ10: =Z10*AE10 -> 0 | AK10: =(AF10*1000)/$J10 -> #DIV/0! | AL10: =(AG10*1000)/$J10 -> #DIV/0! | AM10: =(AH10*1000)/$J10 -> #DIV/0! | AN10: =(AI10*1000)/$J10 -> #DIV/0! | AO10: =(AJ10*1000)/$J10 -> #DIV/0! | AP10: =AP9 -> 1650 | AQ10: =AQ9 -> 19160 | AR10: =AR9 -> 36239 | AS10: =AS9 -> 1298 | AT10: =AT9 -> 4200 | AU10: =AP10*(AG10*0.8) -> 0 | AV10: =AQ10*(AH10*0.012) -> 0 | AW10: =AR10*(AI10*0.044) -> 0 | AX10: =AS10*AJ10 -> 0 | AY10: =AT10*(J10*0.025) -> 0 | AZ10: =AU10+AV10+AW10+AX10+AY10 -> 0 | BA10: 1000 | BB10: =+Tabla2[[#This Row],[COSTO QUIMICA ]]/Tabla2[[#This Row],[VOLUMEN ENVIADO A RO (m3)]] -> #DIV/0!
A11: =+A10+1 -> 46116 | B11: =DAY(Tabla2[[#This Row],[FECHA]]) -> 4 | C11: 1 (NOCHE) | I11: =Tabla2[[#This Row],[VOLUMEN ENVIADO A RO (m3)]]/Tabla2[[#This Row],[Q DE OPERACIÓN (m3/h)]] -> #DIV/0! | J11: 0 | K11: 0 | L11: 0 | M11: 0 | N11: 0 | O11: 0 | P11: 0 | Q11: =L11*(1000/114) -> 0 | R11: =M11*(1000/114) -> 0 | S11: =N11*(1000/114) -> 0 | T11: =O11*(1000/114) -> 0 | U11: =P11*(1000/114) -> 0 | V11: =Q11-Q12 -> 0 | W11: =R11-R12 -> 0 | X11: =S11-S12 -> 0 | Y11: =T11-T12 -> 0 | Z11: =U11-U12 -> 0 | AA11: 1.18 | AB11: 1.28 | AC11: 1.2 | AD11: 1.53 | AE11: 1.2 | AF11: =V11*AA11 -> 0 | AG11: =W11*AB11 -> 0 | AH11: =X11*AC11 -> 0 | AI11: =Y11*AD11 -> 0 | AJ11: =Z11*AE11 -> 0 | AK11: =(AF11*1000)/$J11 -> #DIV/0! | AL11: =(AG11*1000)/$J11 -> #DIV/0! | AM11: =(AH11*1000)/$J11 -> #DIV/0! | AN11: =(AI11*1000)/$J11 -> #DIV/0! | AO11: =(AJ11*1000)/$J11 -> #DIV/0! | AP11: =AP10 -> 1650 | AQ11: =AQ10 -> 19160 | AR11: =AR10 -> 36239 | AS11: =AS10 -> 1298 | AT11: =AT10 -> 4200 | AU11: =AP11*(AG11*0.8) -> 0 | AV11: =AQ11*(AH11*0.012) -> 0 | AW11: =AR11*(AI11*0.044) -> 0 | AX11: =AS11*AJ11 -> 0 | AY11: =AT11*(J11*0.025) -> 0 | AZ11: =AU11+AV11+AW11+AX11+AY11 -> 0 | BA11: 1000 | BB11: =+Tabla2[[#This Row],[COSTO QUIMICA ]]/Tabla2[[#This Row],[VOLUMEN ENVIADO A RO (m3)]] -> #DIV/0!
A12: =+A11 -> 46116 | B12: =DAY(Tabla2[[#This Row],[FECHA]]) -> 4 | C12: 2 (MAÑANA) | I12: =Tabla2[[#This Row],[VOLUMEN ENVIADO A RO (m3)]]/Tabla2[[#This Row],[Q DE OPERACIÓN (m3/h)]] -> #DIV/0! | J12: 0 | K12: 0 | L12: 0 | M12: 0 | N12: 0 | O12: 0 | P12: 0 | Q12: =L12*(1000/114) -> 0 | R12: =M12*(1000/114) -> 0 | S12: =N12*(1000/114) -> 0 | T12: =O12*(1000/114) -> 0 | U12: =P12*(1000/114) -> 0 | V12: =Q12-Q13 -> 0 | W12: =R12-R13 -> 0 | X12: =S12-S13 -> 0 | Y12: =T12-T13 -> 0 | Z12: =U12-U13 -> 0 | AA12: 1.18 | AB12: 1.28 | AC12: 1.2 | AD12: 1.53 | AE12: 1.2 | AF12: =V12*AA12 -> 0 | AG12: =W12*AB12 -> 0 | AH12: =X12*AC12 -> 0 | AI12: =Y12*AD12 -> 0 | AJ12: =Z12*AE12 -> 0 | AK12: =(AF12*1000)/$J12 -> #DIV/0! | AL12: =(AG12*1000)/$J12 -> #DIV/0! | AM12: =(AH12*1000)/$J12 -> #DIV/0! | AN12: =(AI12*1000)/$J12 -> #DIV/0! | AO12: =(AJ12*1000)/$J12 -> #DIV/0! | AP12: =AP11 -> 1650 | AQ12: =AQ11 -> 19160 | AR12: =AR11 -> 36239 | AS12: =AS11 -> 1298 | AT12: =AT11 -> 4200 | AU12: =AP12*(AG12*0.8) -> 0 | AV12: =AQ12*(AH12*0.012) -> 0 | AW12: =AR12*(AI12*0.044) -> 0 | AX12: =AS12*AJ12 -> 0 | AY12: =AT12*(J12*0.025) -> 0 | AZ12: =AU12+AV12+AW12+AX12+AY12 -> 0 | BA12: 1000 | BB12: =+Tabla2[[#This Row],[COSTO QUIMICA ]]/Tabla2[[#This Row],[VOLUMEN ENVIADO A RO (m3)]] -> #DIV/0!
A13: =+A12 -> 46116 | B13: =DAY(Tabla2[[#This Row],[FECHA]]) -> 4 | C13: 3(TARDE) | I13: =Tabla2[[#This Row],[VOLUMEN ENVIADO A RO (m3)]]/Tabla2[[#This Row],[Q DE OPERACIÓN (m3/h)]] -> #DIV/0! | J13: 0 | K13: 0 | L13: 0 | M13: 0 | N13: 0 | O13: 0 | P13: 0 | Q13: =L13*(1000/114) -> 0 | R13: =M13*(1000/114) -> 0 | S13: =N13*(1000/114) -> 0 | T13: =O13*(1000/114) -> 0 | U13: =P13*(1000/114) -> 0 | V13: =Q13-Q14 -> 0 | W13: =R13-R14 -> 0 | X13: =S13-S14 -> 0 | Y13: =T13-T14 -> 0 | Z13: =U13-U14 -> 0 | AA13: 1.18 | AB13: 1.28 | AC13: 1.2 | AD13: 1.53 | AE13: 1.2 | AF13: =V13*AA13 -> 0 | AG13: =W13*AB13 -> 0 | AH13: =X13*AC13 -> 0 | AI13: =Y13*AD13 -> 0 | AJ13: =Z13*AE13 -> 0 | AK13: =(AF13*1000)/$J13 -> #DIV/0! | AL13: =(AG13*1000)/$J13 -> #DIV/0! | AM13: =(AH13*1000)/$J13 -> #DIV/0! | AN13: =(AI13*1000)/$J13 -> #DIV/0! | AO13: =(AJ13*1000)/$J13 -> #DIV/0! | AP13: =AP12 -> 1650 | AQ13: =AQ12 -> 19160 | AR13: =AR12 -> 36239 | AS13: =AS12 -> 1298 | AT13: =AT12 -> 4200 | AU13: =AP13*(AG13*0.8) -> 0 | AV13: =AQ13*(AH13*0.012) -> 0 | AW13: =AR13*(AI13*0.044) -> 0 | AX13: =AS13*AJ13 -> 0 | AY13: =AT13*(J13*0.025) -> 0 | AZ13: =AU13+AV13+AW13+AX13+AY13 -> 0 | BA13: 1000 | BB13: =+Tabla2[[#This Row],[COSTO QUIMICA ]]/Tabla2[[#This Row],[VOLUMEN ENVIADO A RO (m3)]] -> #DIV/0!
A14: =+A13+1 -> 46117 | B14: =DAY(Tabla2[[#This Row],[FECHA]]) -> 5 | C14: 1 (NOCHE) | I14: =Tabla2[[#This Row],[VOLUMEN ENVIADO A RO (m3)]]/Tabla2[[#This Row],[Q DE OPERACIÓN (m3/h)]] -> #DIV/0! | J14: 0 | K14: 0 | L14: 0 | M14: 0 | N14: 0 | O14: 0 | P14: 0 | Q14: =L14*(1000/114) -> 0 | R14: =M14*(1000/114) -> 0 | S14: =N14*(1000/114) -> 0 | T14: =O14*(1000/114) -> 0 | U14: =P14*(1000/114) -> 0 | V14: =Q14-Q15 -> 0 | W14: =R14-R15 -> 0 | X14: =S14-S15 -> 0 | Y14: =T14-T15 -> 0 | Z14: =U14-U15 -> 0 | AA14: 1.18 | AB14: 1.28 | AC14: 1.2 | AD14: 1.53 | AE14: 1.2 | AF14: =V14*AA14 -> 0 | AG14: =W14*AB14 -> 0 | AH14: =X14*AC14 -> 0 | AI14: =Y14*AD14 -> 0 | AJ14: =Z14*AE14 -> 0 | AK14: =(AF14*1000)/$J14 -> #DIV/0! | AL14: =(AG14*1000)/$J14 -> #DIV/0! | AM14: =(AH14*1000)/$J14 -> #DIV/0! | AN14: =(AI14*1000)/$J14 -> #DIV/0! | AO14: =(AJ14*1000)/$J14 -> #DIV/0! | AP14: =AP13 -> 1650 | AQ14: =AQ13 -> 19160 | AR14: =AR13 -> 36239 | AS14: =AS13 -> 1298 | AT14: =AT13 -> 4200 | AU14: =AP14*(AG14*0.8) -> 0 | AV14: =AQ14*(AH14*0.012) -> 0 | AW14: =AR14*(AI14*0.044) -> 0 | AX14: =AS14*AJ14 -> 0 | AY14: =AT14*(J14*0.025) -> 0 | AZ14: =AU14+AV14+AW14+AX14+AY14 -> 0 | BA14: 1000 | BB14: =+Tabla2[[#This Row],[COSTO QUIMICA ]]/Tabla2[[#This Row],[VOLUMEN ENVIADO A RO (m3)]] -> #DIV/0!
A15: =+A14 -> 46117 | B15: =DAY(Tabla2[[#This Row],[FECHA]]) -> 5 | C15: 2 (MAÑANA) | I15: =Tabla2[[#This Row],[VOLUMEN ENVIADO A RO (m3)]]/Tabla2[[#This Row],[Q DE OPERACIÓN (m3/h)]] -> #DIV/0! | J15: 0 | K15: 0 | L15: 0 | M15: 0 | N15: 0 | O15: 0 | P15: 0 | Q15: =L15*(1000/114) -> 0 | R15: =M15*(1000/114) -> 0 | S15: =N15*(1000/114) -> 0 | T15: =O15*(1000/114) -> 0 | U15: =P15*(1000/114) -> 0 | V15: =Q15-Q16 -> 0 | W15: =R15-R16 -> 0 | X15: =S15-S16 -> 0 | Y15: =T15-T16 -> 0 | Z15: =U15-U16 -> 0 | AA15: 1.18 | AB15: 1.28 | AC15: 1.2 | AD15: 1.53 | AE15: 1.2 | AF15: =V15*AA15 -> 0 | AG15: =W15*AB15 -> 0 | AH15: =X15*AC15 -> 0 | AI15: =Y15*AD15 -> 0 | AJ15: =Z15*AE15 -> 0 | AK15: =(AF15*1000)/$J15 -> #DIV/0! | AL15: =(AG15*1000)/$J15 -> #DIV/0! | AM15: =(AH15*1000)/$J15 -> #DIV/0! | AN15: =(AI15*1000)/$J15 -> #DIV/0! | AO15: =(AJ15*1000)/$J15 -> #DIV/0! | AP15: =AP14 -> 1650 | AQ15: =AQ14 -> 19160 | AR15: =AR14 -> 36239 | AS15: =AS14 -> 1298 | AT15: =AT14 -> 4200 | AU15: =AP15*(AG15*0.8) -> 0 | AV15: =AQ15*(AH15*0.012) -> 0 | AW15: =AR15*(AI15*0.044) -> 0 | AX15: =AS15*AJ15 -> 0 | AY15: =AT15*(J15*0.025) -> 0 | AZ15: =AU15+AV15+AW15+AX15+AY15 -> 0 | BA15: 1000 | BB15: =+Tabla2[[#This Row],[COSTO QUIMICA ]]/Tabla2[[#This Row],[VOLUMEN ENVIADO A RO (m3)]] -> #DIV/0!
A16: =+A15 -> 46117 | B16: =DAY(Tabla2[[#This Row],[FECHA]]) -> 5 | C16: 3(TARDE) | I16: =Tabla2[[#This Row],[VOLUMEN ENVIADO A RO (m3)]]/Tabla2[[#This Row],[Q DE OPERACIÓN (m3/h)]] -> #DIV/0! | J16: 0 | K16: 0 | L16: 0 | M16: 0 | N16: 0 | O16: 0 | P16: 0 | Q16: =L16*(1000/114) -> 0 | R16: =M16*(1000/114) -> 0 | S16: =N16*(1000/114) -> 0 | T16: =O16*(1000/114) -> 0 | U16: =P16*(1000/114) -> 0 | V16: =Q16-Q17 -> 0 | W16: =R16-R17 -> 0 | X16: =S16-S17 -> 0 | Y16: =T16-T17 -> 0 | Z16: =U16-U17 -> 0 | AA16: 1.18 | AB16: 1.28 | AC16: 1.2 | AD16: 1.53 | AE16: 1.2 | AF16: =V16*AA16 -> 0 | AG16: =W16*AB16 -> 0 | AH16: =X16*AC16 -> 0 | AI16: =Y16*AD16 -> 0 | AJ16: =Z16*AE16 -> 0 | AK16: =(AF16*1000)/$J16 -> #DIV/0! | AL16: =(AG16*1000)/$J16 -> #DIV/0! | AM16: =(AH16*1000)/$J16 -> #DIV/0! | AN16: =(AI16*1000)/$J16 -> #DIV/0! | AO16: =(AJ16*1000)/$J16 -> #DIV/0! | AP16: =AP15 -> 1650 | AQ16: =AQ15 -> 19160 | AR16: =AR15 -> 36239 | AS16: =AS15 -> 1298 | AT16: =AT15 -> 4200 | AU16: =AP16*(AG16*0.8) -> 0 | AV16: =AQ16*(AH16*0.012) -> 0 | AW16: =AR16*(AI16*0.044) -> 0 | AX16: =AS16*AJ16 -> 0 | AY16: =AT16*(J16*0.025) -> 0 | AZ16: =AU16+AV16+AW16+AX16+AY16 -> 0 | BA16: 1000 | BB16: =+Tabla2[[#This Row],[COSTO QUIMICA ]]/Tabla2[[#This Row],[VOLUMEN ENVIADO A RO (m3)]] -> #DIV/0!
A17: =+A16+1 -> 46118 | B17: =DAY(Tabla2[[#This Row],[FECHA]]) -> 6 | C17: 1 (NOCHE) | I17: 0 | J17: 0 | K17: 0 | L17: 0 | M17: 0 | N17: 0 | O17: 0 | P17: 0 | Q17: =L17*(1000/114) -> 0 | R17: =M17*(1000/114) -> 0 | S17: =N17*(1000/114) -> 0 | T17: =O17*(1000/114) -> 0 | U17: =P17*(1000/114) -> 0 | V17: =Q17-Q18 -> 0 | W17: =R17-R18 -> 0 | X17: =S17-S18 -> 0 | Y17: =T17-T18 -> 0 | Z17: =U17-U18 -> 0 | AA17: 1.18 | AB17: 1.28 | AC17: 1.2 | AD17: 1.53 | AE17: 1.2 | AF17: =V17*AA17 -> 0 | AG17: =W17*AB17 -> 0 | AH17: =X17*AC17 -> 0 | AI17: =Y17*AD17 -> 0 | AJ17: =Z17*AE17 -> 0 | AK17: =(AF17*1000)/$J17 -> #DIV/0! | AL17: =(AG17*1000)/$J17 -> #DIV/0! | AM17: =(AH17*1000)/$J17 -> #DIV/0! | AN17: =(AI17*1000)/$J17 -> #DIV/0! | AO17: =(AJ17*1000)/$J17 -> #DIV/0! | AP17: =AP16 -> 1650 | AQ17: =AQ16 -> 19160 | AR17: =AR16 -> 36239 | AS17: =AS16 -> 1298 | AT17: =AT16 -> 4200 | AU17: =AP17*(AG17*0.8) -> 0 | AV17: =AQ17*(AH17*0.012) -> 0 | AW17: =AR17*(AI17*0.044) -> 0 | AX17: =AS17*AJ17 -> 0 | AY17: =AT17*(J17*0.025) -> 0 | AZ17: =AU17+AV17+AW17+AX17+AY17 -> 0 | BA17: 1000 | BB17: =+Tabla2[[#This Row],[COSTO QUIMICA ]]/Tabla2[[#This Row],[VOLUMEN ENVIADO A RO (m3)]] -> #DIV/0!
