Workbook

Sheet CODIGO (2)
A1: FECHA | B1: VIAJE | C1: HOROMETRO INICIAL | D1: HOROMETRO FINAL | E1: HORAS DE OPERACIÓN | F1: Q TRATAMIENTO | G1: VOLUMEN TRATADO | H1: KG GENERADOS | I1: $ Kg | J1: $ TRANSPORTE | K1: $ / KG | L1: $ AMPLIRROL | M1: META FACTOR ($/KG) | N1: FACTOR ($/KG | O1: FACTOR 2024 KG/M3 | P1: FACTOR GENERACIÓN KG/M3 | Q1: $/ M3 | R1: VOL TRATADO DIA | S1: $/M3
E2: =D2-C2 -> 0 | F2: 84 | G2: =E2*F2 -> 0 | I2: 96 | J2: 750000 | K2: =H2*I2 -> 0 | L2: =K2+J2 -> 750000 | M2: =L2/H2 -> #DIV/0! | N2: 267 | O2: 2.3 | P2: =H2/G2 -> #DIV/0! | Q2: =L2/G2 -> #DIV/0! | R2: 2000 | S2: =L2/R2 -> 375
E3: =D3-C3 -> 0 | F3: 84 | G3: =E3*F3 -> 0 | I3: 96 | J3: 750000 | K3: =H3*I3 -> 0 | L3: =K3+J3 -> 750000 | M3: =L3/H3 -> #DIV/0! | N3: 267 | O3: 2.3 | P3: =H3/G3 -> #DIV/0! | Q3: =L3/G3 -> #DIV/0! | R3: 2000 | S3: =L3/R3 -> 375
E4: =D4-C4 -> 0 | F4: 84 | G4: =E4*F4 -> 0 | I4: 96 | J4: 750000 | K4: =H4*I4 -> 0 | L4: =K4+J4 -> 750000 | M4: =L4/H4 -> #DIV/0! | N4: 267 | O4: =+O3 -> 2.3 | P4: =H4/G4 -> #DIV/0! | Q4: =L4/G4 -> #DIV/0! | R4: 2000 | S4: =L4/R4 -> 375
E5: =D5-C5 -> 0 | F5: 84 | G5: =E5*F5 -> 0 | I5: 96 | J5: 750000 | K5: =H5*I5 -> 0 | L5: =K5+J5 -> 750000 | M5: =L5/H5 -> #DIV/0! | N5: 267 | O5: =+O4 -> 2.3 | P5: =H5/G5 -> #DIV/0! | Q5: =L5/G5 -> #DIV/0! | R5: 2000 | S5: =L5/R5 -> 375
E6: =D6-C6 -> 0 | F6: 84 | G6: =E6*F6 -> 0 | I6: 96 | J6: 750000 | K6: =H6*I6 -> 0 | L6: =K6+J6 -> 750000 | M6: =L6/H6 -> #DIV/0! | N6: 267 | O6: =+O5 -> 2.3 | P6: =H6/G6 -> #DIV/0! | Q6: =L6/G6 -> #DIV/0! | R6: 2000 | S6: =L6/R6 -> 375
E7: =D7-C7 -> 0 | F7: 84 | G7: =E7*F7 -> 0 | I7: 96 | J7: 750000 | K7: =H7*I7 -> 0 | L7: =K7+J7 -> 750000 | M7: =L7/H7 -> #DIV/0! | N7: 267 | O7: =+O6 -> 2.3 | P7: =H7/G7 -> #DIV/0! | Q7: =L7/G7 -> #DIV/0! | R7: 2000 | S7: =L7/R7 -> 375
E8: =D8-C8 -> 0 | F8: 84 | G8: =E8*F8 -> 0 | I8: 96 | J8: 750000 | K8: =H8*I8 -> 0 | L8: =K8+J8 -> 750000 | M8: =L8/H8 -> #DIV/0! | N8: 267 | O8: =+O7 -> 2.3 | P8: =H8/G8 -> #DIV/0! | Q8: =L8/G8 -> #DIV/0! | R8: 2000 | S8: =L8/R8 -> 375
E9: =D9-C9 -> 0 | F9: 84 | G9: =E9*F9 -> 0 | I9: 96 | J9: 750000 | K9: =H9*I9 -> 0 | L9: =K9+J9 -> 750000 | M9: =L9/H9 -> #DIV/0! | N9: 267 | O9: =+O8 -> 2.3 | P9: =H9/G9 -> #DIV/0! | Q9: =L9/G9 -> #DIV/0! | R9: 2000 | S9: =L9/R9 -> 375

Sheet Balance Agua Trata Vs Lodo Gene
B1: AÑO 2024 | C1: Agua Tratada PTAR | D1: Lodos Generados | E1: Valor Disposición de Lodo (SIN IVA) | F1: Valor Transporte | G1: Costo Total Servicio (Transporte + Disposición)(SIN IVA) | H1: Indicador Global (Generado: Disposición+Transporte) | I1: Indicador Disposición de Lodos Generados PTAR ($/m3) | J1: Indicador Total (Transporte + Disposición Final) | K1: Indicador de Generación
B2: MES | C2: (m3) | D2: (Kg) | E2: ($) | F2: ($) | G2: ($) | H2: ($/Kg) | I2: Valor ($/m3 Tratado) | J2: Valor ($/m3 de Agua Tratada) | K2: Kg/m3
B3: ENE | C3: ='[1]Modelo de Consumo - Graficas '!P4+'[1]Modelo de Consumo - Graficas '!$M$4 -> 43573.271 | D3: ='Costo Disposición Lodos - PTAR'!K31 -> #REF! | E3: ='Costo Disposición Lodos - PTAR'!M31 -> #REF! | F3: ='Costo Disposición Lodos - PTAR'!O31 -> 20540000 | G3: =SUM(Tabla2[[#This Row],[Valor Transporte]]+Tabla2[[#This Row],[Valor Disposición de Lodo (SIN IVA)]]) -> #REF! | H3: =Tabla2[[#This Row],[Costo Total Servicio (Transporte + Disposición)(SIN IVA)]]/Tabla2[[#This Row],[Lodos Generados ]] -> #REF! | I3: =#REF!/C3 -> #REF! | J3: =Tabla2[[#This Row],[Costo Total Servicio (Transporte + Disposición)(SIN IVA)]]/Tabla2[[#This Row],[Agua Tratada PTAR ]] -> #REF! | K3: =D3/C3 -> #REF!
B4: FEB | C4: 48224.5 | D4: ='Costo Disposición Lodos - PTAR'!K60 -> #REF! | E4: ='Costo Disposición Lodos - PTAR'!M60 -> #REF! | F4: ='Costo Disposición Lodos - PTAR'!O60 -> 16500000 | G4: =SUM(Tabla2[[#This Row],[Valor Transporte]]+Tabla2[[#This Row],[Valor Disposición de Lodo (SIN IVA)]]) -> #REF! | H4: =Tabla2[[#This Row],[Costo Total Servicio (Transporte + Disposición)(SIN IVA)]]/Tabla2[[#This Row],[Lodos Generados ]] -> #REF! | I4: =#REF!/C4 -> #REF! | J4: =Tabla2[[#This Row],[Costo Total Servicio (Transporte + Disposición)(SIN IVA)]]/Tabla2[[#This Row],[Agua Tratada PTAR ]] -> #REF! | K4: =D4/C4 -> #REF!
B5: MAR
B6: ABR
B7: MAY
B8: JUN
B9: JUL
B10: AGO
B11: SEP
B12: OCT
B13: NOV
B14: DIC
B15: Consolidado Anual | C15: =SUM(C3:C13) -> 91797.771 | D15: =+SUM(D3:D13) -> #REF! | E15: =SUM(E3:E13) -> #REF! | F15: =SUM(F3:F13) -> 37040000 | G15: =SUM(G3:G13) -> #REF! | H15: =Tabla2[[#This Row],[Costo Total Servicio (Transporte + Disposición)(SIN IVA)]]/Tabla2[[#This Row],[Lodos Generados ]] -> #REF! | I15: =Tabla2[[#This Row],[Valor Disposición de Lodo (SIN IVA)]]/Tabla2[[#This Row],[Agua Tratada PTAR ]] -> #REF! | J15: =Tabla2[[#This Row],[Costo Total Servicio (Transporte + Disposición)(SIN IVA)]]/Tabla2[[#This Row],[Agua Tratada PTAR ]] -> #REF! | K15: =Tabla2[[#This Row],[Lodos Generados ]]/Tabla2[[#This Row],[Agua Tratada PTAR ]] -> #REF!
M22: ACUMULADO LODOS SEP
M23: Caudal | N23: Gene kg/m3 | O23: costo /m3
M24: 8400 | N24: =D11/C11 -> #DIV/0! | O24: 250.8862
C73: BALANCE DE LODOS
C74: Agua Tratada GEM (m3) | D74: Lodos Generados (Kg) | E74: Valor Disposición de Lodo (SIN IVA) $ | F74: Valor Transporte $ | G74: Costo Total Servicio (Transporte + Disposición)(SIN IVA) $ | H74: Indicador costo disposición ($/Kg) | I74: Indicador costo tratamiento ($/m3) | J74: Indicador de Generación (Kg/m3) | K74: Indicador costo disposición ($/m3)
C75: 54264 | D75: 146650 | E75: 14078400 | F75: 24000000 | G75: =+E75+F75 -> 38078400 | H75: =+G75/D75 -> 259.65496 | I75: =+G75/C75 -> 701.7249 | J75: =+D75/C75 -> 2.7025284 | K75: =+G75/C75 -> 701.7249

Sheet Costo Disposición Lodos - PTAR
A1: MES | B1: Remisión | C1: Fecha | D1: Cantidad Lodos Generados (Kg) | E1: Precio Unitario Disposición ($) | F1: Valor Disposición Kg ($) | G1: Costo Total + IVA | H1: Cantidad de Viajes | I1: Costo Viaje ($) | J1: Costo total (SIN IVA) | K1: Cantidad Total de Lodo Generado (Kg) | L1: Cantidad Total de Viajes | M1: Valor Total de Disposición Lodo ($) SIN IVA | N1: IVA (Disposición) | O1: Valor Total Viajes ($) | P1: COSTO TOTAL ($) (SIN IVA) | Q1: COSTO TOTAL ($) + IVA | R1: INDICADOR FINAL ($/KG)
A2: DICIEMBRE | B2: =#REF! -> #REF! | C2: =+#REF! -> #REF! | D2: =+#REF! -> #REF! | E2: 96 | F2: =+Tabla5[[#This Row],[Cantidad Lodos Generados (Kg) ]]*Tabla5[[#This Row],[Precio Unitario Disposición ($)]] -> #REF! | G2: =Tabla5[[#This Row],[Valor Disposición Kg ($)]]*1.19 -> #REF! | H2: 1 | I2: 750000 | J2: =Tabla5[[#This Row],[Valor Disposición Kg ($)]]+(Tabla5[[#This Row],[Cantidad de Viajes ]]*Tabla5[[#This Row],[Costo Viaje ($)]]) -> #REF! | K2: =SUM(D2:D83) -> #REF! | L2: =SUM(H2:H30) -> 29 | M2: =SUM(F2:F30) -> #REF! | N2: =M2*19% -> #REF! | O2: =SUM(I2:I30) -> 20830000 | P2: =M2+O2 -> #REF! | Q2: =SUM(M2+N2+O2) -> #REF! | R2: =P2/K2 -> #REF!
B3: =#REF! -> #REF! | C3: =+#REF! -> #REF! | D3: =+#REF! -> #REF! | E3: 96 | F3: =+Tabla5[[#This Row],[Cantidad Lodos Generados (Kg) ]]*Tabla5[[#This Row],[Precio Unitario Disposición ($)]] -> #REF! | G3: =Tabla5[[#This Row],[Valor Disposición Kg ($)]]*1.19 -> #REF! | H3: 1 | I3: 750000 | J3: =Tabla5[[#This Row],[Valor Disposición Kg ($)]]+(Tabla5[[#This Row],[Cantidad de Viajes ]]*Tabla5[[#This Row],[Costo Viaje ($)]]) -> #REF!
B4: =#REF! -> #REF! | C4: =+#REF! -> #REF! | D4: =+#REF! -> #REF! | E4: 96 | F4: =+Tabla5[[#This Row],[Cantidad Lodos Generados (Kg) ]]*Tabla5[[#This Row],[Precio Unitario Disposición ($)]] -> #REF! | G4: =Tabla5[[#This Row],[Valor Disposición Kg ($)]]*1.19 -> #REF! | H4: 1 | I4: 750000 | J4: =Tabla5[[#This Row],[Valor Disposición Kg ($)]]+(Tabla5[[#This Row],[Cantidad de Viajes ]]*Tabla5[[#This Row],[Costo Viaje ($)]]) -> #REF!
B5: =#REF! -> #REF! | C5: =+#REF! -> #REF! | D5: =+#REF! -> #REF! | E5: 96 | F5: =+Tabla5[[#This Row],[Cantidad Lodos Generados (Kg) ]]*Tabla5[[#This Row],[Precio Unitario Disposición ($)]] -> #REF! | G5: =Tabla5[[#This Row],[Valor Disposición Kg ($)]]*1.19 -> #REF! | H5: 1 | I5: 750000 | J5: =Tabla5[[#This Row],[Valor Disposición Kg ($)]]+(Tabla5[[#This Row],[Cantidad de Viajes ]]*Tabla5[[#This Row],[Costo Viaje ($)]]) -> #REF!
B6: =#REF! -> #REF! | C6: =+#REF! -> #REF! | D6: =+#REF! -> #REF! | E6: 96 | F6: =+Tabla5[[#This Row],[Cantidad Lodos Generados (Kg) ]]*Tabla5[[#This Row],[Precio Unitario Disposición ($)]] -> #REF! | G6: =Tabla5[[#This Row],[Valor Disposición Kg ($)]]*1.19 -> #REF! | H6: 1 | I6: 750000 | J6: =Tabla5[[#This Row],[Valor Disposición Kg ($)]]+(Tabla5[[#This Row],[Cantidad de Viajes ]]*Tabla5[[#This Row],[Costo Viaje ($)]]) -> #REF!
B7: =#REF! -> #REF! | C7: =+#REF! -> #REF! | D7: =+#REF! -> #REF! | E7: 96 | F7: =+Tabla5[[#This Row],[Cantidad Lodos Generados (Kg) ]]*Tabla5[[#This Row],[Precio Unitario Disposición ($)]] -> #REF! | G7: =Tabla5[[#This Row],[Valor Disposición Kg ($)]]*1.19 -> #REF! | H7: 1 | I7: 750000 | J7: =Tabla5[[#This Row],[Valor Disposición Kg ($)]]+(Tabla5[[#This Row],[Cantidad de Viajes ]]*Tabla5[[#This Row],[Costo Viaje ($)]]) -> #REF!
B8: =#REF! -> #REF! | C8: =+#REF! -> #REF! | D8: =+#REF! -> #REF! | E8: 96 | F8: =+Tabla5[[#This Row],[Cantidad Lodos Generados (Kg) ]]*Tabla5[[#This Row],[Precio Unitario Disposición ($)]] -> #REF! | G8: =Tabla5[[#This Row],[Valor Disposición Kg ($)]]*1.19 -> #REF! | H8: 1 | I8: 750000 | J8: =Tabla5[[#This Row],[Valor Disposición Kg ($)]]+(Tabla5[[#This Row],[Cantidad de Viajes ]]*Tabla5[[#This Row],[Costo Viaje ($)]]) -> #REF!
B9: =#REF! -> #REF! | C9: =+#REF! -> #REF! | D9: =+#REF! -> #REF! | E9: 96 | F9: =+Tabla5[[#This Row],[Cantidad Lodos Generados (Kg) ]]*Tabla5[[#This Row],[Precio Unitario Disposición ($)]] -> #REF! | G9: =Tabla5[[#This Row],[Valor Disposición Kg ($)]]*1.19 -> #REF! | H9: 1 | I9: 750000 | J9: =Tabla5[[#This Row],[Valor Disposición Kg ($)]]+(Tabla5[[#This Row],[Cantidad de Viajes ]]*Tabla5[[#This Row],[Costo Viaje ($)]]) -> #REF!
B10: =#REF! -> #REF! | C10: =+#REF! -> #REF! | D10: =+#REF! -> #REF! | E10: 96 | F10: =+Tabla5[[#This Row],[Cantidad Lodos Generados (Kg) ]]*Tabla5[[#This Row],[Precio Unitario Disposición ($)]] -> #REF! | G10: =Tabla5[[#This Row],[Valor Disposición Kg ($)]]*1.19 -> #REF! | H10: 1 | I10: 750000 | J10: =Tabla5[[#This Row],[Valor Disposición Kg ($)]]+(Tabla5[[#This Row],[Cantidad de Viajes ]]*Tabla5[[#This Row],[Costo Viaje ($)]]) -> #REF!
B11: =#REF! -> #REF! | C11: =+#REF! -> #REF! | D11: =+#REF! -> #REF! | E11: 96 | F11: =+Tabla5[[#This Row],[Cantidad Lodos Generados (Kg) ]]*Tabla5[[#This Row],[Precio Unitario Disposición ($)]] -> #REF! | G11: =Tabla5[[#This Row],[Valor Disposición Kg ($)]]*1.19 -> #REF! | H11: 1 | I11: 750000 | J11: =Tabla5[[#This Row],[Valor Disposición Kg ($)]]+(Tabla5[[#This Row],[Cantidad de Viajes ]]*Tabla5[[#This Row],[Costo Viaje ($)]]) -> #REF!
B12: =#REF! -> #REF! | C12: =+#REF! -> #REF! | D12: =+#REF! -> #REF! | E12: 96 | F12: =+Tabla5[[#This Row],[Cantidad Lodos Generados (Kg) ]]*Tabla5[[#This Row],[Precio Unitario Disposición ($)]] -> #REF! | G12: =Tabla5[[#This Row],[Valor Disposición Kg ($)]]*1.19 -> #REF! | H12: 1 | I12: 750000 | J12: =Tabla5[[#This Row],[Valor Disposición Kg ($)]]+(Tabla5[[#This Row],[Cantidad de Viajes ]]*Tabla5[[#This Row],[Costo Viaje ($)]]) -> #REF!
B13: =#REF! -> #REF! | C13: =+#REF! -> #REF! | D13: =+#REF! -> #REF! | E13: 96 | F13: =+Tabla5[[#This Row],[Cantidad Lodos Generados (Kg) ]]*Tabla5[[#This Row],[Precio Unitario Disposición ($)]] -> #REF! | G13: =Tabla5[[#This Row],[Valor Disposición Kg ($)]]*1.19 -> #REF! | H13: 1 | I13: 750000 | J13: =Tabla5[[#This Row],[Valor Disposición Kg ($)]]+(Tabla5[[#This Row],[Cantidad de Viajes ]]*Tabla5[[#This Row],[Costo Viaje ($)]]) -> #REF!
B14: =#REF! -> #REF! | C14: =+#REF! -> #REF! | D14: =+#REF! -> #REF! | E14: 96 | F14: =+Tabla5[[#This Row],[Cantidad Lodos Generados (Kg) ]]*Tabla5[[#This Row],[Precio Unitario Disposición ($)]] -> #REF! | G14: =Tabla5[[#This Row],[Valor Disposición Kg ($)]]*1.19 -> #REF! | H14: 1 | I14: 750000 | J14: =Tabla5[[#This Row],[Valor Disposición Kg ($)]]+(Tabla5[[#This Row],[Cantidad de Viajes ]]*Tabla5[[#This Row],[Costo Viaje ($)]]) -> #REF!
... B30: =#REF! -> #REF! | C30: =+#REF! -> #REF! | D30: =+#REF! -> #REF! | E30: 96 | F30: =+Tabla5[[#This Row],[Cantidad Lodos Generados (Kg) ]]*Tabla5[[#This Row],[Precio Unitario Disposición ($)]] -> #REF! | G30: =Tabla5[[#This Row],[Valor Disposición Kg ($)]]*1.19 -> #REF! | H30: 1 | I30: 750000 | J30: =Tabla5[[#This Row],[Valor Disposición Kg ($)]]+(Tabla5[[#This Row],[Cantidad de Viajes ]]*Tabla5[[#This Row],[Costo Viaje ($)]]) -> #REF!
A31: ENERO | B31: =#REF! -> #REF! | C31: =+#REF! -> #REF! | D31: =+#REF! -> #REF! | E31: 96 | F31: =+Tabla5[[#This Row],[Cantidad Lodos Generados (Kg) ]]*Tabla5[[#This Row],[Precio Unitario Disposición ($)]] -> #REF! | G31: =Tabla5[[#This Row],[Valor Disposición Kg ($)]]*1.19 -> #REF! | H31: 1 | I31: 750000 | J31: =Tabla5[[#This Row],[Valor Disposición Kg ($)]]+(Tabla5[[#This Row],[Cantidad de Viajes ]]*Tabla5[[#This Row],[Costo Viaje ($)]]) -> #REF! | K31: =SUM(D31:D59) -> #REF! | L31: =SUM(H31:H59) -> 28 | M31: =SUM(F31:F59) -> #REF! | N31: =M31*19% -> #REF! | O31: =SUM(I31:I59) -> 20540000 | P31: =M31+O31 -> #REF! | Q31: =SUM(M31+N31+O31) -> #REF! | R31: =P31/K31 -> #REF!
B32: =#REF! -> #REF! | C32: =+#REF! -> #REF! | D32: =+#REF! -> #REF! | E32: 96 | F32: =+Tabla5[[#This Row],[Cantidad Lodos Generados (Kg) ]]*Tabla5[[#This Row],[Precio Unitario Disposición ($)]] -> #REF! | G32: =Tabla5[[#This Row],[Valor Disposición Kg ($)]]*1.19 -> #REF! | H32: 1 | I32: 750000 | J32: =Tabla5[[#This Row],[Valor Disposición Kg ($)]]+(Tabla5[[#This Row],[Cantidad de Viajes ]]*Tabla5[[#This Row],[Costo Viaje ($)]]) -> #REF!
B33: =#REF! -> #REF! | C33: =+#REF! -> #REF! | D33: =+#REF! -> #REF! | E33: 96 | F33: =+Tabla5[[#This Row],[Cantidad Lodos Generados (Kg) ]]*Tabla5[[#This Row],[Precio Unitario Disposición ($)]] -> #REF! | G33: =Tabla5[[#This Row],[Valor Disposición Kg ($)]]*1.19 -> #REF! | H33: 1 | I33: 750000 | J33: =Tabla5[[#This Row],[Valor Disposición Kg ($)]]+(Tabla5[[#This Row],[Cantidad de Viajes ]]*Tabla5[[#This Row],[Costo Viaje ($)]]) -> #REF!
B34: =#REF! -> #REF! | C34: =+#REF! -> #REF! | D34: =+#REF! -> #REF! | E34: 96 | F34: =+Tabla5[[#This Row],[Cantidad Lodos Generados (Kg) ]]*Tabla5[[#This Row],[Precio Unitario Disposición ($)]] -> #REF! | G34: =Tabla5[[#This Row],[Valor Disposición Kg ($)]]*1.19 -> #REF! | H34: 1 | I34: 750000 | J34: =Tabla5[[#This Row],[Valor Disposición Kg ($)]]+(Tabla5[[#This Row],[Cantidad de Viajes ]]*Tabla5[[#This Row],[Costo Viaje ($)]]) -> #REF!
B35: =#REF! -> #REF! | C35: =+#REF! -> #REF! | D35: =+#REF! -> #REF! | E35: 96 | F35: =+Tabla5[[#This Row],[Cantidad Lodos Generados (Kg) ]]*Tabla5[[#This Row],[Precio Unitario Disposición ($)]] -> #REF! | G35: =Tabla5[[#This Row],[Valor Disposición Kg ($)]]*1.19 -> #REF! | H35: 1 | I35: 750000 | J35: =Tabla5[[#This Row],[Valor Disposición Kg ($)]]+(Tabla5[[#This Row],[Cantidad de Viajes ]]*Tabla5[[#This Row],[Costo Viaje ($)]]) -> #REF!
B36: =#REF! -> #REF! | C36: =+#REF! -> #REF! | D36: =+#REF! -> #REF! | E36: 96 | F36: =+Tabla5[[#This Row],[Cantidad Lodos Generados (Kg) ]]*Tabla5[[#This Row],[Precio Unitario Disposición ($)]] -> #REF! | G36: =Tabla5[[#This Row],[Valor Disposición Kg ($)]]*1.19 -> #REF! | H36: 1 | I36: 750000 | J36: =Tabla5[[#This Row],[Valor Disposición Kg ($)]]+(Tabla5[[#This Row],[Cantidad de Viajes ]]*Tabla5[[#This Row],[Costo Viaje ($)]]) -> #REF!
B37: =#REF! -> #REF! | C37: =+#REF! -> #REF! | D37: =+#REF! -> #REF! | E37: 96 | F37: =+Tabla5[[#This Row],[Cantidad Lodos Generados (Kg) ]]*Tabla5[[#This Row],[Precio Unitario Disposición ($)]] -> #REF! | G37: =Tabla5[[#This Row],[Valor Disposición Kg ($)]]*1.19 -> #REF! | H37: 1 | I37: 750000 | J37: =Tabla5[[#This Row],[Valor Disposición Kg ($)]]+(Tabla5[[#This Row],[Cantidad de Viajes ]]*Tabla5[[#This Row],[Costo Viaje ($)]]) -> #REF!
B38: =#REF! -> #REF! | C38: =+#REF! -> #REF! | D38: =+#REF! -> #REF! | E38: 96 | F38: =+Tabla5[[#This Row],[Cantidad Lodos Generados (Kg) ]]*Tabla5[[#This Row],[Precio Unitario Disposición ($)]] -> #REF! | G38: =Tabla5[[#This Row],[Valor Disposición Kg ($)]]*1.19 -> #REF! | H38: 1 | I38: 290000 | J38: =Tabla5[[#This Row],[Valor Disposición Kg ($)]]+(Tabla5[[#This Row],[Cantidad de Viajes ]]*Tabla5[[#This Row],[Costo Viaje ($)]]) -> #REF!
B39: =#REF! -> #REF! | C39: =+#REF! -> #REF! | D39: =+#REF! -> #REF! | E39: 96 | F39: =+Tabla5[[#This Row],[Cantidad Lodos Generados (Kg) ]]*Tabla5[[#This Row],[Precio Unitario Disposición ($)]] -> #REF! | G39: =Tabla5[[#This Row],[Valor Disposición Kg ($)]]*1.19 -> #REF! | H39: 1 | I39: 750000 | J39: =Tabla5[[#This Row],[Valor Disposición Kg ($)]]+(Tabla5[[#This Row],[Cantidad de Viajes ]]*Tabla5[[#This Row],[Costo Viaje ($)]]) -> #REF!
B40: =#REF! -> #REF! | C40: =+#REF! -> #REF! | D40: =+#REF! -> #REF! | E40: 96 | F40: =+Tabla5[[#This Row],[Cantidad Lodos Generados (Kg) ]]*Tabla5[[#This Row],[Precio Unitario Disposición ($)]] -> #REF! | G40: =Tabla5[[#This Row],[Valor Disposición Kg ($)]]*1.19 -> #REF! | H40: 1 | I40: 750000 | J40: =Tabla5[[#This Row],[Valor Disposición Kg ($)]]+(Tabla5[[#This Row],[Cantidad de Viajes ]]*Tabla5[[#This Row],[Costo Viaje ($)]]) -> #REF!
B41: =#REF! -> #REF! | C41: =+#REF! -> #REF! | D41: =+#REF! -> #REF! | E41: 96 | F41: =+Tabla5[[#This Row],[Cantidad Lodos Generados (Kg) ]]*Tabla5[[#This Row],[Precio Unitario Disposición ($)]] -> #REF! | G41: =Tabla5[[#This Row],[Valor Disposición Kg ($)]]*1.19 -> #REF! | H41: 1 | I41: 750000 | J41: =Tabla5[[#This Row],[Valor Disposición Kg ($)]]+(Tabla5[[#This Row],[Cantidad de Viajes ]]*Tabla5[[#This Row],[Costo Viaje ($)]]) -> #REF!
B42: =#REF! -> #REF! | C42: =+#REF! -> #REF! | D42: =+#REF! -> #REF! | E42: 96 | F42: =+Tabla5[[#This Row],[Cantidad Lodos Generados (Kg) ]]*Tabla5[[#This Row],[Precio Unitario Disposición ($)]] -> #REF! | G42: =Tabla5[[#This Row],[Valor Disposición Kg ($)]]*1.19 -> #REF! | H42: 1 | I42: 750000 | J42: =Tabla5[[#This Row],[Valor Disposición Kg ($)]]+(Tabla5[[#This Row],[Cantidad de Viajes ]]*Tabla5[[#This Row],[Costo Viaje ($)]]) -> #REF!
B43: =#REF! -> #REF! | C43: =+#REF! -> #REF! | D43: =+#REF! -> #REF! | E43: 96 | F43: =+Tabla5[[#This Row],[Cantidad Lodos Generados (Kg) ]]*Tabla5[[#This Row],[Precio Unitario Disposición ($)]] -> #REF! | G43: =Tabla5[[#This Row],[Valor Disposición Kg ($)]]*1.19 -> #REF! | H43: 1 | I43: 750000 | J43: =Tabla5[[#This Row],[Valor Disposición Kg ($)]]+(Tabla5[[#This Row],[Cantidad de Viajes ]]*Tabla5[[#This Row],[Costo Viaje ($)]]) -> #REF!
... B59: =#REF! -> #REF! | C59: =+#REF! -> #REF! | D59: =+#REF! -> #REF! | E59: 96 | F59: =+Tabla5[[#This Row],[Cantidad Lodos Generados (Kg) ]]*Tabla5[[#This Row],[Precio Unitario Disposición ($)]] -> #REF! | G59: =Tabla5[[#This Row],[Valor Disposición Kg ($)]]*1.19 -> #REF! | H59: 1 | I59: 750000 | J59: =Tabla5[[#This Row],[Valor Disposición Kg ($)]]+(Tabla5[[#This Row],[Cantidad de Viajes ]]*Tabla5[[#This Row],[Costo Viaje ($)]]) -> #REF!
A60: FEBRERO | B60: =#REF! -> #REF! | C60: =+#REF! -> #REF! | D60: =+#REF! -> #REF! | E60: 96 | F60: =+Tabla5[[#This Row],[Cantidad Lodos Generados (Kg) ]]*Tabla5[[#This Row],[Precio Unitario Disposición ($)]] -> #REF! | G60: =Tabla5[[#This Row],[Valor Disposición Kg ($)]]*1.19 -> #REF! | H60: 1 | I60: 750000 | J60: =Tabla5[[#This Row],[Valor Disposición Kg ($)]]+(Tabla5[[#This Row],[Cantidad de Viajes ]]*Tabla5[[#This Row],[Costo Viaje ($)]]) -> #REF! | K60: =SUM(D60:D83) -> #REF! | L60: =SUM(H60:H83) -> 22 | M60: =SUM(F60:F83) -> #REF! | N60: =M60*19% -> #REF! | O60: =SUM(I60:I83) -> 16500000 | P60: =M60+O60 -> #REF! | Q60: =SUM(M60+N60+O60) -> #REF! | R60: =P60/K60 -> #REF!
B61: =#REF! -> #REF! | C61: =+#REF! -> #REF! | D61: =+#REF! -> #REF! | E61: 96 | F61: =+Tabla5[[#This Row],[Cantidad Lodos Generados (Kg) ]]*Tabla5[[#This Row],[Precio Unitario Disposición ($)]] -> #REF! | G61: =Tabla5[[#This Row],[Valor Disposición Kg ($)]]*1.19 -> #REF! | H61: 1 | I61: 750000 | J61: =Tabla5[[#This Row],[Valor Disposición Kg ($)]]+(Tabla5[[#This Row],[Cantidad de Viajes ]]*Tabla5[[#This Row],[Costo Viaje ($)]]) -> #REF!
B62: =#REF! -> #REF! | C62: =+#REF! -> #REF! | D62: =+#REF! -> #REF! | E62: 96 | F62: =+Tabla5[[#This Row],[Cantidad Lodos Generados (Kg) ]]*Tabla5[[#This Row],[Precio Unitario Disposición ($)]] -> #REF! | G62: =Tabla5[[#This Row],[Valor Disposición Kg ($)]]*1.19 -> #REF! | H62: 1 | I62: 750000 | J62: =Tabla5[[#This Row],[Valor Disposición Kg ($)]]+(Tabla5[[#This Row],[Cantidad de Viajes ]]*Tabla5[[#This Row],[Costo Viaje ($)]]) -> #REF!
B63: =#REF! -> #REF! | C63: =+#REF! -> #REF! | D63: =+#REF! -> #REF! | E63: 96 | F63: =+Tabla5[[#This Row],[Cantidad Lodos Generados (Kg) ]]*Tabla5[[#This Row],[Precio Unitario Disposición ($)]] -> #REF! | G63: =Tabla5[[#This Row],[Valor Disposición Kg ($)]]*1.19 -> #REF! | H63: 1 | I63: 750000 | J63: =Tabla5[[#This Row],[Valor Disposición Kg ($)]]+(Tabla5[[#This Row],[Cantidad de Viajes ]]*Tabla5[[#This Row],[Costo Viaje ($)]]) -> #REF!
B65: =#REF! -> #REF! | C65: =+#REF! -> #REF! | D65: =+#REF! -> #REF! | E65: 96 | F65: =+Tabla5[[#This Row],[Cantidad Lodos Generados (Kg) ]]*Tabla5[[#This Row],[Precio Unitario Disposición ($)]] -> #REF! | G65: =Tabla5[[#This Row],[Valor Disposición Kg ($)]]*1.19 -> #REF! | H65: 1 | I65: 750000 | J65: =Tabla5[[#This Row],[Valor Disposición Kg ($)]]+(Tabla5[[#This Row],[Cantidad de Viajes ]]*Tabla5[[#This Row],[Costo Viaje ($)]]) -> #REF!
B66: =#REF! -> #REF! | C66: =+#REF! -> #REF! | D66: =+#REF! -> #REF! | E66: 96 | F66: =+Tabla5[[#This Row],[Cantidad Lodos Generados (Kg) ]]*Tabla5[[#This Row],[Precio Unitario Disposición ($)]] -> #REF! | G66: =Tabla5[[#This Row],[Valor Disposición Kg ($)]]*1.19 -> #REF! | H66: 1 | I66: 750000 | J66: =Tabla5[[#This Row],[Valor Disposición Kg ($)]]+(Tabla5[[#This Row],[Cantidad de Viajes ]]*Tabla5[[#This Row],[Costo Viaje ($)]]) -> #REF!
B67: =#REF! -> #REF! | C67: =+#REF! -> #REF! | D67: =+#REF! -> #REF! | E67: 96 | F67: =+Tabla5[[#This Row],[Cantidad Lodos Generados (Kg) ]]*Tabla5[[#This Row],[Precio Unitario Disposición ($)]] -> #REF! | G67: =Tabla5[[#This Row],[Valor Disposición Kg ($)]]*1.19 -> #REF! | H67: 1 | I67: 750000 | J67: =Tabla5[[#This Row],[Valor Disposición Kg ($)]]+(Tabla5[[#This Row],[Cantidad de Viajes ]]*Tabla5[[#This Row],[Costo Viaje ($)]]) -> #REF!
B68: =#REF! -> #REF! | C68: =+#REF! -> #REF! | D68: =+#REF! -> #REF! | E68: 96 | F68: =+Tabla5[[#This Row],[Cantidad Lodos Generados (Kg) ]]*Tabla5[[#This Row],[Precio Unitario Disposición ($)]] -> #REF! | G68: =Tabla5[[#This Row],[Valor Disposición Kg ($)]]*1.19 -> #REF! | H68: 1 | I68: 750000 | J68: =Tabla5[[#This Row],[Valor Disposición Kg ($)]]+(Tabla5[[#This Row],[Cantidad de Viajes ]]*Tabla5[[#This Row],[Costo Viaje ($)]]) -> #REF!
B69: =#REF! -> #REF! | C69: =+#REF! -> #REF! | D69: =+#REF! -> #REF! | E69: 96 | F69: =+Tabla5[[#This Row],[Cantidad Lodos Generados (Kg) ]]*Tabla5[[#This Row],[Precio Unitario Disposición ($)]] -> #REF! | G69: =Tabla5[[#This Row],[Valor Disposición Kg ($)]]*1.19 -> #REF! | H69: 1 | I69: 750000 | J69: =Tabla5[[#This Row],[Valor Disposición Kg ($)]]+(Tabla5[[#This Row],[Cantidad de Viajes ]]*Tabla5[[#This Row],[Costo Viaje ($)]]) -> #REF!
B70: =#REF! -> #REF! | C70: =+#REF! -> #REF! | D70: =+#REF! -> #REF! | E70: 96 | F70: =+Tabla5[[#This Row],[Cantidad Lodos Generados (Kg) ]]*Tabla5[[#This Row],[Precio Unitario Disposición ($)]] -> #REF! | G70: =Tabla5[[#This Row],[Valor Disposición Kg ($)]]*1.19 -> #REF! | H70: 1 | I70: 750000 | J70: =Tabla5[[#This Row],[Valor Disposición Kg ($)]]+(Tabla5[[#This Row],[Cantidad de Viajes ]]*Tabla5[[#This Row],[Costo Viaje ($)]]) -> #REF!
B71: =#REF! -> #REF! | C71: =+#REF! -> #REF! | D71: =+#REF! -> #REF! | E71: 96 | F71: =+Tabla5[[#This Row],[Cantidad Lodos Generados (Kg) ]]*Tabla5[[#This Row],[Precio Unitario Disposición ($)]] -> #REF! | G71: =Tabla5[[#This Row],[Valor Disposición Kg ($)]]*1.19 -> #REF! | H71: 1 | I71: 750000 | J71: =Tabla5[[#This Row],[Valor Disposición Kg ($)]]+(Tabla5[[#This Row],[Cantidad de Viajes ]]*Tabla5[[#This Row],[Costo Viaje ($)]]) -> #REF!
B72: =#REF! -> #REF! | C72: =+#REF! -> #REF! | D72: =+#REF! -> #REF! | E72: 96 | F72: =+Tabla5[[#This Row],[Cantidad Lodos Generados (Kg) ]]*Tabla5[[#This Row],[Precio Unitario Disposición ($)]] -> #REF! | G72: =Tabla5[[#This Row],[Valor Disposición Kg ($)]]*1.19 -> #REF! | H72: 1 | I72: 750000 | J72: =Tabla5[[#This Row],[Valor Disposición Kg ($)]]+(Tabla5[[#This Row],[Cantidad de Viajes ]]*Tabla5[[#This Row],[Costo Viaje ($)]]) -> #REF!
B73: =#REF! -> #REF! | C73: =+#REF! -> #REF! | D73: =+#REF! -> #REF! | E73: 96 | F73: =+Tabla5[[#This Row],[Cantidad Lodos Generados (Kg) ]]*Tabla5[[#This Row],[Precio Unitario Disposición ($)]] -> #REF! | G73: =Tabla5[[#This Row],[Valor Disposición Kg ($)]]*1.19 -> #REF! | H73: 1 | I73: 750000 | J73: =Tabla5[[#This Row],[Valor Disposición Kg ($)]]+(Tabla5[[#This Row],[Cantidad de Viajes ]]*Tabla5[[#This Row],[Costo Viaje ($)]]) -> #REF!
... B79: =#REF! -> #REF! | C79: =+#REF! -> #REF! | D79: =+#REF! -> #REF! | E79: 96 | F79: =+Tabla5[[#This Row],[Cantidad Lodos Generados (Kg) ]]*Tabla5[[#This Row],[Precio Unitario Disposición ($)]] -> #REF! | G79: =Tabla5[[#This Row],[Valor Disposición Kg ($)]]*1.19 -> #REF! | H79: 1 | I79: 750000 | J79: =Tabla5[[#This Row],[Valor Disposición Kg ($)]]+(Tabla5[[#This Row],[Cantidad de Viajes ]]*Tabla5[[#This Row],[Costo Viaje ($)]]) -> #REF!
B80: =#REF! -> #REF! | C80: =+#REF! -> #REF! | D80: =+#REF! -> #REF! | E80: 96 | F80: =+Tabla5[[#This Row],[Cantidad Lodos Generados (Kg) ]]*Tabla5[[#This Row],[Precio Unitario Disposición ($)]] -> #REF! | G80: =Tabla5[[#This Row],[Valor Disposición Kg ($)]]*1.19 -> #REF! | H80: 1 | I80: 750000 | J80: =+Tabla5[[#This Row],[Valor Disposición Kg ($)]]+Tabla5[[#This Row],[Cantidad de Viajes ]]*Tabla5[[#This Row],[Costo Viaje ($)]] -> #REF!
B81: =#REF! -> #REF! | C81: =+#REF! -> #REF! | D81: =+#REF! -> #REF! | E81: 96 | F81: =+Tabla5[[#This Row],[Cantidad Lodos Generados (Kg) ]]*Tabla5[[#This Row],[Precio Unitario Disposición ($)]] -> #REF! | G81: =Tabla5[[#This Row],[Valor Disposición Kg ($)]]*1.19 -> #REF! | H81: 1 | I81: 750000 | J81: =Tabla5[[#This Row],[Valor Disposición Kg ($)]]+(Tabla5[[#This Row],[Cantidad de Viajes ]]*Tabla5[[#This Row],[Costo Viaje ($)]]) -> #REF!
B82: =#REF! -> #REF! | C82: =+#REF! -> #REF! | D82: =+#REF! -> #REF! | E82: 96 | F82: =+Tabla5[[#This Row],[Cantidad Lodos Generados (Kg) ]]*Tabla5[[#This Row],[Precio Unitario Disposición ($)]] -> #REF! | G82: =Tabla5[[#This Row],[Valor Disposición Kg ($)]]*1.19 -> #REF! | H82: 1 | I82: 750000 | J82: =Tabla5[[#This Row],[Valor Disposición Kg ($)]]+(Tabla5[[#This Row],[Cantidad de Viajes ]]*Tabla5[[#This Row],[Costo Viaje ($)]]) -> #REF!
B83: =#REF! -> #REF! | C83: =+#REF! -> #REF! | D83: =+#REF! -> #REF! | E83: 96 | F83: =+Tabla5[[#This Row],[Cantidad Lodos Generados (Kg) ]]*Tabla5[[#This Row],[Precio Unitario Disposición ($)]] -> #REF! | G83: =Tabla5[[#This Row],[Valor Disposición Kg ($)]]*1.19 -> #REF! | H83: 1 | I83: 750000 | J83: =+Tabla5[[#This Row],[Valor Disposición Kg ($)]]+Tabla5[[#This Row],[Cantidad de Viajes ]]*Tabla5[[#This Row],[Costo Viaje ($)]] -> #REF!
A84: MARZO | B84: 52966 | C84: 45717 | D84: 3090 | E84: 96 | F84: =+D84*E84 -> 296640 | G84: =+F84*1.19 -> 353001.6 | H84: 1 | I84: 750000 | J84: =+F84+H84*I84 -> 1046640 | K84: =SUM(D84:D113) -> 136528.8 | L84: =SUM(H84:H113) -> 30 | M84: =SUM(F84:F113) -> 13106765 | N84: =M84*19% -> 2490285.3 | O84: =SUM(I84:I113) -> 20660000 | P84: =M84+O84 -> 33766765 | Q84: =SUM(M84+N84+O84) -> 36257050 | R84: =P84/K84 -> 247.32338
B85: 52967 | C85: 45719 | D85: 5380 | E85: 96 | F85: =+D85*E85 -> 516480 | G85: =+F85*1.19 -> 614611.2 | H85: 1 | I85: 750000 | J85: =+F85+H85*I85 -> 1266480
B86: 52968 | C86: 45720 | D86: 3160 | E86: 96 | F86: =+D86*E86 -> 303360 | G86: =+F86*1.19 -> 360998.4 | H86: 1 | I86: 750000 | J86: =+F86+H86*I86 -> 1053360
B87: 52971 | C87: 45721 | D87: 4260 | E87: 96 | F87: =+D87*E87 -> 408960 | G87: =+F87*1.19 -> 486662.4 | H87: 1 | I87: 750000 | J87: =+F87+H87*I87 -> 1158960
B88: 52972 | C88: 45721 | D88: 2970 | E88: 96 | F88: =+D88*E88 -> 285120 | G88: =+F88*1.19 -> 339292.8 | H88: 1 | I88: 290000 | J88: =+F88+H88*I88 -> 575120
B89: 53488 | C89: 45722 | D89: 2986.8 | E89: 96 | F89: =+D89*E89 -> 286732.8 | G89: =+F89*1.19 -> 341212.03 | H89: 1 | I89: 750000 | J89: =+F89+H89*I89 -> 1036732.8
B90: 52973 | C90: 45723 | D90: 3780 | E90: 96 | F90: =+D90*E90 -> 362880 | G90: =+F90*1.19 -> 431827.2 | H90: 1 | I90: 750000 | J90: =+F90+H90*I90 -> 1112880
B91: 52974 | C91: 45724 | D91: 4720 | E91: 96 | F91: =+D91*E91 -> 453120 | G91: =+F91*1.19 -> 539212.8 | H91: 1 | I91: 750000 | J91: =+F91+H91*I91 -> 1203120
B92: 52975 | C92: 45726 | D92: 5510 | E92: 96 | F92: =+D92*E92 -> 528960 | G92: =+F92*1.19 -> 629462.4 | H92: 1 | I92: 750000 | J92: =+F92+H92*I92 -> 1278960
B93: 52976 | C93: 45727 | D93: 5220 | E93: 96 | F93: =+D93*E93 -> 501120 | G93: =+F93*1.19 -> 596332.8 | H93: 1 | I93: 750000 | J93: =+F93+H93*I93 -> 1251120
B94: 52977 | C94: 45728 | D94: 4940 | E94: 96 | F94: =+D94*E94 -> 474240 | G94: =+F94*1.19 -> 564345.6 | H94: 1 | I94: 750000 | J94: =+F94+H94*I94 -> 1224240
B95: 52978 | C95: 45729 | D95: 6390 | E95: 96 | F95: =+D95*E95 -> 613440 | G95: =+F95*1.19 -> 729993.6 | H95: 1 | I95: 750000 | J95: =+F95+H95*I95 -> 1363440
B96: 55824 | C96: 45729 | D96: 3896 | E96: 96 | F96: =+D96*E96 -> 374016 | G96: =+F96*1.19 -> 445079.04 | H96: 1 | I96: 290000 | J96: =+F96+H96*I96 -> 664016
... B113: 52995 | C113: 45747 | D113: 4790 | E113: 96 | F113: =+D113*E113 -> 459840 | G113: =+F113*1.19 -> 547209.6 | H113: 1 | I113: 750000 | J113: =+F113+H113*I113 -> 1209840
A114: ABRIL | B114: 52996 | C114: 45748 | D114: 4190 | E114: 96 | F114: =+Tabla52[[#This Row],[Cantidad Lodos Generados (Kg) ]]*Tabla52[[#This Row],[Precio Unitario Disposición ($)]] -> #VALUE! | G114: =+F114*1.19 -> #VALUE! | H114: 1 | I114: 750000 | J114: =+F114+H114*I114 -> #VALUE! | K114: =SUM(D114:D142) -> 134308 | L114: =SUM(H114:H142) -> 29 | M114: =SUM(F114:F142) -> #VALUE! | N114: =M114*19% -> #VALUE! | O114: =SUM(I114:I143) -> 21120000 | P114: =M114+O114 -> #VALUE! | Q114: =SUM(M114+N114+O114) -> #VALUE! | R114: =P114/K114 -> #VALUE!
B115: 57058 | C115: 45748 | D115: 3526 | E115: 96 | F115: =+Tabla52[[#This Row],[Cantidad Lodos Generados (Kg) ]]*Tabla52[[#This Row],[Precio Unitario Disposición ($)]] -> #VALUE! | G115: =+F115*1.19 -> #VALUE! | H115: 1 | I115: 290000 | J115: =+F115+H115*I115 -> #VALUE!
B116: 52997 | C116: 45749 | D116: 3290 | E116: 96 | F116: =+Tabla52[[#This Row],[Cantidad Lodos Generados (Kg) ]]*Tabla52[[#This Row],[Precio Unitario Disposición ($)]] -> #VALUE! | G116: =+F116*1.19 -> #VALUE! | H116: 1 | I116: 750000 | J116: =+F116+H116*I116 -> #VALUE!
B117: 57201 | C117: 45749 | D117: 6070 | E117: 96 | F117: =+Tabla52[[#This Row],[Cantidad Lodos Generados (Kg) ]]*Tabla52[[#This Row],[Precio Unitario Disposición ($)]] -> #VALUE! | G117: =+F117*1.19 -> #VALUE! | H117: 1 | I117: 750000 | J117: =+F117+H117*I117 -> #VALUE!
B118: 52998 | C118: 45750 | D118: 5740 | E118: 96 | F118: =+Tabla52[[#This Row],[Cantidad Lodos Generados (Kg) ]]*Tabla52[[#This Row],[Precio Unitario Disposición ($)]] -> #VALUE! | G118: =+F118*1.19 -> #VALUE! | H118: 1 | I118: 750000 | J118: =+F118+H118*I118 -> #VALUE!
B119: 57202 | C119: 45751 | D119: 5780 | E119: 96 | F119: =+Tabla52[[#This Row],[Cantidad Lodos Generados (Kg) ]]*Tabla52[[#This Row],[Precio Unitario Disposición ($)]] -> #VALUE! | G119: =+F119*1.19 -> #VALUE! | H119: 1 | I119: 750000 | J119: =+F119+H119*I119 -> #VALUE!
B120: 52999 | C120: 45752 | D120: 4790 | E120: 96 | F120: =+Tabla52[[#This Row],[Cantidad Lodos Generados (Kg) ]]*Tabla52[[#This Row],[Precio Unitario Disposición ($)]] -> #VALUE! | G120: =+F120*1.19 -> #VALUE! | H120: 1 | I120: 750000 | J120: =+F120+H120*I120 -> #VALUE!
B121: 53378 | C121: 45754 | D121: 3486 | E121: 96 | F121: =+Tabla52[[#This Row],[Cantidad Lodos Generados (Kg) ]]*Tabla52[[#This Row],[Precio Unitario Disposición ($)]] -> #VALUE! | G121: =+F121*1.19 -> #VALUE! | H121: 1 | I121: 290000 | J121: =+F121+H121*I121 -> #VALUE!
B122: 53000 | C122: 45754 | D122: 4070 | E122: 96 | F122: =+Tabla52[[#This Row],[Cantidad Lodos Generados (Kg) ]]*Tabla52[[#This Row],[Precio Unitario Disposición ($)]] -> #VALUE! | G122: =+F122*1.19 -> #VALUE! | H122: 1 | I122: 750000 | J122: =+F122+H122*I122 -> #VALUE!
B123: 57203 | C123: 45755 | D123: 4640 | E123: 96 | F123: =+Tabla52[[#This Row],[Cantidad Lodos Generados (Kg) ]]*Tabla52[[#This Row],[Precio Unitario Disposición ($)]] -> #VALUE! | G123: =+F123*1.19 -> #VALUE! | H123: 1 | I123: 750000 | J123: =+F123+H123*I123 -> #VALUE!
B124: 57204 | C124: 45756 | D124: 5160 | E124: 96 | F124: =+Tabla52[[#This Row],[Cantidad Lodos Generados (Kg) ]]*Tabla52[[#This Row],[Precio Unitario Disposición ($)]] -> #VALUE! | G124: =+F124*1.19 -> #VALUE! | H124: 1 | I124: 750000 | J124: =+F124+H124*I124 -> #VALUE!
B125: 57205 | C125: 45757 | D125: 4630 | E125: 96 | F125: =+Tabla52[[#This Row],[Cantidad Lodos Generados (Kg) ]]*Tabla52[[#This Row],[Precio Unitario Disposición ($)]] -> #VALUE! | G125: =+F125*1.19 -> #VALUE! | H125: 1 | I125: 750000 | J125: =+F125+H125*I125 -> #VALUE!
B126: 57206 | C126: 45758 | D126: 4110 | E126: 96 | F126: =+Tabla52[[#This Row],[Cantidad Lodos Generados (Kg) ]]*Tabla52[[#This Row],[Precio Unitario Disposición ($)]] -> #VALUE! | G126: =+F126*1.19 -> #VALUE! | H126: 1 | I126: 750000 | J126: =+F126+H126*I126 -> #VALUE!
... B142: 57715 | C142: 45777 | D142: 6050 | E142: 96 | F142: =+Tabla52[[#This Row],[Cantidad Lodos Generados (Kg) ]]*Tabla52[[#This Row],[Precio Unitario Disposición ($)]] -> #VALUE! | G142: =+F142*1.19 -> #VALUE! | H142: 1 | I142: 750000 | J142: =+F142+H142*I142 -> #VALUE!
A143: MAYO | B143: 57716 | C143: 45778 | D143: 3570 | E143: 96 | F143: =+D143*E143 -> 342720 | G143: =+F143*1.19 -> 407836.8 | H143: 1 | I143: 750000 | J143: =+F143+H143*I143 -> 1092720 | K143: =SUM(D143:D176) -> 163498 | L143: =SUM(H143:H176) -> 35 | M143: =SUM(F143:F176) -> 15695808 | N143: =M143*19% -> 2982203.5 | O143: =SUM(I143:I176) -> 24120000 | P143: =M143+O143 -> 39815808 | Q143: =SUM(M143+N143+O143) -> 42798012 | R143: =P143/K143 -> 243.52474
B144: 57717 | C144: 45779 | D144: 4860 | E144: 96 | F144: =+D144*E144 -> 466560 | G144: =+F144*1.19 -> 555206.4 | H144: 1 | I144: 750000 | J144: =+F144+H144*I144 -> 1216560
B145: 58110 | C145: 45780 | D145: 4800 | E145: 96 | F145: =+D145*E145 -> 460800 | G145: =+F145*1.19 -> 548352 | H145: 1 | I145: 750000 | J145: =+F145+H145*I145 -> 1210800
B146: 57096 | C146: 45781 | D146: 3526 | E146: 96 | F146: =+D146*E146 -> 338496 | G146: =+F146*1.19 -> 402810.24 | H146: 2 | I146: 290000 | J146: =+F146+H146*I146 -> 918496
B147: 58111 | C147: 45782 | D147: 5700 | E147: 96 | F147: =+D147*E147 -> 547200 | G147: =+F147*1.19 -> 651168 | H147: 1 | I147: 750000 | J147: =+F147+H147*I147 -> 1297200
B148: 59051 | C148: 45783 | D148: 4610 | E148: 96 | F148: =+D148*E148 -> 442560 | G148: =+F148*1.19 -> 526646.4 | H148: 1 | I148: 750000 | J148: =+F148+H148*I148 -> 1192560
B149: 59052 | C149: 45784 | D149: 4550 | E149: 96 | F149: =+D149*E149 -> 436800 | G149: =+F149*1.19 -> 519792 | H149: 1 | I149: 750000 | J149: =+F149+H149*I149 -> 1186800
B150: 59054 | C150: 45785 | D150: 4590 | E150: 96 | F150: =+D150*E150 -> 440640 | G150: =+F150*1.19 -> 524361.6 | H150: 1 | I150: 750000 | J150: =+F150+H150*I150 -> 1190640
B151: 59055 | C151: 45786 | D151: 5090 | E151: 96 | F151: =+D151*E151 -> 488640 | G151: =+F151*1.19 -> 581481.6 | H151: 1 | I151: 750000 | J151: =+F151+H151*I151 -> 1238640
B152: 59056 | C152: 45787 | D152: 5830 | E152: 96 | F152: =+D152*E152 -> 559680 | G152: =+F152*1.19 -> 666019.2 | H152: 1 | I152: 750000 | J152: =+F152+H152*I152 -> 1309680
B153: 59057 | C153: 45789 | D153: 5330 | E153: 96 | F153: =+D153*E153 -> 511680 | G153: =+F153*1.19 -> 608899.2 | H153: 1 | I153: 750000 | J153: =+F153+H153*I153 -> 1261680
B154: 59058 | C154: 45789 | D154: 5170 | E154: 96 | F154: =+D154*E154 -> 496320 | G154: =+F154*1.19 -> 590620.8 | H154: 1 | I154: 750000 | J154: =+F154+H154*I154 -> 1246320
B155: 59059 | C155: 45790 | D155: 5880 | E155: 96 | F155: =+D155*E155 -> 564480 | G155: =+F155*1.19 -> 671731.2 | H155: 1 | I155: 750000 | J155: =+F155+H155*I155 -> 1314480
... B176: 59079 | C176: 45808 | D176: 4330 | E176: 96 | F176: =+D176*E176 -> 415680 | G176: =+F176*1.19 -> 494659.2 | H176: 1 | I176: 750000 | J176: =+F176+H176*I176 -> 1165680
A177: JUNIO | B177: 59080 | C177: 45809 | D177: 4630 | E177: 96 | F177: =+D177*E177 -> 444480 | G177: =+F177*1.19 -> 528931.2 | H177: 1 | I177: 750000 | J177: =+F177+H177*I177 -> 1194480 | K177: =SUM(D177:D209) -> 146542 | L177: =SUM(H177:H209) -> 33 | M177: =SUM(F177:F209) -> 14068032 | N177: =M177*19% -> 2672926.1 | O177: =SUM(I177:I209) -> 24750000 | P177: =M177+O177 -> 38818032 | Q177: =SUM(M177+N177+O177) -> 41490958 | R177: =P177/K177 -> 264.89356
B178: 59081 | C178: 45811 | D178: 4940 | E178: 96 | F178: =+D178*E178 -> 474240 | G178: =+F178*1.19 -> 564345.6 | H178: 1 | I178: 750000 | J178: =+F178+H178*I178 -> 1224240
B179: 59083 | C179: 45813 | D179: 4800 | E179: 96 | F179: =+D179*E179 -> 460800 | G179: =+F179*1.19 -> 548352 | H179: 1 | I179: 750000 | J179: =+F179+H179*I179 -> 1210800
B180: 59087 | C180: 45814 | D180: 5860 | E180: 96 | F180: =+D180*E180 -> 562560 | G180: =+F180*1.19 -> 669446.4 | H180: 1 | I180: 750000 | J180: =+F180+H180*I180 -> 1312560
B181: 59086 | C181: 45814 | D181: 5280 | E181: 96 | F181: =+D181*E181 -> 506880 | G181: =+F181*1.19 -> 603187.2 | H181: 1 | I181: 750000 | J181: =+F181+H181*I181 -> 1256880
B182: 55639 | C182: 45814 | D182: 3496 | E182: 96 | F182: =+D182*E182 -> 335616 | G182: =+F182*1.19 -> 399383.04 | H182: 1 | I182: 750000 | J182: =+F182+H182*I182 -> 1085616
B183: 59085 | C183: 45814 | D183: 4500 | E183: 96 | F183: =+D183*E183 -> 432000 | G183: =+F183*1.19 -> 514080 | H183: 1 | I183: 750000 | J183: =+F183+H183*I183 -> 1182000
B184: 59088 | C184: 45815 | D184: 4360 | E184: 96 | F184: =+D184*E184 -> 418560 | G184: =+F184*1.19 -> 498086.4 | H184: 1 | I184: 750000 | J184: =+F184+H184*I184 -> 1168560
B185: 59089 | C185: 45816 | D185: 4130 | E185: 96 | F185: =+D185*E185 -> 396480 | G185: =+F185*1.19 -> 471811.2 | H185: 1 | I185: 750000 | J185: =+F185+H185*I185 -> 1146480
B186: 59090 | C186: 45817 | D186: 3370 | E186: 96 | F186: =+D186*E186 -> 323520 | G186: =+F186*1.19 -> 384988.8 | H186: 1 | I186: 750000 | J186: =+F186+H186*I186 -> 1073520
B187: 59091 | C187: 45817 | D187: 5400 | E187: 96 | F187: =+D187*E187 -> 518400 | G187: =+F187*1.19 -> 616896 | H187: 1 | I187: 750000 | J187: =+F187+H187*I187 -> 1268400
...

Sheet Disposición Lodos Díario- PTAR
A1: 2026 | B1: MF | C1: Fecha | D1: Sede | E1: Ciudad | F1: Tpo de Residuo | G1: Manejo Final | H1: Empresa Transportadora | I1: Empresa de Gestión Final | J1: Cantidad Lodos Generados (Kg) | K1: Precio Unitario Disposición ($) | L1: Valor Disposición Kg ($) | M1: Costo Total + IVA | N1: Servicio
A2: ENERO | B2: 47581 | C2: 2026-01-03 | D2: PTAR | E2: Bogotá | F2: Lodos PTAR | G2: Disposición Final | H2: PLANETA SAS ESP | I2: Planeta S.A.S | J2: 6100 | K2: 96 | L2: =+Tabla52[[#This Row],[Cantidad Lodos Generados (Kg) ]]*Tabla52[[#This Row],[Precio Unitario Disposición ($)]] -> 585600 | M2: =Tabla52[[#This Row],[Valor Disposición Kg ($)]]*1.19 -> 696864 | N2: Contenedor
B3: 47664 | C3: 2026-01-06 | D3: PTAR | E3: Bogotá | F3: Lodos PTAR | G3: Disposición Final | H3: PLANETA SAS ESP | I3: Planeta S.A.S | J3: 5830 | K3: 96 | L3: =+Tabla52[[#This Row],[Cantidad Lodos Generados (Kg) ]]*Tabla52[[#This Row],[Precio Unitario Disposición ($)]] -> 559680 | M3: =Tabla52[[#This Row],[Valor Disposición Kg ($)]]*1.19 -> 666019.2 | N3: Contenedor
B4: 47769 | C4: 2026-01-08 | D4: PTAR | E4: Bogotá | F4: Lodos PTAR | G4: Disposición Final | H4: PLANETA SAS ESP | I4: Planeta S.A.S | J4: 5630 | K4: 96 | L4: =+Tabla52[[#This Row],[Cantidad Lodos Generados (Kg) ]]*Tabla52[[#This Row],[Precio Unitario Disposición ($)]] -> 540480 | M4: =Tabla52[[#This Row],[Valor Disposición Kg ($)]]*1.19 -> 643171.2 | N4: Contenedor
B5: 47975 | C5: 2026-01-12 | D5: PTAR | E5: Bogotá | F5: Lodos PTAR | G5: Disposición Final | H5: PLANETA SAS ESP | I5: Planeta S.A.S | J5: 3730 | K5: 96 | L5: =+Tabla52[[#This Row],[Cantidad Lodos Generados (Kg) ]]*Tabla52[[#This Row],[Precio Unitario Disposición ($)]] -> 358080 | M5: =Tabla52[[#This Row],[Valor Disposición Kg ($)]]*1.19 -> 426115.2 | N5: Contenedor
B6: 47911 | C6: 2026-01-13 | D6: PTAR | E6: Bogotá | F6: Lodos PTAR | G6: Disposición Final | H6: PLANETA SAS ESP | I6: Planeta S.A.S | J6: 5320 | K6: 96 | L6: =+Tabla52[[#This Row],[Cantidad Lodos Generados (Kg) ]]*Tabla52[[#This Row],[Precio Unitario Disposición ($)]] -> 510720 | M6: =Tabla52[[#This Row],[Valor Disposición Kg ($)]]*1.19 -> 607756.8 | N6: Contenedor
B7: 48064 | C7: 2026-01-14 | D7: PTAR | E7: Bogotá | F7: Lodos PTAR | G7: Disposición Final | H7: PLANETA SAS ESP | I7: Planeta S.A.S | J7: 4390 | K7: 96 | L7: =+Tabla52[[#This Row],[Cantidad Lodos Generados (Kg) ]]*Tabla52[[#This Row],[Precio Unitario Disposición ($)]] -> 421440 | M7: =Tabla52[[#This Row],[Valor Disposición Kg ($)]]*1.19 -> 501513.6 | N7: Contenedor
B8: 48009 | C8: 2026-01-14 | D8: PTAR | E8: Bogotá | F8: Lodos PTAR | G8: Disposición Final | H8: PLANETA SAS ESP | I8: Planeta S.A.S | J8: 2787.2 | K8: 96 | L8: =+Tabla52[[#This Row],[Cantidad Lodos Generados (Kg) ]]*Tabla52[[#This Row],[Precio Unitario Disposición ($)]] -> 267571.2 | M8: =Tabla52[[#This Row],[Valor Disposición Kg ($)]]*1.19 -> 318409.73 | N8: Canecas
B9: 47993 | C9: 2026-01-14 | D9: PTAR | E9: Bogotá | F9: Lodos PTAR | G9: Disposición Final | H9: PLANETA SAS ESP | I9: Planeta S.A.S | J9: 5800 | K9: 96 | L9: =+Tabla52[[#This Row],[Cantidad Lodos Generados (Kg) ]]*Tabla52[[#This Row],[Precio Unitario Disposición ($)]] -> 556800 | M9: =Tabla52[[#This Row],[Valor Disposición Kg ($)]]*1.19 -> 662592 | N9: Contenedor
B10: 48054 | C10: 2026-01-15 | D10: PTAR | E10: Bogotá | F10: Lodos PTAR | G10: Disposición Final | H10: PLANETA SAS ESP | I10: Planeta S.A.S | J10: 5190 | K10: 96 | L10: =+Tabla52[[#This Row],[Cantidad Lodos Generados (Kg) ]]*Tabla52[[#This Row],[Precio Unitario Disposición ($)]] -> 498240 | M10: =Tabla52[[#This Row],[Valor Disposición Kg ($)]]*1.19 -> 592905.6 | N10: Contenedor
B11: 48103 | C11: 2026-01-16 | D11: PTAR | E11: Bogotá | F11: Lodos PTAR | G11: Disposición Final | H11: PLANETA SAS ESP | I11: Planeta S.A.S | J11: 3560 | K11: 96 | L11: =+Tabla52[[#This Row],[Cantidad Lodos Generados (Kg) ]]*Tabla52[[#This Row],[Precio Unitario Disposición ($)]] -> 341760 | M11: =Tabla52[[#This Row],[Valor Disposición Kg ($)]]*1.19 -> 406694.4 | N11: Contenedor
B12: 48170 | C12: 2026-01-17 | D12: PTAR | E12: Bogotá | F12: Lodos PTAR | G12: Disposición Final | H12: PLANETA SAS ESP | I12: Planeta S.A.S | J12: 3970 | K12: 96 | L12: =+Tabla52[[#This Row],[Cantidad Lodos Generados (Kg) ]]*Tabla52[[#This Row],[Precio Unitario Disposición ($)]] -> 381120 | M12: =Tabla52[[#This Row],[Valor Disposición Kg ($)]]*1.19 -> 453532.8 | N12: Contenedor
B13: 48251 | C13: 2026-01-19 | D13: PTAR | E13: Bogotá | F13: Lodos PTAR | G13: Disposición Final | H13: PLANETA SAS ESP | I13: Planeta S.A.S | J13: 7920 | K13: 96 | L13: =+Tabla52[[#This Row],[Cantidad Lodos Generados (Kg) ]]*Tabla52[[#This Row],[Precio Unitario Disposición ($)]] -> 760320 | M13: =Tabla52[[#This Row],[Valor Disposición Kg ($)]]*1.19 -> 904780.8 | N13: Contenedor
B14: 48203 | C14: 2026-01-19 | D14: PTAR | E14: Bogotá | F14: Lodos PTAR | G14: Disposición Final | H14: PLANETA SAS ESP | I14: Planeta S.A.S | J14: 4600 | K14: 96 | L14: =+Tabla52[[#This Row],[Cantidad Lodos Generados (Kg) ]]*Tabla52[[#This Row],[Precio Unitario Disposición ($)]] -> 441600 | M14: =Tabla52[[#This Row],[Valor Disposición Kg ($)]]*1.19 -> 525504 | N14: Contenedor
... B21: 48743 | C21: 2026-01-29 | D21: PTAR | E21: Bogotá | F21: Lodos PTAR | G21: Disposición Final | H21: PLANETA SAS ESP | I21: Planeta S.A.S | J21: 5670 | K21: 96 | L21: =+Tabla52[[#This Row],[Cantidad Lodos Generados (Kg) ]]*Tabla52[[#This Row],[Precio Unitario Disposición ($)]] -> 544320 | M21: =Tabla52[[#This Row],[Valor Disposición Kg ($)]]*1.19 -> 647740.8 | N21: Contenedor
B22: 48843 | C22: 2026-01-30 | D22: PTAR | E22: Bogotá | F22: Lodos PTAR | G22: Disposición Final | H22: PLANETA SAS ESP | I22: Planeta S.A.S | J22: 4100 | K22: 96 | L22: =+Tabla52[[#This Row],[Cantidad Lodos Generados (Kg) ]]*Tabla52[[#This Row],[Precio Unitario Disposición ($)]] -> 393600 | M22: =+L22*1.19 -> 468384 | N22: Contenedor
A23: FEBRERO | B23: 48961 | C23: 2026-02-02 | D23: PTAR | E23: Bogotá | F23: Lodos PTAR | G23: Disposición Final | H23: PLANETA SAS ESP | I23: Planeta S.A.S | J23: 5260 | K23: 96 | L23: =+J23*K23 -> 504960 | M23: =+L23*1.19 -> 600902.4 | N23: Contenedor
B24: 49062 | C24: 2026-02-03 | D24: PTAR | E24: Bogotá | F24: Lodos PTAR | G24: Disposición Final | H24: PLANETA SAS ESP | I24: Planeta S.A.S | J24: 5860 | K24: 96 | L24: =+J24*K24 -> 562560 | M24: =+L24*1.19 -> 669446.4 | N24: Contenedor
B25: 49174 | C25: 2026-02-04 | D25: PTAR | E25: Bogotá | F25: Lodos PTAR | G25: Disposición Final | H25: PLANETA SAS ESP | I25: Planeta S.A.S | J25: 4610 | K25: 96 | L25: =+J25*K25 -> 442560 | M25: =+L25*1.19 -> 526646.4 | N25: Contenedor
B26: 49123 | C26: 2026-02-04 | D26: PTAR | E26: Bogotá | F26: Lodos PTAR | G26: Disposición Final | H26: PLANETA SAS ESP | I26: Planeta S.A.S | J26: 5490 | K26: 96 | L26: =+J26*K26 -> 527040 | M26: =+L26*1.19 -> 627177.6 | N26: Contenedor
B27: 49096 | C27: 2026-02-04 | D27: PTAR | E27: Bogotá | F27: Lodos PTAR | G27: Disposición Final | H27: PLANETA SAS ESP | I27: Planeta S.A.S | J27: 5760 | K27: 96 | L27: =+J27*K27 -> 552960 | M27: =+L27*1.19 -> 658022.4 | N27: Contenedor
B28: 49143 | C28: 2026-02-05 | D28: PTAR | E28: Bogotá | F28: Lodos PTAR | G28: Disposición Final | H28: PLANETA SAS ESP | I28: Planeta S.A.S | J28: 5220 | K28: 96 | L28: =+J28*K28 -> 501120 | M28: =+L28*1.19 -> 596332.8 | N28: Contenedor
B29: 49211 | C29: 2026-02-06 | D29: PTAR | E29: Bogotá | F29: Lodos PTAR | G29: Disposición Final | H29: PLANETA SAS ESP | I29: Planeta S.A.S | J29: 4170 | K29: 96 | L29: =+J29*K29 -> 400320 | M29: =+L29*1.19 -> 476380.8 | N29: Contenedor
B30: 49265 | C30: 2026-02-07 | D30: PTAR | E30: Bogotá | F30: Lodos PTAR | G30: Disposición Final | H30: PLANETA SAS ESP | I30: Planeta S.A.S | J30: 4960 | K30: 96 | L30: =+J30*K30 -> 476160 | M30: =+L30*1.19 -> 566630.4 | N30: Contenedor
B31: 49345 | C31: 2026-02-09 | D31: PTAR | E31: Bogotá | F31: Lodos PTAR | G31: Disposición Final | H31: PLANETA SAS ESP | I31: Planeta S.A.S | J31: 4190 | K31: 96 | L31: =+J31*K31 -> 402240 | M31: =+L31*1.19 -> 478665.6 | N31: Contenedor
B32: 49470 | C32: 2026-02-11 | D32: PTAR | E32: Bogotá | F32: Lodos PTAR | G32: Disposición Final | H32: PLANETA SAS ESP | I32: Planeta S.A.S | J32: 5410 | K32: 96 | L32: =+J32*K32 -> 519360 | M32: =+L32*1.19 -> 618038.4 | N32: Contenedor
B33: 49555 | C33: 2026-02-12 | D33: PTAR | E33: Bogotá | F33: Lodos PTAR | G33: Disposición Final | H33: PLANETA SAS ESP | I33: Planeta S.A.S | J33: 4700 | K33: 96 | L33: =+J33*K33 -> 451200 | M33: =+L33*1.19 -> 536928 | N33: Contenedor
B34: 49513 | C34: 2026-02-12 | D34: PTAR | E34: Bogotá | F34: Lodos PTAR | G34: Disposición Final | H34: PLANETA SAS ESP | I34: Planeta S.A.S | J34: 2960 | K34: 96 | L34: =+J34*K34 -> 284160 | M34: =+L34*1.19 -> 338150.4 | N34: Contenedor
B35: 49663 | C35: 2026-02-14 | D35: PTAR | E35: Bogotá | F35: Lodos PTAR | G35: Disposición Final | H35: PLANETA SAS ESP | I35: Planeta S.A.S | J35: 4600 | K35: 96 | L35: =+J35*K35 -> 441600 | M35: =+L35*1.19 -> 525504 | N35: Contenedor
... B40: 50226 | C40: 2026-02-25 | D40: PTAR | E40: Bogotá | F40: Lodos PTAR | G40: Disposición Final | H40: PLANETA SAS ESP | I40: Planeta S.A.S | J40: 3916.6 | K40: 96 | L40: =+J40*K40 -> 375993.6 | M40: =+L40*1.19 -> 447432.38 | N40: Canecas
A41: MARZO | B41: 50531 | C41: 2026-03-02 | D41: PTAR | E41: Bogotá | F41: Lodos PTAR | G41: Disposición Final | H41: PLANETA SAS ESP | I41: Planeta S.A.S | J41: 5580 | K41: 96 | L41: =+J41*K41 -> 535680 | M41: =+L41*1.19 -> 637459.2 | N41: Contenedor
B42: 50730 | C42: 2026-03-05 | D42: PTAR | E42: Bogotá | F42: Lodos PTAR | G42: Disposición Final | H42: PLANETA SAS ESP | I42: Planeta S.A.S | J42: 4440 | K42: 96 | L42: =+J42*K42 -> 426240 | M42: =+L42*1.19 -> 507225.6 | N42: Contenedor
B43: 50684 | C43: 2026-03-05 | D43: PTAR | E43: Bogotá | F43: Lodos PTAR | G43: Disposición Final | H43: PLANETA SAS ESP | I43: Planeta S.A.S | J43: 2507 | K43: 96 | L43: =+J43*K43 -> 240672 | M43: =+L43*1.19 -> 286399.68 | N43: Canecas
B44: 50812 | C44: 2026-03-07 | D44: PTAR | E44: Bogotá | F44: Lodos PTAR | G44: Disposición Final | H44: PLANETA SAS ESP | I44: Planeta S.A.S | J44: 4530 | K44: 96 | L44: =+J44*K44 -> 434880 | M44: =+L44*1.19 -> 517507.2 | N44: Contenedor
B45: 50934 | C45: 2026-03-10 | D45: PTAR | E45: Bogotá | F45: Lodos PTAR | G45: Disposición Final | H45: PLANETA SAS ESP | I45: Planeta S.A.S | J45: 5060 | K45: 96 | L45: =+J45*K45 -> 485760 | M45: =+L45*1.19 -> 578054.4 | N45: Contenedor
B46: 51040 | C46: 2026-03-12 | D46: PTAR | E46: Bogotá | F46: Lodos PTAR | G46: Disposición Final | H46: PLANETA SAS ESP | I46: Planeta S.A.S | J46: 5490 | K46: 96 | L46: =+J46*K46 -> 527040 | M46: =+L46*1.19 -> 627177.6 | N46: Contenedor
B47: 51174 | C47: 2026-03-14 | D47: PTAR | E47: Bogotá | F47: Lodos PTAR | G47: Disposición Final | H47: PLANETA SAS ESP | I47: Planeta S.A.S | J47: 4580 | K47: 96 | L47: =+J47*K47 -> 439680 | M47: =+L47*1.19 -> 523219.2 | N47: Contenedor
B48: 51282 | C48: 2026-03-17 | D48: PTAR | E48: Bogotá | F48: Lodos PTAR | G48: Disposición Final | H48: PLANETA SAS ESP | I48: Planeta S.A.S | J48: 3770 | K48: 96 | L48: =+J48*K48 -> 361920 | M48: =+L48*1.19 -> 430684.8 | N48: Contenedor
B49: 51577 | C49: 2026-03-23 | D49: PTAR | E49: Bogotá | F49: Lodos PTAR | G49: Disposición Final | H49: PLANETA SAS ESP | I49: Planeta S.A.S | J49: 5080 | K49: 96 | L49: =+J49*K49 -> 487680 | M49: =+L49*1.19 -> 580339.2 | N49: Contenedor
B50: 51683 | C50: 2026-03-26 | D50: PTAR | E50: Bogotá | F50: Lodos PTAR | G50: Disposición Final | H50: PLANETA SAS ESP | I50: Planeta S.A.S | J50: 3570 | K50: 96 | L50: =+J50*K50 -> 342720 | M50: =+L50*1.19 -> 407836.8 | N50: Contenedor
B51: 51876 | C51: 2026-03-31 | D51: PTAR | E51: Bogotá | F51: Lodos PTAR | G51: Disposición Final | H51: PLANETA SAS ESP | I51: Planeta S.A.S | J51: 1677.6 | K51: 96 | L51: =+J51*K51 -> 161049.6 | M51: =+L51*1.19 -> 191649.02 | N51: Canecas
A52: ABRIL | B52: 52043 | C52: 2026-04-06 | D52: PTAR | E52: Bogotá | F52: Lodos PTAR | G52: Disposición Final | H52: PLANETA SAS ESP | I52: Planeta S.A.S | J52: 4510 | K52: 96 | L52: =+J52*K52 -> 432960 | M52: =+L52*1.19 -> 515222.4 | N52: Contenedor
B53: 52421 | C53: 2026-04-13 | D53: PTAR | E53: Bogotá | F53: Lodos PTAR | G53: Disposición Final | H53: PLANETA SAS ESP | I53: Planeta S.A.S | J53: 3510 | K53: 96 | L53: =+J53*K53 -> 336960 | M53: =+L53*1.19 -> 400982.4 | N53: Contenedor
B54: 52677 | C54: 2026-04-18 | D54: PTAR | E54: Bogotá | F54: Lodos PTAR | G54: Disposición Final | H54: PLANETA SAS ESP | I54: Planeta S.A.S | J54: 4920 | K54: 96 | L54: =+J54*K54 -> 472320 | M54: =+L54*1.19 -> 562060.8 | N54: Contenedor
B55: 52648 | C55: 2026-04-18 | D55: PTAR | E55: Bogotá | F55: Lodos PTAR | G55: Disposición Final | H55: PLANETA SAS ESP | I55: Planeta S.A.S | J55: 2436.6 | K55: 96 | L55: =+J55*K55 -> 233913.6 | M55: =+L55*1.19 -> 278357.18 | N55: Canecas
B56: 52714 | C56: 2026-04-20 | D56: PTAR | E56: Bogotá | F56: Lodos PTAR | G56: Disposición Final | H56: PLANETA SAS ESP | I56: Planeta S.A.S | J56: 3450 | K56: 96 | L56: =+J56*K56 -> 331200 | M56: =+L56*1.19 -> 394128 | N56: Contenedor
B57: 53023 | C57: 2026-04-27 | D57: PTAR | E57: Bogotá | F57: Lodos PTAR | G57: Disposición Final | H57: PLANETA SAS ESP | I57: Planeta S.A.S | J57: 4730 | K57: 96 | L57: =+J57*K57 -> 454080 | M57: =+L57*1.19 -> 540355.2 | N57: Contenedor
B58: 53064 | C58: 2026-04-28 | D58: PTAR | E58: Bogotá | F58: Lodos PTAR | G58: Disposición Final | H58: PLANETA SAS ESP | I58: Planeta S.A.S | J58: 2856.6 | K58: 96 | L58: =+J58*K58 -> 274233.6 | M58: =+L58*1.19 -> 326337.98 | N58: Canecas
B59: 53138 | C59: 2026-04-29 | D59: PTAR | E59: Bogotá | F59: Lodos PTAR | G59: Disposición Final | H59: PLANETA SAS ESP | I59: Planeta S.A.S | J59: 4490 | K59: 96 | L59: =+J59*K59 -> 431040 | M59: =+L59*1.19 -> 512937.6 | N59: Contenedor

Sheet consolidado diario
A1: FECHA | B1: N | C1: Kg | D1: GEM m3 | E1: kg/m3 | F1: factor Kg/m3 | G1: valor kg | H1: transporte | I1: $/dia | J1: $/kg | K1: factor $/kg | L1: ajuste de factor | M1: ajuste de transporte
A2: 45536 | B2: 1 | C2: 0 | D2: 0 | F2: 2.8 | K2: 283
A3: 45537 | B3: 2 | C3: 3730 | D3: 1520 | E3: =+C3/D3 -> 2.4539474 | F3: 2.8 | G3: =+C3*96 -> 358080 | H3: 750000 | I3: =+G3+H3 -> 1108080 | J3: =+I3/C3 -> 297.07239 | K3: 283
A4: 45538 | B4: 3 | C4: 5040 | D4: 1680 | E4: =+C4/D4 -> 3 | F4: 2.8 | G4: =+C4*96 -> 483840 | H4: 750000 | I4: =+G4+H4 -> 1233840 | J4: =+I4/C4 -> 244.80952 | K4: 283
A5: 45539 | B5: 4 | C5: =+$L$7*D5 -> 3582.24 | D5: 1360 | E5: =+C5/D5 -> 2.634 | F5: 2.8 | G5: =+C5*96 -> 343895.04 | H5: =+$M$7*C5 -> 353600 | I5: =+G5+H5 -> 697495.04 | J5: =+I5/C5 -> 194.70919 | K5: 283
A6: 45540 | B6: 5 | C6: =+$L$7*D6 -> 3582.24 | D6: 1360 | E6: =+C6/D6 -> 2.634 | F6: 2.8 | G6: =+C6*96 -> 343895.04 | H6: =+$M$7*C6 -> 353600 | I6: =+G6+H6 -> 697495.04 | J6: =+I6/C6 -> 194.70919 | K6: 283
A7: 45541 | B7: 6 | C7: =+$L$7*D7 -> 3371.52 | D7: 1280 | E7: =+C7/D7 -> 2.634 | F7: 2.8 | G7: =+C7*96 -> 323665.92 | H7: =+$M$7*C7 -> 332800 | I7: =+G7+H7 -> 656465.92 | J7: =+I7/C7 -> 194.70919 | K7: 283 | L7: =10536/4000 -> 2.634 | M7: =1040000/10536 -> 98.709188
A8: 45542 | B8: 7 | C8: 4040 | D8: 1520 | E8: =+C8/D8 -> 2.6578947 | F8: 2.8 | G8: =+C8*96 -> 387840 | H8: 750000 | I8: =+G8+H8 -> 1137840 | J8: =+I8/C8 -> 281.64356 | K8: 283
A9: 45543 | B9: 8 | C9: =+$L$9*D9 -> 2745 | D9: 1360 | E9: =+C9/D9 -> 2.0183824 | F9: 2.8 | G9: =+C9*96 -> 263520 | H9: =+$M$9*C9 -> 375000 | I9: =+G9+H9 -> 638520 | J9: =+I9/C9 -> 232.61202 | K9: 283 | L9: =5490/2720 -> 2.0183824 | M9: =750000/5490 -> 136.61202
A10: 45544 | B10: 9 | C10: =+$L$10*D10 -> 2745 | D10: 1360 | E10: =+C10/D10 -> 2.0183824 | F10: 2.8 | G10: =+C10*96 -> 263520 | H10: =+$M$9*C10 -> 375000 | I10: =+G10+H10 -> 638520 | J10: =+I10/C10 -> 232.61202 | K10: 283 | L10: =5490/2720 -> 2.0183824 | M10: =750000/5490 -> 136.61202
A11: 45545 | B11: 10 | C11: =+$L$11*D11 -> 3150 | D11: 1440 | E11: =+C11/D11 -> 2.1875 | F11: 2.8 | G11: =+C11*96 -> 302400 | H11: =+$M$11*C11 -> 355263.16 | I11: =+G11+H11 -> 657663.16 | J11: =+I11/C11 -> 208.78195 | K11: 283 | L11: =6650/3040 -> 2.1875 | M11: =750000/6650 -> 112.78195
A12: 45546 | B12: 11 | C12: =+$L$11*D12 -> 3500 | D12: 1600 | E12: =+C12/D12 -> 2.1875 | F12: 2.8 | G12: =+C12*96 -> 336000 | H12: =+$M$11*C12 -> 394736.84 | I12: =+G12+H12 -> 730736.84 | J12: =+I12/C12 -> 208.78195 | K12: 283 | L12: =6650/3040 -> 2.1875 | M12: =750000/6650 -> 112.78195
A13: 45547 | B13: 12 | C13: 3890 | D13: 1680 | E13: =+C13/D13 -> 2.3154762 | F13: 2.8 | G13: =+C13*96 -> 373440 | H13: 750000 | I13: =+G13+H13 -> 1123440 | J13: =+I13/C13 -> 288.80206 | K13: 283
A14: 45548 | B14: 13 | C14: 3920 | D14: 1920 | E14: =+C14/D14 -> 2.0416667 | F14: 2.8 | G14: =+C14*96 -> 376320 | H14: 750000 | I14: =+G14+H14 -> 1126320 | J14: =+I14/C14 -> 287.32653 | K14: 283
A15: 45549 | B15: 14 | C15: 0 | D15: 160 | E15: =+C15/D15 -> 0 | F15: 2.8 | G15: =+C15*96 -> 0 | H15: =+$M$14*C15 -> 0 | I15: =+G15+H15 -> 0 | J15: 0 | K15: 283
A16: 45550 | B16: 15 | C16: =+$L$14*D16 -> 0 | D16: 0 | E16: 0 | F16: 2.8 | G16: =+C16*96 -> 0 | H16: =+$M$14*C16 -> 0 | I16: =+G16+H16 -> 0 | J16: 0 | K16: 283
A17: 45551 | B17: 16 | C17: 1684 | D17: 1280 | E17: =+C17/D17 -> 1.315625 | F17: 2.8 | G17: =+C17*96 -> 161664 | H17: =+(750000*C17)/4000 -> 315750 | I17: =+G17+H17 -> 477414 | J17: =+I17/C17 -> 283.5 | K17: 283
A18: 45552 | B18: 17 | C18: =4000-C17 -> 2316 | D18: 1760 | E18: =+C18/D18 -> 1.3159091 | F18: 2.8 | G18: =+C18*96 -> 222336 | H18: =750000-H17 -> 434250 | I18: =+G18+H18 -> 656586 | J18: =+I18/C18 -> 283.5 | K18: 283
A19: 45553 | B19: 18 | C19: 4550 | D19: 1680 | E19: =+C19/D19 -> 2.7083333 | F19: 2.8 | G19: =+C19*96 -> 436800 | H19: 750000 | I19: =+G19+H19 -> 1186800 | J19: =+I19/C19 -> 260.83516 | K19: 283
A20: 45554 | B20: 19 | C20: 4330 | D20: 1520 | E20: =+C20/D20 -> 2.8486842 | F20: 2.8 | G20: =+C20*96 -> 415680 | H20: 750000 | I20: =+G20+H20 -> 1165680 | J20: =+I20/C20 -> 269.21016 | K20: 283
A21: 45555 | B21: 20 | C21: 3840 | D21: 1760 | E21: =+C21/D21 -> 2.1818182 | F21: 2.8 | G21: =+C21*96 -> 368640 | H21: 750000 | I21: =+G21+H21 -> 1118640 | J21: =+I21/C21 -> 291.3125 | K21: 283
A22: 45556 | B22: 21 | C22: 5340 | D22: 1760 | E22: =+C22/D22 -> 3.0340909 | F22: 2.8 | G22: =+C22*96 -> 512640 | H22: 750000 | I22: =+G22+H22 -> 1262640 | J22: =+I22/C22 -> 236.44944 | K22: 283
A23: 45557 | B23: 22 | C23: =L23*D23 -> 384.70588 | D23: 240 | E23: =+C23/D23 -> 1.6029412 | F23: 2.8 | G23: =+C23*96 -> 36931.765 | H23: =C23*M23 -> 66176.471 | I23: =+G23+H23 -> 103108.24 | J23: =+I23/C23 -> 268.01835 | K23: 283 | L23: =4360/2720 -> 1.6029412 | M23: =750000/4360 -> 172.01835
A24: 45558 | B24: 23 | C24: =L24*D24 -> 1795.2941 | D24: 1120 | E24: =+C24/D24 -> 1.6029412 | F24: 2.8 | G24: =+C24*96 -> 172348.24 | H24: =C24*M24 -> 308823.53 | I24: =+G24+H24 -> 481171.76 | J24: =+I24/C24 -> 268.01835 | K24: 283 | L24: =4360/2720 -> 1.6029412 | M24: =750000/4360 -> 172.01835
A25: 45559 | B25: 24 | C25: =L25*D25 -> 2180 | D25: 1360 | E25: =+C25/D25 -> 1.6029412 | F25: 2.8 | G25: =+C25*96 -> 209280 | H25: =C25*M25 -> 375000 | I25: =+G25+H25 -> 584280 | J25: =+I25/C25 -> 268.01835 | K25: 283 | L25: =4360/2720 -> 1.6029412 | M25: =750000/4360 -> 172.01835
A26: 45560 | B26: 25 | C26: 5220 | D26: 1680 | E26: =+C26/D26 -> 3.1071429 | F26: 2.8 | G26: =+C26*96 -> 501120 | H26: 750000 | I26: =+G26+H26 -> 1251120 | J26: =+I26/C26 -> 239.67816 | K26: 283
A27: 45561 | B27: 26 | C27: 3950 | D27: 1680 | E27: =+C27/D27 -> 2.3511905 | F27: 2.8 | G27: =+C27*96 -> 379200 | H27: 750000 | I27: =+G27+H27 -> 1129200 | J27: =+I27/C27 -> 285.87342 | K27: 283
A28: 45562 | B28: 27 | C28: 4560 | D28: 1600 | E28: =+C28/D28 -> 2.85 | F28: 2.8 | G28: =+C28*96 -> 437760 | H28: 750000 | I28: =+G28+H28 -> 1187760 | J28: =+I28/C28 -> 260.47368 | K28: 283
A29: 45563 | B29: 28 | C29: 4870 | D29: 1600 | E29: =+C29/D29 -> 3.04375 | F29: 2.8 | G29: =+C29*96 -> 467520 | H29: 750000 | I29: =+G29+H29 -> 1217520 | J29: =+I29/C29 -> 250.00411 | K29: 283
A30: 45564 | B30: 29 | C30: =+M31 -> 2779.6875 | D30: 1360 | E30: =+C30/D30 -> 2.0438879 | F30: 2.8 | G30: =+C30*96 -> 266850 | H30: =750000/2 -> 375000 | I30: =+G30+H30 -> 641850 | J30: =+I30/C30 -> 230.90725 | K30: 283
A31: 45565 | B31: 30 | C31: =+M31 -> 2779.6875 | D31: 1200 | E31: =+C31/D31 -> 2.3164062 | F31: 2.8 | G31: =+C31*96 -> 266850 | H31: =750000/2 -> 375000 | I31: =+G31+H31 -> 641850 | J31: =+I31/C31 -> 230.90725 | K31: 283 | L31: =5930/2560 -> 2.3164062 | M31: =+D31*L31 -> 2779.6875
C32: =SUM(C2:C31) -> 93875.375 | D32: =SUM(D2:D31) -> 39840 | E32: =+C32/D32 -> 2.3563096 | G32: =SUM(G3:G31) -> 9012036 | H32: =SUM(H3:H31) -> 14540000 | I32: =SUM(I3:I31) -> 23552036 | J32: =+I32/C32 -> 250.8862

Sheet consolidado diario (2)
A1: FECHA | B1: N | C1: Kg | D1: GEM m3 | E1: kg/m3 | F1: factor Kg/m3 | G1: valor kg | H1: transporte | I1: $/dia | J1: $/kg | K1: factor $/kg | L1: ajuste de factor | M1: ajuste de transporte
A2: 45566 | B2: 1 | C2: 2950 | D2: 960 | E2: =+C2/D2 -> 3.0729167 | F2: 2.8 | G2: =+C2*96 -> 283200 | H2: 750000 | I2: =+G2+H2 -> 1033200 | J2: =+I2/C2 -> 350.23729 | K2: 283
A3: 45567 | B3: 2 | C3: 4210 | D3: 1840 | E3: =+C3/D3 -> 2.2880435 | F3: 2.8 | G3: =+C3*96 -> 404160 | H3: 750000 | I3: =+G3+H3 -> 1154160 | J3: =+I3/C3 -> 274.14727 | K3: 283
A4: 45568 | B4: 3 | C4: =L5*D4 -> 2801.7391 | D4: 1920 | E4: =+C4/D4 -> 1.4592391 | F4: 2.8 | G4: =+C4*96 -> 268966.96 | H4: =+M5*C4 -> 391304.35 | I4: =+G4+H4 -> 660271.3 | J4: =+I4/C4 -> 235.6648 | K4: 283 | L4: 1.4592391 | M4: 139.6648
A5: 45569 | B5: 4 | C5: =D5*L5 -> 2568.2609 | D5: 1760 | E5: =+C5/D5 -> 1.4592391 | F5: 2.8 | G5: =+C5*96 -> 246553.04 | H5: =+M5*C5 -> 358695.65 | I5: =+G5+H5 -> 605248.7 | J5: =+I5/C5 -> 235.6648 | K5: 283 | L5: =5370/3680 -> 1.4592391 | M5: =750000/5370 -> 139.6648
A6: 45570 | B6: 5 | C6: 4970 | D6: 480 | E6: =+C6/D6 -> 10.354167 | F6: 2.8 | G6: =+C5*96 -> 246553.04 | H6: 750000 | I6: =+G6+H6 -> 996553.04 | J6: =+I6/C6 -> 200.51369 | K6: 283
A7: 45571 | B7: 6 | C7: 0 | D7: 0 | E7: =+C7/D7 -> #DIV/0! | F7: 2.8 | G7: =+C7*96 -> 0 | H7: =+$M$7*C6 -> 0 | I7: =+G7+H7 -> 0 | J7: =+I7/C7 -> #DIV/0! | K7: 283
A8: 45572 | B8: 7 | C8: =+D8*L9 -> 3330 | D8: 1440 | E8: =+C8/D8 -> 2.3125 | F8: 2.8 | G8: =+C8*96 -> 319680 | H8: 375000 | I8: =+G8+H8 -> 694680 | J8: =+I8/C8 -> 208.61261 | K8: 283 | L8: 2.31 | M8: 112.6
A9: 45573 | B9: 8 | C9: =+D9*L9 -> 3330 | D9: 1440 | E9: =+C9/D9 -> 2.3125 | F9: 2.8 | G9: =+C9*96 -> 319680 | H9: =+C9*M9 -> 375000 | I9: =+G9+H9 -> 694680 | J9: =+I9/C9 -> 208.61261 | K9: 283 | L9: 2.3125 | M9: =750000/6660 -> 112.61261
A10: 45574 | B10: 9 | C10: 4580 | D10: 1680 | E10: =+C10/D10 -> 2.7261905 | F10: 2.8 | G10: =+C10*96 -> 439680 | H10: 750000 | I10: =+G10+H10 -> 1189680 | J10: =+I10/C10 -> 259.75546 | K10: 283
A11: 45575 | B11: 10 | C11: 3630 | D11: 1840 | E11: =+C11/D11 -> 1.9728261 | F11: 2.8 | G11: =+C11*96 -> 348480 | H11: 750000 | I11: =+G11+H11 -> 1098480 | J11: =+I11/C11 -> 302.61157 | K11: 283
A12: 45576 | B12: 11 | C12: 4450 | D12: 1600 | E12: =+C12/D12 -> 2.78125 | F12: 2.8 | G12: =+C12*96 -> 427200 | H12: 750000 | I12: =+G12+H12 -> 1177200 | J12: =+I12/C12 -> 264.53933 | K12: 283
A13: 45577 | B13: 12 | C13: 5130 | D13: 1680 | E13: =+C13/D13 -> 3.0535714 | F13: 2.8 | G13: =+C13*96 -> 492480 | H13: 750000 | I13: =+G13+H13 -> 1242480 | J13: =+I13/C13 -> 242.19883 | K13: 283
A14: 45578 | B14: 13 | C14: =+D14*2 -> 640 | D14: 320 | E14: =+C14/D14 -> 2 | F14: 2.8 | G14: =+C14*96 -> 61440 | H14: =+C14*M14 -> 111111.11 | I14: =+G14+H14 -> 172551.11 | J14: =+I14/C14 -> 269.61111 | K14: 283 | L14: =+C14/D14 -> 2 | M14: =750000/4320 -> 173.61111
A15: 45579 | B15: 14 | C15: =+D15*2 -> 480 | D15: 240 | E15: =+C15/D15 -> 2 | F15: 2.8 | G15: =+C15*96 -> 46080 | H15: =+C15*M15 -> 83333.333 | I15: =+G15+H15 -> 129413.33 | J15: =+I15/C15 -> 269.61111 | K15: 283 | L15: =+C15/D15 -> 2 | M15: =750000/4320 -> 173.61111
A16: 45580 | B16: 15 | C16: =+D16*2 -> 3200 | D16: 1600 | E16: =+C16/D16 -> 2 | F16: 2.8 | G16: =+C16*96 -> 307200 | H16: =+C16*M16 -> 555555.56 | I16: =+G16+H16 -> 862755.56 | J16: =+I16/C16 -> 269.61111 | K16: 283 | L16: =+C16/D16 -> 2 | M16: =750000/4320 -> 173.61111
A17: 45581 | B17: 16 | C17: 5830 | D17: 1440 | E17: =+C17/D17 -> 4.0486111 | F17: 2.8 | G17: =+C17*96 -> 559680 | H17: 750000 | I17: =+G17+H17 -> 1309680 | J17: =+I17/C17 -> 224.64494 | K17: 283
A18: 45582 | B18: 17 | C18: 4530 | D18: 1360 | E18: =+C18/D18 -> 3.3308824 | F18: 2.8 | G18: =+C18*96 -> 434880 | H18: 750000 | I18: =+G18+H18 -> 1184880 | J18: =+I18/C18 -> 261.56291 | K18: 283
A19: 45583 | B19: 18 | C19: 0 | D19: 0 | E19: =+C19/D19 -> #DIV/0! | F19: 2.8 | G19: =+C19*96 -> 0 | H19: =+$M$7*C18 -> 0 | I19: =+G19+H19 -> 0 | J19: =+I19/C19 -> #DIV/0! | K19: 283
A20: 45584 | B20: 19 | C20: =+L22*D20 -> 1449.2308 | D20: 320 | E20: =+C20/D20 -> 4.5288462 | F20: 2.8 | G20: =+C20*96 -> 139126.15 | H20: =+M20*C20 -> 230769.23 | I20: =+G20+H20 -> 369895.38 | J20: =+I20/C20 -> 255.23567 | K20: 283 | L20: =4710/1040 -> 4.5288462 | M20: =750000/4710 -> 159.23567
A21: 45585 | B21: 20 | C21: 0 | D21: 0 | E21: =+C21/D21 -> #DIV/0! | F21: 2.8 | G21: =+C21*96 -> 0 | H21: =+$M$7*C20 -> 0 | I21: =+G21+H21 -> 0 | J21: =+I21/C21 -> #DIV/0! | K21: 283
A22: 45586 | B22: 21 | C22: =+D22*L22 -> 3260.7692 | D22: 720 | E22: =+C22/D22 -> 4.5288462 | F22: 2.8 | G22: =+C22*96 -> 313033.85 | H22: =+M22*C22 -> 519230.77 | I22: =+G22+H22 -> 832264.62 | J22: =+I22/C22 -> 255.23567 | K22: 283 | L22: =4710/1040 -> 4.5288462 | M22: =750000/4710 -> 159.23567
A23: 45587 | B23: 22 | C23: =+D23*L23 -> 3215.3846 | D23: 1760 | E23: =+C23/D23 -> 1.8269231 | F23: 2.8 | G23: =+C23*96 -> 308676.92 | H23: =+C23*M23 -> 423076.92 | I23: =+G23+H23 -> 731753.85 | J23: =+I23/C23 -> 227.57895 | K23: 283 | L23: 1.8269231 | M23: =750000/5700 -> 131.57895
A24: 45588 | B24: 23 | C24: =+D24*L24 -> 2484.6154 | D24: 1360 | E24: =+C24/D24 -> 1.8269231 | F24: 2.8 | G24: =+C24*96 -> 238523.08 | H24: =+C24*M24 -> 326923.08 | I24: =+G24+H24 -> 565446.15 | J24: =+I24/C24 -> 227.57895 | K24: 283 | L24: 1.8269231 | M24: =750000/5700 -> 131.57895
A25: 45589 | B25: 24 | C25: 4410 | D25: 400 | E25: =+C25/D25 -> 11.025 | F25: 2.8 | G25: =+C25*96 -> 423360 | H25: 750000 | I25: =+G25+H25 -> 1173360 | J25: =+I25/C25 -> 266.06803 | K25: 283
A26: 45590 | B26: 25 | C26: =+D26*L26 -> 2234.2857 | D26: 1360 | E26: =+C26/D26 -> 1.6428571 | F26: 2.8 | G26: =+C26*96 -> 214491.43 | H26: =+C26*M26 -> 364285.71 | I26: =+G26+H26 -> 578777.14 | J26: =+I26/C26 -> 259.04348 | K26: 283 | L26: =4600/2800 -> 1.6428571 | M26: =750000/4600 -> 163.04348
A27: 45591 | B27: 26 | C27: =+D27*L27 -> 2365.7143 | D27: 1440 | E27: =+C27/D27 -> 1.6428571 | F27: 2.8 | G27: =+C27*96 -> 227108.57 | H27: =+C27*M27 -> 385714.29 | I27: =+G27+H27 -> 612822.86 | J27: =+I27/C27 -> 259.04348 | K27: 283 | L27: =4600/2800 -> 1.6428571 | M27: =750000/4600 -> 163.04348
A28: 45592 | B28: 27 | C28: =7360 -> 7360 | D28: 480 | E28: =+C28/D28 -> 15.333333 | F28: 2.8 | G28: =+C28*96 -> 706560 | H28: =+C28*M28 -> 667876.59 | I28: =+G28+H28 -> 1374436.6 | J28: =+I28/C28 -> 186.7441 | K28: 283 | L28: =16530/960 -> 17.21875 | M28: =(750000+750000)/(C28+C29) -> 90.744102
A29: 45592 | B29: 28 | C29: 9170 | D29: 480 | E29: =+C29/D29 -> 19.104167 | F29: 2.8 | G29: =+C29*96 -> 880320 | H29: =+C29*M29 -> 832123.41 | I29: =+G29+H29 -> 1712443.4 | J29: =+I29/C29 -> 186.7441 | K29: 283 | L29: =16530/960 -> 17.21875 | M29: =(750000+750000)/(C28+C29) -> 90.744102
A30: 45593 | B30: 29 | C30: =6180 -> 6180 | D30: 760 | E30: =+C30/D30 -> 8.1315789 | F30: 2.8 | G30: =+C30*96 -> 593280 | H30: =+C30*M30 -> 1155860.3 | I30: =+G30+H30 -> 1749140.3 | J30: =+I30/C30 -> 283.03242 | K30: 283 | L30: 5.2763158 | M30: =(750000+750000)/(C30+C31) -> 187.03242
A31: 45593 | B31: 30 | C31: 1840 | D31: 760 | E31: =+C31/D31 -> 2.4210526 | F31: 2.8 | G31: =+C31*96 -> 176640 | H31: =+C31*M31 -> 344139.65 | I31: =+G31+H31 -> 520779.65 | J31: =+I31/C31 -> 283.03242 | K31: 283 | L31: 5.2763158 | M31: =(750000+750000)/(C30+C31) -> 187.03242
A32: 45594 | B32: 31 | C32: 5310 | D32: 1600 | E32: =+C32/D32 -> 3.31875 | F32: 2.8 | G32: =+C32*96 -> 509760 | H32: 750000 | I32: =+G32+H32 -> 1259760 | J32: =+I32/C32 -> 237.24294 | K32: 283
A33: 45595 | B33: 32 | C33: 4490 | D33: 1520 | E33: =+C33/D33 -> 2.9539474 | F33: 2.8 | G33: =+C33*96 -> 431040 | H33: 750000 | I33: =+G33+H33 -> 1181040 | J33: =+I33/C33 -> 263.03786 | K33: 283
A34: 45596 | B34: 33 | D34: 1760 | E34: =+C34/D34 -> 0 | F34: 2.8 | J34: =+I34/C34 -> #DIV/0!
C35: =SUM(C2:C33) -> 110400 | D35: 36320 | E35: =+C35/D35 -> 3.0396476 | G35: =SUM(G2:G33) -> 10367833 | H35: =SUM(H2:H33) -> 16500000 | I35: =SUM(I2:I33) -> 26867833 | J35: =+I35/C35 -> 243.36805 | K35: 283
D39: ACUMULADO LODOS
D40: Caudal | E40: Gene kg/m3 | F40: costo /m3
D41: =+D35 -> 36320 | E41: =+E35 -> 3.0396476 | F41: =+J35 -> 243.36805

Sheet consolidado diario (5)
A1: FECHA | B1: N | C1: Kg | D1: GEM m3 | E1: kg/m3 | F1: factor Kg/m3 | G1: valor kg | H1: transporte | I1: $/dia | J1: $/kg | K1: factor $/kg | L1: ajuste de factor | M1: ajuste de transporte
A3: 45629 | B3: =DAY(A3) -> 3 | C3: 6850 | D3: 1360 | E3: =+C3/D3 -> 5.0367647 | F3: 2.8 | G3: =+C3*96 -> 657600 | H3: 750000 | I3: =+G3+H3 -> 1407600 | J3: =+I3/C3 -> 205.48905 | K3: 283
A4: 45630 | B4: =DAY(A4) -> 4 | C4: 4970 | D4: 783.61611 | E4: =+C4/D4 -> 6.3423913 | F4: 2.8 | G4: =+C4*96 -> 477120 | H4: 750000 | I4: =+G4+H4 -> 1227120 | J4: =+I4/C4 -> 246.90543 | K4: 283
A5: 45630 | B5: =DAY(A5) -> 4 | C5: 6700 | D5: 1056.3839 | E5: =+C5/D5 -> 6.3423913 | F5: 2.8 | G5: =+C5*96 -> 643200 | H5: 750000 | I5: =+G5+H5 -> 1393200 | J5: =+I5/C5 -> 207.9403 | K5: 283
A6: 45631 | B6: =DAY(A6) -> 5 | C6: 4430 | D6: 1920 | E6: =+C6/D6 -> 2.3072917 | F6: 2.8 | G6: =+C6*96 -> 425280 | H6: 750000 | I6: =+G6+H6 -> 1175280 | J6: =+I6/C6 -> 265.30023 | K6: 283
A7: 45632 | B7: =DAY(A7) -> 6 | C7: 4850 | D7: 1760 | E7: =+C7/D7 -> 2.7556818 | F7: 2.8 | G7: =+C7*96 -> 465600 | H7: 750000 | I7: =+G7+H7 -> 1215600 | J7: =+I7/C7 -> 250.63918 | K7: 283
A8: 45635 | B8: =DAY(A8) -> 9 | C8: 1910 | D8: 1200 | E8: =+C8/D8 -> 1.5916667 | F8: 2.8 | G8: =+C8*96 -> 183360 | H8: 750000 | I8: =+G8+H8 -> 933360 | J8: =+I8/C8 -> 488.67016 | K8: 283
A9: 45636 | B9: =DAY(A9) -> 10 | C9: 4930 | D9: 1840 | E9: =+C9/D9 -> 2.6793478 | F9: 2.8 | G9: =+C9*96 -> 473280 | H9: 750000 | I9: =+G9+H9 -> 1223280 | J9: =+I9/C9 -> 248.12982 | K9: 283
A10: 45637 | B10: =DAY(A10) -> 11 | C10: 4510 | D10: 1840 | E10: =+C10/D10 -> 2.451087 | F10: 2.8 | G10: =+C10*96 -> 432960 | H10: 750000 | I10: =+G10+H10 -> 1182960 | J10: =+I10/C10 -> 262.29712 | K10: 283

Sheet consolidado diario (3)
A1: FECHA | B1: N | C1: Kg | D1: GEM m3 | E1: kg/m3 | F1: factor Kg/m3 | G1: valor kg | H1: transporte | I1: $/dia | J1: $/kg | K1: factor $/kg | L1: ajuste de factor | M1: ajuste de transporte
A2: 45598 | B2: =DAY(A2) -> 2 | C2: 6710 | D2: 1760 | E2: =+C2/D2 -> 3.8125 | F2: 2.8 | G2: =+C2*96 -> 644160 | H2: 750000 | I2: =+G2+H2 -> 1394160 | J2: =+I2/C2 -> 207.77347 | K2: 283
A3: 45599 | B3: =DAY(A3) -> 3 | C3: 6490 | D3: 0 | E3: =+C3/D3 -> #DIV/0! | F3: 2.8 | G3: =+C3*96 -> 623040 | H3: 750000 | I3: =+G3+H3 -> 1373040 | J3: =+I3/C3 -> 211.5624 | K3: 283
A4: 45601 | B4: =DAY(A4) -> 5 | C4: 2710 | D4: 1600 | E4: =+C4/D4 -> 1.69375 | F4: 2.8 | G4: =+C4*96 -> 260160 | H4: 750000 | I4: =+G4+H4 -> 1010160 | J4: =+I4/C4 -> 372.75277 | K4: 283
A5: 45602 | B5: =DAY(A5) -> 6 | C5: 4340 | D5: 1760 | E5: =+C5/D5 -> 2.4659091 | F5: 2.8 | G5: =+C5*96 -> 416640 | H5: 750000 | I5: =+G5+H5 -> 1166640 | J5: =+I5/C5 -> 268.81106 | K5: 283
A6: 45603 | B6: =DAY(A6) -> 7 | C6: 4700 | D6: 1680 | E6: =+C6/D6 -> 2.797619 | F6: 2.8 | G6: =+C6*96 -> 451200 | H6: 750000 | I6: =+G6+H6 -> 1201200 | J6: =+I6/C6 -> 255.57447 | K6: 283
A7: 45604 | B7: =DAY(A7) -> 8 | C7: 5910 | D7: 1840 | E7: =+C7/D7 -> 3.2119565 | F7: 2.8 | G7: =+C7*96 -> 567360 | H7: 750000 | I7: =+G7+H7 -> 1317360 | J7: =+I7/C7 -> 222.90355 | K7: 283
A8: 45605 | B8: =DAY(A8) -> 9 | C8: 3790 | D8: 1760 | E8: =+C8/D8 -> 2.1534091 | F8: 2.8 | G8: =+C8*96 -> 363840 | H8: 750000 | I8: =+G8+H8 -> 1113840 | J8: =+I8/C8 -> 293.88918 | K8: 283
A9: 45606 | B9: =DAY(A9) -> 10 | C9: 4300 | D9: 480 | E9: =+C9/D9 -> 8.9583333 | F9: 2.8 | G9: =+C9*96 -> 412800 | H9: 750000 | I9: =+G9+H9 -> 1162800 | J9: =+I9/C9 -> 270.4186 | K9: 283
A10: 45607 | B10: =DAY(A10) -> 11 | C10: 3502 | D10: 960 | E10: =+C10/D10 -> 3.6479167 | F10: 2.8 | G10: =+C10*96 -> 336192 | H10: 428467 | I10: =+G10+H10 -> 764659 | J10: =+I10/C10 -> 218.34923 | K10: 283
A11: 45608 | B11: =DAY(A11) -> 12 | C11: 2628 | D11: 720 | E11: =+C11/D11 -> 3.65 | F11: 2.8 | G11: =+C11*96 -> 252288 | H11: =750000-H10 -> 321533 | I11: =+G11+H11 -> 573821 | J11: =+I11/C11 -> 218.34893 | K11: 283
A12: 45609 | B12: =DAY(A12) -> 13 | C12: 0 | D12: 560 | E12: =+C12/D12 -> 0 | F12: 2.8 | G12: =+C12*96 -> 0 | H12: =+$M$11*C12 -> 0 | I12: =+G12+H12 -> 0 | J12: =+I12/C12 -> #DIV/0! | K12: 283
A13: 45610 | B13: =DAY(A13) -> 14 | C13: 4780 | D13: 1280 | E13: =+C13/D13 -> 3.734375 | F13: 2.8 | G13: =+C13*96 -> 458880 | H13: 750000 | I13: =+G13+H13 -> 1208880 | J13: =+I13/C13 -> 252.90377 | K13: 283
A14: 45611 | B14: =DAY(A14) -> 15 | C14: 797 | D14: 400 | E14: =+C14/D14 -> 1.9925 | F14: 2.8 | G14: =+C14*96 -> 76512 | H14: 129383 | I14: =+G14+H14 -> 205895 | J14: =+I14/C14 -> 258.33752 | K14: 283
A15: 45612 | B15: =DAY(A15) -> 16 | C15: 3823 | D15: 1920 | E15: =+C15/D15 -> 1.9911458 | F15: 2.8 | G15: =+C15*96 -> 367008 | H15: 620617 | I15: =+G15+H15 -> 987625 | J15: =+I15/C15 -> 258.33769 | K15: 283
A16: 45613 | B16: =DAY(A16) -> 17 | C16: 1402 | D16: 640 | E16: =+C16/D16 -> 2.190625 | F16: 2.8 | G16: =+C16*96 -> 134592 | H16: 206988 | I16: =+G16+H16 -> 341580 | J16: =+I16/C16 -> 243.63766 | K16: 283
A17: 45614 | B17: =DAY(A17) -> 18 | C17: 3678 | D17: 1680 | E17: =+C17/D17 -> 2.1892857 | F17: 2.8 | G17: =+C17*96 -> 353088 | H17: 543011 | I17: =+G17+H17 -> 896099 | J17: =+I17/C17 -> 243.63757 | K17: 283
A18: 45615 | B18: =DAY(A18) -> 19 | C18: 2960 | D18: 1680 | E18: =+C18/D18 -> 1.7619048 | F18: 2.8 | G18: =+C18*96 -> 284160 | H18: 750000 | I18: =+G18+H18 -> 1034160 | J18: =+I18/C18 -> 349.37838 | K18: 283
A19: 45617 | B19: =DAY(A19) -> 21 | C19: 2810 | D19: 1840 | E19: =+C19/D19 -> 1.5271739 | F19: 2.8 | G19: =+C19*96 -> 269760 | H19: 750000 | I19: =+G19+H19 -> 1019760 | J19: =+I19/C19 -> 362.90391 | K19: 283
A20: 45618 | B20: =DAY(A20) -> 22 | C20: 1385 | D20: 1840 | E20: =+C20/D20 -> 0.75271739 | F20: 2.8 | G20: =+C20*96 -> 132960 | H20: 375000 | I20: =+G20+H20 -> 507960 | J20: =+I20/C20 -> 366.75812 | K20: 283
A21: 45619 | B21: =DAY(A21) -> 23 | C21: 1385 | D21: 1840 | E21: =+C21/D21 -> 0.75271739 | F21: 2.8 | G21: =+C21*96 -> 132960 | H21: 375000 | I21: =+G21+H21 -> 507960 | J21: =+I21/C21 -> 366.75812 | K21: 283
A22: 45620 | B22: =DAY(A22) -> 24 | C22: 1661.5789 | D22: 560 | E22: =+C22/D22 -> 2.9671053 | F22: 2.8 | G22: =+C22*96 -> 159511.58 | H22: 276315.79 | I22: =+G22+H22 -> 435827.37 | J22: =+I22/C22 -> 262.29712 | K22: 283
A23: 45621 | B23: =DAY(A23) -> 25 | C23: 2848.4211 | D23: 960 | E23: =+C23/D23 -> 2.9671053 | F23: 2.8 | G23: =+C23*96 -> 273448.42 | H23: 473684.21 | I23: =+G23+H23 -> 747132.63 | J23: =+I23/C23 -> 262.29712 | K23: 283
A24: 45622 | B24: =DAY(A24) -> 26 | C24: 1525 | D24: 1760 | E24: =+C24/D24 -> 0.86647727 | F24: 2.8 | G24: =+C24*96 -> 146400 | H24: 375000 | I24: =+G24+H24 -> 521400 | J24: =+I24/C24 -> 341.90164 | K24: 283
... A28: 45626 | B28: =DAY(A28) -> 30 | C28: 6410 | D28: 1760 | E28: =+C28/D28 -> 3.6420455 | F28: 2.8 | G28: =+C28*96 -> 615360 | H28: 750000 | I28: =+G28+H28 -> 1365360 | J28: =+I28/C28 -> 213.00468 | K28: 283

Sheet ENERO
A1: FECHA | B1: Día | C1: HOROMETRO INICIAL | D1: HOROMETRO FINAL | E1: HORAS DE OPERACIÓN | F1: Q TRATAMIENTO | G1: VOLUMEN TRATADO (m3) | H1: KG GENERADOS | I1: $ Kg | J1: $ TRANSPORTE | K1: $ / KG | L1: $ AMPLIRROL | M1: ($/KG) | N1: FACTOR ($/KG) | O1: FACTOR 2024 KG/M3 | P1: FACTOR GENERACIÓN KG/M3 | Q1: $/ M3 | R1: FACTOR $/m3 2024 | S1: VOL TRATADO DIA | T1: $/M3
A2: 2026-01-03 | B2: =DAY(A2) -> 3 | C2: 16494 | D2: 16511 | E2: =D2-C2 -> 17 | F2: 88 | G2: =E2*F2 -> 1496 | H2: 6100 | I2: 96 | J2: 600000 | K2: =H2*I2 -> 585600 | L2: =K2+J2 -> 1185600 | M2: =L2/H2 -> 194.36066 | N2: 267 | O2: 2.3 | P2: =H2/G2 -> 4.0775401 | Q2: =L2/G2 -> 792.51337 | R2: 629 | S2: 2000 | T2: =L2/S2 -> 592.8
A3: 2026-01-06 | B3: =DAY(A3) -> 6 | C3: =+D2 -> 16511 | D3: 16528 | E3: =D3-C3 -> 17 | F3: 88 | G3: =E3*F3 -> 1496 | H3: 5830 | I3: 96 | J3: 600000 | K3: =H3*I3 -> 559680 | L3: =K3+J3 -> 1159680 | M3: =L3/H3 -> 198.91595 | N3: 267 | O3: 2.3 | P3: =H3/G3 -> 3.8970588 | Q3: =L3/G3 -> 775.18717 | R3: 629 | S3: 2000 | T3: =L3/S3 -> 579.84
A4: 2026-01-08 | B4: =DAY(A4) -> 8 | C4: =+D3 -> 16528 | D4: 16550 | E4: =D4-C4 -> 22 | F4: 88 | G4: =E4*F4 -> 1936 | H4: 5630 | I4: 96 | J4: 600000 | K4: =H4*I4 -> 540480 | L4: =K4+J4 -> 1140480 | M4: =L4/H4 -> 202.57194 | N4: 267 | O4: =+O3 -> 2.3 | P4: =H4/G4 -> 2.9080579 | Q4: =L4/G4 -> 589.09091 | R4: 629 | S4: 2000 | T4: =L4/S4 -> 570.24
A5: 2026-01-12 | B5: =DAY(A5) -> 12 | C5: =+D4 -> 16550 | D5: 16579 | E5: =D5-C5 -> 29 | F5: 88 | G5: =E5*F5 -> 2552 | H5: 3730 | I5: 96 | J5: 600000 | K5: =H5*I5 -> 358080 | L5: =K5+J5 -> 958080 | M5: =L5/H5 -> 256.85791 | N5: 267 | O5: =+O4 -> 2.3 | P5: =H5/G5 -> 1.4615987 | Q5: =L5/G5 -> 375.4232 | R5: 629 | S5: 2000 | T5: =L5/S5 -> 479.04
A6: 2026-01-13 | B6: =DAY(A6) -> 13 | C6: =+D5 -> 16579 | D6: 16588 | E6: =D6-C6 -> 9 | F6: 88 | G6: =E6*F6 -> 792 | H6: 5320 | I6: 96 | J6: 600000 | K6: =H6*I6 -> 510720 | L6: =K6+J6 -> 1110720 | M6: =L6/H6 -> 208.78195 | N6: 267 | O6: =+O5 -> 2.3 | P6: =H6/G6 -> 6.7171717 | Q6: =L6/G6 -> 1402.4242 | R6: 629 | S6: 2001 | T6: =L6/S6 -> 555.08246
A7: 2026-01-14 | B7: =DAY(A7) -> 14 | C7: =+D6 -> 16588 | D7: 16604 | E7: =D7-C7 -> 16 | F7: 88 | G7: =E7*F7 -> 1408 | H7: 4390 | I7: 96 | J7: 600000 | K7: =H7*I7 -> 421440 | L7: =K7+J7 -> 1021440 | M7: =L7/H7 -> 232.67426 | N7: 267 | O7: =+O5 -> 2.3 | P7: =H7/G7 -> 3.1178977 | Q7: =L7/G7 -> 725.45455 | R7: 629 | S7: 2000 | T7: =L7/S7 -> 510.72
A8: 2026-01-14 | B8: =DAY(A8) -> 14 | C8: =+D7 -> 16604 | D8: 16614 | E8: =D8-C8 -> 10 | F8: 88 | G8: =E8*F8 -> 880 | H8: 5800 | I8: 96 | J8: 600000 | K8: =H8*I8 -> 556800 | L8: =K8+J8 -> 1156800 | M8: =L8/H8 -> 199.44828 | N8: 267 | O8: =+O7 -> 2.3 | P8: =H8/G8 -> 6.5909091 | Q8: =L8/G8 -> 1314.5455 | R8: 629 | S8: 2000 | T8: =L8/S8 -> 578.4
A9: 2026-01-15 | B9: =DAY(A9) -> 15 | C9: =+D8 -> 16614 | D9: 16628 | E9: =D9-C9 -> 14 | F9: 88 | G9: =E9*F9 -> 1232 | H9: 5190 | I9: 96 | J9: 600000 | K9: =H9*I9 -> 498240 | L9: =K9+J9 -> 1098240 | M9: =L9/H9 -> 211.60694 | N9: 267 | O9: =+O8 -> 2.3 | P9: =H9/G9 -> 4.2126623 | Q9: =L9/G9 -> 891.42857 | R9: 629 | S9: 2000 | T9: =L9/S9 -> 549.12
A10: 2026-01-16 | B10: =DAY(A10) -> 16 | C10: =+D9 -> 16628 | D10: 16642 | E10: =D10-C10 -> 14 | F10: 88 | G10: =E10*F10 -> 1232 | H10: 3560 | I10: 96 | J10: 600000 | K10: =H10*I10 -> 341760 | L10: =K10+J10 -> 941760 | M10: =L10/H10 -> 264.53933 | N10: 267 | O10: =+O9 -> 2.3 | P10: =H10/G10 -> 2.8896104 | Q10: =L10/G10 -> 764.41558 | R10: 629 | S10: 2000 | T10: =L10/S10 -> 470.88
A11: 2026-01-17 | B11: =DAY(A11) -> 17 | C11: =+D10 -> 16642 | D11: 16659 | E11: =D11-C11 -> 17 | F11: 88 | G11: =E11*F11 -> 1496 | H11: 3970 | I11: 96 | J11: 600000 | K11: =H11*I11 -> 381120 | L11: =K11+J11 -> 981120 | M11: =L11/H11 -> 247.1335 | N11: 267 | O11: =+O10 -> 2.3 | P11: =H11/G11 -> 2.6537433 | Q11: =L11/G11 -> 655.82888 | R11: 629 | S11: 2000 | T11: =L11/S11 -> 490.56
A12: 2026-01-19 | B12: =DAY(A12) -> 19 | C12: =+D11 -> 16659 | D12: 16670 | E12: =D12-C12 -> 11 | F12: 88 | G12: =E12*F12 -> 968 | H12: 7920 | I12: 96 | J12: 600000 | K12: =H12*I12 -> 760320 | L12: =K12+J12 -> 1360320 | M12: =L12/H12 -> 171.75758 | N12: 267 | O12: =+O11 -> 2.3 | P12: =H12/G12 -> 8.1818182 | Q12: =L12/G12 -> 1405.2893 | R12: 629 | S12: 2000 | T12: =L12/S12 -> 680.16
A13: 2026-01-19 | B13: =DAY(A13) -> 19 | C13: =+D12 -> 16670 | D13: 16684 | E13: =D13-C13 -> 14 | F13: 88 | G13: =E13*F13 -> 1232 | H13: 4600 | I13: 96 | J13: 600000 | K13: =H13*I13 -> 441600 | L13: =K13+J13 -> 1041600 | M13: =L13/H13 -> 226.43478 | N13: 267 | O13: =+O12 -> 2.3 | P13: =H13/G13 -> 3.7337662 | Q13: =L13/G13 -> 845.45455 | R13: 629 | S13: 2000 | T13: =L13/S13 -> 520.8
A14: 2026-01-20 | B14: =DAY(A14) -> 20 | C14: =+D13 -> 16684 | D14: 16698 | E14: =D14-C14 -> 14 | F14: 88 | G14: =E14*F14 -> 1232 | H14: 6970 | I14: 96 | J14: 600000 | K14: =H14*I14 -> 669120 | L14: =K14+J14 -> 1269120 | M14: =L14/H14 -> 182.08321 | N14: 267 | O14: =+O13 -> 2.3 | P14: =H14/G14 -> 5.6574675 | Q14: =L14/G14 -> 1030.1299 | R14: 629 | S14: 2000 | T14: =L14/S14 -> 634.56
A15: 2026-01-22 | B15: =DAY(A15) -> 22 | C15: =+D14 -> 16698 | D15: 16727 | E15: =D15-C15 -> 29 | F15: 88 | G15: =E15*F15 -> 2552 | H15: 5370 | I15: 96 | J15: 600000 | K15: =H15*I15 -> 515520 | L15: =K15+J15 -> 1115520 | M15: =L15/H15 -> 207.73184 | N15: 267 | O15: =+O14 -> 2.3 | P15: =H15/G15 -> 2.104232 | Q15: =L15/G15 -> 437.11599 | R15: 629 | S15: 2000 | T15: =L15/S15 -> 557.76
A16: 2026-01-24 | B16: =DAY(A16) -> 24 | C16: =+D15 -> 16727 | D16: 16756 | E16: =D16-C16 -> 29 | F16: 88 | G16: =E16*F16 -> 2552 | H16: 5730 | I16: 96 | J16: 600000 | K16: =H16*I16 -> 550080 | L16: =K16+J16 -> 1150080 | M16: =L16/H16 -> 200.71204 | N16: 267 | O16: =+O15 -> 2.3 | P16: =H16/G16 -> 2.2452978 | Q16: =L16/G16 -> 450.65831 | R16: 629 | S16: 2000 | T16: =L16/S16 -> 575.04
A17: 2026-01-27 | B17: =DAY(A17) -> 27 | C17: =+D16 -> 16756 | D17: 16781 | E17: =D17-C17 -> 25 | F17: 88 | G17: =E17*F17 -> 2200 | H17: 5020 | I17: 96 | J17: 600000 | K17: =H17*I17 -> 481920 | L17: =K17+J17 -> 1081920 | M17: =L17/H17 -> 215.52191 | N17: 267 | O17: =+O16 -> 2.3 | P17: =H17/G17 -> 2.2818182 | Q17: =L17/G17 -> 491.78182 | R17: 629 | S17: 2000 | T17: =L17/S17 -> 540.96
A18: 2026-01-28 | B18: =DAY(A18) -> 28 | C18: =+D17 -> 16781 | D18: 16797 | E18: =D18-C18 -> 16 | F18: 88 | G18: =E18*F18 -> 1408 | H18: 4380 | I18: 96 | J18: 600000 | K18: =H18*I18 -> 420480 | L18: =K18+J18 -> 1020480 | M18: =L18/H18 -> 232.9863 | N18: 267 | O18: =+O17 -> 2.3 | P18: =H18/G18 -> 3.1107955 | Q18: =L18/G18 -> 724.77273 | R18: 629 | S18: 2000 | T18: =L18/S18 -> 510.24
A19: 2026-01-29 | B19: =DAY(A19) -> 29 | C19: =+D18 -> 16797 | D19: 16810 | E19: =D19-C19 -> 13 | F19: 88 | G19: =E19*F19 -> 1144 | H19: 5670 | I19: 96 | J19: 600000 | K19: =H19*I19 -> 544320 | L19: =K19+J19 -> 1144320 | M19: =L19/H19 -> 201.82011 | N19: 267 | O19: =+O18 -> 2.3 | P19: =H19/G19 -> 4.9562937 | Q19: =L19/G19 -> 1000.2797 | R19: 629 | S19: 2000 | T19: =L19/S19 -> 572.16
A20: 2026-01-30 | B20: =DAY(A20) -> 30 | C20: =+D19 -> 16810 | D20: 16822 | E20: =D20-C20 -> 12 | F20: 88 | G20: =E20*F20 -> 1056 | H20: 4100 | I20: 96 | J20: 600000 | K20: =H20*I20 -> 393600 | L20: =K20+J20 -> 993600 | M20: =L20/H20 -> 242.34146 | N20: 267 | O20: =+O19 -> 2.3 | P20: =H20/G20 -> 3.8825758 | Q20: =L20/G20 -> 940.90909 | R20: 629 | S20: 2000 | T20: =L20/S20 -> 496.8
B21: =DAY(A21) -> 0
B22: =DAY(A22) -> 0
B23: =DAY(A23) -> 0
B24: =DAY(A24) -> 0
B25: =DAY(A25) -> 0 | W25: 39468
B26: =DAY(A26) -> 0 | X26: 115670
B27: =DAY(A27) -> 0
B28: =DAY(A28) -> 0
B29: =DAY(A29) -> 0
B30: =DAY(A30) -> 0
B31: =DAY(A31) -> 0
B32: =DAY(A32) -> 0
B33: =DAY(A33) -> 0
C35: =+SUM(C2:C33) -> 316320 | D35: =+SUM(D2:D33) -> 316648 | E35: =+SUM(E2:E33) -> 328 | F35: =+SUM(F2:F33) -> 1672 | G35: =+SUM(G2:G33) -> 28864 | H35: =+SUM(H2:H33) -> 99280 | I35: =+SUM(I2:I33) -> 1824 | J35: =+SUM(J2:J33) -> 11400000 | ... T35: =+SUM(T2:T33) -> 10465.162 | V35: BALANCE DE LODOS
V36: Agua Tratada GEM (m3) | W36: Lodos Generados (Kg) | X36: Valor Disposición de Lodo (SIN IVA) $ | Y36: Valor Transporte $ | Z36: Costo Total Servicio (Transporte + Disposición)(SIN IVA) $ | AA36: Indicador costo disposición ($/Kg) | AB36: Indicador costo tratamiento ($/m3) | AC36: Indicador de Generación (Kg/m3) | AD36: Indicador costo disposición ($/m3)
V37: =+G35 -> 28864 | W37: =+H35 -> 99280 | X37: =+K35 -> 9530880 | Y37: =+J35 -> 11400000 | Z37: =+X37+Y37 -> 20930880 | AA37: =+Z37/W37 -> 210.82675 | AB37: =+Z37/V37 -> 725.15521 | AC37: =+W37/V37 -> 3.4395787 | AD37: =+Z37/V37 -> 725.15521
V41: BALANCE DE LODOS
V42: Agua Tratada GEM (m3) | W42: Agua Tratada proyectada (m3) | X42: Lodos Generados (Kg) | Y42: Lodos proyectados (Kg) | Z42: Valor Disposición de Lodo (SIN IVA) $ | AA42: Valor Transporte $ | AB42: Costo Total Servicio (Transporte + Disposición)(SIN IVA) $ | AC42: Indicador costo disposición ($/Kg) | AD42: Indicador costo tratamiento ($/m3) | AE42: Indicador de Generación (Kg/m3) | AF42: Indicador costo proyectado ($/m3) | AG42: Indicador de Generación proyectado (Kg/m3)
V43: 29325 | W43: 27228 | X43: =+H35 -> 99280 | Y43: 92575.2 | Z43: =+K35 -> 9530880 | AA43: =+J35 -> 11400000 | AB43: =+Z43+AA43 -> 20930880 | AC43: =+AB43/X43 -> 210.82675 | AD43: =+AB43/V43 -> 713.7555 | AE43: =+X43/V43 -> 3.3855072 | AF43: 780 | AG43: =+Y43/W43 -> 3.4

Sheet FEBRERO
A1: FECHA | B1: Día | C1: HOROMETRO INICIAL | D1: HOROMETRO FINAL | E1: HORAS DE OPERACIÓN | F1: Q TRATAMIENTO | G1: VOLUMEN TRATADO (m3) | H1: KG GENERADOS | I1: $ Kg | J1: $ TRANSPORTE | K1: $ / KG | L1: $ AMPLIRROL | M1: ($/KG) | N1: FACTOR ($/KG) | O1: FACTOR 2024 KG/M3 | P1: FACTOR GENERACIÓN KG/M3 | Q1: $/ M3 | R1: FACTOR $/m3 2024 | S1: VOL TRATADO DIA | T1: $/M3
A2: 2026-02-02 | B2: =DAY(A2) -> 2 | C2: 16810 | D2: 16856 | E2: =D2-C2 -> 46 | F2: 80 | G2: =E2*F2 -> 3680 | H2: 5260 | I2: 96 | J2: 600000 | K2: =H2*I2 -> 504960 | L2: =K2+J2 -> 1104960 | M2: =L2/H2 -> 210.06844 | N2: 267 | O2: 2.3 | P2: =H2/G2 -> 1.4293478 | Q2: =L2/G2 -> 300.26087 | R2: 629 | S2: 2000 | T2: =L2/S2 -> 552.48
A3: 2026-02-03 | B3: =DAY(A3) -> 3 | C3: =+D2 -> 16856 | D3: 16870 | E3: =D3-C3 -> 14 | F3: 80 | G3: =E3*F3 -> 1120 | H3: 5860 | I3: 96 | J3: 600000 | K3: =H3*I3 -> 562560 | L3: =K3+J3 -> 1162560 | M3: =L3/H3 -> 198.38908 | N3: 267 | O3: 2.3 | P3: =H3/G3 -> 5.2321429 | Q3: =L3/G3 -> 1038 | R3: 629 | S3: 2000 | T3: =L3/S3 -> 581.28
A4: 2026-02-04 | B4: =DAY(A4) -> 4 | C4: =+D3 -> 16870 | D4: 16893 | E4: =D4-C4 -> 23 | F4: 80 | G4: =E4*F4 -> 1840 | H4: 4610 | I4: 96 | J4: 600000 | K4: =H4*I4 -> 442560 | L4: =K4+J4 -> 1042560 | M4: =L4/H4 -> 226.15184 | N4: 267 | O4: =+O3 -> 2.3 | P4: =H4/G4 -> 2.5054348 | Q4: =L4/G4 -> 566.6087 | R4: 629 | S4: 2000 | T4: =L4/S4 -> 521.28
A5: 2026-02-04 | B5: =DAY(A5) -> 4 | C5: =+D4 -> 16893 | D5: =+D4+7.5 -> 16900.5 | E5: =D5-C5 -> 7.5 | F5: 80 | G5: =E5*F5 -> 600 | H5: 5490 | I5: 96 | J5: 600000 | K5: =H5*I5 -> 527040 | L5: =K5+J5 -> 1127040 | M5: =L5/H5 -> 205.28962 | N5: 267 | O5: =+O4 -> 2.3 | P5: =H5/G5 -> 9.15 | Q5: =L5/G5 -> 1878.4 | R5: 629 | S5: 2000 | T5: =L5/S5 -> 563.52
A6: 2026-02-04 | B6: =DAY(A6) -> 4 | C6: =+D5 -> 16900.5 | D6: =+D5+7.5 -> 16908 | E6: =D6-C6 -> 7.5 | F6: 80 | G6: =E6*F6 -> 600 | H6: 5760 | I6: 96 | J6: 600000 | K6: =H6*I6 -> 552960 | L6: =K6+J6 -> 1152960 | M6: =L6/H6 -> 200.16667 | N6: 267 | O6: =+O5 -> 2.3 | P6: =H6/G6 -> 9.6 | Q6: =L6/G6 -> 1921.6 | R6: 629 | S6: 2001 | T6: =L6/S6 -> 576.1919
A7: 2026-02-05 | B7: =DAY(A7) -> 5 | C7: =+D6 -> 16908 | D7: =+D6+7.5 -> 16915.5 | E7: =D7-C7 -> 7.5 | F7: 80 | G7: =E7*F7 -> 600 | H7: 5220 | I7: 96 | J7: 600000 | K7: =H7*I7 -> 501120 | L7: =K7+J7 -> 1101120 | M7: =L7/H7 -> 210.94253 | N7: 267 | O7: =+O5 -> 2.3 | P7: =H7/G7 -> 8.7 | Q7: =L7/G7 -> 1835.2 | R7: 629 | S7: 2000 | T7: =L7/S7 -> 550.56
A8: 2026-02-06 | B8: =DAY(A8) -> 6 | C8: =+D7 -> 16915.5 | D8: 16923 | E8: =D8-C8 -> 7.5 | F8: 80 | G8: =E8*F8 -> 600 | H8: 4170 | I8: 96 | J8: 600000 | K8: =H8*I8 -> 400320 | L8: =K8+J8 -> 1000320 | M8: =L8/H8 -> 239.88489 | N8: 267 | O8: =+O7 -> 2.3 | P8: =H8/G8 -> 6.95 | Q8: =L8/G8 -> 1667.2 | R8: 629 | S8: 2000 | T8: =L8/S8 -> 500.16
A9: 2026-02-07 | B9: =DAY(A9) -> 7 | C9: =+D8 -> 16923 | D9: =+D8+21.6 -> 16944.6 | E9: =D9-C9 -> 21.6 | F9: 80 | G9: =E9*F9 -> 1728 | H9: 4960 | I9: 96 | J9: 600000 | K9: =H9*I9 -> 476160 | L9: =K9+J9 -> 1076160 | M9: =L9/H9 -> 216.96774 | N9: 267 | O9: =+O8 -> 2.3 | P9: =H9/G9 -> 2.8703704 | Q9: =L9/G9 -> 622.77778 | R9: 629 | S9: 2000 | T9: =L9/S9 -> 538.08
A10: 2026-02-09 | B10: =DAY(A10) -> 9 | C10: =+D9 -> 16944.6 | D10: =+D9+21.6 -> 16966.2 | E10: =D10-C10 -> 21.6 | F10: 80 | G10: =E10*F10 -> 1728 | H10: 4190 | I10: 96 | J10: 600000 | K10: =H10*I10 -> 402240 | L10: =K10+J10 -> 1002240 | M10: =L10/H10 -> 239.19809 | N10: 267 | O10: =+O9 -> 2.3 | P10: =H10/G10 -> 2.4247685 | Q10: =L10/G10 -> 580 | R10: 629 | S10: 2000 | T10: =L10/S10 -> 501.12
A11: 2026-02-11 | B11: =DAY(A11) -> 11 | C11: =+D10 -> 16966.2 | D11: 16988 | E11: =D11-C11 -> 21.8 | F11: 80 | G11: =E11*F11 -> 1744 | H11: 5410 | I11: 96 | J11: 600000 | K11: =H11*I11 -> 519360 | L11: =K11+J11 -> 1119360 | M11: =L11/H11 -> 206.90573 | N11: 267 | O11: =+O10 -> 2.3 | P11: =H11/G11 -> 3.1020642 | Q11: =L11/G11 -> 641.83486 | R11: 629 | S11: 2000 | T11: =L11/S11 -> 559.68
A12: 2026-02-12 | B12: =DAY(A12) -> 12 | C12: =+D11 -> 16988 | D12: =+D11+22 -> 17010 | E12: =D12-C12 -> 22 | F12: 80 | G12: =E12*F12 -> 1760 | H12: 4700 | I12: 96 | J12: 600000 | K12: =H12*I12 -> 451200 | L12: =K12+J12 -> 1051200 | M12: =L12/H12 -> 223.65957 | N12: 267 | O12: =+O11 -> 2.3 | P12: =H12/G12 -> 2.6704545 | Q12: =L12/G12 -> 597.27273 | R12: 629 | S12: 2000 | T12: =L12/S12 -> 525.6
A13: 2026-02-12 | B13: =DAY(A13) -> 12 | C13: =+D12 -> 17010 | D13: =+D12+22 -> 17032 | E13: =D13-C13 -> 22 | F13: 80 | G13: =E13*F13 -> 1760 | H13: 2960 | I13: 96 | J13: 600000 | K13: =H13*I13 -> 284160 | L13: =K13+J13 -> 884160 | M13: =L13/H13 -> 298.7027 | N13: 267 | O13: =+O12 -> 2.3 | P13: =H13/G13 -> 1.6818182 | Q13: =L13/G13 -> 502.36364 | R13: 629 | S13: 2000 | T13: =L13/S13 -> 442.08
A14: 2026-02-14 | B14: =DAY(A14) -> 14 | C14: =+D13 -> 17032 | D14: =+D13+22 -> 17054 | E14: =D14-C14 -> 22 | F14: 80 | G14: =E14*F14 -> 1760 | H14: 4600 | I14: 96 | J14: 600000 | K14: =H14*I14 -> 441600 | L14: =K14+J14 -> 1041600 | M14: =L14/H14 -> 226.43478 | N14: 267 | O14: =+O13 -> 2.3 | P14: =H14/G14 -> 2.6136364 | Q14: =L14/G14 -> 591.81818 | R14: 629 | S14: 2000 | T14: =L14/S14 -> 520.8
A15: 2026-02-17 | B15: =DAY(A15) -> 17 | C15: =+D14 -> 17054 | D15: 17076 | E15: =D15-C15 -> 22 | F15: 80 | G15: =E15*F15 -> 1760 | H15: 2410 | I15: 96 | J15: 600000 | K15: =H15*I15 -> 231360 | L15: =K15+J15 -> 831360 | M15: =L15/H15 -> 344.96266 | N15: 267 | O15: =+O14 -> 2.3 | P15: =H15/G15 -> 1.3693182 | Q15: =L15/G15 -> 472.36364 | R15: 629 | S15: 2000 | T15: =L15/S15 -> 415.68
A16: 2026-02-19 | B16: =DAY(A16) -> 19 | C16: =+D15 -> 17076 | D16: 17107 | E16: =D16-C16 -> 31 | F16: 80 | G16: =E16*F16 -> 2480 | H16: 3670 | I16: 96 | J16: 600000 | K16: =H16*I16 -> 352320 | L16: =K16+J16 -> 952320 | M16: =L16/H16 -> 259.48774 | N16: 267 | O16: =+O15 -> 2.3 | P16: =H16/G16 -> 1.4798387 | Q16: =L16/G16 -> 384 | R16: 629 | S16: 2000 | T16: =L16/S16 -> 476.16
A17: 2026-02-23 | B17: =DAY(A17) -> 23 | C17: =+D16 -> 17107 | D17: 17145 | E17: =D17-C17 -> 38 | F17: 80 | G17: =E17*F17 -> 3040 | H17: 2990 | I17: 96 | J17: 600000 | K17: =H17*I17 -> 287040 | L17: =K17+J17 -> 887040 | M17: =L17/H17 -> 296.6689 | N17: 267 | O17: =+O16 -> 2.3 | P17: =H17/G17 -> 0.98355263 | Q17: =L17/G17 -> 291.78947 | R17: 629 | S17: 2000 | T17: =L17/S17 -> 443.52
A18: 2026-02-25 | B18: =DAY(A18) -> 25 | C18: =+D17 -> 17145 | D18: 17164 | E18: =D18-C18 -> 19 | F18: 80 | G18: =E18*F18 -> 1520 | H18: 3916.6 | I18: 96 | J18: 600000 | K18: =H18*I18 -> 375993.6 | L18: =K18+J18 -> 975993.6 | M18: =L18/H18 -> 249.1941 | N18: 267 | O18: =+O17 -> 2.3 | P18: =H18/G18 -> 2.5767105 | Q18: =L18/G18 -> 642.10105 | R18: 629 | S18: 2000 | T18: =L18/S18 -> 487.9968
B19: =DAY(A19) -> 0
B20: =DAY(A20) -> 0
B21: =DAY(A21) -> 0
B22: =DAY(A22) -> 0
B23: =DAY(A23) -> 0 | X23: 39468
B24: =DAY(A24) -> 0 | Z24: 115670
B25: =DAY(A25) -> 0
B26: =DAY(A26) -> 0
B27: =DAY(A27) -> 0
B28: =DAY(A28) -> 0
B29: =DAY(A29) -> 0
B30: =DAY(A30) -> 0
B31: =DAY(A31) -> 0
C33: =+SUM(C2:C31) -> 288398.8 | D33: =+SUM(D2:D31) -> 288752.8 | E33: =+SUM(E2:E31) -> 354 | F33: =+SUM(F2:F31) -> 1360 | G33: =+SUM(G2:G31) -> 28320 | H33: =+SUM(H2:H31) -> 76176.6 | I33: =+SUM(I2:I31) -> 1632 | J33: =+SUM(J2:J31) -> 10200000 | ... T33: =+SUM(T2:T31) -> 8756.1887 | V33: BALANCE DE LODOS
V34: Agua Tratada GEM (m3) | W34: Agua Tratada proyectada (m3) | X34: Lodos Generados (Kg) | Y34: Lodos proyectados (Kg) | Z34: Valor Disposición de Lodo (SIN IVA) $ | AA34: Valor Transporte $ | AB34: Costo Total Servicio (Transporte + Disposición)(SIN IVA) $ | AC34: Indicador costo disposición ($/Kg) | AD34: Indicador costo tratamiento ($/m3) | AE34: Indicador de Generación (Kg/m3) | AF34: Indicador costo proyectado ($/m3) | AG34: Indicador de Generación proyectado (Kg/m3)
V35: =+G33 -> 28320 | W35: 26637.416 | X35: =+H33 -> 76176.6 | Y35: 90567 | Z35: =+K33 -> 7312953.6 | AA35: =+J33 -> 10200000 | AB35: =+Z35+AA35 -> 17512954 | AC35: =+AB35/X35 -> 229.89939 | AD35: =+AB35/V35 -> 618.39525 | AE35: =+X35/V35 -> 2.6898517 | AF35: 780 | AG35: =+Y35/W35 -> 3.399992

Sheet MARZO
A1: FECHA | B1: Día | C1: HOROMETRO INICIAL | D1: HOROMETRO FINAL | E1: HORAS DE OPERACIÓN | F1: Q TRATAMIENTO | G1: VOLUMEN TRATADO (m3) | H1: KG GENERADOS | I1: $ Kg | J1: $ TRANSPORTE | K1: $ / KG | L1: $ AMPLIRROL | M1: ($/KG) | N1: FACTOR ($/KG) | O1: FACTOR 2026 KG/M3 | P1: FACTOR GENERACIÓN KG/M3 | Q1: $/ M3 | R1: PROYECIÓN $/m3 2026
A2: 2026-03-02 | B2: =DAY(A2) -> 2 | C2: 17231 | D2: 17251 | E2: =D2-C2 -> 20 | F2: 80 | G2: =E2*F2 -> 1600 | H2: 5580 | I2: 96 | J2: 600000 | K2: =H2*I2 -> 535680 | L2: =K2+J2 -> 1135680 | M2: =L2/H2 -> 203.52688 | N2: 267 | O2: 3.4 | P2: =H2/G2 -> 3.4875 | Q2: =L2/G2 -> 709.8 | R2: 726
A3: 2026-03-05 | B3: =DAY(A3) -> 5 | C3: =+D2 -> 17251 | D3: 17311 | E3: =D3-C3 -> 60 | F3: 80 | G3: =E3*F3 -> 4800 | H3: 4440 | I3: 96 | J3: 600000 | K3: =H3*I3 -> 426240 | L3: =K3+J3 -> 1026240 | M3: =L3/H3 -> 231.13514 | N3: 267 | O3: 3.4 | P3: =H3/G3 -> 0.925 | Q3: =L3/G3 -> 213.8 | R3: 726
A4: 2026-03-07 | B4: =DAY(A4) -> 7 | C4: =+D3 -> 17311 | D4: 17346 | E4: =D4-C4 -> 35 | F4: 80 | G4: =E4*F4 -> 2800 | H4: 4530 | I4: 96 | J4: 600000 | K4: =H4*I4 -> 434880 | L4: =K4+J4 -> 1034880 | M4: =L4/H4 -> 228.45033 | N4: 267 | O4: 3.4 | P4: =H4/G4 -> 1.6178571 | Q4: =L4/G4 -> 369.6 | R4: 726
A5: 2026-03-10 | B5: =DAY(A5) -> 10 | C5: =+D4 -> 17346 | D5: 17384 | E5: =D5-C5 -> 38 | F5: 80 | G5: =E5*F5 -> 3040 | H5: 5060 | I5: 96 | J5: 600000 | K5: =H5*I5 -> 485760 | L5: =K5+J5 -> 1085760 | M5: =L5/H5 -> 214.57708 | N5: 267 | O5: 3.4 | P5: =H5/G5 -> 1.6644737 | Q5: =L5/G5 -> 357.15789 | R5: 726
A6: 2026-03-12 | B6: =DAY(A6) -> 12 | C6: =+D5 -> 17384 | D6: 17419 | E6: =D6-C6 -> 35 | F6: 80 | G6: =E6*F6 -> 2800 | H6: 5490 | I6: 96 | J6: 600000 | K6: =H6*I6 -> 527040 | L6: =K6+J6 -> 1127040 | M6: =L6/H6 -> 205.28962 | N6: 267 | O6: 3.4 | P6: =H6/G6 -> 1.9607143 | Q6: =L6/G6 -> 402.51429 | R6: 726
A7: 2026-03-14 | B7: =DAY(A7) -> 14 | C7: =+D6 -> 17419 | D7: 17451 | E7: =D7-C7 -> 32 | F7: 80 | G7: =E7*F7 -> 2560 | H7: 4580 | I7: 96 | J7: 600000 | K7: =H7*I7 -> 439680 | L7: =K7+J7 -> 1039680 | M7: =L7/H7 -> 227.00437 | N7: 267 | O7: 3.4 | P7: =H7/G7 -> 1.7890625 | Q7: =L7/G7 -> 406.125 | R7: 726
A8: 2026-03-17 | B8: =DAY(A8) -> 17 | C8: =+D7 -> 17451 | D8: 17477 | E8: =D8-C8 -> 26 | F8: 80 | G8: =E8*F8 -> 2080 | H8: 3770 | I8: 96 | J8: 600000 | K8: =H8*I8 -> 361920 | L8: =K8+J8 -> 961920 | M8: =L8/H8 -> 255.15119 | N8: 267 | O8: 3.4 | P8: =H8/G8 -> 1.8125 | Q8: =L8/G8 -> 462.46154 | R8: 726
A9: 2026-03-23 | B9: =DAY(A9) -> 23 | C9: =+D8 -> 17477 | D9: 17540 | E9: =D9-C9 -> 63 | F9: 80 | G9: =E9*F9 -> 5040 | H9: 5080 | I9: 96 | J9: 600000 | K9: =H9*I9 -> 487680 | L9: =K9+J9 -> 1087680 | M9: =L9/H9 -> 214.11024 | N9: 267 | O9: 3.4 | P9: =H9/G9 -> 1.0079365 | Q9: =L9/G9 -> 215.80952 | R9: 726
A10: 2026-03-26 | B10: =DAY(A10) -> 26 | C10: =+D9 -> 17540 | D10: 17583 | E10: =D10-C10 -> 43 | F10: 80 | G10: =E10*F10 -> 3440 | H10: 3570 | I10: 96 | J10: 600000 | K10: =H10*I10 -> 342720 | L10: =K10+J10 -> 942720 | M10: =L10/H10 -> 264.06723 | N10: 267 | O10: 3.4 | P10: =H10/G10 -> 1.0377907 | Q10: =L10/G10 -> 274.04651 | R10: 726
B11: =DAY(A11) -> 0
B12: =DAY(A12) -> 0
B13: =DAY(A13) -> 0
B14: =DAY(A14) -> 0
B15: =DAY(A15) -> 0
B16: =DAY(A16) -> 0
B17: =DAY(A17) -> 0
B18: =DAY(A18) -> 0
B19: =DAY(A19) -> 0
B20: =DAY(A20) -> 0
B21: =DAY(A21) -> 0 | V21: 39468
B22: =DAY(A22) -> 0 | X22: 115670
B23: =DAY(A23) -> 0
B24: =DAY(A24) -> 0
B25: =DAY(A25) -> 0
B26: =DAY(A26) -> 0
B27: =DAY(A27) -> 0
B28: =DAY(A28) -> 0
B29: =DAY(A29) -> 0
C31: =+SUM(C2:C29) -> 156410 | D31: =+SUM(D2:D29) -> 156762 | E31: =+SUM(E2:E29) -> 352 | F31: =+SUM(F2:F29) -> 720 | G31: =+SUM(G2:G29) -> 28160 | H31: =+SUM(H2:H29) -> 42100 | I31: =+SUM(I2:I29) -> 864 | J31: =+SUM(J2:J29) -> 5400000 | ... R31: =+SUM(R2:R29) -> 6534 | T31: BALANCE DE LODOS
T32: Agua Tratada GEM (m3) | U32: Agua Tratada proyectada (m3) | V32: Lodos Generados (Kg) | W32: Lodos proyectados (Kg) | X32: Valor Disposición de Lodo (SIN IVA) $ | Y32: Valor Transporte $ | Z32: Costo Total Servicio (Transporte + Disposición)(SIN IVA) $ | AA32: Indicador costo disposición ($/Kg) | AB32: Indicador costo tratamiento ($/m3) | AC32: Indicador de Generación (Kg/m3) | AD32: Indicador costo proyectado ($/m3) | AE32: Indicador de Generación proyectado (Kg/m3)
T33: =+G31 -> 28160 | U33: 25371.211 | V33: =+H31 -> 42100 | W33: 86262.118 | X33: =+K31 -> 4041600 | Y33: =+J31 -> 5400000 | Z33: =+X33+Y33 -> 9441600 | AA33: =+Z33/V33 -> 224.26603 | AB33: =+Z33/T33 -> 335.28409 | AC33: =+V33/T33 -> 1.4950284 | AD33: 726 | AE33: =+W33/U33 -> 3.4

Sheet ABRIL
A1: FECHA | B1: Día | C1: HOROMETRO INICIAL | D1: HOROMETRO FINAL | E1: HORAS DE OPERACIÓN | F1: Q TRATAMIENTO | G1: VOLUMEN TRATADO (m3) | H1: KG GENERADOS | I1: $ Kg | J1: $ TRANSPORTE | K1: $ / KG | L1: $ AMPLIRROL | M1: ($/KG) | N1: FACTOR ($/KG) | O1: FACTOR 2026 KG/M3 | P1: FACTOR GENERACIÓN KG/M3 | Q1: $/ M3 | R1: PROYECIÓN $/m3 2026
A2: 2026-04-06 | B2: =DAY(A2) -> 6 | C2: 17569 | D2: 17646 | E2: =D2-C2 -> 77 | F2: 80 | G2: =E2*F2 -> 6160 | H2: 4510 | I2: 96 | J2: 600000 | K2: =H2*I2 -> 432960 | L2: =K2+J2 -> 1032960 | M2: =L2/H2 -> 229.03769 | N2: 267 | O2: 3.4 | P2: =H2/G2 -> 0.73214286 | Q2: =L2/G2 -> 167.68831 | R2: 726
A3: 2026-04-13 | B3: =DAY(A3) -> 13 | C3: =+D2 -> 17646 | D3: 17739 | E3: =D3-C3 -> 93 | F3: 80 | G3: =E3*F3 -> 7440 | H3: 3510 | I3: 96 | J3: 600000 | K3: =H3*I3 -> 336960 | L3: =K3+J3 -> 936960 | M3: =L3/H3 -> 266.94017 | N3: 267 | O3: 3.4 | P3: =H3/G3 -> 0.47177419 | Q3: =L3/G3 -> 125.93548 | R3: 726
A4: 2026-04-18 | B4: =DAY(A4) -> 18 | C4: =+D3 -> 17739 | D4: 17829 | E4: =D4-C4 -> 90 | F4: 80 | G4: =E4*F4 -> 7200 | H4: 4920 | I4: 96 | J4: 600000 | K4: =H4*I4 -> 472320 | L4: =K4+J4 -> 1072320 | M4: =L4/H4 -> 217.95122 | N4: 267 | O4: 3.4 | P4: =H4/G4 -> 0.68333333 | Q4: =L4/G4 -> 148.93333 | R4: 726
A5: 2026-04-20 | B5: =DAY(A5) -> 20 | C5: =+D4 -> 17829 | D5: 17866 | E5: =D5-C5 -> 37 | F5: 80 | G5: =E5*F5 -> 2960 | H5: 3450 | I5: 96 | J5: 600000 | K5: =H5*I5 -> 331200 | L5: =K5+J5 -> 931200 | M5: =L5/H5 -> 269.91304 | N5: 267 | O5: 3.4 | P5: =H5/G5 -> 1.1655405 | Q5: =L5/G5 -> 314.59459 | R5: 726
A6: 2026-04-27 | B6: =DAY(A6) -> 27 | C6: =+D5 -> 17866 | D6: 17965 | E6: =D6-C6 -> 99 | F6: 80 | G6: =E6*F6 -> 7920 | H6: 4730 | I6: 96 | J6: 600000 | K6: =H6*I6 -> 454080 | L6: =K6+J6 -> 1054080 | M6: =L6/H6 -> 222.84989 | N6: 267 | O6: 3.4 | P6: =H6/G6 -> 0.59722222 | Q6: =L6/G6 -> 133.09091 | R6: 726
A7: 2026-04-29 | B7: =DAY(A7) -> 29 | C7: =+D6 -> 17965 | D7: 18006 | E7: =D7-C7 -> 41 | F7: 80 | G7: =E7*F7 -> 3280 | H7: 4490 | I7: 96 | J7: 600000 | K7: =H7*I7 -> 431040 | L7: =K7+J7 -> 1031040 | M7: =L7/H7 -> 229.63029 | N7: 267 | O7: 3.4 | P7: =H7/G7 -> 1.3689024 | Q7: =L7/G7 -> 314.34146 | R7: 726
B11: =DAY(A11) -> 0
B12: =DAY(A12) -> 0
B13: =DAY(A13) -> 0
B14: =DAY(A14) -> 0
B15: =DAY(A15) -> 0
B16: =DAY(A16) -> 0
B17: =DAY(A17) -> 0
B18: =DAY(A18) -> 0
B19: =DAY(A19) -> 0
B20: =DAY(A20) -> 0
B21: =DAY(A21) -> 0 | V21: 39468
B22: =DAY(A22) -> 0 | X22: 115670
B23: =DAY(A23) -> 0
B24: =DAY(A24) -> 0
B25: =DAY(A25) -> 0
B26: =DAY(A26) -> 0
B27: =DAY(A27) -> 0
B28: =DAY(A28) -> 0
B29: =DAY(A29) -> 0
C31: =+SUM(C2:C29) -> 106614 | D31: =+SUM(D2:D29) -> 107051 | E31: =+SUM(E2:E29) -> 437 | F31: =+SUM(F2:F29) -> 480 | G31: =+SUM(G2:G29) -> 34960 | H31: =+SUM(H2:H29) -> 25610 | I31: =+SUM(I2:I29) -> 576 | J31: =+SUM(J2:J29) -> 3600000 | ... R31: =+SUM(R2:R29) -> 4356 | T31: BALANCE DE LODOS
T32: Agua Tratada GEM (m3) | U32: Agua Tratada proyectada (m3) | V32: Lodos Generados (Kg) | W32: Lodos proyectados (Kg) | X32: Valor Disposición de Lodo (SIN IVA) $ | Y32: Valor Transporte $ | Z32: Costo Total Servicio (Transporte + Disposición)(SIN IVA) $ | AA32: Indicador costo disposición ($/Kg) | AB32: Indicador costo tratamiento ($/m3) | AC32: Indicador de Generación (Kg/m3) | AD32: Indicador costo proyectado ($/m3) | AE32: Indicador de Generación proyectado (Kg/m3)
T33: =+G31 -> 34960 | U33: 28996.039 | V33: =+H31 -> 25610 | W33: 98586.533 | X33: =+K31 -> 2458560 | Y33: =+J31 -> 3600000 | Z33: =+X33+Y33 -> 6058560 | AA33: =+Z33/V33 -> 236.57009 | AB33: =+Z33/T33 -> 173.29977 | AC33: =+V33/T33 -> 0.73255149 | AD33: 726 | AE33: =+W33/U33 -> 3.4

Sheet MAYO
A1: FECHA | B1: Día | C1: HOROMETRO INICIAL | D1: HOROMETRO FINAL | E1: HORAS DE OPERACIÓN | F1: Q TRATAMIENTO | G1: VOLUMEN TRATADO (m3) | H1: KG GENERADOS | I1: $ Kg | J1: $ TRANSPORTE | K1: $ / KG | L1: $ AMPLIRROL | M1: ($/KG) | N1: FACTOR ($/KG) | O1: FACTOR 2026 KG/M3 | P1: FACTOR GENERACIÓN KG/M3 | Q1: $/ M3 | R1: PROYECIÓN $/m3 2026
A2: 2026-05-08 | B2: =DAY(A2) -> 8 | C2: 18036 | D2: 18134 | E2: =D2-C2 -> 98 | F2: 80 | G2: =E2*F2 -> 7840 | H2: 5180 | I2: 96 | J2: 600000 | K2: =H2*I2 -> 497280 | L2: =K2+J2 -> 1097280 | M2: =L2/H2 -> 211.83012 | N2: 267 | O2: 3.4 | P2: =H2/G2 -> 0.66071429 | Q2: =L2/G2 -> 139.95918 | R2: 726
A3: 2026-05-12 | B3: =DAY(A3) -> 12 | C3: =+D2 -> 18134 | D3: 18188 | E3: =D3-C3 -> 54 | F3: 80 | G3: =E3*F3 -> 4320 | H3: 4480 | I3: 96 | J3: 600000 | K3: =H3*I3 -> 430080 | L3: =K3+J3 -> 1030080 | M3: =L3/H3 -> 229.92857 | N3: 267 | O3: 3.4 | P3: =H3/G3 -> 1.037037 | Q3: =L3/G3 -> 238.44444 | R3: 726
A4: 2026-05-13 | B4: =DAY(A4) -> 13 | C4: =+D3 -> 18188 | D4: 18207 | E4: =D4-C4 -> 19 | F4: 80 | G4: =E4*F4 -> 1520 | H4: 5610 | I4: 96 | J4: 600000 | K4: =H4*I4 -> 538560 | L4: =K4+J4 -> 1138560 | M4: =L4/H4 -> 202.95187 | N4: 267 | O4: 3.4 | P4: =H4/G4 -> 3.6907895 | Q4: =L4/G4 -> 749.05263 | R4: 726
A5: 2026-05-14 | B5: =DAY(A5) -> 14 | C5: =+D4 -> 18207 | D5: 18226 | E5: =D5-C5 -> 19 | F5: 80 | G5: =E5*F5 -> 1520 | H5: 5280 | I5: 96 | J5: 600000 | K5: =H5*I5 -> 506880 | L5: =K5+J5 -> 1106880 | M5: =L5/H5 -> 209.63636 | N5: 267 | O5: 3.4 | P5: =H5/G5 -> 3.4736842 | Q5: =L5/G5 -> 728.21053 | R5: 726
A6: 2026-05-16 | B6: =DAY(A6) -> 16 | C6: =+D5 -> 18226 | D6: 18254 | E6: =D6-C6 -> 28 | F6: 80 | G6: =E6*F6 -> 2240 | H6: 5060 | I6: 96 | J6: 600000 | K6: =H6*I6 -> 485760 | L6: =K6+J6 -> 1085760 | M6: =L6/H6 -> 214.57708 | N6: 267 | O6: 3.4 | P6: =H6/G6 -> 2.2589286 | Q6: =L6/G6 -> 484.71429 | R6: 726
A7: 2026-05-20 | B7: =DAY(A7) -> 20 | C7: =+D6 -> 18254 | D7: 18289 | E7: =D7-C7 -> 35 | F7: 80 | G7: =E7*F7 -> 2800 | H7: 4530 | I7: 96 | J7: 600000 | K7: =H7*I7 -> 434880 | L7: =K7+J7 -> 1034880 | M7: =L7/H7 -> 228.45033 | N7: 267 | O7: 3.4 | P7: =H7/G7 -> 1.6178571 | Q7: =L7/G7 -> 369.6 | R7: 726
A8: 2026-05-21 | B8: =DAY(A8) -> 21 | C8: =+D7 -> 18289 | D8: 18311 | E8: =D8-C8 -> 22 | F8: 80 | G8: =E8*F8 -> 1760 | H8: 4890 | I8: 96 | J8: 600000 | K8: =H8*I8 -> 469440 | L8: =K8+J8 -> 1069440 | M8: =L8/H8 -> 218.69939 | N8: 267 | O8: 3.4 | P8: =H8/G8 -> 2.7784091 | Q8: =L8/G8 -> 607.63636 | R8: 726
A9: 2026-05-22 | B9: =DAY(A9) -> 22 | C9: =+D8 -> 18311 | D9: 18330 | E9: =D9-C9 -> 19 | F9: 80 | G9: =E9*F9 -> 1520 | H9: 4510 | I9: 96 | J9: 600000 | K9: =H9*I9 -> 432960 | L9: =K9+J9 -> 1032960 | M9: =L9/H9 -> 229.03769 | N9: 267 | O9: 3.4 | P9: =H9/G9 -> 2.9671053 | Q9: =L9/G9 -> 679.57895 | R9: 726
A10: 2026-05-26 | B10: =DAY(A10) -> 26 | C10: =+D9 -> 18330 | D10: 18379 | E10: =D10-C10 -> 49 | F10: 80 | G10: =E10*F10 -> 3920 | H10: 4490 | I10: 96 | J10: 600000 | K10: =H10*I10 -> 431040 | L10: =K10+J10 -> 1031040 | M10: =L10/H10 -> 229.63029 | N10: 267 | O10: 3.4 | P10: =H10/G10 -> 1.1454082 | Q10: =L10/G10 -> 263.02041 | R10: 726
A11: 2026-05-27 | B11: =DAY(A11) -> 27 | C11: =+D10 -> 18379 | D11: 18397 | E11: =D11-C11 -> 18 | F11: 80 | G11: =E11*F11 -> 1440 | H11: 5340 | I11: 96 | J11: 600000 | K11: =H11*I11 -> 512640 | L11: =K11+J11 -> 1112640 | M11: =L11/H11 -> 208.35955 | N11: 267 | O11: 3.4 | P11: =H11/G11 -> 3.7083333 | Q11: =L11/G11 -> 772.66667 | R11: 726
A12: 2026-05-28 | B12: =DAY(A12) -> 28 | C12: =+D11 -> 18397 | D12: 18415 | E12: =D12-C12 -> 18 | F12: 80 | G12: =E12*F12 -> 1440 | H12: 3840 | I12: 96 | J12: 600000 | K12: =H12*I12 -> 368640 | L12: =K12+J12 -> 968640 | M12: =L12/H12 -> 252.25 | N12: 267 | O12: 3.4 | P12: =H12/G12 -> 2.6666667 | Q12: =L12/G12 -> 672.66667 | R12: 726
B13: =DAY(A13) -> 0
B14: =DAY(A14) -> 0
B15: =DAY(A15) -> 0
B16: =DAY(A16) -> 0
B17: =DAY(A17) -> 0
B18: =DAY(A18) -> 0 | V18: 39468
B19: =DAY(A19) -> 0 | X19: 115670
B20: =DAY(A20) -> 0
B21: =DAY(A21) -> 0
B22: =DAY(A22) -> 0
B23: =DAY(A23) -> 0
B24: =DAY(A24) -> 0
B25: =DAY(A25) -> 0
B26: =DAY(A26) -> 0
C28: =+SUM(C2:C26) -> 200751 | D28: =+SUM(D2:D26) -> 201130 | E28: =+SUM(E2:E26) -> 379 | F28: =+SUM(F2:F26) -> 880 | G28: =+SUM(G2:G26) -> 30320 | H28: =+SUM(H2:H26) -> 53210 | I28: =+SUM(I2:I26) -> 1056 | J28: =+SUM(J2:J26) -> 6600000 | ... R28: =+SUM(R2:R26) -> 7986 | T28: BALANCE DE LODOS
T29: Agua Tratada GEM (m3) | U29: Agua Tratada proyectada (m3) | V29: Lodos Generados (Kg) | W29: Lodos proyectados (Kg) | X29: Valor Disposición de Lodo (SIN IVA) $ | Y29: Valor Transporte $ | Z29: Costo Total Servicio (Transporte + Disposición)(SIN IVA) $ | AA29: Indicador costo disposición ($/Kg) | AB29: Indicador costo tratamiento ($/m3) | AC29: Indicador de Generación (Kg/m3) | AD29: Indicador costo proyectado ($/m3) | AE29: Indicador de Generación proyectado (Kg/m3)
T30: =+G28 -> 30320 | U30: 31422 | V30: =+H28 -> 53210 | W30: 106833 | X30: =+K28 -> 5108160 | Y30: =+J28 -> 6600000 | Z30: =+X30+Y30 -> 11708160 | AA30: =+Z30/V30 -> 220.03684 | AB30: =+Z30/T30 -> 386.15303 | AC30: =+V30/T30 -> 1.7549472 | AD30: 726 | AE30: =+W30/U30 -> 3.3999427

Sheet Hoja1
A5: enero
A12: febrero
A19: Marzo
A25: Abril
A32: Mayo
A38: Junio
A46: Julio
A52: Agosto
A60: Septiembre
A67: Octubre
A74: Noviembre
D78: MES | E78: M3 TRATADOS | F78: KG GENERADOS | J78: INDICADOR $/Kg | K78: Indicador Kg/m3 | L78: INDICADOR $/M3
D79: ENERO | E79: 45730 | F79: 101860 | G79: 9010560 | H79: 17250000 | I79: =+H79+G79 -> 26260560 | J79: =+I79/F79 -> 257.81033 | K79: =+F79/E79 -> 2.2274218 | L79: =+I79/E79 -> 574.25235
D80: FEBRERO | E80: 48225 | F80: 81070 | G80: 7782720 | H80: 16500000 | I80: =+H80+G80 -> 24282720 | J80: =+I80/F80 -> 299.52782 | K80: =+F80/E80 -> 1.6810783 | L80: =+I80/E80 -> 503.5297
D81: MARZO | E81: 55448 | F81: 123280 | G81: 11834880 | H81: 19500000 | I81: =+H81+G81 -> 31334880 | J81: =+I81/F81 -> 254.17651 | K81: =+F81/E81 -> 2.2233444 | L81: =+I81/E81 -> 565.12192
D82: ABRIL | E82: 47833 | F82: 123410 | G82: 12893568 | H82: 20370000 | I82: =+H82+G82 -> 33263568 | J82: =+I82/F82 -> 269.53706 | K82: =+F82/E82 -> 2.580018 | L82: =+I82/E82 -> 695.41045
D83: MAYO | E83: 54852 | F83: 153400 | G83: 14726400 | H83: 23250000 | I83: =+H83+G83 -> 37976400 | J83: =+I83/F83 -> 247.56454 | K83: =+F83/E83 -> 2.7966163 | L83: =+I83/E83 -> 692.34303
D84: JUNIO | E84: 45612 | F84: 139760 | G84: 13416960 | H84: 23250000 | I84: =+H84+G84 -> 36666960 | J84: =+I84/F84 -> 262.35661 | K84: =+F84/E84 -> 3.0641059 | L84: =+I84/E84 -> 803.88845
D85: JULIO | E85: 54264 | F85: 146650 | G85: 14078400 | H85: 24000004 | I85: =+H85+G85 -> 38078404 | J85: =+I85/F85 -> 259.65499 | K85: =+F85/E85 -> 2.7025284 | L85: =+I85/E85 -> 701.72497
D86: AGOSTO | E86: 44604 | F86: 118720 | G86: 11397120 | H86: 18750001 | I86: =+H86+G86 -> 30147121 | J86: =+I86/F86 -> 253.93464 | K86: =+F86/E86 -> 2.6616447 | L86: =+I86/E86 -> 675.8838
D87: SEPTIEMBRE | E87: 35926 | F87: 115670 | G87: 11104320 | H87: 18750001 | I87: =+H87+G87 -> 29854321 | J87: =+I87/F87 -> 258.09908 | K87: =+F87/E87 -> 3.2196738 | L87: =+I87/E87 -> 830.99485
D88: OCTUBRE | E88: 37140 | F88: 142490 | G88: 13679040 | H88: 16800000 | I88: =+H88+G88 -> 30479040 | J88: =+I88/F88 -> 213.90301 | K88: =+F88/E88 -> 3.8365644 | L88: =+I88/E88 -> 820.65267
D89: NOVIEMBRE | E89: 33254 | F89: 138007 | G89: 13248672 | H89: 16800000 | I89: =+H89+G89 -> 30048672 | J89: =+I89/F89 -> 217.73296 | K89: =+F89/E89 -> 4.1500872 | L89: =+I89/E89 -> 903.61075
D90: DICIEMBRE | E90: 32935 | F90: 161306 | G90: 15485376 | H90: 19200000 | I90: =+H90+G90 -> 34685376 | J90: =+I90/F90 -> 215.02843 | K90: =+F90/E90 -> 4.8977076 | L90: =+I90/E90 -> 1053.1464
E91: =+SUM(E79:E90) -> 535823 | F91: =+SUM(F79:F90) -> 1545623 | G91: =+SUM(G79:G90) -> 148658016 | H91: =+SUM(H79:H90) -> 234420006
D96: BALANCE DE LODOS
D97: AÑO | E97: Agua Tratada GEM (m3) | F97: Lodos Generados (Kg) | G97: Valor Disposición de Lodo (SIN IVA) $ | H97: Valor Transporte $ | I97: Costo Total Servicio (Transporte + Disposición)(SIN IVA) $ | J97: Indicador costo disposición ($/Kg) | K97: Indicador costo tratamiento ($/m3) | L97: Indicador de Generación (Kg/m3) | M97: Indicador costo disposición ($/m3)
D98: 2025 | E98: =+E91 -> 535823 | F98: =+F91 -> 1545623 | G98: =+G91 -> 148658016 | H98: =+H91 -> 234420006 | I98: =+G98+H98 -> 383078022 | J98: =+I98/F98 -> 247.847 | K98: =+I98/E98 -> 714.93389 | L98: =+F98/E98 -> 2.8845776 | M98: =+I98/E98 -> 714.93389
D99: 2024 | E99: 477323 | F99: 1130937 | G99: 106125619 | H99: 185800000 | I99: 2.9192562e+08 | J99: 258.12717 | K99: 611.58682 | L99: 2.3693237 | M99: =+K99 -> 611.58682

Sheet Hoja2
